Workbook

Sheet Employees
A1: Employee_ID | B1: Full_Name | C1: Gender | D1: Department | F1: Designation | G1: Company | H1: City | I1: Salary_Monthly | J1: Joining_Date | K1: Experience_Years | L1: Performance_Rating | M1: Employment_Status | N1: Manager_ID
A2: EMP0001 | B2: Priyanka Jena | C2: F | D2: DevOps | E2: =PROPER(D2) -> Devops | F2: SRE | G2: CoastalDev Studio | H2: Bhubaneswar | I2: 82466 | K2: 1.8 | L2: 4.5 | M2: Bikash Biswal
A3: EMP0002 | B3: Ranjit Samal | C3: female | D3: Design | E3: =PROPER(D3) -> Design | F3: UI Designer | G3: InfySoft Bhubaneswar | H3: Puri | I3: 56048 | J3: 05-03-2022 | K3: 2.8 | L3: 1.5 | M3: Resigned | N3: EMP0001
A4: EMP0003 | B4: Subhasree Dhal | C4: female | D4: DevOps | E4: =PROPER(D4) -> Devops | F4: SRE | G4: NilGiri Digitals | H4: Berhampur | I4: 196711 | J4: 07-03-2021 | K4: 3.8 | L4: 3.4 | M4: Active | N4: EMP0002
A5: EMP0004 | B5: Bikash Jena | C5: male | D5: Engineering | E5: =PROPER(D5) -> Engineering | F5: Tech Lead | G5: CoastalDev Studio | H5: Bhubaneswar | I5: 55130 | J5: 21-03-2021 | K5: 3.8 | L5: 2.7 | M5: On Leave | N5: EMP0002
A6: EMP0005 | B6: Bikash Nanda | C6: female | D6: Design | E6: =PROPER(D6) -> Design | F6: Design Lead | G6: SambalpurNet | H6: Cuttack | I6: 112039 | J6: 21-07-2023 | K6: 1.5 | L6: 4.9 | M6: Active | N6: EMP0003
A7: EMP0006 | B7: Tapas Sahu | C7: F | D7: Sales | E7: =PROPER(D7) -> Sales | F7: Account Manager | G7: BlueLotus IT | H7: Bhubaneswar | I7: 90908 | J7: 31-07-2022 | K7: 2.4 | L7: 2.9 | M7: Active | N7: EMP0002
A8: EMP0007 | B8: Jyotirmayee Ratha | C8: Female | D8: DevOps | E8: =PROPER(D8) -> Devops | F8: SRE | G8: SambalpurNet | H8: Rourkela | I8: 146760 | J8: 28-12-2018 | K8: 6 | M8: Active | N8: EMP0002
A9: EMP0008 | B9: Tanmay Nanda | C9: Male | D9: Product | E9: =PROPER(D9) -> Product | F9: Associate PM | G9: TributeAI | H9: Bhubaneswar | I9: 163509 | J9: 2023-01-31 | K9: 1.9 | L9: 2.3 | M9: Active | N9: EMP0004
A10: EMP0009 | B10: Bikash Routray | C10: male | D10: Sales | E10: =PROPER(D10) -> Sales | F10: Business Developer | G10: OdishaCode Labs | H10: Puri | I10: 27340 | J10: 14-11-2018 | K10: 6.1 | L10: 3.2 | M10: Active | N10: EMP0003
A11: EMP0010 | B11: Sudhansu Dhal | C11: Female | D11: Design | E11: =PROPER(D11) -> Design | F11: UX Researcher | G11: KalingaTech Pvt Ltd | H11: Bhubaneswar | I11: 48871 | J11: 21-02-2022 | K11: 2.9 | M11: On Leave | N11: EMP0005
A12: EMP0011 | B12: Lipsa Prusty | C12: female | D12: Engineering | E12: =PROPER(D12) -> Engineering | F12: Software Engineer | G12: NilGiri Digitals | H12: Bhubaneswar | I12: 181618 | J12: 22-03-2020 | K12: 4.8 | L12: 4.7 | M12: Active | N12: EMP0009
A13: EMP0012 | B13: Puspita Mahapatra | C13: M | D13: HR | E13: =PROPER(D13) -> Hr | F13: Talent Acquisition | G13: TributeAI | H13: Bhubaneswar | I13: 215352 | J13: 03-09-2023 | K13: 1.3 | L13: 2.6 | M13: Active | N13: EMP0007
A14: EMP0013 | B14: Nirmal Samal | C14: Male | D14: Data Science | E14: =PROPER(D14) -> Data Science | F14: Data Analyst | G14: NilGiri Digitals | H14: Puri | I14: 60493 | J14: 01-08-2022 | K14: 2.4 | L14: 4.6 | M14: On Leave | N14: EMP0006
A15: EMP0014 | B15: Chinmaya Ratha | C15: Female | D15: Design | E15: =PROPER(D15) -> Design | F15: Visual Designer | G15: NilGiri Digitals | H15: Berhampur | I15: 114298 | J15: 26-01-2020 | K15: 4.9 | L15: 3.5 | M15: Active | N15: EMP0004
A16: EMP0015 | B16: Tanmay Jena | C16: Female | D16: DevOps | E16: =PROPER(D16) -> Devops | F16: Cloud Architect | G16: SambalpurNet | H16: Bhubaneswar | I16: 204206 | J16: 10-11-2019 | K16: 5.1 | L16: 1.7 | M16: On Leave | N16: EMP0005
A17: EMP0016 | B17: Sudhansu Behura | C17: F | D17: Product | E17: =PROPER(D17) -> Product | F17: Associate PM | G17: CoastalDev Studio | H17: Berhampur | I17: 89394 | J17: 2021-05-06 | K17: 3.7 | L17: 4.1 | M17: Active | N17: EMP0009
A18: EMP0017 | B18: Sangita Padhi | C18: M | D18: Sales | E18: =PROPER(D18) -> Sales | F18: Sales Manager | G18: CoastalDev Studio | H18: Bhubaneswar | I18: 123031 | J18: 08-11-2023 | K18: 1.2 | L18: 4.8 | M18: Resigned | N18: EMP0006
A19: EMP0018 | B19: Barsha Prusty | C19: male | D19: Engineering | E19: =PROPER(D19) -> Engineering | F19: Architect | G19: BlueLotus IT | H19: Bhubaneswar | I19: 104303 | J19: 20-08-2021 | K19: 3.4 | L19: 1.8 | M19: On Leave | N19: EMP0010
A20: EMP0019 | B20: Lipsa Behura | C20: Female | D20: Data Science | E20: =PROPER(D20) -> Data Science | F20: Data Scientist | G20: UtkalSoft Technologies | H20: Bhubaneswar | I20: 135019 | J20: 20-02-2020 | K20: 4.9 | L20: 3 | M20: Active | N20: EMP0005
A21: EMP0020 | B21: Namita Sahu | C21: male | D21: Marketing | E21: =PROPER(D21) -> Marketing | F21: Digital Marketer | G21: NilGiri Digitals | H21: Puri | I21: 18476 | J21: 09-10-2019 | K21: 5.2 | L21: 4.3 | M21: Active | N21: EMP0013
A22: EMP0021 | B22: Sudhansu Choudhury | C22: M | D22: DevOps | E22: =PROPER(D22) -> Devops | F22: Sr DevOps | G22: TributeAI | H22: Bhubaneswar | I22: 61682 | J22: 09-03-2020 | K22: 4.8 | L22: 4.4 | M22: On Leave | N22: EMP0007
A23: EMP0022 | B23: Sudhansu Mohapatra | C23: Female | D23: Marketing | E23: =PROPER(D23) -> Marketing | F23: Digital Marketer | G23: OdishaCode Labs | H23: Berhampur | I23: 67370 | J23: 28-02-2024 | K23: 0.8 | L23: 3 | M23: Active | N23: EMP0002
... A34: EMP0033 | B34: Priyanka Ratha | C34: F | D34: Engineering | E34: =PROPER(D34) -> Engineering | F34: Tech Lead | G34: InfySoft Bhubaneswar | H34: Puri | I34: 82622 | J34: 22-02-2024 | K34: 0.9 | L34: 4.8 | M34: Active | N34: EMP0004
A35: EMP0034 | B35: Chinmaya Prusty | C35: Male | D35: Sales | E35: =PROPER(D35) -> Sales | F35: Account Manager | G35: InfySoft Bhubaneswar | H35: Bhubaneswar | J35: 19-07-2020 | K35: 4.5 | L35: 3.8 | M35: Active | N35: EMP0018
A36: EMP0035 | B36: Tanmay Padhi | C36: male | D36: Data Science | E36: =PROPER(D36) -> Data Science | F36: Data Analyst | G36: TechNova Solutions | H36: Berhampur | I36: 107257 | J36: 05-02-2023 | K36: 1.9 | L36: 4.9 | M36: Active | N36: EMP0009
A37: EMP0036 | B37: Saurav Biswal | C37: male | D37: Finance | E37: =PROPER(D37) -> Finance | F37: Finance Analyst | G37: InfySoft Bhubaneswar | H37: Rourkela | I37: 169784 | J37: 16-09-2018 | K37: 6.3 | L37: 2.4 | M37: Active | N37: EMP0013
A38: EMP0037 | B38: Saurav Nanda | C38: F | D38: Marketing | E38: =PROPER(D38) -> Marketing | F38: Content Strategist | G38: InfySoft Bhubaneswar | H38: Cuttack | I38: 99048 | J38: 21-09-2018 | K38: 6.3 | L38: 3.1 | M38: On Leave | N38: EMP0018
A39: EMP0038 | B39: Alka Nanda | C39: female | D39: QA | E39: =PROPER(D39) -> Qa | F39: Test Analyst | G39: KalingaTech Pvt Ltd | H39: Puri | I39: 182023 | J39: 07-12-2022 | K39: 2.1 | L39: 4.7 | M39: Resigned | N39: EMP0026
A40: EMP0039 | B40: Puspita Nanda | C40: female | D40: DevOps | E40: =PROPER(D40) -> Devops | F40: Cloud Architect | G40: InfySoft Bhubaneswar | H40: Berhampur | I40: 140041 | J40: 15-06-2021 | K40: 3.6 | L40: 3.4 | M40: Active | N40: EMP0016
A41: EMP0040 | B41: Chinmaya Biswal | C41: male | D41: Marketing | E41: =PROPER(D41) -> Marketing | F41: Digital Marketer | G41: KalingaTech Pvt Ltd | H41: Bhubaneswar | I41: 159138 | J41: 10-08-2023 | K41: 1.4 | L41: 2.9 | M41: Active | N41: EMP0027
A42: EMP0041 | B42: Sangita Ratha | C42: F | D42: DevOps | E42: =PROPER(D42) -> Devops | F42: SRE | G42: SambalpurNet | H42: Bhubaneswar | I42: 25880 | J42: 20-09-2019 | K42: 5.3 | L42: 3.1 | M42: Active | N42: EMP0022
A43: EMP0042 | B43: Sangita Jena | C43: female | D43: Engineering | E43: =PROPER(D43) -> Engineering | F43: Senior Developer | G43: NilGiri Digitals | H43: Cuttack | I43: 68820 | J43: 04-12-2021 | K43: 3.1 | L43: 2.6 | M43: Resigned | N43: EMP0011
A44: EMP0043 | B44: Rahul Ratha | C44: M | D44: Data Science | E44: =PROPER(D44) -> Data Science | F44: Data Analyst | G44: TributeAI | H44: Rourkela | I44: 148155 | J44: 18-01-2020 | K44: 5 | L44: 3.3 | M44: Resigned | N44: EMP0031
A45: EMP0044 | B45: Nirmal Padhi | C45: female | D45: HR | E45: =PROPER(D45) -> Hr | F45: HR Manager | G45: OdishaCode Labs | H45: Puri | I45: 209821 | J45: 2020-05-30 | K45: 4.6 | L45: 2.7 | M45: Active | N45: EMP0041
A46: EMP0045 | B46: Dibya Prusty | C46: M | D46: Engineering | E46: =PROPER(D46) -> Engineering | F46: Architect | G46: SilverByte Systems | H46: Puri | I46: 152528 | J46: 11-03-2020 | K46: 4.8 | L46: 4.3 | M46: Active | N46: EMP0025
A47: EMP0046 | B47: Ipsita Routray | C47: F | D47: HR | E47: =PROPER(D47) -> Hr | F47: Talent Acquisition | G47: SilverByte Systems | H47: Rourkela | I47: 97366 | J47: 21-11-2021 | K47: 3.1 | L47: 2.3 | M47: Active | N47: EMP0036
... A114: EMP0113 | B114: Nirmal Choudhury | C114: male | D114: Marketing | E114: =PROPER(D114) -> Marketing | F114: Content Strategist | G114: SambalpurNet | H114: Berhampur | I114: 46613 | J114: 03-05-2020 | K114: 4.7 | L114: 3.8 | M114: On Leave | N114: EMP0101
A115: EMP0114 | B115: Sudhansu Dhal | C115: M | D115: Sales | E115: =PROPER(D115) -> Sales | F115: Business Developer | G115: TributeAI | H115: Bhubaneswar | I115: 49155 | J115: 26-02-2023 | K115: 1.8 | M115: Active | N115: EMP0014
A116: EMP0115 | B116: Puspita Behura | C116: male | D116: sales | E116: =PROPER(D116) -> Sales | F116: Sales Manager | G116: InfySoft Bhubaneswar | H116: Berhampur | I116: 153126 | J116: 30-04-2018 | K116: 6.7 | L116: 4.7 | M116: On Leave | N116: EMP0092
A117: EMP0116 | B117: Smita Nanda | C117: Female | D117: devops | E117: =PROPER(D117) -> Devops | F117: SRE | G117: ZeroOneSystems | H117: Berhampur | I117: 107461 | J117: 13-03-2018 | K117: 6.8 | L117: 3.1 | M117: Active | N117: EMP0100
A118: EMP0117 | B118: Dibya Parida | C118: Female | D118: Design | E118: =PROPER(D118) -> Design | F118: UI Designer | G118: ZeroOneSystems | H118: Bhubaneswar | I118: 145043 | J118: 11-01-2018 | K118: 7 | L118: 3.8 | M118: Active | N118: EMP0063
A119: EMP0118 | B119: Satyajit Mishra | C119: female | D119: HR | E119: =PROPER(D119) -> Hr | F119: HR Manager | G119: KalingaTech Pvt Ltd | H119: Berhampur | I119: 58648 | J119: 26-09-2020 | K119: 4.3 | L119: 2.4 | M119: Resigned | N119: EMP0001
A120: EMP0119 | B120: Tanmay Prusty | C120: Male | D120: Sales | E120: =PROPER(D120) -> Sales | F120: Sales Manager | G120: UtkalSoft Technologies | H120: Berhampur | I120: 66700 | J120: 25-07-2018 | K120: 6.4 | L120: 3.3 | M120: Resigned | N120: EMP0055
A121: EMP0120 | B121: Sangita Senapati | C121: Male | D121: Design | E121: =PROPER(D121) -> Design | F121: UI Designer | G121: OdishaCode Labs | H121: Puri | I121: 103329 | J121: 15-09-2022 | K121: 2.3 | L121: 2.5 | M121: Active | N121: EMP0100
A122: EMP0121 | B122: Puspita Pattnaik | C122: Male | D122: Marketing | E122: =PROPER(D122) -> Marketing | F122: Digital Marketer | G122: KalingaTech Pvt Ltd | H122: Bhubaneswar | I122: 175475 | J122: 01-05-2022 | K122: 2.7 | L122: 2.6 | M122: Active | N122: EMP0099
A123: EMP0122 | B123: Saurav Nanda | C123: female | D123: Marketing | E123: =PROPER(D123) -> Marketing | F123: Digital Marketer | G123: ZeroOneSystems | H123: Cuttack | I123: 207513 | J123: 21-11-2020 | K123: 4.1 | L123: 4.7 | M123: On Leave | N123: EMP0030
A124: EMP0123 | B124: Namita Mahapatra | C124: F | D124: Data Science | E124: =PROPER(D124) -> Data Science | F124: Data Scientist | G124: TributeAI | H124: Bhubaneswar | I124: 130003 | J124: 05-02-2021 | K124: 3.9 | L124: 1.9 | M124: Resigned | N124: EMP0041
A125: EMP0124 | B125: Namita Nanda | C125: Male | D125: Finance | E125: =PROPER(D125) -> Finance | F125: Finance Analyst | G125: SilverByte Systems | H125: Bhubaneswar | I125: 43422 | J125: 28-01-2024 | K125: 0.9 | L125: 3.8 | M125: On Leave | N125: EMP0023
A126: EMP0125 | B126: Smita Nanda | C126: M | D126: Marketing | E126: =PROPER(D126) -> Marketing | F126: Digital Marketer | G126: BlueLotus IT | H126: Puri | I126: 169094 | J126: 24-06-2024 | K126: 0.5 | L126: 3.8 | M126: Active | N126: EMP0009
A127: EMP0126 | B127: Satyajit Jena | C127: F | D127: Marketing | E127: =PROPER(D127) -> Marketing | F127: Brand Manager | G127: InfySoft Bhubaneswar | H127: Bhubaneswar | I127: 171587 | J127: 26-07-2019 | K127: 5.4 | L127: 3.4 | M127: Active | N127: EMP0087
A128: EMP0127 | B128: Rajan Mishra | C128: M | D128: Engineering | E128: =PROPER(D128) -> Engineering | F128: Software Engineer | G128: OdishaCode Labs | H128: Bhubaneswar | I128: 134602 | J128: 04-08-2021 | K128: 3.4 | L128: 4.4 | M128: Active | N128: EMP0100
A129: EMP0128 | B129: Saurav Dhal | C129: Female | D129: Marketing | E129: =PROPER(D129) -> Marketing | F129: Content Strategist | G129: UtkalSoft Technologies | H129: Cuttack | I129: 75928 | J129: 07-03-2020 | K129: 4.8 | M129: Active | N129: EMP0066
A130: EMP0129 | B130: Debasmita Tripathy | C130: M | D130: Data Science | E130: =PROPER(D130) -> Data Science | F130: BI Developer | G130: SambalpurNet | H130: Bhubaneswar | I130: 169926 | J130: 19-09-2020 | K130: 4.3 | L130: 4.6 | M130: Active | N130: EMP0032
A131: EMP0130 | B131: Lipsa Nanda | C131: F | D131: Finance | E131: =PROPER(D131) -> Finance | F131: Finance Analyst | G131: SilverByte Systems | H131: Bhubaneswar | I131: 33691 | J131: 09-04-2023 | K131: 1.7 | L131: 1.7 | M131: Active | N131: EMP0115
A132: EMP0131 | B132: Namita Nanda | C132: F | D132: Marketing | E132: =PROPER(D132) -> Marketing | F132: Brand Manager | G132: NilGiri Digitals | H132: Puri | I132: 45224 | J132: 17-05-2018 | K132: 6.6 | L132: 1.7 | M132: Active | N132: EMP0114
A133: EMP0132 | B133: Ipsita Pattnaik | C133: female | D133: Design | E133: =PROPER(D133) -> Design | F133: UX Researcher | G133: SilverByte Systems | H133: Bhubaneswar | I133: 60261 | J133: 23-02-2018 | K133: 6.9 | L133: 3.2 | M133: Active | N133: EMP0029
A134: EMP0133 | B134: Debasmita Prusty | C134: M | D134: Marketing | E134: =PROPER(D134) -> Marketing | F134: Digital Marketer | G134: CoastalDev Studio | H134: Rourkela | I134: 195850 | J134: 20-09-2018 | K134: 6.3 | L134: 2.9 | M134: Resigned | N134: EMP0107
A135: EMP0134 | B135: Nirmal Choudhury | C135: M | D135: QA | E135: =PROPER(D135) -> Qa | F135: QA Lead | G135: BlueLotus IT | H135: Cuttack | I135: 172635 | J135: 26-12-2021 | K135: 3 | L135: 2.6 | M135: Active | N135: EMP0133
A136: EMP0135 | B136: Rahul Mishra | C136: F | D136: Marketing | E136: =PROPER(D136) -> Marketing | F136: Digital Marketer | G136: SambalpurNet | H136: Bhubaneswar | I136: 91791 | J136: 03-03-2019 | K136: 5.8 | L136: 1.9 | M136: Active | N136: EMP0081
A137: EMP0136 | B137: Dibya Behura | C137: male | D137: Data Science | E137: =PROPER(D137) -> Data Science | F137: ML Engineer | G137: TechNova Solutions | H137: Rourkela | I137: 75944 | J137: 19-09-2022 | K137: 2.3 | L137: 1.6 | M137: Active | N137: EMP0016
A138: EMP0137 | B138: Saurav Sahoo | C138: F | D138: Finance | E138: =PROPER(D138) -> Finance | F138: CFO | G138: SilverByte Systems | H138: Bhubaneswar | I138: 63115 | J138: 13-11-2022 | K138: 2.1 | L138: 1.7 | M138: Active | N138: EMP0082
A139: EMP0138 | B139: Priyanka Behura | C139: M | D139: Product | E139: =PROPER(D139) -> Product | F139: Associate PM | G139: CoastalDev Studio | H139: Cuttack | I139: 190530 | J139: 23-01-2024 | K139: 0.9 | L139: 2.4 | M139: Resigned | N139: EMP0093
A140: EMP0139 | B140: Prasant Pattnaik | C140: M | D140: design | E140: =PROPER(D140) -> Design | F140: Design Lead | G140: UtkalSoft Technologies | H140: Bhubaneswar | I140: 56860 | J140: 06-02-2024 | K140: 0.9 | M140: On Leave | N140: EMP0052
A141: EMP0140 | B141: Puspita Routray | C141: female | D141: HR | E141: =PROPER(D141) -> Hr | F141: Talent Acquisition | G141: UtkalSoft Technologies | H141: Bhubaneswar | I141: 174126 | J141: 26-09-2023 | K141: 1.3 | L141: 2.8 | M141: Active | N141: EMP0065
A142: EMP0141 | B142: Alka Senapati | C142: Male | D142: Data Science | E142: =PROPER(D142) -> Data Science | F142: Data Analyst | G142: SilverByte Systems | H142: Bhubaneswar | I142: 149593 | J142: 17-02-2021 | K142: 3.9 | L142: 4.2 | M142: On Leave | N142: EMP0048
A143: EMP0142 | B143: Satyajit Dhal | C143: Male | D143: QA | E143: =PROPER(D143) -> Qa | F143: Senior QA | G143: OdishaCode Labs | H143: Bhubaneswar | I143: 74665 | J143: 21-12-2019 | K143: 5 | L143: 4 | M143: Active | N143: EMP0131
A144: EMP0143 | B144: Sangita Parida | C144: male | D144: DevOps | E144: =PROPER(D144) -> Devops | F144: Cloud Architect | G144: SambalpurNet | H144: Bhubaneswar | I144: 90827 | J144: 31-10-2021 | K144: 3.2 | L144: 1.7 | M144: Resigned | N144: EMP0043
A145: EMP0144 | B145: Dibya Behura | C145: M | D145: QA | E145: =PROPER(D145) -> Qa | F145: QA Engineer | G145: InfySoft Bhubaneswar | H145: Cuttack | I145: 63381 | J145: 11-04-2020 | K145: 4.7 | L145: 2.1 | M145: Active | N145: EMP0111
A146: EMP0145 | B146: Puspita Mahapatra | C146: female | D146: marketing | E146: =PROPER(D146) -> Marketing | F146: Brand Manager | G146: UtkalSoft Technologies | H146: Berhampur | I146: 38253 | J146: 26-08-2023 | K146: 1.4 | L146: 3 | M146: Active | N146: EMP0024
A147: EMP0146 | B147: Alka Choudhury | C147: female | D147: Engineering | E147: =PROPER(D147) -> Engineering | F147: Senior Developer | G147: UtkalSoft Technologies | H147: Berhampur | I147: 81373 | J147: 11-04-2021 | K147: 3.7 | L147: 2.2 | M147: Active | N147: EMP0099
A148: EMP0147 | B148: Chinmaya Samal | C148: Male | D148: DevOps | E148: =PROPER(D148) -> Devops | F148: Sr DevOps | G148: BlueLotus IT | H148: Puri | I148: 123174 | J148: 31-03-2021 | K148: 3.8 | L148: 4.8 | M148: On Leave | N148: EMP0055
A149: EMP0148 | B149: Rajan Dhal | C149: Male | D149: data science | E149: =PROPER(D149) -> Data Science | F149: BI Developer | G149: InfySoft Bhubaneswar | H149: Bhubaneswar | I149: 168332 | J149: 16-09-2019 | K149: 5.3 | L149: 1.5 | M149: Active | N149: EMP0104
A150: EMP0149 | B150: Chinmaya Mahapatra | C150: Male | D150: HR | E150: =PROPER(D150) -> Hr | F150: HR Executive | G150: NilGiri Digitals | H150: Bhubaneswar | I150: 219745 | J150: 06-11-2020 | K150: 4.2 | L150: 4 | M150: On Leave | N150: EMP0009
A151: EMP0150 | B151: Priyanka Biswal | C151: Male | D151: Sales | E151: =PROPER(D151) -> Sales | F151: Account Manager | G151: CoastalDev Studio | H151: Cuttack | I151: 214161 | J151: 17-11-2023 | K151: 1.1 | L151: 4.4 | M151: Active | N151: EMP0019
A152: EMP0151 | B152: Lipsa Ratha | C152: F | D152: HR | E152: =PROPER(D152) -> Hr | F152: HR Manager | G152: OdishaCode Labs | H152: Cuttack | I152: 89103 | J152: 03-03-2019 | K152: 5.8 | L152: 3.3 | M152: Resigned | N152: EMP0110
... A170: EMP0169 | B170: Lipsa Pattnaik | C170: M | D170: Data Science | E170: =PROPER(D170) -> Data Science | F170: Data Analyst | G170: CoastalDev Studio | H170: Cuttack | I170: 123694 | J170: 27-02-2023 | K170: 1.8 | L170: 2.4 | M170: On Leave | N170: EMP0142
A171: EMP0170 | B171: Abhishek Sahu | C171: M | D171: Sales | E171: =PROPER(D171) -> Sales | F171: Business Developer | G171: TributeAI | H171: Bhubaneswar | I171: 122059 | J171: 20-06-2020 | K171: 4.5 | M171: Resigned | N171: EMP0092
A172: EMP0171 | B172: Rahul Parida | C172: male | D172: Engineering | E172: =PROPER(D172) -> Engineering | F172: Architect | G172: BlueLotus IT | H172: Cuttack | I172: 180770 | J172: 01-04-2023 | K172: 1.8 | L172: 2.5 | M172: Active | N172: EMP0024
A173: EMP0172 | B173: Alka Sahoo | C173: F | D173: HR | E173: =PROPER(D173) -> Hr | F173: HR Manager | G173: ZeroOneSystems | H173: Rourkela | I173: 116868 | J173: 2023-01-16 | K173: 2 | L173: 1.6 | M173: Resigned | N173: EMP0158
A174: EMP0173 | B174: Prasant Samal | C174: female | D174: QA | E174: =PROPER(D174) -> Qa | F174: QA Lead | G174: CoastalDev Studio | H174: Bhubaneswar | I174: 114814 | J174: 21-01-2023 | K174: 1.9 | L174: 2.8 | M174: Active | N174: EMP0170
A175: EMP0174 | B175: Ipsita Mohapatra | C175: F | D175: Design | E175: =PROPER(D175) -> Design | F175: Design Lead | G175: UtkalSoft Technologies | H175: Bhubaneswar | I175: 37507 | J175: 29-07-2018 | K175: 6.4 | L175: 4.1 | M175: Active | N175: EMP0029
A176: EMP0175 | B176: Dibya Ratha | C176: F | D176: Sales | E176: =PROPER(D176) -> Sales | F176: Account Manager | G176: SilverByte Systems | H176: Bhubaneswar | I176: 162109 | J176: 24-10-2019 | K176: 5.2 | L176: 4.6 | M176: Resigned | N176: EMP0170
A177: EMP0176 | B177: Puspita Jena | C177: M | D177: QA | E177: =PROPER(D177) -> Qa | F177: Test Analyst | G177: TributeAI | H177: Puri | I177: 82695 | J177: 10-03-2023 | K177: 1.8 | L177: 2.9 | M177: Active | N177: EMP0018
A178: EMP0177 | B178: Lipsa Ratha | C178: Male | D178: HR | E178: =PROPER(D178) -> Hr | F178: Talent Acquisition | G178: CoastalDev Studio | H178: Berhampur | I178: 40296 | J178: 19-08-2019 | K178: 5.4 | L178: 4.3 | M178: On Leave | N178: EMP0041
A179: EMP0178 | B179: Lipsa Routray | C179: female | D179: Marketing | E179: =PROPER(D179) -> Marketing | F179: Digital Marketer | G179: ZeroOneSystems | H179: Bhubaneswar | I179: 147550 | J179: 28-12-2023 | K179: 1 | L179: 4.7 | M179: Active | N179: EMP0067
A180: EMP0179 | B180: Satyajit Nanda | C180: female | D180: Marketing | E180: =PROPER(D180) -> Marketing | F180: Digital Marketer | G180: NilGiri Digitals | H180: Puri | I180: 163247 | J180: 25-11-2021 | K180: 3.1 | L180: 3.5 | M180: Active | N180: EMP0095
A181: EMP0180 | B181: Abhishek Pattnaik | C181: M | D181: Product | E181: =PROPER(D181) -> Product | F181: Associate PM | G181: SilverByte Systems | H181: Bhubaneswar | I181: 92419 | J181: 11-07-2022 | K181: 2.5 | L181: 1.6 | M181: Active | N181: EMP0112
A182: EMP0181 | B182: Ipsita Samal | C182: Male | D182: QA | E182: =PROPER(D182) -> Qa | F182: QA Lead | G182: InfySoft Bhubaneswar | H182: Bhubaneswar | I182: 166315 | J182: 29-05-2018 | K182: 6.6 | L182: 2.8 | M182: Active | N182: EMP0039
A183: EMP0182 | B183: Priyanka Mishra | C183: M | D183: Product | E183: =PROPER(D183) -> Product | F183: Product Manager | G183: ZeroOneSystems | H183: Bhubaneswar | I183: 116226 | J183: 11-08-2022 | K183: 2.4 | L183: 2.1 | M183: On Leave | N183: EMP0144
... A188: EMP0187 | B188: Ankita Parida | C188: Female | D188: Engineering | E188: =PROPER(D188) -> Engineering | F188: Senior Developer | G188: TechNova Solutions | H188: Berhampur | I188: 189038 | J188: 20-03-2023 | K188: 1.8 | L188: 3.2 | M188: Active | N188: EMP0113
A189: EMP0188 | B189: Dibya Jena | C189: F | D189: Marketing | E189: =PROPER(D189) -> Marketing | F189: Brand Manager | G189: SambalpurNet | H189: Berhampur | I189: 104855 | J189: 27-08-2021 | K189: 3.4 | M189: Active | N189: EMP0046
A190: EMP0189 | B190: Debasmita Tripathy | C190: Female | D190: Marketing | E190: =PROPER(D190) -> Marketing | F190: Brand Manager | G190: KalingaTech Pvt Ltd | H190: Cuttack | I190: 145073 | J190: 19-06-2023 | K190: 1.5 | L190: 2.9 | M190: Active | N190: EMP0035
A191: EMP0190 | B191: Sangita Jena | C191: F | D191: Engineering | E191: =PROPER(D191) -> Engineering | F191: Tech Lead | G191: KalingaTech Pvt Ltd | H191: Cuttack | I191: 98046 | J191: 08-08-2020 | K191: 4.4 | L191: 2.6 | M191: Active | N191: EMP0108
A192: EMP0191 | B192: Rahul Ratha | C192: female | D192: sales | E192: =PROPER(D192) -> Sales | F192: Account Manager | G192: ZeroOneSystems | H192: Puri | I192: 149981 | J192: 16-04-2020 | K192: 4.7 | L192: 1.6 | M192: On Leave | N192: EMP0028
A193: EMP0192 | B193: Ankita Pattnaik | C193: female | D193: DevOps | E193: =PROPER(D193) -> Devops | F193: DevOps Engineer | G193: SilverByte Systems | H193: Rourkela | I193: 144014 | J193: 15-04-2023 | K193: 1.7 | L193: 4.5 | M193: Active | N193: EMP0173
A194: EMP0193 | B194: Subhasree Parida | C194: Male | D194: HR | E194: =PROPER(D194) -> Hr | F194: HR Manager | G194: KalingaTech Pvt Ltd | H194: Bhubaneswar | J194: 17-08-2020 | K194: 4.4 | L194: 2.1 | M194: Active | N194: EMP0161
A195: EMP0194 | B195: Nirmal Mishra | C195: Male | D195: Marketing | E195: =PROPER(D195) -> Marketing | F195: Content Strategist | G195: SilverByte Systems | H195: Bhubaneswar | I195: 213196 | J195: 15-11-2022 | K195: 2.1 | L195: 3.1 | M195: On Leave | N195: EMP0004
A196: EMP0195 | B196: Abhishek Padhi | C196: M | D196: Engineering | E196: =PROPER(D196) -> Engineering | F196: Software Engineer | G196: SilverByte Systems | H196: Cuttack | I196: 94389 | J196: 22-12-2022 | K196: 2 | L196: 4.2 | M196: On Leave | N196: EMP0144
A197: EMP0196 | B197: Tanmay Choudhury | C197: Female | D197: DevOps | E197: =PROPER(D197) -> Devops | F197: Cloud Architect | G197: TechNova Solutions | H197: Bhubaneswar | I197: 218566 | J197: 25-11-2021 | K197: 3.1 | L197: 4.9 | M197: Active | N197: EMP0094
...

Sheet Projects
A1: Project_ID | B1: Project_Name | C1: Client_Name | D1: Company | E1: Technology_Stack | F1: Budget_Lakhs | G1: Actual_Cost_Lakhs | H1: Start_Date | I1: Deadline | J1: Completion_Date | K1: Status | L1: Team_Size | M1: Billable_Hours | N1: Lead_Employee_ID
A2: PROJ001 | B2: Supply Chain Optimizer | C2: GreenEnergy Co | D2: TechNova Solutions | E2: Android Kotlin | F2: 172.82 | G2: 149.22 | H2: 30-03-2022 | I2: 20-11-2022 | K2: Cancelled | L2: 16 | M2: 7765.2 | N2: EMP0508
A3: PROJ002 | B3: Supply Chain Optimizer | C3: TravelNest | D3: OdishaCode Labs | E3: ML/AI | F3: 123.83 | G3: 158.34 | H3: 01-11-2023 | I3: 28-04-2024 | K3: Cancelled | L3: 4 | M3: 2114.3 | N3: EMP0526
A4: PROJ003 | B4: Data Warehouse Migration | C4: FinServPro | D4: KalingaTech Pvt Ltd | E4: Angular | F4: 110.56 | G4: 114.91 | H4: 07-12-2021 | I4: 13-05-2022 | K4: Under Review | L4: 14 | M4: 1820.4 | N4: EMP0134
A5: PROJ004 | B5: IoT Gateway | C5: GlobalTrade Inc | D5: OdishaCode Labs | E5: AWS | F5: 167.36 | G5: 156.31 | H5: 04-08-2024 | I5: 03-11-2024 | K5: In Progress | L5: 5 | M5: 4444.4 | N5: EMP0530
A6: PROJ005 | B6: IoT Gateway | C6: SmartCity Gov | D6: TributeAI | E6: Flutter | F6: 111.58 | G6: 82.9 | H6: 27-03-2023 | I6: 20-07-2023 | J6: 19-07-2023 | K6: Completed | L6: 16 | M6: 10825.8 | N6: EMP0214
A7: PROJ006 | B7: Smart Grid System | C7: EduSpark | D7: InfySoft Bhubaneswar | E7: Node.js | F7: 167.64 | G7: 168.44 | H7: 05-03-2021 | I7: 06-10-2021 | K7: In Progress | L7: 17 | M7: 5174.3 | N7: EMP0161
A8: PROJ007 | B8: Fleet Management | C8: GlobalTrade Inc | D8: UtkalSoft Technologies | E8: ML/AI | F8: 78.19 | G8: 69.7 | H8: 04-09-2021 | I8: 10-11-2021 | K8: Under Review | L8: 15 | M8: 10820.4 | N8: EMP0105
A9: PROJ008 | B9: Smart Grid System | C9: FinServPro | D9: InfySoft Bhubaneswar | E9: iOS Swift | F9: 101.73 | G9: 115.49 | H9: 26-10-2023 | I9: 08-04-2024 | K9: Under Review | L9: 8 | M9: 5141.9 | N9: EMP0241
A10: PROJ009 | B10: Analytics Dashboard | C10: GlobalTrade Inc | D10: OdishaCode Labs | E10: Data Engineering | F10: 96.83 | G10: 89.11 | H10: 19-08-2022 | I10: 18-01-2023 | K10: On Hold | L10: 3 | M10: 458.3 | N10: EMP0414
A11: PROJ010 | B11: Supply Chain Optimizer | C11: LogiTrack | D11: BlueLotus IT | E11: .NET | F11: 63.75 | G11: 59.08 | H11: 23-07-2024 | I11: 06-12-2024 | K11: Under Review | L11: 4 | M11: 3512.1 | N11: EMP0508
A12: PROJ011 | B12: DigitalBank Portal | C12: SmartCity Gov | D12: BlueLotus IT | E12: Azure | F12: 16.57 | G12: 20.44 | H12: 07-10-2022 | I12: 08-08-2023 | K12: In Progress | L12: 18 | M12: 12125.9 | N12: EMP0291
A13: PROJ012 | B13: Smart Grid System | C13: GreenEnergy Co | D13: InfySoft Bhubaneswar | E13: DevOps/K8s | F13: 10.59 | G13: 10.16 | H13: 17-02-2023 | I13: 16-06-2023 | K13: Cancelled | L13: 23 | M13: 18151.5 | N13: EMP0352
A14: PROJ013 | B14: HR Automation Suite | C14: FinServPro | D14: CoastalDev Studio | E14: Azure | F14: 9.07 | G14: 10.12 | H14: 24-08-2022 | I14: 21-03-2023 | K14: On Hold | L14: 14 | M14: 8129.3 | N14: EMP0094
A15: PROJ014 | B15: Analytics Dashboard | C15: MediCare Systems | D15: SilverByte Systems | E15: DevOps/K8s | F15: 139.64 | G15: 171.38 | H15: 04-03-2023 | I15: 20-12-2023 | K15: On Hold | L15: 16 | M15: 5854.7 | N15: EMP0371
A16: PROJ015 | B16: DigitalBank Portal | C16: GreenEnergy Co | D16: UtkalSoft Technologies | E16: Node.js | F16: 57.32 | G16: 74.5 | H16: 06-05-2023 | I16: 15-07-2023 | K16: On Hold | L16: 8 | M16: 2307 | N16: EMP0538
A17: PROJ016 | B17: Analytics Dashboard | C17: TravelNest | D17: SambalpurNet | E17: Salesforce | F17: 190.76 | G17: 200.88 | H17: 12-02-2023 | I17: 08-05-2023 | K17: Under Review | L17: 24 | M17: 17402.8 | N17: EMP0119
A18: PROJ017 | B18: IoT Gateway | C18: AutoDrive | D18: UtkalSoft Technologies | E18: React | F18: 61.25 | G18: 53.5 | H18: 10-02-2021 | I18: 18-07-2021 | K18: Cancelled | L18: 9 | M18: 7651.3 | N18: EMP0540
... A37: PROJ036 | B37: DigitalBank Portal | C37: TravelNest | D37: KalingaTech Pvt Ltd | E37: Azure | F37: 82.32 | G37: 97.59 | H37: 21-07-2022 | I37: 06-07-2023 | K37: Cancelled | L37: 16 | M37: 1988 | N37: EMP0321
A38: PROJ037 | B38: Analytics Dashboard | C38: EduSpark | D38: SilverByte Systems | E38: iOS Swift | F38: 55.06 | G38: 57.15 | H38: 21-11-2022 | I38: 16-06-2023 | J38: 02-06-2023 | K38: Completed | L38: 5 | M38: 3111 | N38: EMP0390
A39: PROJ038 | B39: Fleet Management | C39: InsureNow | D39: InfySoft Bhubaneswar | E39: iOS Swift | F39: 19.87 | G39: 16.01 | H39: 24-12-2023 | I39: 28-06-2024 | K39: On Hold | L39: 18 | M39: 4154.7 | N39: EMP0010
A40: PROJ039 | B40: Smart Grid System | C40: RetailPlus | D40: InfySoft Bhubaneswar | E40: AWS | F40: 52.99 | G40: 49.34 | H40: 23-02-2021 | I40: 18-09-2021 | K40: On Hold | L40: 14 | M40: 7275.9 | N40: EMP0429
A41: PROJ040 | B41: Inventory Tracker | C41: SportsPro | D41: TechNova Solutions | E41: Salesforce | F41: 38.03 | G41: 31.61 | H41: 03-07-2021 | I41: 09-02-2022 | K41: In Progress | L41: 11 | M41: 1228.3 | N41: EMP0279
A42: PROJ041 | B42: ML Fraud Detection | C42: SportsPro | D42: BlueLotus IT | E42: Data Engineering | F42: 93.95 | G42: 94.74 | H42: 01-07-2022 | I42: 12-11-2022 | K42: Cancelled | L42: 15 | M42: 7707.2 | N42: EMP0096
A43: PROJ042 | B43: E-Commerce Platform | C43: FinServPro | D43: ZeroOneSystems | E43: iOS Swift | F43: 183.85 | G43: 234.02 | H43: 14-03-2024 | I43: 22-08-2024 | K43: In Progress | L43: 9 | M43: 2621 | N43: EMP0337
A44: PROJ043 | B44: Talent Management | C44: EduSpark | D44: OdishaCode Labs | E44: React | F44: 23.27 | G44: 20.03 | H44: 19-10-2022 | I44: 04-08-2023 | K44: Cancelled | L44: 14 | M44: 2340.5 | N44: EMP0180
A45: PROJ044 | B45: Supply Chain Optimizer | C45: GlobalTrade Inc | D45: SambalpurNet | E45: Azure | F45: 59.86 | G45: 42.4 | H45: 09-06-2021 | I45: 08-05-2022 | K45: On Hold | L45: 4 | M45: 2436.2 | N45: EMP0499
A46: PROJ045 | B46: E-Commerce Platform | C46: InsureNow | D46: CoastalDev Studio | E46: AWS | F46: 166.14 | G46: 137.43 | H46: 23-07-2024 | I46: 28-04-2025 | K46: On Hold | L46: 24 | M46: 19549.7 | N46: EMP0371
A47: PROJ046 | B47: HR Automation Suite | C47: RetailPlus | D47: NilGiri Digitals | E47: DevOps/K8s | F47: 17 | G47: 19.66 | H47: 15-01-2024 | I47: 05-08-2024 | K47: Cancelled | L47: 16 | M47: 10245.3 | N47: EMP0447
A48: PROJ047 | B48: Inventory Tracker | C48: BankFirst Ltd | D48: TributeAI | E48: iOS Swift | F48: 151.97 | G48: 162.7 | H48: 15-12-2024 | I48: 01-11-2025 | K48: Under Review | L48: 5 | M48: 4070.4 | N48: EMP0216
A49: PROJ048 | B49: Data Warehouse Migration | C49: LogiTrack | D49: NilGiri Digitals | E49: Angular | F49: 165.98 | G49: 150.33 | H49: 31-05-2023 | I49: 02-10-2023 | K49: Under Review | L49: 23 | M49: 18188.4 | N49: EMP0003
A50: PROJ049 | B50: LMS Portal | C50: BankFirst Ltd | D50: SilverByte Systems | E50: DevOps/K8s | F50: 191.68 | G50: 192.46 | H50: 28-12-2024 | I50: 16-10-2025 | K50: On Hold | L50: 4 | M50: 1183.6 | N50: EMP0264
A51: PROJ050 | B51: Cloud Migration | C51: InsureNow | D51: KalingaTech Pvt Ltd | E51: Salesforce | F51: 22.2 | G51: 27.12 | H51: 12-10-2022 | I51: 20-12-2022 | K51: On Hold | L51: 24 | M51: 19237.2 | N51: EMP0142
A52: PROJ051 | B52: Inventory Tracker | C52: SmartCity Gov | D52: BlueLotus IT | E52: Data Engineering | F52: 187.09 | G52: 217.27 | H52: 06-05-2023 | I52: 31-12-2023 | J52: 17-12-2023 | K52: Completed | L52: 3 | M52: 1263.6 | N52: EMP0024
A53: PROJ052 | B53: Real-Time Reporting | C53: BankFirst Ltd | D53: TechNova Solutions | E53: Salesforce | F53: 189.62 | G53: 214.88 | H53: 27-04-2024 | I53: 13-02-2025 | K53: In Progress | L53: 22 | M53: 9937.5 | N53: EMP0337
A54: PROJ053 | B54: DigitalBank Portal | C54: MediCare Systems | D54: TechNova Solutions | E54: AWS | F54: 109.35 | G54: 101.38 | H54: 12-04-2022 | I54: 12-04-2023 | K54: On Hold | L54: 10 | M54: 8136.3 | N54: EMP0131
A55: PROJ054 | B55: IoT Gateway | C55: EduSpark | D55: NilGiri Digitals | E55: React | F55: 16.93 | G55: 21.91 | H55: 08-03-2022 | I55: 01-07-2022 | K55: Under Review | L55: 13 | M55: 11014.5 | N55: EMP0049
A56: PROJ055 | B56: Fleet Management | C56: FinServPro | D56: SilverByte Systems | E56: React | F56: 176.7 | G56: 159.98 | H56: 22-01-2022 | I56: 14-01-2023 | J56: 19-12-2022 | K56: Completed | L56: 9 | M56: 6364.8 | N56: EMP0215
A57: PROJ056 | B57: Talent Management | C57: RetailPlus | D57: CoastalDev Studio | E57: Java | F57: 9.9 | G57: 8.9 | H57: 17-01-2023 | I57: 22-09-2023 | K57: On Hold | L57: 25 | M57: 22353.9 | N57: EMP0152
A58: PROJ057 | B58: Analytics Dashboard | C58: TravelNest | D58: ZeroOneSystems | E58: AWS | F58: 79.99 | G58: 72.56 | H58: 26-06-2023 | I58: 30-05-2024 | K58: In Progress | L58: 9 | M58: 5178.9 | N58: EMP0595
A59: PROJ058 | B59: Data Warehouse Migration | C59: BankFirst Ltd | D59: InfySoft Bhubaneswar | E59: Salesforce | F59: 138 | G59: 103.18 | H59: 10-01-2024 | I59: 23-11-2024 | K59: Under Review | L59: 13 | M59: 9223.3 | N59: EMP0561
A60: PROJ059 | B60: E-Commerce Platform | C60: SmartCity Gov | D60: UtkalSoft Technologies | E60: iOS Swift | F60: 7.95 | G60: 9.6 | H60: 28-11-2022 | I60: 30-09-2023 | K60: In Progress | L60: 25 | M60: 19881.3 | N60: EMP0522
A61: PROJ060 | B61: Cloud Migration | C61: AutoDrive | D61: SilverByte Systems | E61: React | F61: 138.01 | G61: 102.5 | H61: 18-05-2024 | I61: 30-04-2025 | K61: Cancelled | L61: 13 | M61: 7864.1 | N61: EMP0536
A62: PROJ061 | B62: DigitalBank Portal | C62: AgroTech Farms | D62: ZeroOneSystems | E62: DevOps/K8s | F62: 62 | G62: 75.73 | H62: 19-11-2021 | I62: 30-06-2022 | K62: Cancelled | L62: 22 | M62: 10432.5 | N62: EMP0215
A63: PROJ062 | B63: Cloud Migration | C63: BankFirst Ltd | D63: UtkalSoft Technologies | E63: DevOps/K8s | F63: 129.58 | G63: 125.48 | H63: 02-12-2023 | I63: 18-09-2024 | K63: On Hold | L63: 3 | M63: 2207.2 | N63: EMP0566
A64: PROJ063 | B64: Smart Parking | C64: GlobalTrade Inc | D64: ZeroOneSystems | E64: AWS | F64: 177.78 | G64: 195.17 | H64: 17-09-2021 | I64: 09-12-2021 | K64: On Hold | L64: 14 | M64: 10283.3 | N64: EMP0600
A65: PROJ064 | B65: Cloud Migration | C65: EduSpark | D65: SilverByte Systems | E65: Salesforce | F65: 9.07 | G65: 8.52 | H65: 16-06-2022 | I65: 14-05-2023 | K65: On Hold | L65: 17 | M65: 15240.3 | N65: EMP0195
A66: PROJ065 | B66: Inventory Tracker | C66: RetailPlus | D66: KalingaTech Pvt Ltd | E66: Data Engineering | F66: 159.91 | G66: 191.06 | H66: 05-07-2022 | I66: 09-09-2022 | K66: Cancelled | L66: 9 | M66: 5475.2 | N66: EMP0588
A67: PROJ066 | B67: Fleet Management | C67: InsureNow | D67: TributeAI | E67: ML/AI | F67: 136.17 | G67: 105.19 | H67: 06-01-2022 | I67: 05-04-2022 | K67: In Progress | L67: 14 | M67: 6868.9 | N67: EMP0185
A68: PROJ067 | B68: HR Automation Suite | C68: PayQuick | D68: CoastalDev Studio | E68: Salesforce | F68: 162.07 | G68: 138.02 | H68: 14-09-2021 | I68: 22-06-2022 | J68: 12-08-2022 | K68: Completed | L68: 14 | M68: 6049.2 | N68: EMP0431
A69: PROJ068 | B69: HR Automation Suite | C69: GlobalTrade Inc | D69: ZeroOneSystems | E69: ML/AI | F69: 116.76 | G69: 106.01 | H69: 27-06-2023 | I69: 16-02-2024 | K69: Cancelled | L69: 13 | M69: 2705.9 | N69: EMP0026
A70: PROJ069 | B70: ML Fraud Detection | C70: InsureNow | D70: SilverByte Systems | E70: React | F70: 132.03 | G70: 98.38 | H70: 03-03-2023 | I70: 11-06-2023 | K70: Under Review | L70: 9 | M70: 2185 | N70: EMP0339
A71: PROJ070 | B71: Smart Grid System | C71: SportsPro | D71: InfySoft Bhubaneswar | E71: React | F71: 168.63 | G71: 167.85 | H71: 23-05-2021 | I71: 03-02-2022 | K71: Cancelled | L71: 24 | M71: 15758.1 | N71: EMP0216
A72: PROJ071 | B72: Fleet Management | C72: GreenEnergy Co | D72: InfySoft Bhubaneswar | E72: DevOps/K8s | F72: 62.87 | G72: 64.99 | H72: 20-09-2024 | I72: 19-03-2025 | J72: 08-04-2025 | K72: Completed | L72: 17 | M72: 3608 | N72: EMP0134
A73: PROJ072 | B73: Analytics Dashboard | C73: GreenEnergy Co | D73: SambalpurNet | E73: Angular | F73: 197.17 | G73: 194.12 | H73: 20-03-2021 | I73: 29-11-2021 | J73: 19-12-2021 | K73: Completed | L73: 3 | M73: 1332.1 | N73: EMP0243
A74: PROJ073 | B74: Cloud Migration | C74: AutoDrive | D74: UtkalSoft Technologies | E74: Android Kotlin | F74: 125.62 | G74: 93.39 | H74: 08-09-2021 | I74: 12-08-2022 | J74: 18-07-2022 | K74: Completed | L74: 3 | M74: 1401.9 | N74: EMP0027
A75: PROJ074 | B75: ERP Implementation | C75: FinServPro | D75: TributeAI | E75: DevOps/K8s | F75: 189.08 | G75: 192.83 | H75: 06-04-2021 | I75: 28-07-2021 | J75: 25-08-2021 | K75: Completed | L75: 3 | M75: 2063.6 | N75: EMP0401
A76: PROJ075 | B76: Real-Time Reporting | C76: PayQuick | D76: BlueLotus IT | E76: Flutter | F76: 127.81 | G76: 124.32 | H76: 17-01-2023 | I76: 03-11-2023 | K76: Under Review | L76: 2 | M76: 1618.2 | N76: EMP0231
A77: PROJ076 | B77: Cloud Migration | C77: AgroTech Farms | D77: SambalpurNet | E77: AWS | F77: 128.48 | G77: 147.78 | H77: 27-07-2022 | I77: 02-06-2023 | K77: Under Review | L77: 4 | M77: 3067.1 | N77: EMP0022
A78: PROJ077 | B78: Talent Management | C78: PayQuick | D78: TributeAI | E78: Salesforce | F78: 168.48 | G78: 139.92 | H78: 17-09-2023 | I78: 12-08-2024 | K78: On Hold | L78: 19 | M78: 12786.7 | N78: EMP0412
A79: PROJ078 | B79: Data Warehouse Migration | C79: SmartCity Gov | D79: InfySoft Bhubaneswar | E79: Flutter | F79: 5.87 | G79: 5.22 | H79: 15-03-2022 | I79: 21-08-2022 | K79: On Hold | L79: 8 | M79: 958.7 | N79: EMP0558
A80: PROJ079 | B80: Cloud Migration | C80: AgroTech Farms | D80: InfySoft Bhubaneswar | E80: React | F80: 9.57 | G80: 8.95 | H80: 18-08-2023 | I80: 12-04-2024 | K80: On Hold | L80: 10 | M80: 4573.4 | N80: EMP0208
A81: PROJ080 | B81: Talent Management | C81: GreenEnergy Co | D81: KalingaTech Pvt Ltd | E81: DevOps/K8s | F81: 143.73 | G81: 182.41 | H81: 08-03-2022 | I81: 01-02-2023 | K81: In Progress | L81: 12 | M81: 1974.4 | N81: EMP0483
A82: PROJ081 | B82: Smart Parking | C82: AgroTech Farms | D82: NilGiri Digitals | E82: Node.js | F82: 15.28 | G82: 18.42 | H82: 16-12-2022 | I82: 31-10-2023 | K82: In Progress | L82: 4 | M82: 1919 | N82: EMP0180
A83: PROJ082 | B83: Mobile Banking App | C83: InsureNow | D83: SilverByte Systems | E83: iOS Swift | F83: 10.69 | G83: 12.4 | H83: 19-04-2021 | I83: 28-10-2021 | K83: Under Review | L83: 22 | M83: 19607.1 | N83: EMP0014
A84: PROJ083 | B84: LMS Portal | C84: PayQuick | D84: CoastalDev Studio | E84: Android Kotlin | F84: 140.45 | G84: 107.36 | H84: 23-01-2023 | I84: 06-12-2023 | J84: 14-12-2023 | K84: Completed | L84: 11 | M84: 7278.4 | N84: EMP0238
A85: PROJ084 | B85: IoT Gateway | C85: InsureNow | D85: ZeroOneSystems | E85: Android Kotlin | F85: 99.32 | G85: 75.05 | H85: 01-10-2021 | I85: 15-07-2022 | J85: 12-09-2022 | K85: Completed | L85: 14 | M85: 7185.2 | N85: EMP0001
A86: PROJ085 | B86: ML Fraud Detection | C86: AgroTech Farms | D86: NilGiri Digitals | E86: iOS Swift | F86: 93.51 | G86: 88.77 | H86: 29-05-2023 | I86: 24-11-2023 | K86: On Hold | L86: 6 | M86: 1009.2 | N86: EMP0156
A87: PROJ086 | B87: AI Chatbot | C87: MediCare Systems | D87: NilGiri Digitals | E87: .NET | F87: 27.34 | G87: 19.34 | H87: 14-01-2021 | I87: 03-10-2021 | K87: Under Review | L87: 15 | M87: 7811.8 | N87: EMP0444
A88: PROJ087 | B88: Analytics Dashboard | C88: BankFirst Ltd | D88: KalingaTech Pvt Ltd | E88: .NET | F88: 177.84 | G88: 161.83 | H88: 27-05-2024 | I88: 01-01-2025 | K88: Cancelled | L88: 19 | M88: 10552.9 | N88: EMP0197
A89: PROJ088 | B89: Analytics Dashboard | C89: RetailPlus | D89: BlueLotus IT | E89: Java | F89: 66.91 | G89: 64.67 | H89: 17-02-2023 | I89: 18-01-2024 | K89: Under Review | L89: 20 | M89: 12241.3 | N89: EMP0504
A90: PROJ089 | B90: Mobile Banking App | C90: InsureNow | D90: TributeAI | E90: AWS | F90: 22.25 | G90: 23.94 | H90: 02-03-2023 | I90: 18-05-2023 | K90: In Progress | L90: 25 | M90: 5721.7 | N90: EMP0256
A91: PROJ090 | B91: DigitalBank Portal | C91: BankFirst Ltd | D91: KalingaTech Pvt Ltd | E91: Data Engineering | F91: 146.28 | G91: 179.79 | H91: 24-12-2022 | I91: 25-03-2023 | K91: Cancelled | L91: 22 | M91: 16468.6 | N91: EMP0360
A92: PROJ091 | B92: ML Fraud Detection | C92: TravelNest | D92: TributeAI | E92: Azure | F92: 147.04 | G92: 158.61 | H92: 01-04-2022 | I92: 11-08-2022 | K92: In Progress | L92: 3 | M92: 1861.2 | N92: EMP0500
A93: PROJ092 | B93: Smart Parking | C93: LogiTrack | D93: SambalpurNet | E93: Salesforce | F93: 86.62 | G93: 97.12 | H93: 11-01-2023 | I93: 04-09-2023 | K93: In Progress | L93: 9 | M93: 6691.3 | N93: EMP0518
A94: PROJ093 | B94: HR Automation Suite | C94: GreenEnergy Co | D94: OdishaCode Labs | E94: Android Kotlin | F94: 152.57 | G94: 169.36 | H94: 02-04-2024 | I94: 09-06-2024 | K94: Cancelled | L94: 7 | M94: 3766.2 | N94: EMP0522
A95: PROJ094 | B95: Real-Time Reporting | C95: GreenEnergy Co | D95: InfySoft Bhubaneswar | E95: Data Engineering | F95: 166.53 | G95: 207.35 | H95: 24-02-2021 | I95: 13-02-2022 | K95: Under Review | L95: 3 | M95: 1143.3 | N95: EMP0086
A96: PROJ095 | B96: Data Warehouse Migration | C96: EduSpark | D96: SilverByte Systems | E96: Angular | F96: 164.06 | G96: 135 | H96: 27-05-2022 | I96: 06-01-2023 | K96: Cancelled | L96: 18 | M96: 2681.8 | N96: EMP0535
A97: PROJ096 | B97: Talent Management | C97: InsureNow | D97: SilverByte Systems | E97: Angular | F97: 100.01 | G97: 87.7 | H97: 07-12-2024 | I97: 18-06-2025 | J97: 17-08-2025 | K97: Completed | L97: 15 | M97: 7065.2 | N97: EMP0148
A98: PROJ097 | B98: Fleet Management | C98: FinServPro | D98: SambalpurNet | E98: Angular | F98: 52.08 | G98: 55.74 | H98: 09-08-2022 | I98: 20-06-2023 | K98: On Hold | L98: 6 | M98: 3493 | N98: EMP0206
A99: PROJ098 | B99: LMS Portal | C99: MediCare Systems | D99: SambalpurNet | E99: Angular | F99: 106.89 | G99: 76.37 | H99: 31-07-2024 | I99: 26-12-2024 | K99: Under Review | L99: 12 | M99: 2200.8 | N99: EMP0173
A100: PROJ099 | B100: Smart Grid System | C100: GlobalTrade Inc | D100: UtkalSoft Technologies | E100: Angular | F100: 72.95 | G100: 74.1 | H100: 13-11-2021 | I100: 24-07-2022 | K100: In Progress | L100: 16 | M100: 7702.7 | N100: EMP0211
A101: PROJ100 | B101: E-Commerce Platform | C101: LogiTrack | D101: UtkalSoft Technologies | E101: Python | F101: 30.47 | G101: 35.38 | H101: 22-02-2024 | I101: 16-12-2024 | K101: Cancelled | L101: 14 | M101: 3896.9 | N101: EMP0008
A102: PROJ101 | B102: ML Fraud Detection | C102: TravelNest | D102: ZeroOneSystems | E102: iOS Swift | F102: 149.75 | G102: 128.3 | H102: 16-08-2023 | I102: 19-05-2024 | K102: On Hold | L102: 24 | M102: 5896.4 | N102: EMP0133
A103: PROJ102 | B103: Talent Management | C103: GreenEnergy Co | D103: UtkalSoft Technologies | E103: DevOps/K8s | F103: 69.56 | G103: 80.52 | H103: 25-04-2023 | I103: 22-04-2024 | K103: In Progress | L103: 4 | M103: 1925.3 | N103: EMP0074
A104: PROJ103 | B104: Mobile Banking App | C104: LogiTrack | D104: SambalpurNet | E104: Data Engineering | G104: 34.06 | H104: 03-11-2022 | I104: 15-05-2023 | K104: Cancelled | L104: 2 | M104: 1338.7 | N104: EMP0335
A105: PROJ104 | B105: DigitalBank Portal | C105: LogiTrack | D105: ZeroOneSystems | E105: Angular | F105: 138.18 | G105: 155.53 | H105: 31-03-2021 | I105: 02-02-2022 | K105: Cancelled | L105: 15 | M105: 5248.8 | N105: EMP0471
A106: PROJ105 | B106: ML Fraud Detection | C106: MediCare Systems | D106: UtkalSoft Technologies | E106: Data Engineering | F106: 53.7 | G106: 43.35 | H106: 12-06-2023 | I106: 03-09-2023 | K106: Cancelled | L106: 19 | M106: 13650 | N106: EMP0202
A107: PROJ106 | B107: Analytics Dashboard | C107: AutoDrive | D107: OdishaCode Labs | E107: Data Engineering | F107: 183.88 | G107: 214.92 | H107: 09-06-2022 | I107: 09-02-2023 | K107: In Progress | L107: 11 | M107: 8369.8 | N107: EMP0555
A108: PROJ107 | B108: Customer 360 View | C108: AgroTech Farms | D108: InfySoft Bhubaneswar | E108: Data Engineering | F108: 41.85 | G108: 38.45 | H108: 24-05-2022 | I108: 28-12-2022 | J108: 29-01-2023 | K108: Completed | L108: 15 | M108: 9902 | N108: EMP0362
A109: PROJ108 | B109: ML Fraud Detection | C109: SmartCity Gov | D109: KalingaTech Pvt Ltd | E109: Python | F109: 25.12 | G109: 29.12 | H109: 05-09-2024 | I109: 29-12-2024 | J109: 20-02-2025 | K109: Completed | L109: 5 | M109: 1671.6 | N109: EMP0474
A110: PROJ109 | B110: Smart Grid System | C110: InsureNow | D110: NilGiri Digitals | E110: Data Engineering | F110: 177.92 | G110: 191.73 | H110: 27-03-2024 | I110: 09-02-2025 | K110: In Progress | L110: 12 | M110: 6189.9 | N110: EMP0289
A111: PROJ110 | B111: DigitalBank Portal | C111: InsureNow | D111: TechNova Solutions | E111: Java | F111: 94.44 | G111: 70.27 | H111: 26-06-2023 | I111: 01-05-2024 | J111: 12-05-2024 | K111: Completed | L111: 14 | M111: 8648.4 | N111: EMP0347
A112: PROJ111 | B112: Talent Management | C112: GlobalTrade Inc | D112: TributeAI | E112: Python | F112: 137.82 | G112: 119.78 | H112: 26-09-2023 | I112: 11-09-2024 | K112: On Hold | L112: 2 | M112: 1659.4 | N112: EMP0003
A113: PROJ112 | B113: DigitalBank Portal | C113: SmartCity Gov | D113: UtkalSoft Technologies | E113: Salesforce | F113: 148.06 | G113: 118.44 | H113: 24-07-2024 | I113: 14-10-2024 | K113: Cancelled | L113: 10 | M113: 7624.9 | N113: EMP0399
A114: PROJ113 | B114: Analytics Dashboard | C114: GlobalTrade Inc | D114: OdishaCode Labs | E114: ML/AI | F114: 115.18 | G114: 112.73 | H114: 31-05-2022 | I114: 10-01-2023 | K114: In Progress | L114: 15 | M114: 9179.5 | N114: EMP0569
A115: PROJ114 | B115: Smart Parking | C115: AutoDrive | D115: InfySoft Bhubaneswar | E115: Android Kotlin | F115: 37.88 | G115: 39.02 | H115: 28-02-2023 | I115: 09-10-2023 | K115: Cancelled | L115: 7 | M115: 6247.9 | N115: EMP0045
A116: PROJ115 | B116: Fleet Management | C116: GlobalTrade Inc | D116: BlueLotus IT | E116: Salesforce | G116: 122.3 | H116: 04-09-2021 | I116: 30-07-2022 | K116: Under Review | L116: 18 | M116: 1994.5 | N116: EMP0254
A117: PROJ116 | B117: IoT Gateway | C117: SportsPro | D117: SilverByte Systems | E117: .NET | F117: 109.93 | G117: 112.97 | H117: 25-03-2023 | I117: 16-02-2024 | K117: Cancelled | L117: 22 | M117: 5020.4 | N117: EMP0159
A118: PROJ117 | B118: Data Warehouse Migration | C118: GlobalTrade Inc | D118: ZeroOneSystems | E118: Python | F118: 16.98 | G118: 20.63 | H118: 09-05-2021 | I118: 10-02-2022 | K118: Under Review | L118: 25 | M118: 5901.1 | N118: EMP0171
...

Sheet Attendance
A1: Employee_ID | B1: Record_ID | C1: Date | D1: Login_Time | E1: Logout_Time | F1: Work_Hours | G1: Status | H1: WFH_Flag
A2: EMP0076 | B2: ATT00001 | C2: 02-09-2024 | D2: 0.34791667 | E2: 14:21 | F2: 6.9 | G2: Present | H2: no
A3: EMP0076 | B3: ATT00002 | C3: 03-09-2024 | D3: 10:30 | E3: 17:30 | F3: 7.78 | G3: Present | H3: yes
A4: EMP0076 | B4: ATT00003 | C4: 04-09-2024 | G4: Absent | H4: no
A5: EMP0076 | B5: ATT00004 | C5: 05-09-2024 | D5: 08:40 | E5: 17:40 | F5: 9.99 | G5: Present | H5: no
A6: EMP0076 | B6: ATT00005 | C6: 06-09-2024 | D6: 09:22 | E6: 19:22 | F6: 10.75 | G6: Present | H6: Yes
A7: EMP0076 | B7: ATT00006 | C7: 09-09-2024 | D7: 09:57 | E7: 16:57 | F7: 7.23 | G7: Present | H7: no
A8: EMP0076 | B8: ATT00007 | C8: 10-09-2024 | D8: 10:02 | E8: 21:02 | F8: 11.44 | G8: Present | H8: yes
A9: EMP0076 | B9: ATT00008 | C9: 11-09-2024 | D9: 10:11 | E9: 16:11 | F9: 6.6 | G9: Present | H9: no
A10: EMP0076 | B10: ATT00009 | C10: 12-09-2024 | D10: 08:47 | E10: 17:47 | F10: 9.87 | G10: Present | H10: No
A11: EMP0076 | B11: ATT00010 | C11: 13-09-2024 | D11: 08:52 | E11: 14:52 | F11: 6.69 | G11: Present | H11: Yes
A12: EMP0076 | B12: ATT00011 | C12: 16-09-2024 | D12: 10:47 | E12: 19:47 | F12: 9.38 | G12: Present | H12: Yes
A13: EMP0076 | B13: ATT00012 | C13: 17-09-2024 | D13: 10:06 | E13: 20:06 | F13: 10.03 | G13: Present | H13: yes
A14: EMP0076 | B14: ATT00013 | C14: 18-09-2024 | D14: 08:51 | E14: 17:51 | F14: 9.92 | G14: Present | H14: Yes
A15: EMP0076 | B15: ATT00014 | C15: 19-09-2024 | D15: 10:55 | E15: 21:55 | F15: 11.21 | G15: Present | H15: Yes
A16: EMP0076 | B16: ATT00015 | C16: 20-09-2024 | D16: 10:08 | E16: 20:08 | F16: 10.73 | G16: Present | H16: No
... A18: EMP0076 | B18: ATT00017 | C18: 24-09-2024 | D18: 09:39 | E18: 17:39 | F18: 8.28 | G18: Present | H18: No
A19: EMP0076 | B19: ATT00018 | C19: 25-09-2024 | G19: Half Day | H19: no
A20: EMP0076 | B20: ATT00019 | C20: 26-09-2024 | D20: 08:30 | E20: 19:30 | F20: 11.18 | G20: Present | H20: no
A21: EMP0076 | B21: ATT00020 | C21: 27-09-2024 | D21: 09:53 | E21: 16:53 | F21: 7.89 | G21: Present | H21: Yes
A22: EMP0076 | B22: ATT00021 | C22: 30-09-2024 | D22: 08:21 | E22: 18:21 | F22: 10.33 | G22: Present | H22: No
A23: EMP0076 | B23: ATT00022 | C23: 01-10-2024 | D23: 09:09 | E23: 16:09 | F23: 7.45 | G23: Present | H23: no
A24: EMP0076 | B24: ATT00023 | C24: 02-10-2024 | D24: 09:39 | E24: 18:39 | F24: 9.82 | G24: Present | H24: no
A25: EMP0076 | B25: ATT00024 | C25: 03-10-2024 | D25: 08:00 | E25: 17:00 | F25: 9.05 | G25: Present | H25: No
A26: EMP0076 | B26: ATT00025 | C26: 04-10-2024 | D26: 08:32 | E26: 15:32 | F26: 7.62 | G26: Present | H26: yes
A27: EMP0076 | B27: ATT00026 | C27: 07-10-2024 | D27: 10:55 | E27: 17:55 | F27: 7.45 | G27: Present | H27: Yes
A28: EMP0076 | B28: ATT00027 | C28: 08-10-2024 | D28: 09:36 | E28: 18:36 | F28: 9.31 | G28: Present | H28: No
A29: EMP0076 | B29: ATT00028 | C29: 2024/10/09 | D29: 09:05 | E29: 17:05 | F29: 8.44 | G29: Present | H29: No
A30: EMP0076 | B30: ATT00029 | C30: 10-10-2024 | D30: 09:52 | E30: 16:52 | F30: 7.26 | G30: Present | H30: yes
A31: EMP0076 | B31: ATT00030 | C31: 11-10-2024 | D31: 10:08 | E31: 20:08 | F31: 10.71 | G31: Present | H31: no
... A56: EMP0061 | B56: ATT00055 | C56: 17-09-2024 | D56: 10:59 | E56: 16:59 | F56: 6.51 | G56: Present | H56: Yes
A57: EMP0061 | B57: ATT00056 | C57: 18-09-2024 | G57: Leave | H57: Yes
A58: EMP0061 | B58: ATT00057 | C58: 19-09-2024 | D58: 10:05 | E58: 17:05 | F58: 7.08 | G58: Present | H58: No
A59: EMP0061 | B59: ATT00058 | C59: 20-09-2024 | D59: 08:32 | E59: 15:32 | F59: 7.7 | G59: Present | H59: Yes
A60: EMP0061 | B60: ATT00059 | C60: 23-09-2024 | D60: 09:00 | E60: 18:00 | F60: 9.57 | G60: Present | H60: no
A61: EMP0061 | B61: ATT00060 | C61: 24-09-2024 | D61: 10:33 | E61: 20:33 | F61: 10.48 | G61: Present | H61: Yes
A62: EMP0061 | B62: ATT00061 | C62: 25-09-2024 | D62: 09:05 | E62: 17:05 | F62: 8.99 | G62: Present | H62: no
A63: EMP0061 | B63: ATT00062 | C63: 26-09-2024 | D63: 09:57 | E63: 16:57 | F63: 7.9 | G63: Present | H63: yes
A64: EMP0061 | B64: ATT00063 | C64: 27-09-2024 | D64: 10:57 | E64: 20:57 | F64: 10.09 | G64: Present | H64: no
A65: EMP0061 | B65: ATT00064 | C65: 30-09-2024 | D65: 08:08 | E65: 19:08 | F65: 11.43 | G65: Present | H65: no
A66: EMP0061 | B66: ATT00065 | C66: 01-10-2024 | D66: 08:01 | E66: 18:01 | F66: 10.4 | G66: Present | H66: Yes
A67: EMP0061 | B67: ATT00066 | C67: 02-10-2024 | D67: 09:01 | E67: 16:01 | F67: 7.4 | G67: Present | H67: yes
A68: EMP0061 | B68: ATT00067 | C68: 03-10-2024 | D68: 09:22 | E68: 18:22 | F68: 9.42 | G68: Present | H68: Yes
A69: EMP0061 | B69: ATT00068 | C69: 04-10-2024 | D69: 10:20 | E69: 19:20 | F69: 9.04 | G69: Present | H69: no
... A76: EMP0061 | B76: ATT00075 | C76: 15-10-2024 | D76: 08:06 | E76: 15:06 | F76: 7.59 | G76: Present | H76: yes
A77: EMP0061 | B77: ATT00076 | C77: 16-10-2024 | G77: Half Day | H77: No
A78: EMP0061 | B78: ATT00077 | C78: 17-10-2024 | D78: 10:59 | E78: 17:59 | F78: 7.29 | G78: Present | H78: No
A79: EMP0061 | B79: ATT00078 | C79: 18-10-2024 | D79: 10:42 | E79: 16:42 | F79: 6.85 | G79: Present | H79: No
A80: EMP0061 | B80: ATT00079 | C80: 21-10-2024 | D80: 09:31 | E80: 15:31 | F80: 6.52 | G80: Present | H80: no
A81: EMP0061 | B81: ATT00080 | C81: 22-10-2024 | D81: 08:24 | E81: 16:24 | F81: 8.64 | G81: Present | H81: yes
A82: EMP0061 | B82: ATT00081 | C82: 23-10-2024 | D82: 10:28 | E82: 17:28 | F82: 7.3 | G82: Present | H82: yes
A83: EMP0061 | B83: ATT00082 | C83: 24-10-2024 | D83: 09:54 | E83: 18:54 | F83: 9.26 | G83: Present | H83: No
A84: EMP0061 | B84: ATT00083 | C84: 25-10-2024 | D84: 09:16 | E84: 20:16 | F84: 11.08 | G84: Present | H84: yes
A85: EMP0061 | B85: ATT00084 | C85: 28-10-2024 | G85: Absent | H85: no
A86: EMP0061 | B86: ATT00085 | C86: 29-10-2024 | D86: 08:47 | E86: 19:47 | F86: 11.4 | G86: Present | H86: no
A87: EMP0061 | B87: ATT00086 | C87: 30-10-2024 | D87: 08:33 | E87: 15:33 | F87: 7.79 | G87: Present | H87: no
A88: EMP0470 | B88: ATT00087 | C88: 02-09-2024 | D88: 08:38 | E88: 18:38 | F88: 10.47 | G88: Present | H88: No
A89: EMP0470 | B89: ATT00088 | C89: 03-09-2024 | D89: 10:45 | E89: 20:45 | F89: 10.83 | G89: Present | H89: yes
A90: EMP0470 | B90: ATT00089 | C90: 04-09-2024 | D90: 08:01 | E90: 16:01 | F90: 8.83 | G90: Present | H90: Yes
A91: EMP0470 | B91: ATT00090 | C91: 05-09-2024 | D91: 09:45 | E91: 17:45 | F91: 8.98 | G91: Present | H91: no
A92: EMP0470 | B92: ATT00091 | C92: 06-09-2024 | D92: 08:22 | E92: 18:22 | F92: 10.05 | G92: Present | H92: No
A93: EMP0470 | B93: ATT00092 | C93: 09-09-2024 | D93: 08:59 | E93: 18:59 | F93: 10.55 | G93: Present | H93: Yes
A94: EMP0470 | B94: ATT00093 | C94: 10-09-2024 | D94: 10:09 | E94: 19:09 | F94: 9.73 | G94: Present | H94: yes
A95: EMP0470 | B95: ATT00094 | C95: 11-09-2024 | D95: 08:32 | E95: 18:32 | F95: 10.39 | G95: Present | H95: Yes
A96: EMP0470 | B96: ATT00095 | C96: 2024/09/12 | D96: 09:48 | E96: 17:48 | F96: 8.04 | G96: Present | H96: yes
A97: EMP0470 | B97: ATT00096 | C97: 13-09-2024 | D97: 09:14 | E97: 16:14 | F97: 7.16 | G97: Present | H97: No
... A129: EMP0470 | B129: ATT00128 | C129: 29-10-2024 | D129: 08:09 | E129: 19:09 | F129: 11.48 | G129: Present | H129: yes
A130: EMP0470 | B130: ATT00129 | C130: 30-10-2024 | G130: Leave | H130: no
A131: EMP0042 | B131: ATT00130 | C131: 02-09-2024 | D131: 09:44 | E131: 18:44 | F131: 9.64 | G131: Present | H131: Yes
A132: EMP0042 | B132: ATT00131 | C132: 03-09-2024 | D132: 09:25 | E132: 19:25 | F132: 10.99 | G132: Present | H132: yes
A133: EMP0042 | B133: ATT00132 | C133: 04-09-2024 | D133: 08:31 | E133: 16:31 | F133: 8.7 | G133: Present | H133: no
A134: EMP0042 | B134: ATT00133 | C134: 05-09-2024 | D134: 09:28 | E134: 16:28 | F134: 7.47 | G134: Present | H134: Yes
A135: EMP0042 | B135: ATT00134 | C135: 06-09-2024 | D135: 09:07 | E135: 17:07 | F135: 8.52 | G135: Present | H135: Yes
A136: EMP0042 | B136: ATT00135 | C136: 09-09-2024 | D136: 08:24 | E136: 18:24 | F136: 10.72 | G136: Present | H136: No
A137: EMP0042 | B137: ATT00136 | C137: 10-09-2024 | D137: 10:31 | E137: 17:31 | F137: 7.96 | G137: Present | H137: No
A138: EMP0042 | B138: ATT00137 | C138: 11-09-2024 | D138: 10:44 | E138: 18:44 | F138: 8.49 | G138: Present | H138: no
A139: EMP0042 | B139: ATT00138 | C139: 12-09-2024 | D139: 10:07 | E139: 18:07 | F139: 8.05 | G139: Present | H139: no
A140: EMP0042 | B140: ATT00139 | C140: 13-09-2024 | D140: 10:33 | E140: 19:33 | F140: 9.72 | G140: Present | H140: no
A141: EMP0042 | B141: ATT00140 | C141: 16-09-2024 | D141: 09:11 | E141: 15:11 | F141: 6.88 | G141: Present | H141: No
A142: EMP0042 | B142: ATT00141 | C142: 17-09-2024 | D142: 09:36 | E142: 18:36 | F142: 9.65 | G142: Present | H142: No
... A175: EMP0282 | B175: ATT00174 | C175: 03-09-2024 | D175: 09:31 | E175: 15:31 | F175: 6.89 | G175: Present | H175: Yes
A176: EMP0282 | B176: ATT00175 | C176: 04-09-2024 | G176: Absent | H176: Yes
A177: EMP0282 | B177: ATT00176 | C177: 05-09-2024 | D177: 08:00 | E177: 16:00 | F177: 8.13 | G177: Present | H177: yes
A178: EMP0282 | B178: ATT00177 | C178: 06-09-2024 | D178: 10:01 | E178: 20:01 | F178: 10 | G178: Present | H178: No
A179: EMP0282 | B179: ATT00178 | C179: 09-09-2024 | D179: 09:13 | E179: 17:13 | F179: 8.58 | G179: Present | H179: yes
A180: EMP0282 | B180: ATT00179 | C180: 10-09-2024 | D180: 08:11 | E180: 18:11 | F180: 10.91 | G180: Present | H180: Yes
A181: EMP0282 | B181: ATT00180 | C181: 11-09-2024 | D181: 09:17 | E181: 18:17 | F181: 9.6 | G181: Present | H181: No
A182: EMP0282 | B182: ATT00181 | C182: 12-09-2024 | D182: 10:30 | E182: 21:30 | F182: 11.34 | G182: Present | H182: no
A183: EMP0282 | B183: ATT00182 | C183: 13-09-2024 | D183: 10:51 | E183: 19:51 | F183: 9.51 | G183: Present | H183: Yes
A184: EMP0282 | B184: ATT00183 | C184: 2024/09/16 | D184: 09:04 | E184: 17:04 | F184: 8.58 | G184: Present | H184: No
A185: EMP0282 | B185: ATT00184 | C185: 2024/09/17 | D185: 09:36 | E185: 18:36 | F185: 9.67 | G185: Present | H185: no
A186: EMP0282 | B186: ATT00185 | C186: 18-09-2024 | D186: 10:01 | E186: 21:01 | F186: 11.44 | G186: Present | H186: no
A187: EMP0282 | B187: ATT00186 | C187: 19-09-2024 | D187: 08:06 | E187: 16:06 | F187: 8.2 | G187: Present | H187: No
A188: EMP0282 | B188: ATT00187 | C188: 20-09-2024 | D188: 09:01 | E188: 16:01 | F188: 7.96 | G188: Present | H188: yes
... A228: EMP0212 | B228: ATT00227 | C228: 17-09-2024 | D228: 10:03 | E228: 17:03 | F228: 7.5 | G228: Present | H228: Yes
A229: EMP0212 | B229: ATT00228 | C229: 18-09-2024 | G229: Leave | H229: yes
A230: EMP0212 | B230: ATT00229 | C230: 19-09-2024 | D230: 10:04 | E230: 17:04 | F230: 7.66 | G230: Present | H230: No
A231: EMP0212 | B231: ATT00230 | C231: 20-09-2024 | D231: 09:31 | E231: 15:31 | F231: 6.63 | G231: Present | H231: no
A232: EMP0212 | B232: ATT00231 | C232: 23-09-2024 | D232: 09:59 | E232: 15:59 | F232: 6.75 | G232: Present | H232: yes
A233: EMP0212 | B233: ATT00232 | C233: 24-09-2024 | D233: 09:47 | E233: 19:47 | F233: 10.85 | G233: Present | H233: Yes
...

Sheet Hiring
A1: Candidate_ID | B1: Full_Name | C1: Applied_Role | D1: Department | F1: Source | H1: Interview_Round1_Score | I1: Interview_Round2_Score | J1: Final_Score | K1: Expected_Salary | L1: Offered_Salary | M1: Offer_Status | N1: Interview_Date | O1: Company | P1: Years_Experience
A2: CAND0001 | B2: Abhishek Ratha | C2: Product Manager | D2: Data Science | E2: =PROPER(D2) -> Data Science | F2: Job Portal | G2: =PROPER(F2) -> Job Portal | H2: 3.8 | I2: 7.9 | J2: 5.8 | K2: 123018 | L2: 135000 | M2: Pending | N2: 08-04-2024 | O2: SambalpurNet | P2: 4.7
A3: CAND0002 | B3: Bikash Behura | C3: DevOps Engineer | D3: Data Science | E3: =PROPER(D3) -> Data Science | F3: LinkedIn | G3: =PROPER(F3) -> Linkedin | H3: 3.1 | I3: 3.3 | J3: 3.2 | K3: 139712 | L3: 132960 | M3: Accepted | N3: 27-05-2024 | O3: TechNova Solutions | P3: 5.7
A4: CAND0003 | B4: Ankita Behura | C4: HR Executive | D4: Engineering | E4: =PROPER(D4) -> Engineering | F4: linkedin | G4: =PROPER(F4) -> Linkedin | H4: 4.1 | I4: 6.7 | J4: 5.4 | K4: 26013 | L4: 28384 | M4: Pending | N4: 18-09-2024 | O4: TechNova Solutions | P4: 14.5
A5: CAND0004 | B5: Sudhansu Prusty | C5: DevOps Engineer | D5: HR | E5: =PROPER(D5) -> Hr | F5: Campus | G5: =PROPER(F5) -> Campus | H5: 3.5 | I5: 8.8 | J5: 6.2 | K5: 176914 | L5: 170600 | M5: Pending | N5: 11-12-2023 | O5: CoastalDev Studio | P5: 11.7
A6: CAND0005 | B6: Puspita Pattnaik | C6: QA Engineer | D6: DevOps | E6: =PROPER(D6) -> Devops | F6: LinkedIn | G6: =PROPER(F6) -> Linkedin | H6: 3.1 | I6: 7.9 | J6: 5.5 | K6: 155983 | L6: 164134 | M6: Withdrawn | N6: 13-12-2024 | O6: OdishaCode Labs | P6: 7
A7: CAND0006 | B7: Soumya Senapati | C7: Product Manager | D7: Sales | E7: =PROPER(D7) -> Sales | F7: Walk-in | G7: =PROPER(F7) -> Walk-In | H7: 4.3 | I7: 9.6 | J7: 6.9 | K7: 37894 | L7: 39365 | M7: Accepted | N7: 28-04-2023 | O7: SambalpurNet | P7: 4.3
A8: CAND0007 | B8: Satyajit Padhi | C8: DevOps Engineer | D8: Product | E8: =PROPER(D8) -> Product | F8: LinkedIn | G8: =PROPER(F8) -> Linkedin | I8: 8.5 | K8: 164283 | L8: 170751 | M8: Accepted | N8: 01-02-2023 | O8: UtkalSoft Technologies | P8: 11
A9: CAND0008 | B9: Sudhansu Biswal | C9: Cloud Architect | D9: Data Science | E9: =PROPER(D9) -> Data Science | F9: Job Portal | G9: =PROPER(F9) -> Job Portal | H9: 8.1 | I9: 4.2 | J9: 6.2 | K9: 86255 | M9: Rejected | N9: 23-09-2024 | O9: ZeroOneSystems | P9: 13
A10: CAND0009 | B10: Smita Sahu | C10: HR Executive | D10: DevOps | E10: =PROPER(D10) -> Devops | F10: linkedin | G10: =PROPER(F10) -> Linkedin | H10: 4.3 | I10: 4.8 | J10: 4.5 | K10: 24144 | L10: 25381 | M10: Accepted | N10: 18-05-2023 | O10: BlueLotus IT | P10: 8.8
A11: CAND0010 | B11: Nirmal Ratha | C11: Business Analyst | D11: QA | E11: =PROPER(D11) -> Qa | F11: Campus | G11: =PROPER(F11) -> Campus | H11: 7.5 | I11: 6.9 | J11: 7.2 | K11: 191563 | M11: Withdrawn | N11: 28-08-2024 | O11: ZeroOneSystems | P11: 5.9
A12: CAND0011 | B12: Nirmal Padhi | C12: Product Manager | D12: DevOps | E12: =PROPER(D12) -> Devops | F12: Campus | G12: =PROPER(F12) -> Campus | H12: 7.4 | I12: 3.3 | J12: 5.3 | K12: 170124 | L12: 160467 | M12: Accepted | N12: 13-10-2024 | O12: KalingaTech Pvt Ltd | P12: 9
A13: CAND0012 | B13: Nirmal Padhi | C13: Product Manager | D13: QA | E13: =PROPER(D13) -> Qa | F13: linkedin | G13: =PROPER(F13) -> Linkedin | H13: 9.6 | I13: 9.1 | J13: 9.3 | K13: 108417 | L13: 122402 | M13: Negotiating | N13: 20-10-2024 | O13: TributeAI | P13: 6.5
A14: CAND0013 | B14: Tapas Dhal | C14: Sales Manager | D14: DevOps | E14: =PROPER(D14) -> Devops | F14: LinkedIn | G14: =PROPER(F14) -> Linkedin | H14: 8.8 | I14: 8.6 | J14: 8.7 | L14: 166699 | M14: Pending | N14: 13-07-2023 | O14: SambalpurNet | P14: 11.2
A15: CAND0014 | B15: Abhishek Prusty | C15: Sales Manager | D15: Product | E15: =PROPER(D15) -> Product | F15: Naukri | G15: =PROPER(F15) -> Naukri | H15: 7 | I15: 8.8 | J15: 7.9 | K15: 144314 | L15: 135340 | M15: Rejected | N15: 02-09-2023 | O15: NilGiri Digitals | P15: 7.6
A16: CAND0015 | B16: Smita Prusty | C16: Software Engineer | D16: DevOps | E16: =PROPER(D16) -> Devops | F16: LinkedIn | G16: =PROPER(F16) -> Linkedin | H16: 3.1 | I16: 8.5 | J16: 5.8 | M16: Accepted | N16: 13-03-2023 | O16: TechNova Solutions | P16: 9.8
A17: CAND0016 | B17: Ankita Choudhury | C17: Sales Manager | D17: HR | E17: =PROPER(D17) -> Hr | F17: linkedin | G17: =PROPER(F17) -> Linkedin | H17: 9 | I17: 4.8 | J17: 6.9 | K17: 75018 | L17: 70245 | M17: Accepted | N17: 08-12-2023 | O17: SilverByte Systems | P17: 4.9
A18: CAND0017 | B18: Sudhansu Sahu | C18: HR Executive | D18: Design | E18: =PROPER(D18) -> Design | F18: LinkedIn | G18: =PROPER(F18) -> Linkedin | H18: 4 | I18: 4 | J18: 4 | K18: 134338 | L18: 151435 | M18: Accepted | N18: 27-08-2023 | O18: ZeroOneSystems | P18: 10
A19: CAND0018 | B19: Tanmay Padhi | C19: Business Analyst | D19: Engineering | E19: =PROPER(D19) -> Engineering | F19: naukri | G19: =PROPER(F19) -> Naukri | H19: 8.8 | I19: 6.4 | J19: 7.6 | K19: 75363 | M19: Pending | N19: 29-10-2023 | O19: OdishaCode Labs | P19: 8.2
A20: CAND0019 | B20: Chinmaya Mishra | C20: DevOps Engineer | D20: Finance | E20: =PROPER(D20) -> Finance | F20: naukri | G20: =PROPER(F20) -> Naukri | H20: 4.5 | I20: 4.4 | J20: 4.5 | K20: 60126 | M20: Rejected | N20: 08-05-2024 | O20: InfySoft Bhubaneswar | P20: 5
A21: CAND0020 | B21: Dibya Routray | C21: Cloud Architect | D21: Product | E21: =PROPER(D21) -> Product | F21: LinkedIn | G21: =PROPER(F21) -> Linkedin | H21: 5.5 | I21: 7.3 | J21: 6.4 | K21: 67215 | L21: 58147 | M21: Rejected | N21: 11-09-2023 | O21: TechNova Solutions | P21: 0.9
A22: CAND0021 | B22: Ankita Prusty | C22: Business Analyst | D22: Engineering | E22: =PROPER(D22) -> Engineering | F22: Walk-in | G22: =PROPER(F22) -> Walk-In | H22: 8.5 | I22: 7.6 | J22: 8.1 | K22: 113954 | M22: Rejected | N22: 14-05-2024 | O22: NilGiri Digitals | P22: 11.7
A23: CAND0022 | B23: Satyajit Pattnaik | C23: Sales Manager | D23: Marketing | E23: =PROPER(D23) -> Marketing | F23: Job Portal | G23: =PROPER(F23) -> Job Portal | H23: 6.5 | I23: 9.1 | J23: 7.8 | K23: 183795 | L23: 208454 | M23: Accepted | N23: 26-07-2023 | O23: OdishaCode Labs | P23: 4.8
A24: CAND0023 | B24: Rahul Nanda | C24: Product Manager | D24: Sales | E24: =PROPER(D24) -> Sales | F24: Naukri | G24: =PROPER(F24) -> Naukri | H24: 5.5 | I24: 8.6 | J24: 7 | K24: 64504 | M24: Pending | N24: 26-11-2023 | O24: BlueLotus IT | P24: 11.4
A25: CAND0024 | B25: Rajan Dhal | C25: Product Manager | D25: Finance | E25: =PROPER(D25) -> Finance | F25: Naukri | G25: =PROPER(F25) -> Naukri | H25: 3.8 | I25: 5.5 | J25: 4.7 | K25: 196050 | L25: 225137 | M25: Accepted | N25: 05-04-2024 | O25: KalingaTech Pvt Ltd | P25: 8.7
A26: CAND0025 | B26: Puspita Dhal | C26: Sales Manager | D26: Sales | E26: =PROPER(D26) -> Sales | F26: linkedin | G26: =PROPER(F26) -> Linkedin | H26: 6.7 | I26: 3.7 | J26: 5.2 | K26: 66622 | L26: 66872 | M26: Rejected | N26: 03-04-2024 | O26: KalingaTech Pvt Ltd | P26: 5.1
A27: CAND0026 | B27: Ankita Mishra | C27: HR Executive | D27: Marketing | E27: =PROPER(D27) -> Marketing | F27: Referral | G27: =PROPER(F27) -> Referral | H27: 3.1 | I27: 4.3 | J27: 3.7 | K27: 60845 | L27: 66284 | M27: Negotiating | N27: 23-10-2023 | O27: SilverByte Systems | P27: 5.9
A28: CAND0027 | B28: Namita Biswal | C28: QA Engineer | D28: QA | E28: =PROPER(D28) -> Qa | F28: Job Portal | G28: =PROPER(F28) -> Job Portal | H28: 3.4 | I28: 9 | J28: 6.2 | K28: 129397 | L28: 117989 | M28: Accepted | N28: 21-09-2023 | O28: OdishaCode Labs | P28: 11.7
A29: CAND0028 | B29: Ranjit Parida | C29: DevOps Engineer | D29: DevOps | E29: =PROPER(D29) -> Devops | F29: Campus | G29: =PROPER(F29) -> Campus | H29: 4.2 | I29: 5.2 | J29: 4.7 | K29: 199530 | M29: Pending | N29: 30-11-2024 | O29: KalingaTech Pvt Ltd | P29: 9.2
A30: CAND0029 | B30: Namita Behura | C30: HR Executive | D30: DevOps | E30: =PROPER(D30) -> Devops | F30: Naukri | G30: =PROPER(F30) -> Naukri | H30: 6.6 | I30: 4.2 | J30: 5.4 | K30: 169961 | L30: 185498 | M30: Accepted | N30: 24-09-2024 | O30: SilverByte Systems | P30: 11.6
A31: CAND0030 | B31: Soumya Prusty | C31: Sales Manager | D31: Sales | E31: =PROPER(D31) -> Sales | F31: Job Portal | G31: =PROPER(F31) -> Job Portal | H31: 8.5 | I31: 5.5 | J31: 7 | K31: 131761 | L31: 125277 | M31: Negotiating | N31: 17-06-2023 | O31: TechNova Solutions | P31: 11.3
A32: CAND0031 | B32: Nirmal Mishra | C32: QA Engineer | D32: Sales | E32: =PROPER(D32) -> Sales | F32: naukri | G32: =PROPER(F32) -> Naukri | H32: 9.7 | I32: 8.8 | J32: 9.2 | K32: 180507 | L32: 193212 | M32: Accepted | N32: 02-04-2023 | O32: SilverByte Systems | P32: 6.8
A33: CAND0032 | B33: Subhasree Parida | C33: Cloud Architect | D33: Data Science | E33: =PROPER(D33) -> Data Science | F33: Referral | G33: =PROPER(F33) -> Referral | H33: 3.8 | I33: 6.2 | J33: 5 | K33: 158520 | L33: 151325 | M33: Pending | N33: 10-03-2023 | O33: KalingaTech Pvt Ltd | P33: 4.3
A34: CAND0033 | B34: Debasmita Mohapatra | C34: Product Manager | D34: Design | E34: =PROPER(D34) -> Design | F34: Campus | G34: =PROPER(F34) -> Campus | H34: 9.8 | I34: 8.5 | J34: 9.2 | K34: 125983 | L34: 129695 | M34: Negotiating | N34: 21-05-2023 | O34: ZeroOneSystems | P34: 6.3
A35: CAND0034 | B35: Ipsita Behura | C35: Sales Manager | D35: Sales | E35: =PROPER(D35) -> Sales | F35: LinkedIn | G35: =PROPER(F35) -> Linkedin | H35: 4.5 | J35: 4.5 | K35: 103827 | L35: 117799 | M35: Rejected | N35: 26-12-2024 | O35: SilverByte Systems | P35: 9.8
A36: CAND0035 | B36: Lipsa Tripathy | C36: Data Analyst | D36: HR | E36: =PROPER(D36) -> Hr | F36: naukri | G36: =PROPER(F36) -> Naukri | H36: 7.7 | I36: 5.9 | J36: 6.8 | K36: 131980 | M36: Withdrawn | N36: 09-04-2024 | O36: UtkalSoft Technologies | P36: 13.5
A37: CAND0036 | B37: Rajan Routray | C37: UI Designer | D37: Marketing | E37: =PROPER(D37) -> Marketing | F37: naukri | G37: =PROPER(F37) -> Naukri | H37: 5.3 | I37: 9.5 | J37: 7.4 | K37: 83588 | L37: 91424 | M37: Withdrawn | N37: 18-04-2024 | O37: SilverByte Systems | P37: 4.8
A38: CAND0037 | B38: Subhasree Padhi | C38: HR Executive | D38: Engineering | E38: =PROPER(D38) -> Engineering | F38: LinkedIn | G38: =PROPER(F38) -> Linkedin | H38: 6.1 | I38: 6.2 | J38: 6.2 | K38: 139840 | L38: 125731 | M38: Rejected | N38: 24-10-2024 | O38: CoastalDev Studio | P38: 11.7
A39: CAND0038 | B39: Amlan Biswal | C39: UI Designer | D39: Sales | E39: =PROPER(D39) -> Sales | F39: Referral | G39: =PROPER(F39) -> Referral | H39: 7.9 | I39: 3.3 | J39: 5.6 | K39: 100081 | L39: 89054 | M39: Negotiating | N39: 06-07-2024 | O39: CoastalDev Studio | P39: 3.9
A40: CAND0039 | B40: Subhasree Sahu | C40: Cloud Architect | D40: Sales | E40: =PROPER(D40) -> Sales | F40: Campus | G40: =PROPER(F40) -> Campus | H40: 5.7 | I40: 3.9 | J40: 4.8 | M40: Negotiating | N40: 05-01-2024 | O40: BlueLotus IT | P40: 0.7
A41: CAND0040 | B41: Lipsa Prusty | C41: Data Analyst | D41: Data Science | E41: =PROPER(D41) -> Data Science | F41: Campus | G41: =PROPER(F41) -> Campus | H41: 7 | I41: 6.2 | J41: 6.6 | K41: 184893 | L41: 192973 | M41: Accepted | N41: 19-10-2024 | O41: ZeroOneSystems | P41: 9.2
A42: CAND0041 | B42: Namita Tripathy | C42: Business Analyst | D42: Finance | E42: =PROPER(D42) -> Finance | F42: linkedin | G42: =PROPER(F42) -> Linkedin | H42: 6.6 | I42: 7.9 | J42: 7.2 | K42: 94557 | M42: Rejected | N42: 19-07-2024 | O42: NilGiri Digitals | P42: 0.6
A43: CAND0042 | B43: Lipsa Mohapatra | C43: QA Engineer | D43: DevOps | E43: =PROPER(D43) -> Devops | F43: Referral | G43: =PROPER(F43) -> Referral | H43: 5.1 | I43: 3.6 | J43: 4.3 | K43: 145379 | L43: 144200 | M43: Pending | N43: 29-07-2024 | O43: CoastalDev Studio | P43: 6.3
A44: CAND0043 | B44: Sangita Parida | C44: HR Executive | D44: HR | E44: =PROPER(D44) -> Hr | F44: LinkedIn | G44: =PROPER(F44) -> Linkedin | H44: 4.5 | I44: 4.4 | J44: 4.5 | K44: 155745 | M44: Withdrawn | N44: 29-09-2023 | O44: InfySoft Bhubaneswar | P44: 9.5
A45: CAND0044 | B45: Debasmita Parida | C45: Sales Manager | D45: QA | E45: =PROPER(D45) -> Qa | F45: naukri | G45: =PROPER(F45) -> Naukri | H45: 4.8 | I45: 6.1 | J45: 5.4 | K45: 195587 | M45: Negotiating | N45: 03-08-2023 | O45: BlueLotus IT | P45: 8.7
A46: CAND0045 | B46: Priyanka Jena | C46: Software Engineer | D46: Design | E46: =PROPER(D46) -> Design | F46: Job Portal | G46: =PROPER(F46) -> Job Portal | H46: 3.3 | I46: 6 | J46: 4.7 | K46: 172657 | L46: 163716 | M46: Rejected | N46: 24-08-2024 | O46: CoastalDev Studio | P46: 7.2
A47: CAND0046 | B47: Ipsita Sahu | C47: Data Analyst | D47: Finance | E47: =PROPER(D47) -> Finance | F47: Naukri | G47: =PROPER(F47) -> Naukri | H47: 5.9 | J47: 5.9 | K47: 61815 | L47: 66009 | M47: Accepted | N47: 30-01-2023 | O47: TechNova Solutions | P47: 13.8
A48: CAND0047 | B48: Namita Parida | C48: UI Designer | D48: Engineering | E48: =PROPER(D48) -> Engineering | F48: LinkedIn | G48: =PROPER(F48) -> Linkedin | H48: 3.1 | I48: 4.7 | J48: 3.9 | K48: 146052 | L48: 129873 | M48: Withdrawn | N48: 20-06-2023 | O48: OdishaCode Labs | P48: 4.1
A49: CAND0048 | B49: Rahul Mohapatra | C49: Sales Manager | D49: Product | E49: =PROPER(D49) -> Product | F49: Naukri | G49: =PROPER(F49) -> Naukri | H49: 4.8 | I49: 7.9 | J49: 6.3 | K49: 53469 | L49: 47821 | M49: Accepted | N49: 23-06-2023 | O49: BlueLotus IT | P49: 4.2
A50: CAND0049 | B50: Tapas Mohapatra | C50: Sales Manager | D50: Product | E50: =PROPER(D50) -> Product | F50: Naukri | G50: =PROPER(F50) -> Naukri | H50: 4.3 | I50: 5.3 | J50: 4.8 | K50: 82666 | L50: 78032 | M50: Negotiating | N50: 03-02-2024 | O50: BlueLotus IT | P50: 6.5
A51: CAND0050 | B51: Abhishek Mishra | C51: Product Manager | D51: Marketing | E51: =PROPER(D51) -> Marketing | F51: Walk-in | G51: =PROPER(F51) -> Walk-In | H51: 7.2 | I51: 5.9 | J51: 6.6 | K51: 112022 | L51: 111420 | M51: Negotiating | N51: 06-06-2023 | O51: InfySoft Bhubaneswar | P51: 14.5
A52: CAND0051 | B52: Soumya Biswal | C52: Product Manager | D52: Data Science | E52: =PROPER(D52) -> Data Science | F52: LinkedIn | G52: =PROPER(F52) -> Linkedin | H52: 5.1 | I52: 6.6 | J52: 5.8 | K52: 190492 | L52: 194921 | M52: Pending | N52: 08-04-2024 | O52: InfySoft Bhubaneswar | P52: 9.2
A53: CAND0052 | B53: Saurav Mishra | C53: Sales Manager | D53: Marketing | E53: =PROPER(D53) -> Marketing | F53: Naukri | G53: =PROPER(F53) -> Naukri | H53: 3.9 | I53: 6.3 | J53: 5.1 | K53: 30777 | L53: 26704 | M53: Accepted | N53: 03-11-2024 | O53: TechNova Solutions | P53: 3.7
A54: CAND0053 | B54: Subhasree Samal | C54: Sales Manager | D54: Engineering | E54: =PROPER(D54) -> Engineering | F54: linkedin | G54: =PROPER(F54) -> Linkedin | H54: 9.3 | I54: 5.2 | J54: 7.2 | K54: 187040 | M54: Accepted | N54: 26-05-2023 | O54: NilGiri Digitals | P54: 12.1
A55: CAND0054 | B55: Namita Sahoo | C55: Software Engineer | D55: Design | E55: =PROPER(D55) -> Design | F55: Campus | G55: =PROPER(F55) -> Campus | H55: 6.8 | I55: 3.5 | J55: 5.2 | K55: 144671 | L55: 150032 | M55: Rejected | N55: 15-09-2023 | O55: OdishaCode Labs | P55: 14.9
A56: CAND0055 | B56: Amlan Pattnaik | C56: DevOps Engineer | D56: Marketing | E56: =PROPER(D56) -> Marketing | F56: naukri | G56: =PROPER(F56) -> Naukri | H56: 8.5 | I56: 9.6 | J56: 9.1 | K56: 20578 | M56: Accepted | N56: 20-09-2023 | O56: NilGiri Digitals | P56: 14.3
A57: CAND0056 | B57: Amlan Mishra | C57: Sales Manager | D57: Product | E57: =PROPER(D57) -> Product | F57: Job Portal | G57: =PROPER(F57) -> Job Portal | H57: 3.1 | I57: 3.9 | J57: 3.5 | K57: 56944 | M57: Accepted | N57: 04-02-2023 | O57: SambalpurNet | P57: 13.1
A58: CAND0057 | B58: Rajan Choudhury | C58: Business Analyst | D58: Sales | E58: =PROPER(D58) -> Sales | F58: Referral | G58: =PROPER(F58) -> Referral | H58: 7.9 | I58: 4.8 | J58: 6.3 | K58: 107452 | M58: Rejected | N58: 02-11-2023 | O58: OdishaCode Labs | P58: 13.5
A59: CAND0058 | B59: Bikash Jena | C59: Product Manager | D59: Sales | E59: =PROPER(D59) -> Sales | F59: naukri | G59: =PROPER(F59) -> Naukri | H59: 9.3 | I59: 7.9 | J59: 8.6 | K59: 35226 | L59: 31094 | M59: Negotiating | N59: 13-03-2023 | O59: ZeroOneSystems | P59: 14
A60: CAND0059 | B60: Debasmita Prusty | C60: DevOps Engineer | D60: DevOps | E60: =PROPER(D60) -> Devops | F60: Naukri | G60: =PROPER(F60) -> Naukri | H60: 6.2 | I60: 4.8 | J60: 5.5 | K60: 105266 | L60: 102061 | M60: Accepted | N60: 18-04-2024 | O60: KalingaTech Pvt Ltd | P60: 1.2
A61: CAND0060 | B61: Nirmal Dhal | C61: Software Engineer | D61: Engineering | E61: =PROPER(D61) -> Engineering | F61: Walk-in | G61: =PROPER(F61) -> Walk-In | H61: 6.6 | I61: 9 | J61: 7.8 | K61: 48089 | M61: Accepted | N61: 05-02-2024 | O61: TributeAI | P61: 12.6
A62: CAND0061 | B62: Tanmay Prusty | C62: Data Analyst | D62: Data Science | E62: =PROPER(D62) -> Data Science | F62: Referral | G62: =PROPER(F62) -> Referral | H62: 8 | J62: 8 | K62: 173697 | L62: 152999 | M62: Pending | N62: 26-02-2023 | O62: UtkalSoft Technologies | P62: 14.2
A63: CAND0062 | B63: Rahul Routray | C63: Sales Manager | D63: Finance | E63: =PROPER(D63) -> Finance | F63: Campus | G63: =PROPER(F63) -> Campus | H63: 4.1 | I63: 4.6 | J63: 4.3 | K63: 178122 | M63: Pending | N63: 17-12-2024 | O63: InfySoft Bhubaneswar | P63: 3.6
A64: CAND0063 | B64: Subhasree Mohapatra | C64: Cloud Architect | D64: DevOps | E64: =PROPER(D64) -> Devops | F64: Job Portal | G64: =PROPER(F64) -> Job Portal | H64: 5.9 | I64: 4.3 | J64: 5.1 | K64: 69391 | M64: Withdrawn | N64: 14-01-2024 | O64: TechNova Solutions | P64: 9.4
A65: CAND0064 | B65: Rahul Samal | C65: HR Executive | D65: Design | E65: =PROPER(D65) -> Design | F65: linkedin | G65: =PROPER(F65) -> Linkedin | H65: 8 | I65: 9.3 | J65: 8.7 | K65: 27129 | L65: 26908 | M65: Negotiating | N65: 20-07-2023 | O65: SambalpurNet | P65: 10.9
A66: CAND0065 | B66: Prasant Mishra | C66: HR Executive | D66: Sales | E66: =PROPER(D66) -> Sales | F66: Naukri | G66: =PROPER(F66) -> Naukri | H66: 8.9 | I66: 9.5 | J66: 9.2 | K66: 129107 | L66: 145758 | M66: Rejected | N66: 08-05-2023 | O66: TechNova Solutions | P66: 1
A67: CAND0066 | B67: Sudhansu Ratha | C67: DevOps Engineer | D67: QA | E67: =PROPER(D67) -> Qa | F67: linkedin | G67: =PROPER(F67) -> Linkedin | H67: 5.3 | I67: 6.3 | J67: 5.8 | K67: 119642 | L67: 117619 | M67: Accepted | N67: 05-08-2023 | O67: KalingaTech Pvt Ltd | P67: 1.6
A68: CAND0067 | B68: Tapas Routray | C68: Sales Manager | D68: DevOps | E68: =PROPER(D68) -> Devops | F68: Naukri | G68: =PROPER(F68) -> Naukri | I68: 4.5 | K68: 133370 | L68: 120603 | M68: Negotiating | N68: 26-09-2024 | O68: CoastalDev Studio | P68: 5.1
A69: CAND0068 | B69: Bikash Choudhury | C69: Software Engineer | D69: Finance | E69: =PROPER(D69) -> Finance | F69: Walk-in | G69: =PROPER(F69) -> Walk-In | H69: 6.8 | I69: 7.2 | J69: 7 | K69: 174045 | L69: 197218 | M69: Accepted | N69: 01-02-2024 | O69: TributeAI | P69: 1.2
A70: CAND0069 | B70: Alka Samal | C70: Cloud Architect | D70: Finance | E70: =PROPER(D70) -> Finance | F70: Job Portal | G70: =PROPER(F70) -> Job Portal | H70: 8.8 | I70: 5.1 | J70: 7 | K70: 70392 | M70: Accepted | N70: 30-05-2023 | O70: CoastalDev Studio | P70: 8.9
A71: CAND0070 | B71: Satyajit Choudhury | C71: Sales Manager | D71: Product | E71: =PROPER(D71) -> Product | F71: LinkedIn | G71: =PROPER(F71) -> Linkedin | H71: 7.5 | I71: 7 | J71: 7.2 | K71: 123290 | M71: Accepted | N71: 23-05-2024 | O71: ZeroOneSystems | P71: 7.7
A72: CAND0071 | B72: Dibya Padhi | C72: Data Analyst | D72: Design | E72: =PROPER(D72) -> Design | F72: Campus | G72: =PROPER(F72) -> Campus | I72: 4.5 | K72: 56511 | L72: 63401 | M72: Negotiating | N72: 04-03-2023 | O72: BlueLotus IT | P72: 2.5
A73: CAND0072 | B73: Rahul Choudhury | C73: DevOps Engineer | D73: Finance | E73: =PROPER(D73) -> Finance | F73: Job Portal | G73: =PROPER(F73) -> Job Portal | H73: 8.4 | I73: 7.9 | J73: 8.2 | K73: 125829 | M73: Rejected | N73: 27-05-2023 | O73: BlueLotus IT | P73: 3.7
A74: CAND0073 | B74: Nirmal Choudhury | C74: Business Analyst | D74: Finance | E74: =PROPER(D74) -> Finance | F74: Job Portal | G74: =PROPER(F74) -> Job Portal | H74: 8.5 | I74: 5.1 | J74: 6.8 | K74: 34216 | M74: Pending | N74: 01-07-2023 | O74: OdishaCode Labs | P74: 1.9
A75: CAND0074 | B75: Smita Nanda | C75: HR Executive | D75: Product | E75: =PROPER(D75) -> Product | F75: Job Portal | G75: =PROPER(F75) -> Job Portal | H75: 9.4 | I75: 3.1 | J75: 6.2 | K75: 141909 | L75: 150344 | M75: Accepted | N75: 25-11-2024 | O75: SambalpurNet | P75: 1.5
A76: CAND0075 | B76: Aditya Mohapatra | C76: Cloud Architect | D76: QA | E76: =PROPER(D76) -> Qa | F76: Campus | G76: =PROPER(F76) -> Campus | H76: 6.4 | I76: 8.2 | J76: 7.3 | K76: 61665 | L76: 64147 | M76: Pending | N76: 08-04-2023 | O76: SambalpurNet | P76: 4.9
A77: CAND0076 | B77: Rajan Mohapatra | C77: Cloud Architect | D77: Data Science | E77: =PROPER(D77) -> Data Science | F77: naukri | G77: =PROPER(F77) -> Naukri | H77: 5.2 | I77: 4.2 | J77: 4.7 | K77: 141496 | M77: Pending | N77: 07-11-2023 | O77: InfySoft Bhubaneswar | P77: 2
A78: CAND0077 | B78: Lipsa Ratha | C78: UI Designer | D78: Data Science | E78: =PROPER(D78) -> Data Science | F78: Job Portal | G78: =PROPER(F78) -> Job Portal | H78: 3.5 | I78: 8.8 | J78: 6.2 | K78: 35262 | L78: 32631 | M78: Accepted | N78: 13-06-2023 | O78: UtkalSoft Technologies | P78: 14.7
A79: CAND0078 | B79: Subhasree Mishra | C79: Cloud Architect | D79: HR | E79: =PROPER(D79) -> Hr | F79: Walk-in | G79: =PROPER(F79) -> Walk-In | H79: 5.8 | I79: 8.7 | J79: 7.2 | K79: 110287 | L79: 106409 | M79: Rejected | N79: 04-06-2023 | O79: InfySoft Bhubaneswar | P79: 8.7
A80: CAND0079 | B80: Smita Mishra | C80: Business Analyst | D80: Design | E80: =PROPER(D80) -> Design | F80: Campus | G80: =PROPER(F80) -> Campus | H80: 7.1 | I80: 7.2 | J80: 7.2 | K80: 143803 | L80: 164896 | M80: Accepted | N80: 10-03-2023 | O80: KalingaTech Pvt Ltd | P80: 6
A81: CAND0080 | B81: Namita Pattnaik | C81: QA Engineer | D81: HR | E81: =PROPER(D81) -> Hr | F81: Campus | G81: =PROPER(F81) -> Campus | H81: 3.9 | I81: 6.2 | J81: 5 | M81: Negotiating | N81: 14-10-2023 | O81: OdishaCode Labs | P81: 5.3
A82: CAND0081 | B82: Alka Padhi | C82: QA Engineer | D82: Data Science | E82: =PROPER(D82) -> Data Science | F82: Referral | G82: =PROPER(F82) -> Referral | H82: 7.4 | I82: 8.8 | J82: 8.1 | K82: 97734 | L82: 92021 | M82: Negotiating | N82: 25-11-2024 | O82: ZeroOneSystems | P82: 3.6
A83: CAND0082 | B83: Namita Senapati | C83: Product Manager | D83: Marketing | E83: =PROPER(D83) -> Marketing | F83: Referral | G83: =PROPER(F83) -> Referral | H83: 7.5 | I83: 4 | J83: 5.8 | K83: 190672 | L83: 166185 | M83: Negotiating | N83: 02-12-2024 | O83: TributeAI | P83: 9.9
A84: CAND0083 | B84: Ankita Parida | C84: Sales Manager | D84: DevOps | E84: =PROPER(D84) -> Devops | F84: naukri | G84: =PROPER(F84) -> Naukri | H84: 5.6 | I84: 8 | J84: 6.8 | K84: 93200 | L84: 93867 | M84: Negotiating | N84: 27-03-2023 | O84: CoastalDev Studio | P84: 11.2
A85: CAND0084 | B85: Ipsita Behura | C85: Business Analyst | D85: QA | E85: =PROPER(D85) -> Qa | F85: Referral | G85: =PROPER(F85) -> Referral | H85: 6.9 | J85: 6.9 | K85: 77608 | L85: 67908 | M85: Negotiating | N85: 04-10-2023 | O85: ZeroOneSystems | P85: 6.8
A86: CAND0085 | B86: Bikash Pattnaik | C86: Product Manager | D86: DevOps | E86: =PROPER(D86) -> Devops | F86: Job Portal | G86: =PROPER(F86) -> Job Portal | H86: 4 | I86: 5.2 | J86: 4.6 | K86: 47895 | M86: Negotiating | N86: 26-02-2023 | O86: KalingaTech Pvt Ltd | P86: 6.4
A87: CAND0086 | B87: Dibya Mohapatra | C87: Cloud Architect | D87: DevOps | E87: =PROPER(D87) -> Devops | F87: Job Portal | G87: =PROPER(F87) -> Job Portal | H87: 5.8 | I87: 7.8 | J87: 6.8 | K87: 193111 | L87: 205760 | M87: Accepted | N87: 12-08-2023 | O87: TributeAI | P87: 10.7
A88: CAND0087 | B88: Soumya Jena | C88: Product Manager | D88: HR | E88: =PROPER(D88) -> Hr | F88: linkedin | G88: =PROPER(F88) -> Linkedin | H88: 8.1 | I88: 6.5 | J88: 7.3 | K88: 151012 | L88: 136761 | M88: Rejected | N88: 21-09-2023 | O88: OdishaCode Labs | P88: 7.5
A89: CAND0088 | B89: Nirmal Nanda | C89: QA Engineer | D89: Finance | E89: =PROPER(D89) -> Finance | F89: naukri | G89: =PROPER(F89) -> Naukri | H89: 8.4 | I89: 3.7 | J89: 6.1 | K89: 155732 | L89: 152306 | M89: Accepted | N89: 13-06-2023 | O89: KalingaTech Pvt Ltd | P89: 12.6
A90: CAND0089 | B90: Sangita Samal | C90: Cloud Architect | D90: HR | E90: =PROPER(D90) -> Hr | F90: Job Portal | G90: =PROPER(F90) -> Job Portal | H90: 8.8 | I90: 7.1 | J90: 8 | K90: 144744 | M90: Withdrawn | N90: 05-05-2023 | O90: OdishaCode Labs | P90: 12.8
A91: CAND0090 | B91: Aditya Mohapatra | C91: Product Manager | D91: Engineering | E91: =PROPER(D91) -> Engineering | F91: linkedin | G91: =PROPER(F91) -> Linkedin | H91: 9.9 | I91: 8.5 | J91: 9.2 | K91: 188620 | L91: 175386 | M91: Accepted | N91: 31-01-2023 | O91: CoastalDev Studio | P91: 12.8
A92: CAND0091 | B92: Aditya Parida | C92: HR Executive | D92: Sales | E92: =PROPER(D92) -> Sales | F92: Campus | G92: =PROPER(F92) -> Campus | H92: 8.3 | I92: 6.7 | J92: 7.5 | K92: 95485 | L92: 107800 | M92: Accepted | N92: 11-12-2023 | O92: KalingaTech Pvt Ltd | P92: 2.1
A93: CAND0092 | B93: Chinmaya Mohapatra | C93: Cloud Architect | D93: Finance | E93: =PROPER(D93) -> Finance | F93: linkedin | G93: =PROPER(F93) -> Linkedin | H93: 5.1 | I93: 3.1 | J93: 4.1 | K93: 95659 | L93: 109976 | M93: Accepted | N93: 04-06-2023 | O93: NilGiri Digitals | P93: 4
A94: CAND0093 | B94: Namita Mohapatra | C94: UI Designer | D94: Design | E94: =PROPER(D94) -> Design | F94: Campus | G94: =PROPER(F94) -> Campus | H94: 3.5 | I94: 6.8 | J94: 5.2 | K94: 79589 | L94: 70936 | M94: Rejected | N94: 02-12-2023 | O94: KalingaTech Pvt Ltd | P94: 13
A95: CAND0094 | B95: Ranjit Nanda | C95: QA Engineer | D95: Marketing | E95: =PROPER(D95) -> Marketing | F95: LinkedIn | G95: =PROPER(F95) -> Linkedin | H95: 6.8 | I95: 5.9 | J95: 6.3 | K95: 147422 | L95: 151979 | M95: Pending | N95: 22-05-2023 | O95: KalingaTech Pvt Ltd | P95: 12.3
A96: CAND0095 | B96: Sangita Pattnaik | C96: Software Engineer | D96: Product | E96: =PROPER(D96) -> Product | F96: Walk-in | G96: =PROPER(F96) -> Walk-In | H96: 8.2 | I96: 8.1 | J96: 8.1 | K96: 135674 | L96: 115839 | M96: Withdrawn | N96: 09-06-2024 | O96: InfySoft Bhubaneswar | P96: 8.9
A97: CAND0096 | B97: Amlan Prusty | C97: DevOps Engineer | D97: Marketing | E97: =PROPER(D97) -> Marketing | F97: Naukri | G97: =PROPER(F97) -> Naukri | H97: 6.7 | I97: 4.1 | J97: 5.4 | K97: 190442 | L97: 165080 | M97: Accepted | N97: 20-04-2023 | O97: CoastalDev Studio | P97: 8.4
A98: CAND0097 | B98: Puspita Pattnaik | C98: QA Engineer | D98: Finance | E98: =PROPER(D98) -> Finance | F98: Referral | G98: =PROPER(F98) -> Referral | H98: 9 | I98: 6.5 | J98: 7.8 | K98: 90894 | L98: 89108 | M98: Withdrawn | N98: 08-11-2024 | O98: TechNova Solutions | P98: 12.5
A99: CAND0098 | B99: Smita Choudhury | C99: Product Manager | D99: Finance | E99: =PROPER(D99) -> Finance | F99: Campus | G99: =PROPER(F99) -> Campus | H99: 8.6 | I99: 3.5 | J99: 6 | K99: 63434 | M99: Negotiating | N99: 02-02-2024 | O99: NilGiri Digitals | P99: 12.8
A100: CAND0099 | B100: Satyajit Dhal | C100: Product Manager | D100: HR | E100: =PROPER(D100) -> Hr | F100: Job Portal | G100: =PROPER(F100) -> Job Portal | H100: 4.6 | I100: 6 | J100: 5.3 | K100: 189712 | L100: 205441 | M100: Pending | N100: 10-02-2024 | O100: CoastalDev Studio | P100: 11.1
...

Sheet KPL_Summary
A1: 📊 BHUBANESWAR TECH — TEAM & COMPANY KPI METRICS
A3: Quarter | B3: Year | C3: Company | D3: Total_Employees | E3: Active_Employees | F3: Resigned_Employees | G3: Attrition_Pct | H3: New_Hires | I3: Avg_Performance_Rating | J3: Billable_Hours_Total | K3: Revenue_Contribution_Lakhs | L3: Avg_Salary_Monthly | M3: Avg_Interview_Score
A4: Q1 | B4: 2022 | C4: NilGiri Digitals | D4: 249 | E4: 233 | F4: 16 | G4: 6.43 | H4: 40 | I4: 3.11 | J4: 10192.5 | K4: 21457.42 | L4: 61353 | M4: 6.72
A5: Q1 | B5: 2022 | C5: TechNova Solutions | D5: 83 | E5: 63 | F5: 20 | G5: 24.1 | H5: 15 | I5: 3.67 | J5: 4423 | K5: 4529.78 | L5: 44142 | M5: 7.41
A6: Q1 | B6: 2022 | C6: CoastalDev Studio | D6: 192 | E6: 176 | F6: 16 | G6: 8.33 | H6: 21 | I6: 3.59 | J6: 4247.7 | K6: 7652.85 | L6: 83712 | M6: 5.84
A7: Q1 | B7: 2022 | C7: ZeroOneSystems | D7: 232 | E7: 229 | F7: 3 | G7: 1.29 | H7: 27 | I7: 3.94 | J7: 8246.6 | K7: 16759.42 | L7: 68983 | M7: 7.6
A8: Q1 | B8: 2022 | C8: InfySoft Bhubaneswar | D8: 115 | E8: 101 | F8: 14 | G8: 12.17 | H8: 9 | I8: 3.99 | J8: 5634.8 | K8: 3750.14 | L8: 62396 | M8: 7.24
A9: Q1 | B9: 2022 | C9: OdishaCode Labs | D9: 116 | E9: 111 | F9: 5 | G9: 4.31 | H9: 36 | I9: 4.62 | J9: 10783.2 | K9: 21845.3 | L9: 117012 | M9: 8.2
A10: Q2 | B10: 2022 | C10: SambalpurNet | D10: 99 | E10: 93 | F10: 6 | G10: 6.06 | H10: 31 | I10: 4.63 | J10: 12970.4 | K10: 17454.6 | L10: 114211 | M10: 5.61
A11: Q2 | B11: 2022 | C11: TechNova Solutions | D11: 290 | E11: 278 | F11: 12 | G11: 4.14 | H11: 36 | I11: 3.98 | J11: 7389.1 | K11: 16217.95 | L11: 63493 | M11: 7.43
A12: Q2 | B12: 2022 | C12: InfySoft Bhubaneswar | D12: 157 | E12: 143 | F12: 14 | G12: 8.92 | H12: 34 | I12: 4.62 | J12: 7544.8 | K12: 15525.89 | L12: 53608 | M12: 6.01
A13: Q2 | B13: 2022 | C13: BlueLotus IT | D13: 74 | E13: 69 | F13: 5 | G13: 6.76 | H13: 15 | I13: 3.5 | J13: 9302.4 | K13: 6177.5 | L13: 109789 | M13: 7.19
A14: Q2 | B14: 2022 | C14: CoastalDev Studio | D14: 197 | E14: 179 | F14: 18 | G14: 9.14 | H14: 24 | I14: 4.62 | J14: 10961.5 | K14: 7701.38 | L14: 92663 | M14: 5.73
A15: Q2 | B15: 2022 | C15: SilverByte Systems | D15: 202 | E15: 187 | F15: 15 | G15: 7.43 | H15: 37 | I15: 3.37 | J15: 4062.8 | K15: 8060.16 | L15: 115046 | M15: 8.26
... A75: Q4 | B75: 2024 | C75: KalingaTech Pvt Ltd | D75: 171 | E75: 151 | F75: 20 | G75: 11.7 | H75: 33 | I75: 3.65 | J75: 4758.8 | K75: 9837.24 | L75: 96140 | M75: 6.77

Sheet All answers
B1: 📋 BHUBANESWAR TECH DATASET — PRACTICE QUESTIONS | F1: Performance_Rating | G1: (9)Create a column 'Performance_Band': Rating ≥ 4.5 → 'Excellent', 3.5–4.4 → 'Good', < 3.5 → 'Needs Improvement'. Use IFS. | I1: Budget_Lakhs | J1: Actual_Cost_Lakhs | K1: (10)In Projects sheet, flag projects where Actual_Cost > Budget as 'Over Budget', else 'Within Budget'. Use IF. | M1: Offered_Salary | N1: Expected_Salary | O1: (11)In Hiring sheet, create 'Salary_Negotiated' column: Yes if Offered_Salary ≠ Expected_Salary, else No. ( Salary_Negotiated) | Q1: Work_Hours | R1: (12)Flag attendance records where Work_Hours is blank. Use IF + ISBLANK. | T1: Attrition_Pct | U1: (13)In KPI sheet, create a column: If Attrition_Pct > 10 → 'High Attrition', else 'Normal'. Use IF. | W1: Employee_ID | X1: (14)Use IFERROR with VLOOKUP to fetch employee name from Employee_ID in Attendance sheet. Handle errors. | Z1: Employee_ID | AA1: (15)Extract the numeric part of Employee_ID (e.g., EMP0001 → 0001). Use MID or RIGHT. | AC1: Department | AD1: (16)Standardize the Department column — some values are lowercase. Use PROPER or UPPER. Create a helper column. | AF1: Full_Name | AG1: Department | AH1: Company | AI1: (17)Create a full label: 'Saurav Mohapatra | Engineering | TechNova Solutions'. Use CONCAT or &. | AK1: Full_Name | AL1: (18)Extract initials from employee Full_Name (e.g., Saurav Mohapatra → S.M.). Use LEFT + FIND + MID. | AN1: Source | AO1: (19)Standardize the 'Source' column in Hiring sheet (linkedin → LinkedIn, naukri → Naukri). Use IF + UPPER. | AQ1: Full_Name | AR1: (20)Find all employees whose surname is 'Mishra'. Use SEARCH or RIGHT in combination with IF. | AT1: Project_Name | AU1: (21)Count characters in Project_Name to identify unusually short names. Use LEN. | AW1: (22)Calculate tenure (in years) for each employee from their Joining_Date to today. Use DATEDIF. | AY1: Interview_Date | AZ1: Modified Interview date | BA1: (23)Extract Month and Year from Interview_Date in Hiring sheet. | BC1: Deadline | BD1: Modified Deadline | BE1: Status | BF1: (24)Find projects that are overdue: Deadline has passed but Status ≠ 'Completed'. Use TODAY() + IF. | BH1: Joining_Date | BI1: Modified Joining Date | BJ1: (25)Calculate working days each employee has been with the company. Use NETWORKDAYS. | BL1: (26)Find employees who joined in Q1 (Jan–Mar) of any year. Use MONTH() + IF. | BM1: Modified Interview date | BN1: Modified Joining Date | BO1: (27)Calculate the gap between Interview_Date and Joining_Date for placed candidates. Use DATEDIF. | BP1: Employee_ID | BQ1: Department | BR1: Employee_ID | BS1: Record_ID | BT1: (28)For each Attendance record, fetch the Employee's Department using VLOOKUP (from Employees sheet). | BV1: Employee_ID | BW1: Full_Name | BX1: Project_Name | BY1: Lead_Employee_ID | BZ1: (29)For each Project, fetch the Lead Employee's Name using XLOOKUP (from Employees sheet). | CB1: Full_Name (Hiring) | CC1: Full_Name (employees) | CD1: Designation | CE1: (31)Fetch the Designation of each employee who appears in the Hiring sheet as a candidate. | CG1: (32)Use XLOOKUP with IFERROR to find a Candidate by ID. Return 'Not Found' if not present.
F2: 4.5 | G2: {=_xlfn.IFS(F2>=4.5,"Excellent",AND(F2>=3.5,F2<=4.4),"Good",F2<3.5,"Needs Improvement")} -> Excellent | I2: 172.82 | J2: 149.22 | K2: =IF(J2>I2,"Over Budget","Within Budget") -> Within Budget | M2: 135000 | N2: 123018 | O2: =IF(M2<>N2,"Yes","No") -> Yes | Q2: 6.9 | R2: =IF(ISBLANK(Q2),"No","Yes") -> Yes | T2: 6.43 | U2: =IF(T2>10,"High Attrition","No") -> No | W2: EMP0076 | X2: =VLOOKUP(W2,Employees!$A$1:$B$601,2,FALSE) -> Bikash Biswal | Z2: EMP0001 | AA2: =RIGHT(Z2,4) -> 0001 | AC2: DevOps | AD2: =PROPER(AC2) -> Devops | AF2: Priyanka Jena | AG2: DevOps | AH2: CoastalDev Studio | AI2: =_xlfn.CONCAT(AF2,"|",AG2,"|",AH2) -> Priyanka Jena|DevOps|CoastalDev Studio | AK2: Priyanka Jena | AL2: =LEFT(AK2,1)&"."&MID(AK2,FIND(" ",AK2)+1,1)&"." -> P.J. | AN2: Job Portal | AO2: =IF(UPPER(AN2)="linkedin","Linkedln",IF(UPPER(AN2)="naukri","Naukri")) -> FALSE | AQ2: Priyanka Jena | AR2: =IF(ISNUMBER(SEARCH("Mishra",AQ2)),"Mishra","NO") -> NO | AT2: Supply Chain Optimizer | AU2: =LEN(AT2) -> 22 | AY2: 08-04-2024 | AZ2: =DATE(RIGHT(AY2,4),MID(AY2,4,2),LEFT(AY2,2)) -> 45390 | BA2: =MONTH(AZ2)&"-"&YEAR(AZ2) -> 4-2024 | BC2: 20-11-2022 | BD2: =DATE(RIGHT(BC2,4),MID(BC2,4,2),LEFT(BC2,2)) -> 44885 | BE2: Cancelled | BF2: =IF(AND(BD2<TODAY(),BE2<>"Completed"),"Overdue","On Track") -> Overdue | BM2: =DATE(RIGHT(AY2,4),MID(AY2,4,2),LEFT(AY2,2)) -> 45390 | BO2: =ABS(BN2-BM2) -> 45390 | BP2: EMP0001 | BQ2: DevOps | BR2: EMP0076 | BS2: ATT00001 | BT2: =VLOOKUP(BR2,$BP$2:$BQ$601,2,FALSE) -> Marketing | BV2: EMP0001 | BW2: Priyanka Jena | BX2: Supply Chain Optimizer | BY2: EMP0508 | BZ2: =VLOOKUP(BY2,$BV$2:$BW$601,2,FALSE) -> Barsha Pattnaik | CB2: Abhishek Ratha | CC2: Priyanka Jena | CD2: SRE | CE2: {=_xlfn.XLOOKUP(CB2:CB401,CC2:CC601,CD2:CD601,"Not Found",0)} -> Not Found | CG2: =IFERROR(_xlfn.XLOOKUP(Hiring!A2,Hiring!A2:A401,Hiring!B2:B401,,0),"Not Found") -> Abhishek Ratha
A3: SECTION A — AGGREGATE & CONDITIONAL FUNCTIONS | C3: Department | D3: Monthly Salary | F3: 1.5 | G3: {=_xlfn.IFS(F3>=4.5,"Excellent",AND(F3>=3.5,F3<=4.4),"Good",F3<3.5,"Needs Improvement")} -> Needs Improvement | I3: 123.83 | J3: 158.34 | K3: =IF(J3>I3,"Over Budget","Within Budget") -> Over Budget | M3: 132960 | N3: 139712 | O3: =IF(M3<>N3,"Yes","No") -> Yes | Q3: 7.78 | R3: =IF(ISBLANK(Q3),"No","Yes") -> Yes | T3: 24.1 | U3: =IF(T3>10,"High Attrition","No") -> High Attrition | W3: EMP0076 | X3: =VLOOKUP(W3,Employees!$A$1:$B$601,2,FALSE) -> Bikash Biswal | Z3: EMP0002 | AA3: =RIGHT(Z3,4) -> 0002 | AC3: Design | AD3: =PROPER(AC3) -> Design | AF3: Ranjit Samal | AG3: Design | AH3: InfySoft Bhubaneswar | AI3: =_xlfn.CONCAT(AF3,"|",AG3,"|",AH3) -> Ranjit Samal|Design|InfySoft Bhubaneswar | AK3: Ranjit Samal | AL3: =LEFT(AK3,1)&"."&MID(AK3,FIND(" ",AK3)+1,1)&"." -> R.S. | AN3: LinkedIn | AO3: =IF(UPPER(AN3)="linkedin","Linkedln",IF(UPPER(AN3)="naukri","Naukri")) -> Linkedln | AQ3: Ranjit Samal | AR3: =IF(ISNUMBER(SEARCH("Mishra",AQ3)),"Mishra","NO") -> NO | AT3: Supply Chain Optimizer | AU3: =LEN(AT3) -> 22 | AW3: =DATEDIF(BI3,TODAY(),"Y") -> 4 | AY3: 27-05-2024 | AZ3: =DATE(RIGHT(AY3,4),MID(AY3,4,2),LEFT(AY3,2)) -> 45439 | BA3: =MONTH(AZ3)&"-"&YEAR(AZ3) -> 5-2024 | BC3: 28-04-2024 | BD3: =DATE(RIGHT(BC3,4),MID(BC3,4,2),LEFT(BC3,2)) -> 45410 | BE3: Cancelled | BF3: =IF(AND(BD3<TODAY(),BE3<>"Completed"),"Overdue","On Track") -> Overdue | BH3: 05-03-2022 | BI3: =IF(LEN(LEFT(BH3,FIND("-",BH3)-1))=4,DATE(LEFT(BH3,4),MID(BH3,6,2),RIGHT(BH3,2)),DATE(RIGHT(BH3,4),MID(BH3,4,2),LEFT(BH3,2))) -> 44625 | BJ3: =NETWORKDAYS(BI3,TODAY()) -> 1160 | BL3: =IF(MONTH(BI3)<=3,"Q1","No") -> Q1 | BM3: =DATE(RIGHT(AY3,4),MID(AY3,4,2),LEFT(AY3,2)) -> 45439 | BN3: =IF(LEN(LEFT(BH3,FIND("-",BH3)-1))=4,DATE(LEFT(BH3,4),MID(BH3,6,2),RIGHT(BH3,2)),DATE(RIGHT(BH3,4),MID(BH3,4,2),LEFT(BH3,2))) -> 44625 | BO3: =ABS(BN3-BM3) -> 814 | BP3: EMP0002 | BQ3: Design | BR3: EMP0076 | BS3: ATT00002 | BT3: =VLOOKUP(BR3,$BP$2:$BQ$601,2,FALSE) -> Marketing | BV3: EMP0002 | BW3: Ranjit Samal | BX3: Supply Chain Optimizer | BY3: EMP0526 | BZ3: =VLOOKUP(BY3,$BV$2:$BW$601,2,FALSE) -> Ipsita Biswal | CB3: Bikash Behura | CC3: Ranjit Samal | CD3: UI Designer | CE3: Account Manager | CG3: =IFERROR(_xlfn.XLOOKUP(Hiring!A3,Hiring!A3:A402,Hiring!B3:B402,,0),"Not Found") -> Bikash Behura
A4: Q1 | B4: Calculate total monthly salary bill for each Department. Use SUMIF on Employees sheet. | C4: Engineering | D4: =SUMIFS(Employees!I:I,Employees!D:D,C4) -> 7253668 | F4: 3.4 | G4: {=_xlfn.IFS(F4>=4.5,"Excellent",AND(F4>=3.5,F4<=4.4),"Good",F4<3.5,"Needs Improvement")} -> Needs Improvement | I4: 110.56 | J4: 114.91 | K4: =IF(J4>I4,"Over Budget","Within Budget") -> Over Budget | M4: 28384 | N4: 26013 | O4: =IF(M4<>N4,"Yes","No") -> Yes | R4: =IF(ISBLANK(Q4),"No","Yes") -> No | T4: 8.33 | U4: =IF(T4>10,"High Attrition","No") -> No | W4: EMP0076 | X4: =VLOOKUP(W4,Employees!$A$1:$B$601,2,FALSE) -> Bikash Biswal | Z4: EMP0003 | AA4: =RIGHT(Z4,4) -> 0003 | AC4: DevOps | AD4: =PROPER(AC4) -> Devops | AF4: Subhasree Dhal | AG4: DevOps | AH4: NilGiri Digitals | AI4: =_xlfn.CONCAT(AF4,"|",AG4,"|",AH4) -> Subhasree Dhal|DevOps|NilGiri Digitals | AK4: Subhasree Dhal | AL4: =LEFT(AK4,1)&"."&MID(AK4,FIND(" ",AK4)+1,1)&"." -> S.D. | AN4: linkedin | AO4: =IF(UPPER(AN4)="linkedin","Linkedln",IF(UPPER(AN4)="naukri","Naukri")) -> Linkedln | AQ4: Subhasree Dhal | AR4: =IF(ISNUMBER(SEARCH("Mishra",AQ4)),"Mishra","NO") -> NO | AT4: Data Warehouse Migration | AU4: =LEN(AT4) -> 24 | AW4: =DATEDIF(BI4,TODAY(),"Y") -> 5 | AY4: 18-09-2024 | AZ4: =DATE(RIGHT(AY4,4),MID(AY4,4,2),LEFT(AY4,2)) -> 45553 | BA4: =MONTH(AZ4)&"-"&YEAR(AZ4) -> 9-2024 | BC4: 13-05-2022 | BD4: =DATE(RIGHT(BC4,4),MID(BC4,4,2),LEFT(BC4,2)) -> 44694 | BE4: Under Review | BF4: =IF(AND(BD4<TODAY(),BE4<>"Completed"),"Overdue","On Track") -> Overdue | BH4: 07-03-2021 | BI4: =IF(LEN(LEFT(BH4,FIND("-",BH4)-1))=4,DATE(LEFT(BH4,4),MID(BH4,6,2),RIGHT(BH4,2)),DATE(RIGHT(BH4,4),MID(BH4,4,2),LEFT(BH4,2))) -> 44262 | BJ4: =NETWORKDAYS(BI4,TODAY()) -> 1420 | BL4: =IF(MONTH(BI4)<=3,"Q1","No") -> Q1 | BM4: =DATE(RIGHT(AY4,4),MID(AY4,4,2),LEFT(AY4,2)) -> 45553 | BN4: =IF(LEN(LEFT(BH4,FIND("-",BH4)-1))=4,DATE(LEFT(BH4,4),MID(BH4,6,2),RIGHT(BH4,2)),DATE(RIGHT(BH4,4),MID(BH4,4,2),LEFT(BH4,2))) -> 44262 | BO4: =ABS(BN4-BM4) -> 1291 | BP4: EMP0003 | BQ4: DevOps | BR4: EMP0076 | BS4: ATT00003 | BT4: =VLOOKUP(BR4,$BP$2:$BQ$601,2,FALSE) -> Marketing | BV4: EMP0003 | BW4: Subhasree Dhal | BX4: Data Warehouse Migration | BY4: EMP0134 | BZ4: =VLOOKUP(BY4,$BV$2:$BW$601,2,FALSE) -> Nirmal Choudhury | CB4: Ankita Behura | CC4: Subhasree Dhal | CD4: SRE | CE4: Not Found | CG4: =IFERROR(_xlfn.XLOOKUP(Hiring!A4,Hiring!A4:A403,Hiring!B4:B403,,0),"Not Found") -> Ankita Behura
A5: Q2 | B5: Count how many employees have a Performance_Rating above 4.0. Use COUNTIF. | C5: =COUNTIF(Employees!L:L,">4.0") -> 160 | F5: 2.7 | G5: {=_xlfn.IFS(F5>=4.5,"Excellent",AND(F5>=3.5,F5<=4.4),"Good",F5<3.5,"Needs Improvement")} -> Needs Improvement | I5: 167.36 | J5: 156.31 | K5: =IF(J5>I5,"Over Budget","Within Budget") -> Within Budget | M5: 170600 | N5: 176914 | O5: =IF(M5<>N5,"Yes","No") -> Yes | Q5: 9.99 | R5: =IF(ISBLANK(Q5),"No","Yes") -> Yes | T5: 1.29 | U5: =IF(T5>10,"High Attrition","No") -> No | W5: EMP0076 | X5: =VLOOKUP(W5,Employees!$A$1:$B$601,2,FALSE) -> Bikash Biswal | Z5: EMP0004 | AA5: =RIGHT(Z5,4) -> 0004 | AC5: Engineering | AD5: =PROPER(AC5) -> Engineering | AF5: Bikash Jena | AG5: Engineering | AH5: CoastalDev Studio | AI5: =_xlfn.CONCAT(AF5,"|",AG5,"|",AH5) -> Bikash Jena|Engineering|CoastalDev Studio | AK5: Bikash Jena | AL5: =LEFT(AK5,1)&"."&MID(AK5,FIND(" ",AK5)+1,1)&"." -> B.J. | AN5: Campus | AO5: =IF(UPPER(AN5)="linkedin","Linkedln",IF(UPPER(AN5)="naukri","Naukri")) -> FALSE | AQ5: Bikash Jena | AR5: =IF(ISNUMBER(SEARCH("Mishra",AQ5)),"Mishra","NO") -> NO | AT5: IoT Gateway | AU5: =LEN(AT5) -> 11 | AW5: =DATEDIF(BI5,TODAY(),"Y") -> 5 | AY5: 11-12-2023 | AZ5: =DATE(RIGHT(AY5,4),MID(AY5,4,2),LEFT(AY5,2)) -> 45271 | BA5: =MONTH(AZ5)&"-"&YEAR(AZ5) -> 12-2023 | BC5: 03-11-2024 | BD5: =DATE(RIGHT(BC5,4),MID(BC5,4,2),LEFT(BC5,2)) -> 45599 | BE5: In Progress | BF5: =IF(AND(BD5<TODAY(),BE5<>"Completed"),"Overdue","On Track") -> Overdue | BH5: 21-03-2021 | BI5: =IF(LEN(LEFT(BH5,FIND("-",BH5)-1))=4,DATE(LEFT(BH5,4),MID(BH5,6,2),RIGHT(BH5,2)),DATE(RIGHT(BH5,4),MID(BH5,4,2),LEFT(BH5,2))) -> 44276 | BJ5: =NETWORKDAYS(BI5,TODAY()) -> 1410 | BL5: =IF(MONTH(BI5)<=3,"Q1","No") -> Q1 | BM5: =DATE(RIGHT(AY5,4),MID(AY5,4,2),LEFT(AY5,2)) -> 45271 | BN5: =IF(LEN(LEFT(BH5,FIND("-",BH5)-1))=4,DATE(LEFT(BH5,4),MID(BH5,6,2),RIGHT(BH5,2)),DATE(RIGHT(BH5,4),MID(BH5,4,2),LEFT(BH5,2))) -> 44276 | BO5: =ABS(BN5-BM5) -> 995 | BP5: EMP0004 | BQ5: Engineering | BR5: EMP0076 | BS5: ATT00004 | BT5: =VLOOKUP(BR5,$BP$2:$BQ$601,2,FALSE) -> Marketing | BV5: EMP0004 | BW5: Bikash Jena | BX5: IoT Gateway | BY5: EMP0530 | BZ5: =VLOOKUP(BY5,$BV$2:$BW$601,2,FALSE) -> Ankita Choudhury | CB5: Sudhansu Prusty | CC5: Bikash Jena | CD5: Tech Lead | CE5: CFO | CG5: =IFERROR(_xlfn.XLOOKUP(Hiring!A5,Hiring!A5:A404,Hiring!B5:B404,,0),"Not Found") -> Sudhansu Prusty
A6: Q3 | B6: Find the average Final Interview Score for candidates hired from 'LinkedIn'. Use AVERAGEIF on Hiring sheet. | C6: =AVERAGEIFS(Hiring!J:J,Hiring!G:G,"Linkedin") -> 6.4920455 | F6: 4.9 | G6: {=_xlfn.IFS(F6>=4.5,"Excellent",AND(F6>=3.5,F6<=4.4),"Good",F6<3.5,"Needs Improvement")} -> Excellent | I6: 111.58 | J6: 82.9 | K6: =IF(J6>I6,"Over Budget","Within Budget") -> Within Budget | M6: 164134 | N6: 155983 | O6: =IF(M6<>N6,"Yes","No") -> Yes | Q6: 10.75 | R6: =IF(ISBLANK(Q6),"No","Yes") -> Yes | T6: 12.17 | U6: =IF(T6>10,"High Attrition","No") -> High Attrition | W6: EMP0076 | X6: =VLOOKUP(W6,Employees!$A$1:$B$601,2,FALSE) -> Bikash Biswal | Z6: EMP0005 | AA6: =RIGHT(Z6,4) -> 0005 | AC6: Design | AD6: =PROPER(AC6) -> Design | AF6: Bikash Nanda | AG6: Design | AH6: SambalpurNet | AI6: =_xlfn.CONCAT(AF6,"|",AG6,"|",AH6) -> Bikash Nanda|Design|SambalpurNet | AK6: Bikash Nanda | AL6: =LEFT(AK6,1)&"."&MID(AK6,FIND(" ",AK6)+1,1)&"." -> B.N. | AN6: LinkedIn | AO6: =IF(UPPER(AN6)="linkedin","Linkedln",IF(UPPER(AN6)="naukri","Naukri")) -> Linkedln | AQ6: Bikash Nanda | AR6: =IF(ISNUMBER(SEARCH("Mishra",AQ6)),"Mishra","NO") -> NO | AT6: IoT Gateway | AU6: =LEN(AT6) -> 11 | AW6: =DATEDIF(BI6,TODAY(),"Y") -> 3 | AY6: 13-12-2024 | AZ6: =DATE(RIGHT(AY6,4),MID(AY6,4,2),LEFT(AY6,2)) -> 45639 | BA6: =MONTH(AZ6)&"-"&YEAR(AZ6) -> 12-2024 | BC6: 20-07-2023 | BD6: =DATE(RIGHT(BC6,4),MID(BC6,4,2),LEFT(BC6,2)) -> 45127 | BE6: Completed | BF6: =IF(AND(BD6<TODAY(),BE6<>"Completed"),"Overdue","On Track") -> On Track | BH6: 21-07-2023 | BI6: =IF(LEN(LEFT(BH6,FIND("-",BH6)-1))=4,DATE(LEFT(BH6,4),MID(BH6,6,2),RIGHT(BH6,2)),DATE(RIGHT(BH6,4),MID(BH6,4,2),LEFT(BH6,2))) -> 45128 | BJ6: =NETWORKDAYS(BI6,TODAY()) -> 801 | BL6: =IF(MONTH(BI6)<=3,"Q1","No") -> No | BM6: =DATE(RIGHT(AY6,4),MID(AY6,4,2),LEFT(AY6,2)) -> 45639 | BN6: =IF(LEN(LEFT(BH6,FIND("-",BH6)-1))=4,DATE(LEFT(BH6,4),MID(BH6,6,2),RIGHT(BH6,2)),DATE(RIGHT(BH6,4),MID(BH6,4,2),LEFT(BH6,2))) -> 45128 | BO6: =ABS(BN6-BM6) -> 511 | BP6: EMP0005 | BQ6: Design | BR6: EMP0076 | BS6: ATT00005 | BT6: =VLOOKUP(BR6,$BP$2:$BQ$601,2,FALSE) -> Marketing | BV6: EMP0005 | BW6: Bikash Nanda | BX6: IoT Gateway | BY6: EMP0214 | BZ6: =VLOOKUP(BY6,$BV$2:$BW$601,2,FALSE) -> Chinmaya Behura | CB6: Puspita Pattnaik | CC6: Bikash Nanda | CD6: Design Lead | CE6: Digital Marketer | CG6: =IFERROR(_xlfn.XLOOKUP(Hiring!A6,Hiring!A6:A405,Hiring!B6:B405,,0),"Not Found") -> Puspita Pattnaik
A7: Q4 | B7: Calculate total Billable Hours per Company using SUMIF on KPI sheet. | C7: Company | D7: Billable Hours_Total | F7: 2.9 | G7: {=_xlfn.IFS(F7>=4.5,"Excellent",AND(F7>=3.5,F7<=4.4),"Good",F7<3.5,"Needs Improvement")} -> Needs Improvement | I7: 167.64 | J7: 168.44 | K7: =IF(J7>I7,"Over Budget","Within Budget") -> Over Budget | M7: 39365 | N7: 37894 | O7: =IF(M7<>N7,"Yes","No") -> Yes | Q7: 7.23 | R7: =IF(ISBLANK(Q7),"No","Yes") -> Yes | T7: 4.31 | U7: =IF(T7>10,"High Attrition","No") -> No | W7: EMP0076 | X7: =VLOOKUP(W7,Employees!$A$1:$B$601,2,FALSE) -> Bikash Biswal | Z7: EMP0006 | AA7: =RIGHT(Z7,4) -> 0006 | AC7: Sales | AD7: =PROPER(AC7) -> Sales | AF7: Tapas Sahu | AG7: Sales | AH7: BlueLotus IT | AI7: =_xlfn.CONCAT(AF7,"|",AG7,"|",AH7) -> Tapas Sahu|Sales|BlueLotus IT | AK7: Tapas Sahu | AL7: =LEFT(AK7,1)&"."&MID(AK7,FIND(" ",AK7)+1,1)&"." -> T.S. | AN7: Walk-in | AO7: =IF(UPPER(AN7)="linkedin","Linkedln",IF(UPPER(AN7)="naukri","Naukri")) -> FALSE | AQ7: Tapas Sahu | AR7: =IF(ISNUMBER(SEARCH("Mishra",AQ7)),"Mishra","NO") -> NO | AT7: Smart Grid System | AU7: =LEN(AT7) -> 17 | AW7: =DATEDIF(BI7,TODAY(),"Y") -> 4 | AY7: 28-04-2023 | AZ7: =DATE(RIGHT(AY7,4),MID(AY7,4,2),LEFT(AY7,2)) -> 45044 | BA7: =MONTH(AZ7)&"-"&YEAR(AZ7) -> 4-2023 | BC7: 06-10-2021 | BD7: =DATE(RIGHT(BC7,4),MID(BC7,4,2),LEFT(BC7,2)) -> 44475 | BE7: In Progress | BF7: =IF(AND(BD7<TODAY(),BE7<>"Completed"),"Overdue","On Track") -> Overdue | BH7: 31-07-2022 | BI7: =IF(LEN(LEFT(BH7,FIND("-",BH7)-1))=4,DATE(LEFT(BH7,4),MID(BH7,6,2),RIGHT(BH7,2)),DATE(RIGHT(BH7,4),MID(BH7,4,2),LEFT(BH7,2))) -> 44773 | BJ7: =NETWORKDAYS(BI7,TODAY()) -> 1055 | BL7: =IF(MONTH(BI7)<=3,"Q1","No") -> No | BM7: =DATE(RIGHT(AY7,4),MID(AY7,4,2),LEFT(AY7,2)) -> 45044 | BN7: =IF(LEN(LEFT(BH7,FIND("-",BH7)-1))=4,DATE(LEFT(BH7,4),MID(BH7,6,2),RIGHT(BH7,2)),DATE(RIGHT(BH7,4),MID(BH7,4,2),LEFT(BH7,2))) -> 44773 | BO7: =ABS(BN7-BM7) -> 271 | BP7: EMP0006 | BQ7: Sales | BR7: EMP0076 | BS7: ATT00006 | BT7: =VLOOKUP(BR7,$BP$2:$BQ$601,2,FALSE) -> Marketing | BV7: EMP0006 | BW7: Tapas Sahu | BX7: Smart Grid System | BY7: EMP0161 | BZ7: =VLOOKUP(BY7,$BV$2:$BW$601,2,FALSE) -> Tapas Behura | CB7: Soumya Senapati | CC7: Tapas Sahu | CD7: Account Manager | CE7: Product Owner | CG7: =IFERROR(_xlfn.XLOOKUP(Hiring!A7,Hiring!A7:A406,Hiring!B7:B406,,0),"Not Found") -> Soumya Senapati
C8: InfySoft Bhubaneswar | D8: =SUMIFS(KPL_Summary!J4:J75,KPL_Summary!C4:C75,'All answers'!C8) -> 65260.4 | F8: 0 | G8: {=_xlfn.IFS(F8>=4.5,"Excellent",AND(F8>=3.5,F8<=4.4),"Good",F8<3.5,"Needs Improvement")} -> Needs Improvement | I8: 78.19 | J8: 69.7 | K8: =IF(J8>I8,"Over Budget","Within Budget") -> Within Budget | M8: 170751 | N8: 164283 | O8: =IF(M8<>N8,"Yes","No") -> Yes | Q8: 11.44 | R8: =IF(ISBLANK(Q8),"No","Yes") -> Yes | T8: 6.06 | U8: =IF(T8>10,"High Attrition","No") -> No | W8: EMP0076 | X8: =VLOOKUP(W8,Employees!$A$1:$B$601,2,FALSE) -> Bikash Biswal | Z8: EMP0007 | AA8: =RIGHT(Z8,4) -> 0007 | AC8: DevOps | AD8: =PROPER(AC8) -> Devops | AF8: Jyotirmayee Ratha | AG8: DevOps | AH8: SambalpurNet | AI8: =_xlfn.CONCAT(AF8,"|",AG8,"|",AH8) -> Jyotirmayee Ratha|DevOps|SambalpurNet | AK8: Jyotirmayee Ratha | AL8: =LEFT(AK8,1)&"."&MID(AK8,FIND(" ",AK8)+1,1)&"." -> J.R. | AN8: LinkedIn | AO8: =IF(UPPER(AN8)="linkedin","Linkedln",IF(UPPER(AN8)="naukri","Naukri")) -> Linkedln | AQ8: Jyotirmayee Ratha | AR8: =IF(ISNUMBER(SEARCH("Mishra",AQ8)),"Mishra","NO") -> NO | AT8: Fleet Management | AU8: =LEN(AT8) -> 16 | AW8: =DATEDIF(BI8,TODAY(),"Y") -> 7 | AY8: 01-02-2023 | AZ8: =DATE(RIGHT(AY8,4),MID(AY8,4,2),LEFT(AY8,2)) -> 44958 | BA8: =MONTH(AZ8)&"-"&YEAR(AZ8) -> 2-2023 | BC8: 10-11-2021 | BD8: =DATE(RIGHT(BC8,4),MID(BC8,4,2),LEFT(BC8,2)) -> 44510 | BE8: Under Review | BF8: =IF(AND(BD8<TODAY(),BE8<>"Completed"),"Overdue","On Track") -> Overdue | BH8: 28-12-2018 | BI8: =IF(LEN(LEFT(BH8,FIND("-",BH8)-1))=4,DATE(LEFT(BH8,4),MID(BH8,6,2),RIGHT(BH8,2)),DATE(RIGHT(BH8,4),MID(BH8,4,2),LEFT(BH8,2))) -> 43462 | BJ8: =NETWORKDAYS(BI8,TODAY()) -> 1991 | BL8: =IF(MONTH(BI8)<=3,"Q1","No") -> No | BM8: =DATE(RIGHT(AY8,4),MID(AY8,4,2),LEFT(AY8,2)) -> 44958 | BN8: =IF(LEN(LEFT(BH8,FIND("-",BH8)-1))=4,DATE(LEFT(BH8,4),MID(BH8,6,2),RIGHT(BH8,2)),DATE(RIGHT(BH8,4),MID(BH8,4,2),LEFT(BH8,2))) -> 43462 | BO8: =ABS(BN8-BM8) -> 1496 | BP8: EMP0007 | BQ8: DevOps | BR8: EMP0076 | BS8: ATT00007 | BT8: =VLOOKUP(BR8,$BP$2:$BQ$601,2,FALSE) -> Marketing | BV8: EMP0007 | BW8: Jyotirmayee Ratha | BX8: Fleet Management | BY8: EMP0105 | BZ8: =VLOOKUP(BY8,$BV$2:$BW$601,2,FALSE) -> Barsha Mahapatra | CB8: Satyajit Padhi | CC8: Jyotirmayee Ratha | CD8: SRE | CE8: Not Found | CG8: =IFERROR(_xlfn.XLOOKUP(Hiring!A8,Hiring!A8:A407,Hiring!B8:B407,,0),"Not Found") -> Satyajit Padhi
A9: Q5 | B9: Using SUMIFS, find total salary paid to 'Data Science' employees in 'Bhubaneswar' with salary > 50000. | C9: =SUMIFS(Employees!I:I,Employees!E:E,"Data Science",Employees!H:H,"Bhubaneswar",Employees!I:I,">50000") -> 3776916 | F9: 2.3 | G9: {=_xlfn.IFS(F9>=4.5,"Excellent",AND(F9>=3.5,F9<=4.4),"Good",F9<3.5,"Needs Improvement")} -> Needs Improvement | I9: 101.73 | J9: 115.49 | K9: =IF(J9>I9,"Over Budget","Within Budget") -> Over Budget | N9: 86255 | O9: =IF(M9<>N9,"Yes","No") -> Yes | Q9: 6.6 | R9: =IF(ISBLANK(Q9),"No","Yes") -> Yes | T9: 4.14 | U9: =IF(T9>10,"High Attrition","No") -> No | W9: EMP0076 | X9: =VLOOKUP(W9,Employees!$A$1:$B$601,2,FALSE) -> Bikash Biswal | Z9: EMP0008 | AA9: =RIGHT(Z9,4) -> 0008 | AC9: Product | AD9: =PROPER(AC9) -> Product | AF9: Tanmay Nanda | AG9: Product | AH9: TributeAI | AI9: =_xlfn.CONCAT(AF9,"|",AG9,"|",AH9) -> Tanmay Nanda|Product|TributeAI | AK9: Tanmay Nanda | AL9: =LEFT(AK9,1)&"."&MID(AK9,FIND(" ",AK9)+1,1)&"." -> T.N. | AN9: Job Portal | AO9: =IF(UPPER(AN9)="linkedin","Linkedln",IF(UPPER(AN9)="naukri","Naukri")) -> FALSE | AQ9: Tanmay Nanda | AR9: =IF(ISNUMBER(SEARCH("Mishra",AQ9)),"Mishra","NO") -> NO | AT9: Smart Grid System | AU9: =LEN(AT9) -> 17 | AW9: =DATEDIF(BI9,TODAY(),"Y") -> 3 | AY9: 23-09-2024 | AZ9: =DATE(RIGHT(AY9,4),MID(AY9,4,2),LEFT(AY9,2)) -> 45558 | BA9: =MONTH(AZ9)&"-"&YEAR(AZ9) -> 9-2024 | BC9: 08-04-2024 | BD9: =DATE(RIGHT(BC9,4),MID(BC9,4,2),LEFT(BC9,2)) -> 45390 | BE9: Under Review | BF9: =IF(AND(BD9<TODAY(),BE9<>"Completed"),"Overdue","On Track") -> Overdue | BH9: 2023-01-31 | BI9: =IF(LEN(LEFT(BH9,FIND("-",BH9)-1))=4,DATE(LEFT(BH9,4),MID(BH9,6,2),RIGHT(BH9,2)),DATE(RIGHT(BH9,4),MID(BH9,4,2),LEFT(BH9,2))) -> 44957 | BJ9: =NETWORKDAYS(BI9,TODAY()) -> 924 | BL9: =IF(MONTH(BI9)<=3,"Q1","No") -> Q1 | BM9: =DATE(RIGHT(AY9,4),MID(AY9,4,2),LEFT(AY9,2)) -> 45558 | BN9: =IF(LEN(LEFT(BH9,FIND("-",BH9)-1))=4,DATE(LEFT(BH9,4),MID(BH9,6,2),RIGHT(BH9,2)),DATE(RIGHT(BH9,4),MID(BH9,4,2),LEFT(BH9,2))) -> 44957 | BO9: =ABS(BN9-BM9) -> 601 | BP9: EMP0008 | BQ9: Product | BR9: EMP0076 | BS9: ATT00008 | BT9: =VLOOKUP(BR9,$BP$2:$BQ$601,2,FALSE) -> Marketing | BV9: EMP0008 | BW9: Tanmay Nanda | BX9: Smart Grid System | BY9: EMP0241 | BZ9: =VLOOKUP(BY9,$BV$2:$BW$601,2,FALSE) -> Tapas Parida | CB9: Sudhansu Biswal | CC9: Tanmay Nanda | CD9: Associate PM | CE9: BI Developer | CG9: =IFERROR(_xlfn.XLOOKUP(Hiring!A9,Hiring!A9:A408,Hiring!B9:B408,,0),"Not Found") -> Sudhansu Biswal
A10: Q6 | B10: Count employees who are 'Active' AND have performance rating ≥ 4.5. Use COUNTIFS. | C10: =COUNTIFS(Employees!M:M,"Active",Employees!L:L,">=4.5") -> 70 | F10: 3.2 | G10: {=_xlfn.IFS(F10>=4.5,"Excellent",AND(F10>=3.5,F10<=4.4),"Good",F10<3.5,"Needs Improvement")} -> Needs Improvement | I10: 96.83 | J10: 89.11 | K10: =IF(J10>I10,"Over Budget","Within Budget") -> Within Budget | M10: 25381 | N10: 24144 | O10: =IF(M10<>N10,"Yes","No") -> Yes | Q10: 9.87 | R10: =IF(ISBLANK(Q10),"No","Yes") -> Yes | T10: 8.92 | U10: =IF(T10>10,"High Attrition","No") -> No | W10: EMP0076 | X10: =VLOOKUP(W10,Employees!$A$1:$B$601,2,FALSE) -> Bikash Biswal | Z10: EMP0009 | AA10: =RIGHT(Z10,4) -> 0009 | AC10: Sales | AD10: =PROPER(AC10) -> Sales | AF10: Bikash Routray | AG10: Sales | AH10: OdishaCode Labs | AI10: =_xlfn.CONCAT(AF10,"|",AG10,"|",AH10) -> Bikash Routray|Sales|OdishaCode Labs | AK10: Bikash Routray | AL10: =LEFT(AK10,1)&"."&MID(AK10,FIND(" ",AK10)+1,1)&"." -> B.R. | AN10: linkedin | AO10: =IF(UPPER(AN10)="linkedin","Linkedln",IF(UPPER(AN10)="naukri","Naukri")) -> Linkedln | AQ10: Bikash Routray | AR10: =IF(ISNUMBER(SEARCH("Mishra",AQ10)),"Mishra","NO") -> NO | AT10: Analytics Dashboard | AU10: =LEN(AT10) -> 19 | AW10: =DATEDIF(BI10,TODAY(),"Y") -> 7 | AY10: 18-05-2023 | AZ10: =DATE(RIGHT(AY10,4),MID(AY10,4,2),LEFT(AY10,2)) -> 45064 | BA10: =MONTH(AZ10)&"-"&YEAR(AZ10) -> 5-2023 | BC10: 18-01-2023 | BD10: =DATE(RIGHT(BC10,4),MID(BC10,4,2),LEFT(BC10,2)) -> 44944 | BE10: On Hold | BF10: =IF(AND(BD10<TODAY(),BE10<>"Completed"),"Overdue","On Track") -> Overdue | BH10: 14-11-2018 | BI10: =IF(LEN(LEFT(BH10,FIND("-",BH10)-1))=4,DATE(LEFT(BH10,4),MID(BH10,6,2),RIGHT(BH10,2)),DATE(RIGHT(BH10,4),MID(BH10,4,2),LEFT(BH10,2))) -> 43418 | BJ10: =NETWORKDAYS(BI10,TODAY()) -> 2023 | BL10: =IF(MONTH(BI10)<=3,"Q1","No") -> No | BM10: =DATE(RIGHT(AY10,4),MID(AY10,4,2),LEFT(AY10,2)) -> 45064 | BN10: =IF(LEN(LEFT(BH10,FIND("-",BH10)-1))=4,DATE(LEFT(BH10,4),MID(BH10,6,2),RIGHT(BH10,2)),DATE(RIGHT(BH10,4),MID(BH10,4,2),LEFT(BH10,2))) -> 43418 | BO10: =ABS(BN10-BM10) -> 1646 | BP10: EMP0009 | BQ10: Sales | BR10: EMP0076 | BS10: ATT00009 | BT10: =VLOOKUP(BR10,$BP$2:$BQ$601,2,FALSE) -> Marketing | BV10: EMP0009 | BW10: Bikash Routray | BX10: Analytics Dashboard | BY10: EMP0414 | BZ10: =VLOOKUP(BY10,$BV$2:$BW$601,2,FALSE) -> Alka Prusty | CB10: Smita Sahu | CC10: Bikash Routray | CD10: Business Developer | CE10: Not Found | CG10: =IFERROR(_xlfn.XLOOKUP(Hiring!A10,Hiring!A10:A409,Hiring!B10:B409,,0),"Not Found") -> Smita Sahu
A11: Q7 | B11: Find the project with the highest Budget. Use MAX + INDEX-MATCH. | C11: =INDEX(Projects!B2:B201,MATCH(MAX(Projects!F2:F201),Projects!F2:F201,0)) -> Analytics Dashboard | F11: 0 | G11: {=_xlfn.IFS(F11>=4.5,"Excellent",AND(F11>=3.5,F11<=4.4),"Good",F11<3.5,"Needs Improvement")} -> Needs Improvement | I11: 63.75 | J11: 59.08 | K11: =IF(J11>I11,"Over Budget","Within Budget") -> Within Budget | N11: 191563 | O11: =IF(M11<>N11,"Yes","No") -> Yes | Q11: 6.69 | R11: =IF(ISBLANK(Q11),"No","Yes") -> Yes | T11: 6.76 | U11: =IF(T11>10,"High Attrition","No") -> No | W11: EMP0076 | X11: =VLOOKUP(W11,Employees!$A$1:$B$601,2,FALSE) -> Bikash Biswal | Z11: EMP0010 | AA11: =RIGHT(Z11,4) -> 0010 | AC11: Design | AD11: =PROPER(AC11) -> Design | AF11: Sudhansu Dhal | AG11: Design | AH11: KalingaTech Pvt Ltd | AI11: =_xlfn.CONCAT(AF11,"|",AG11,"|",AH11) -> Sudhansu Dhal|Design|KalingaTech Pvt Ltd | AK11: Sudhansu Dhal | AL11: =LEFT(AK11,1)&"."&MID(AK11,FIND(" ",AK11)+1,1)&"." -> S.D. | AN11: Campus | AO11: =IF(UPPER(AN11)="linkedin","Linkedln",IF(UPPER(AN11)="naukri","Naukri")) -> FALSE | AQ11: Sudhansu Dhal | AR11: =IF(ISNUMBER(SEARCH("Mishra",AQ11)),"Mishra","NO") -> NO | AT11: Supply Chain Optimizer | AU11: =LEN(AT11) -> 22 | AW11: =DATEDIF(BI11,TODAY(),"Y") -> 4 | AY11: 28-08-2024 | AZ11: =DATE(RIGHT(AY11,4),MID(AY11,4,2),LEFT(AY11,2)) -> 45532 | BA11: =MONTH(AZ11)&"-"&YEAR(AZ11) -> 8-2024 | BC11: 06-12-2024 | BD11: =DATE(RIGHT(BC11,4),MID(BC11,4,2),LEFT(BC11,2)) -> 45632 | BE11: Under Review | BF11: =IF(AND(BD11<TODAY(),BE11<>"Completed"),"Overdue","On Track") -> Overdue | BH11: 21-02-2022 | BI11: =IF(LEN(LEFT(BH11,FIND("-",BH11)-1))=4,DATE(LEFT(BH11,4),MID(BH11,6,2),RIGHT(BH11,2)),DATE(RIGHT(BH11,4),MID(BH11,4,2),LEFT(BH11,2))) -> 44613 | BJ11: =NETWORKDAYS(BI11,TODAY()) -> 1170 | BL11: =IF(MONTH(BI11)<=3,"Q1","No") -> Q1 | BM11: =DATE(RIGHT(AY11,4),MID(AY11,4,2),LEFT(AY11,2)) -> 45532 | BN11: =IF(LEN(LEFT(BH11,FIND("-",BH11)-1))=4,DATE(LEFT(BH11,4),MID(BH11,6,2),RIGHT(BH11,2)),DATE(RIGHT(BH11,4),MID(BH11,4,2),LEFT(BH11,2))) -> 44613 | BO11: =ABS(BN11-BM11) -> 919 | BP11: EMP0010 | BQ11: Design | BR11: EMP0076 | BS11: ATT00010 | BT11: =VLOOKUP(BR11,$BP$2:$BQ$601,2,FALSE) -> Marketing | BV11: EMP0010 | BW11: Sudhansu Dhal | BX11: Supply Chain Optimizer | BY11: EMP0508 | BZ11: =VLOOKUP(BY11,$BV$2:$BW$601,2,FALSE) -> Barsha Pattnaik | CB11: Nirmal Ratha | CC11: Sudhansu Dhal | CD11: UX Researcher | CE11: Not Found | CG11: =IFERROR(_xlfn.XLOOKUP(Hiring!A11,Hiring!A11:A410,Hiring!B11:B410,,0),"Not Found") -> Nirmal Ratha
A12: Q8 | B12: Calculate average work hours for employees working more than 9 hours/day. Use AVERAGEIF on Attendance sheet. | C12: =AVERAGEIF(Attendance!F:F,">9") -> 10.241798 | F12: 4.7 | G12: {=_xlfn.IFS(F12>=4.5,"Excellent",AND(F12>=3.5,F12<=4.4),"Good",F12<3.5,"Needs Improvement")} -> Excellent | I12: 16.57 | J12: 20.44 | K12: =IF(J12>I12,"Over Budget","Within Budget") -> Over Budget | M12: 160467 | N12: 170124 | O12: =IF(M12<>N12,"Yes","No") -> Yes | Q12: 9.38 | R12: =IF(ISBLANK(Q12),"No","Yes") -> Yes | T12: 9.14 | U12: =IF(T12>10,"High Attrition","No") -> No | W12: EMP0076 | X12: =VLOOKUP(W12,Employees!$A$1:$B$601,2,FALSE) -> Bikash Biswal | Z12: EMP0011 | AA12: =RIGHT(Z12,4) -> 0011 | AC12: Engineering | AD12: =PROPER(AC12) -> Engineering | AF12: Lipsa Prusty | AG12: Engineering | AH12: NilGiri Digitals | AI12: =_xlfn.CONCAT(AF12,"|",AG12,"|",AH12) -> Lipsa Prusty|Engineering|NilGiri Digitals | AK12: Lipsa Prusty | AL12: =LEFT(AK12,1)&"."&MID(AK12,FIND(" ",AK12)+1,1)&"." -> L.P. | AN12: Campus | AO12: =IF(UPPER(AN12)="linkedin","Linkedln",IF(UPPER(AN12)="naukri","Naukri")) -> FALSE | AQ12: Lipsa Prusty | AR12: =IF(ISNUMBER(SEARCH("Mishra",AQ12)),"Mishra","NO") -> NO | AT12: DigitalBank Portal | AU12: =LEN(AT12) -> 18 | AW12: =DATEDIF(BI12,TODAY(),"Y") -> 6 | AY12: 13-10-2024 | AZ12: =DATE(RIGHT(AY12,4),MID(AY12,4,2),LEFT(AY12,2)) -> 45578 | BA12: =MONTH(AZ12)&"-"&YEAR(AZ12) -> 10-2024 | BC12: 08-08-2023 | BD12: =DATE(RIGHT(BC12,4),MID(BC12,4,2),LEFT(BC12,2)) -> 45146 | BE12: In Progress | BF12: =IF(AND(BD12<TODAY(),BE12<>"Completed"),"Overdue","On Track") -> Overdue | BH12: 22-03-2020 | BI12: =IF(LEN(LEFT(BH12,FIND("-",BH12)-1))=4,DATE(LEFT(BH12,4),MID(BH12,6,2),RIGHT(BH12,2)),DATE(RIGHT(BH12,4),MID(BH12,4,2),LEFT(BH12,2))) -> 43912 | BJ12: =NETWORKDAYS(BI12,TODAY()) -> 1670 | BL12: =IF(MONTH(BI12)<=3,"Q1","No") -> Q1 | BM12: =DATE(RIGHT(AY12,4),MID(AY12,4,2),LEFT(AY12,2)) -> 45578 | BN12: =IF(LEN(LEFT(BH12,FIND("-",BH12)-1))=4,DATE(LEFT(BH12,4),MID(BH12,6,2),RIGHT(BH12,2)),DATE(RIGHT(BH12,4),MID(BH12,4,2),LEFT(BH12,2))) -> 43912 | BO12: =ABS(BN12-BM12) -> 1666 | BP12: EMP0011 | BQ12: Engineering | BR12: EMP0076 | BS12: ATT00011 | BT12: =VLOOKUP(BR12,$BP$2:$BQ$601,2,FALSE) -> Marketing | BV12: EMP0011 | BW12: Lipsa Prusty | BX12: DigitalBank Portal | BY12: EMP0291 | BZ12: =VLOOKUP(BY12,$BV$2:$BW$601,2,FALSE) -> Rajan Routray | CB12: Nirmal Padhi | CC12: Lipsa Prusty | CD12: Software Engineer | CE12: HR Manager | CG12: =IFERROR(_xlfn.XLOOKUP(Hiring!A12,Hiring!A12:A411,Hiring!B12:B411,,0),"Not Found") -> Nirmal Padhi
F13: 2.6 | G13: {=_xlfn.IFS(F13>=4.5,"Excellent",AND(F13>=3.5,F13<=4.4),"Good",F13<3.5,"Needs Improvement")} -> Needs Improvement | I13: 10.59 | J13: 10.16 | K13: =IF(J13>I13,"Over Budget","Within Budget") -> Within Budget | M13: 122402 | N13: 108417 | O13: =IF(M13<>N13,"Yes","No") -> Yes | Q13: 10.03 | R13: =IF(ISBLANK(Q13),"No","Yes") -> Yes | T13: 7.43 | U13: =IF(T13>10,"High Attrition","No") -> No | W13: EMP0076 | X13: =VLOOKUP(W13,Employees!$A$1:$B$601,2,FALSE) -> Bikash Biswal | Z13: EMP0012 | AA13: =RIGHT(Z13,4) -> 0012 | AC13: HR | AD13: =PROPER(AC13) -> Hr | AF13: Puspita Mahapatra | AG13: HR | AH13: TributeAI | AI13: =_xlfn.CONCAT(AF13,"|",AG13,"|",AH13) -> Puspita Mahapatra|HR|TributeAI | AK13: Puspita Mahapatra | AL13: =LEFT(AK13,1)&"."&MID(AK13,FIND(" ",AK13)+1,1)&"." -> P.M. | AN13: linkedin | AO13: =IF(UPPER(AN13)="linkedin","Linkedln",IF(UPPER(AN13)="naukri","Naukri")) -> Linkedln | AQ13: Puspita Mahapatra | AR13: =IF(ISNUMBER(SEARCH("Mishra",AQ13)),"Mishra","NO") -> NO | AT13: Smart Grid System | AU13: =LEN(AT13) -> 17 | AW13: =DATEDIF(BI13,TODAY(),"Y") -> 2 | AY13: 20-10-2024 | AZ13: =DATE(RIGHT(AY13,4),MID(AY13,4,2),LEFT(AY13,2)) -> 45585 | BA13: =MONTH(AZ13)&"-"&YEAR(AZ13) -> 10-2024 | BC13: 16-06-2023 | BD13: =DATE(RIGHT(BC13,4),MID(BC13,4,2),LEFT(BC13,2)) -> 45093 | BE13: Cancelled | BF13: =IF(AND(BD13<TODAY(),BE13<>"Completed"),"Overdue","On Track") -> Overdue | BH13: 03-09-2023 | BI13: =IF(LEN(LEFT(BH13,FIND("-",BH13)-1))=4,DATE(LEFT(BH13,4),MID(BH13,6,2),RIGHT(BH13,2)),DATE(RIGHT(BH13,4),MID(BH13,4,2),LEFT(BH13,2))) -> 45172 | BJ13: =NETWORKDAYS(BI13,TODAY()) -> 770 | BL13: =IF(MONTH(BI13)<=3,"Q1","No") -> No | BM13: =DATE(RIGHT(AY13,4),MID(AY13,4,2),LEFT(AY13,2)) -> 45585 | BN13: =IF(LEN(LEFT(BH13,FIND("-",BH13)-1))=4,DATE(LEFT(BH13,4),MID(BH13,6,2),RIGHT(BH13,2)),DATE(RIGHT(BH13,4),MID(BH13,4,2),LEFT(BH13,2))) -> 45172 | BO13: =ABS(BN13-BM13) -> 413 | BP13: EMP0012 | BQ13: HR | BR13: EMP0076 | BS13: ATT00012 | BT13: =VLOOKUP(BR13,$BP$2:$BQ$601,2,FALSE) -> Marketing | BV13: EMP0012 | BW13: Puspita Mahapatra | BX13: Smart Grid System | BY13: EMP0352 | BZ13: =VLOOKUP(BY13,$BV$2:$BW$601,2,FALSE) -> Alka Sahoo | CB13: Nirmal Padhi | CC13: Puspita Mahapatra | CD13: Talent Acquisition | CE13: HR Manager | CG13: =IFERROR(_xlfn.XLOOKUP(Hiring!A13,Hiring!A13:A412,Hiring!B13:B412,,0),"Not Found") -> Nirmal Padhi
A14: SECTION B — LOGICAL FUNCTIONS | F14: 4.6 | G14: {=_xlfn.IFS(F14>=4.5,"Excellent",AND(F14>=3.5,F14<=4.4),"Good",F14<3.5,"Needs Improvement")} -> Excellent | I14: 9.07 | J14: 10.12 | K14: =IF(J14>I14,"Over Budget","Within Budget") -> Over Budget | M14: 166699 | O14: =IF(M14<>N14,"Yes","No") -> Yes | Q14: 9.92 | R14: =IF(ISBLANK(Q14),"No","Yes") -> Yes | T14: 2.87 | U14: =IF(T14>10,"High Attrition","No") -> No | W14: EMP0076 | X14: =VLOOKUP(W14,Employees!$A$1:$B$601,2,FALSE) -> Bikash Biswal | Z14: EMP0013 | AA14: =RIGHT(Z14,4) -> 0013 | AC14: Data Science | AD14: =PROPER(AC14) -> Data Science | AF14: Nirmal Samal | AG14: Data Science | AH14: NilGiri Digitals | AI14: =_xlfn.CONCAT(AF14,"|",AG14,"|",AH14) -> Nirmal Samal|Data Science|NilGiri Digitals | AK14: Nirmal Samal | AL14: =LEFT(AK14,1)&"."&MID(AK14,FIND(" ",AK14)+1,1)&"." -> N.S. | AN14: LinkedIn | AO14: =IF(UPPER(AN14)="linkedin","Linkedln",IF(UPPER(AN14)="naukri","Naukri")) -> Linkedln | AQ14: Nirmal Samal | AR14: =IF(ISNUMBER(SEARCH("Mishra",AQ14)),"Mishra","NO") -> NO | AT14: HR Automation Suite | AU14: =LEN(AT14) -> 19 | AW14: =DATEDIF(BI14,TODAY(),"Y") -> 4 | AY14: 13-07-2023 | AZ14: =DATE(RIGHT(AY14,4),MID(AY14,4,2),LEFT(AY14,2)) -> 45120 | BA14: =MONTH(AZ14)&"-"&YEAR(AZ14) -> 7-2023 | BC14: 21-03-2023 | BD14: =DATE(RIGHT(BC14,4),MID(BC14,4,2),LEFT(BC14,2)) -> 45006 | BE14: On Hold | BF14: =IF(AND(BD14<TODAY(),BE14<>"Completed"),"Overdue","On Track") -> Overdue | BH14: 01-08-2022 | BI14: =IF(LEN(LEFT(BH14,FIND("-",BH14)-1))=4,DATE(LEFT(BH14,4),MID(BH14,6,2),RIGHT(BH14,2)),DATE(RIGHT(BH14,4),MID(BH14,4,2),LEFT(BH14,2))) -> 44774 | BJ14: =NETWORKDAYS(BI14,TODAY()) -> 1055 | BL14: =IF(MONTH(BI14)<=3,"Q1","No") -> No | BM14: =DATE(RIGHT(AY14,4),MID(AY14,4,2),LEFT(AY14,2)) -> 45120 | BN14: =IF(LEN(LEFT(BH14,FIND("-",BH14)-1))=4,DATE(LEFT(BH14,4),MID(BH14,6,2),RIGHT(BH14,2)),DATE(RIGHT(BH14,4),MID(BH14,4,2),LEFT(BH14,2))) -> 44774 | BO14: =ABS(BN14-BM14) -> 346 | BP14: EMP0013 | BQ14: Data Science | BR14: EMP0076 | BS14: ATT00013 | BT14: =VLOOKUP(BR14,$BP$2:$BQ$601,2,FALSE) -> Marketing | BV14: EMP0013 | BW14: Nirmal Samal | BX14: HR Automation Suite | BY14: EMP0094 | BZ14: =VLOOKUP(BY14,$BV$2:$BW$601,2,FALSE) -> Abhishek Parida | CB14: Tapas Dhal | CC14: Nirmal Samal | CD14: Data Analyst | CE14: Not Found | CG14: =IFERROR(_xlfn.XLOOKUP(Hiring!A14,Hiring!A14:A413,Hiring!B14:B413,,0),"Not Found") -> Tapas Dhal
A15: Q9 | B15: Create a column 'Performance_Band': Rating ≥ 4.5 → 'Excellent', 3.5–4.4 → 'Good', < 3.5 → 'Needs Improvement'. Use IFS. | C15: Done | F15: 3.5 | G15: {=_xlfn.IFS(F15>=4.5,"Excellent",AND(F15>=3.5,F15<=4.4),"Good",F15<3.5,"Needs Improvement")} -> Good | I15: 139.64 | J15: 171.38 | K15: =IF(J15>I15,"Over Budget","Within Budget") -> Over Budget | M15: 135340 | N15: 144314 | O15: =IF(M15<>N15,"Yes","No") -> Yes | Q15: 11.21 | R15: =IF(ISBLANK(Q15),"No","Yes") -> Yes | T15: 1.11 | U15: =IF(T15>10,"High Attrition","No") -> No | W15: EMP0076 | X15: =VLOOKUP(W15,Employees!$A$1:$B$601,2,FALSE) -> Bikash Biswal | Z15: EMP0014 | AA15: =RIGHT(Z15,4) -> 0014 | AC15: Design | AD15: =PROPER(AC15) -> Design | AF15: Chinmaya Ratha | AG15: Design | AH15: NilGiri Digitals | AI15: =_xlfn.CONCAT(AF15,"|",AG15,"|",AH15) -> Chinmaya Ratha|Design|NilGiri Digitals | AK15: Chinmaya Ratha | AL15: =LEFT(AK15,1)&"."&MID(AK15,FIND(" ",AK15)+1,1)&"." -> C.R. | AN15: Naukri | AO15: =IF(UPPER(AN15)="linkedin","Linkedln",IF(UPPER(AN15)="naukri","Naukri")) -> Naukri | AQ15: Chinmaya Ratha | AR15: =IF(ISNUMBER(SEARCH("Mishra",AQ15)),"Mishra","NO") -> NO | AT15: Analytics Dashboard | AU15: =LEN(AT15) -> 19 | AW15: =DATEDIF(BI15,TODAY(),"Y") -> 6 | AY15: 02-09-2023 | AZ15: =DATE(RIGHT(AY15,4),MID(AY15,4,2),LEFT(AY15,2)) -> 45171 | BA15: =MONTH(AZ15)&"-"&YEAR(AZ15) -> 9-2023 | BC15: 20-12-2023 | BD15: =DATE(RIGHT(BC15,4),MID(BC15,4,2),LEFT(BC15,2)) -> 45280 | BE15: On Hold | BF15: =IF(AND(BD15<TODAY(),BE15<>"Completed"),"Overdue","On Track") -> Overdue | BH15: 26-01-2020 | BI15: =IF(LEN(LEFT(BH15,FIND("-",BH15)-1))=4,DATE(LEFT(BH15,4),MID(BH15,6,2),RIGHT(BH15,2)),DATE(RIGHT(BH15,4),MID(BH15,4,2),LEFT(BH15,2))) -> 43856 | BJ15: =NETWORKDAYS(BI15,TODAY()) -> 1710 | BL15: =IF(MONTH(BI15)<=3,"Q1","No") -> Q1 | BM15: =DATE(RIGHT(AY15,4),MID(AY15,4,2),LEFT(AY15,2)) -> 45171 | BN15: =IF(LEN(LEFT(BH15,FIND("-",BH15)-1))=4,DATE(LEFT(BH15,4),MID(BH15,6,2),RIGHT(BH15,2)),DATE(RIGHT(BH15,4),MID(BH15,4,2),LEFT(BH15,2))) -> 43856 | BO15: =ABS(BN15-BM15) -> 1315 | BP15: EMP0014 | BQ15: Design | BR15: EMP0076 | BS15: ATT00014 | BT15: =VLOOKUP(BR15,$BP$2:$BQ$601,2,FALSE) -> Marketing | BV15: EMP0014 | BW15: Chinmaya Ratha | BX15: Analytics Dashboard | BY15: EMP0371 | BZ15: =VLOOKUP(BY15,$BV$2:$BW$601,2,FALSE) -> Amlan Sahu | CB15: Abhishek Prusty | CC15: Chinmaya Ratha | CD15: Visual Designer | CE15: Junior Developer | CG15: =IFERROR(_xlfn.XLOOKUP(Hiring!A15,Hiring!A15:A414,Hiring!B15:B414,,0),"Not Found") -> Abhishek Prusty
A16: Q10 | B16: In Projects sheet, flag projects where Actual_Cost > Budget as 'Over Budget', else 'Within Budget'. Use IF. | C16: Done | F16: 1.7 | G16: {=_xlfn.IFS(F16>=4.5,"Excellent",AND(F16>=3.5,F16<=4.4),"Good",F16<3.5,"Needs Improvement")} -> Needs Improvement | I16: 57.32 | J16: 74.5 | K16: =IF(J16>I16,"Over Budget","Within Budget") -> Over Budget | M16: 0 | N16: 0 | O16: =IF(M16<>N16,"Yes","No") -> No | Q16: 10.73 | R16: =IF(ISBLANK(Q16),"No","Yes") -> Yes | T16: 12.2 | U16: =IF(T16>10,"High Attrition","No") -> High Attrition | W16: EMP0076 | X16: =VLOOKUP(W16,Employees!$A$1:$B$601,2,FALSE) -> Bikash Biswal | Z16: EMP0015 | AA16: =RIGHT(Z16,4) -> 0015 | AC16: DevOps | AD16: =PROPER(AC16) -> Devops | AF16: Tanmay Jena | AG16: DevOps | AH16: SambalpurNet | AI16: =_xlfn.CONCAT(AF16,"|",AG16,"|",AH16) -> Tanmay Jena|DevOps|SambalpurNet | AK16: Tanmay Jena | AL16: =LEFT(AK16,1)&"."&MID(AK16,FIND(" ",AK16)+1,1)&"." -> T.J. | AN16: LinkedIn | AO16: =IF(UPPER(AN16)="linkedin","Linkedln",IF(UPPER(AN16)="naukri","Naukri")) -> Linkedln | AQ16: Tanmay Jena | AR16: =IF(ISNUMBER(SEARCH("Mishra",AQ16)),"Mishra","NO") -> NO | AT16: DigitalBank Portal | AU16: =LEN(AT16) -> 18 | AW16: =DATEDIF(BI16,TODAY(),"Y") -> 6 | AY16: 13-03-2023 | AZ16: =DATE(RIGHT(AY16,4),MID(AY16,4,2),LEFT(AY16,2)) -> 44998 | BA16: =MONTH(AZ16)&"-"&YEAR(AZ16) -> 3-2023 | BC16: 15-07-2023 | BD16: =DATE(RIGHT(BC16,4),MID(BC16,4,2),LEFT(BC16,2)) -> 45122 | BE16: On Hold | BF16: =IF(AND(BD16<TODAY(),BE16<>"Completed"),"Overdue","On Track") -> Overdue | BH16: 10-11-2019 | BI16: =IF(LEN(LEFT(BH16,FIND("-",BH16)-1))=4,DATE(LEFT(BH16,4),MID(BH16,6,2),RIGHT(BH16,2)),DATE(RIGHT(BH16,4),MID(BH16,4,2),LEFT(BH16,2))) -> 43779 | BJ16: =NETWORKDAYS(BI16,TODAY()) -> 1765 | BL16: =IF(MONTH(BI16)<=3,"Q1","No") -> No | BM16: =DATE(RIGHT(AY16,4),MID(AY16,4,2),LEFT(AY16,2)) -> 44998 | BN16: =IF(LEN(LEFT(BH16,FIND("-",BH16)-1))=4,DATE(LEFT(BH16,4),MID(BH16,6,2),RIGHT(BH16,2)),DATE(RIGHT(BH16,4),MID(BH16,4,2),LEFT(BH16,2))) -> 43779 | BO16: =ABS(BN16-BM16) -> 1219 | BP16: EMP0015 | BQ16: DevOps | BR16: EMP0076 | BS16: ATT00015 | BT16: =VLOOKUP(BR16,$BP$2:$BQ$601,2,FALSE) -> Marketing | BV16: EMP0015 | BW16: Tanmay Jena | BX16: DigitalBank Portal | BY16: EMP0538 | BZ16: =VLOOKUP(BY16,$BV$2:$BW$601,2,FALSE) -> Barsha Routray | CB16: Smita Prusty | CC16: Tanmay Jena | CD16: Cloud Architect | CE16: Not Found | CG16: =IFERROR(_xlfn.XLOOKUP(Hiring!A16,Hiring!A16:A415,Hiring!B16:B415,,0),"Not Found") -> Smita Prusty
A17: Q11 | B17: In Hiring sheet, create 'Salary_Negotiated' column: Yes if Offered_Salary ≠ Expected_Salary, else No. | C17: Done | F17: 4.1 | G17: {=_xlfn.IFS(F17>=4.5,"Excellent",AND(F17>=3.5,F17<=4.4),"Good",F17<3.5,"Needs Improvement")} -> Good | I17: 190.76 | J17: 200.88 | K17: =IF(J17>I17,"Over Budget","Within Budget") -> Over Budget | M17: 70245 | N17: 75018 | O17: =IF(M17<>N17,"Yes","No") -> Yes | Q17: 10.16 | R17: =IF(ISBLANK(Q17),"No","Yes") -> Yes | T17: 2.15 | U17: =IF(T17>10,"High Attrition","No") -> No | W17: EMP0076 | X17: =VLOOKUP(W17,Employees!$A$1:$B$601,2,FALSE) -> Bikash Biswal | Z17: EMP0016 | AA17: =RIGHT(Z17,4) -> 0016 | AC17: Product | AD17: =PROPER(AC17) -> Product | AF17: Sudhansu Behura | AG17: Product | AH17: CoastalDev Studio | AI17: =_xlfn.CONCAT(AF17,"|",AG17,"|",AH17) -> Sudhansu Behura|Product|CoastalDev Studio | AK17: Sudhansu Behura | AL17: =LEFT(AK17,1)&"."&MID(AK17,FIND(" ",AK17)+1,1)&"." -> S.B. | AN17: linkedin | AO17: =IF(UPPER(AN17)="linkedin","Linkedln",IF(UPPER(AN17)="naukri","Naukri")) -> Linkedln | AQ17: Sudhansu Behura | AR17: =IF(ISNUMBER(SEARCH("Mishra",AQ17)),"Mishra","NO") -> NO | AT17: Analytics Dashboard | AU17: =LEN(AT17) -> 19 | AW17: =DATEDIF(BI17,TODAY(),"Y") -> 5 | AY17: 08-12-2023 | AZ17: =DATE(RIGHT(AY17,4),MID(AY17,4,2),LEFT(AY17,2)) -> 45268 | BA17: =MONTH(AZ17)&"-"&YEAR(AZ17) -> 12-2023 | BC17: 08-05-2023 | BD17: =DATE(RIGHT(BC17,4),MID(BC17,4,2),LEFT(BC17,2)) -> 45054 | BE17: Under Review | BF17: =IF(AND(BD17<TODAY(),BE17<>"Completed"),"Overdue","On Track") -> Overdue | BH17: 2021-05-06 | BI17: =IF(LEN(LEFT(BH17,FIND("-",BH17)-1))=4,DATE(LEFT(BH17,4),MID(BH17,6,2),RIGHT(BH17,2)),DATE(RIGHT(BH17,4),MID(BH17,4,2),LEFT(BH17,2))) -> 44322 | BJ17: =NETWORKDAYS(BI17,TODAY()) -> 1377 | BL17: =IF(MONTH(BI17)<=3,"Q1","No") -> No | BM17: =DATE(RIGHT(AY17,4),MID(AY17,4,2),LEFT(AY17,2)) -> 45268 | BN17: =IF(LEN(LEFT(BH17,FIND("-",BH17)-1))=4,DATE(LEFT(BH17,4),MID(BH17,6,2),RIGHT(BH17,2)),DATE(RIGHT(BH17,4),MID(BH17,4,2),LEFT(BH17,2))) -> 44322 | BO17: =ABS(BN17-BM17) -> 946 | BP17: EMP0016 | BQ17: Product | BR17: EMP0076 | BS17: ATT00016 | BT17: =VLOOKUP(BR17,$BP$2:$BQ$601,2,FALSE) -> Marketing | BV17: EMP0016 | BW17: Sudhansu Behura | BX17: Analytics Dashboard | BY17: EMP0119 | BZ17: =VLOOKUP(BY17,$BV$2:$BW$601,2,FALSE) -> Tanmay Prusty | CB17: Ankita Choudhury | CC17: Sudhansu Behura | CD17: Associate PM | CE17: Finance Analyst | CG17: =IFERROR(_xlfn.XLOOKUP(Hiring!A17,Hiring!A17:A416,Hiring!B17:B416,,0),"Not Found") -> Ankita Choudhury
A18: Q12 | B18: Flag attendance records where Work_Hours is blank. Use IF + ISBLANK. | C18: Done | F18: 4.8 | G18: {=_xlfn.IFS(F18>=4.5,"Excellent",AND(F18>=3.5,F18<=4.4),"Good",F18<3.5,"Needs Improvement")} -> Excellent | I18: 61.25 | J18: 53.5 | K18: =IF(J18>I18,"Over Budget","Within Budget") -> Within Budget | M18: 151435 | N18: 134338 | O18: =IF(M18<>N18,"Yes","No") -> Yes | Q18: 8.28 | R18: =IF(ISBLANK(Q18),"No","Yes") -> Yes | T18: 6.02 | U18: =IF(T18>10,"High Attrition","No") -> No | W18: EMP0076 | X18: =VLOOKUP(W18,Employees!$A$1:$B$601,2,FALSE) -> Bikash Biswal | Z18: EMP0017 | AA18: =RIGHT(Z18,4) -> 0017 | AC18: Sales | AD18: =PROPER(AC18) -> Sales | AF18: Sangita Padhi | AG18: Sales | AH18: CoastalDev Studio | AI18: =_xlfn.CONCAT(AF18,"|",AG18,"|",AH18) -> Sangita Padhi|Sales|CoastalDev Studio | AK18: Sangita Padhi | AL18: =LEFT(AK18,1)&"."&MID(AK18,FIND(" ",AK18)+1,1)&"." -> S.P. | AN18: LinkedIn | AO18: =IF(UPPER(AN18)="linkedin","Linkedln",IF(UPPER(AN18)="naukri","Naukri")) -> Linkedln | AQ18: Sangita Padhi | AR18: =IF(ISNUMBER(SEARCH("Mishra",AQ18)),"Mishra","NO") -> NO | AT18: IoT Gateway | AU18: =LEN(AT18) -> 11 | AW18: =DATEDIF(BI18,TODAY(),"Y") -> 2 | AY18: 27-08-2023 | AZ18: =DATE(RIGHT(AY18,4),MID(AY18,4,2),LEFT(AY18,2)) -> 45165 | BA18: =MONTH(AZ18)&"-"&YEAR(AZ18) -> 8-2023 | BC18: 18-07-2021 | BD18: =DATE(RIGHT(BC18,4),MID(BC18,4,2),LEFT(BC18,2)) -> 44395 | BE18: Cancelled | BF18: =IF(AND(BD18<TODAY(),BE18<>"Completed"),"Overdue","On Track") -> Overdue | BH18: 08-11-2023 | BI18: =IF(LEN(LEFT(BH18,FIND("-",BH18)-1))=4,DATE(LEFT(BH18,4),MID(BH18,6,2),RIGHT(BH18,2)),DATE(RIGHT(BH18,4),MID(BH18,4,2),LEFT(BH18,2))) -> 45238 | BJ18: =NETWORKDAYS(BI18,TODAY()) -> 723 | BL18: =IF(MONTH(BI18)<=3,"Q1","No") -> No | BM18: =DATE(RIGHT(AY18,4),MID(AY18,4,2),LEFT(AY18,2)) -> 45165 | BN18: =IF(LEN(LEFT(BH18,FIND("-",BH18)-1))=4,DATE(LEFT(BH18,4),MID(BH18,6,2),RIGHT(BH18,2)),DATE(RIGHT(BH18,4),MID(BH18,4,2),LEFT(BH18,2))) -> 45238 | BO18: =ABS(BN18-BM18) -> 73 | BP18: EMP0017 | BQ18: Sales | BR18: EMP0076 | BS18: ATT00017 | BT18: =VLOOKUP(BR18,$BP$2:$BQ$601,2,FALSE) -> Marketing | BV18: EMP0017 | BW18: Sangita Padhi | BX18: IoT Gateway | BY18: EMP0540 | BZ18: =VLOOKUP(BY18,$BV$2:$BW$601,2,FALSE) -> Tanmay Senapati | CB18: Sudhansu Sahu | CC18: Sangita Padhi | CD18: Sales Manager | CE18: UI Designer | CG18: =IFERROR(_xlfn.XLOOKUP(Hiring!A18,Hiring!A18:A417,Hiring!B18:B417,,0),"Not Found") -> Sudhansu Sahu
A19: Q13 | B19: In KPI sheet, create a column: If Attrition_Pct > 10 → 'High Attrition', else 'Normal'. Use IF. | C19: Done | F19: 1.8 | G19: {=_xlfn.IFS(F19>=4.5,"Excellent",AND(F19>=3.5,F19<=4.4),"Good",F19<3.5,"Needs Improvement")} -> Needs Improvement | I19: 149.91 | J19: 115.82 | K19: =IF(J19>I19,"Over Budget","Within Budget") -> Within Budget | N19: 75363 | O19: =IF(M19<>N19,"Yes","No") -> Yes | R19: =IF(ISBLANK(Q19),"No","Yes") -> No | T19: 2.96 | U19: =IF(T19>10,"High Attrition","No") -> No | W19: EMP0076 | X19: =VLOOKUP(W19,Employees!$A$1:$B$601,2,FALSE) -> Bikash Biswal | Z19: EMP0018 | AA19: =RIGHT(Z19,4) -> 0018 | AC19: Engineering | AD19: =PROPER(AC19) -> Engineering | AF19: Barsha Prusty | AG19: Engineering | AH19: BlueLotus IT | AI19: =_xlfn.CONCAT(AF19,"|",AG19,"|",AH19) -> Barsha Prusty|Engineering|BlueLotus IT | AK19: Barsha Prusty | AL19: =LEFT(AK19,1)&"."&MID(AK19,FIND(" ",AK19)+1,1)&"." -> B.P. | AN19: naukri | AO19: =IF(UPPER(AN19)="linkedin","Linkedln",IF(UPPER(AN19)="naukri","Naukri")) -> Naukri | AQ19: Barsha Prusty | AR19: =IF(ISNUMBER(SEARCH("Mishra",AQ19)),"Mishra","NO") -> NO | AT19: IoT Gateway | AU19: =LEN(AT19) -> 11 | AW19: =DATEDIF(BI19,TODAY(),"Y") -> 4 | AY19: 29-10-2023 | AZ19: =DATE(RIGHT(AY19,4),MID(AY19,4,2),LEFT(AY19,2)) -> 45228 | BA19: =MONTH(AZ19)&"-"&YEAR(AZ19) -> 10-2023 | BC19: 30-08-2024 | BD19: =DATE(RIGHT(BC19,4),MID(BC19,4,2),LEFT(BC19,2)) -> 45534 | BE19: Cancelled | BF19: =IF(AND(BD19<TODAY(),BE19<>"Completed"),"Overdue","On Track") -> Overdue | BH19: 20-08-2021 | BI19: =IF(LEN(LEFT(BH19,FIND("-",BH19)-1))=4,DATE(LEFT(BH19,4),MID(BH19,6,2),RIGHT(BH19,2)),DATE(RIGHT(BH19,4),MID(BH19,4,2),LEFT(BH19,2))) -> 44428 | BJ19: =NETWORKDAYS(BI19,TODAY()) -> 1301 | BL19: =IF(MONTH(BI19)<=3,"Q1","No") -> No | BM19: =DATE(RIGHT(AY19,4),MID(AY19,4,2),LEFT(AY19,2)) -> 45228 | BN19: =IF(LEN(LEFT(BH19,FIND("-",BH19)-1))=4,DATE(LEFT(BH19,4),MID(BH19,6,2),RIGHT(BH19,2)),DATE(RIGHT(BH19,4),MID(BH19,4,2),LEFT(BH19,2))) -> 44428 | BO19: =ABS(BN19-BM19) -> 800 | BP19: EMP0018 | BQ19: Engineering | BR19: EMP0076 | BS19: ATT00018 | BT19: =VLOOKUP(BR19,$BP$2:$BQ$601,2,FALSE) -> Marketing | BV19: EMP0018 | BW19: Barsha Prusty | BX19: IoT Gateway | BY19: EMP0169 | BZ19: =VLOOKUP(BY19,$BV$2:$BW$601,2,FALSE) -> Lipsa Pattnaik | CB19: Tanmay Padhi | CC19: Barsha Prusty | CD19: Architect | CE19: Data Analyst | CG19: =IFERROR(_xlfn.XLOOKUP(Hiring!A19,Hiring!A19:A418,Hiring!B19:B418,,0),"Not Found") -> Tanmay Padhi
A20: Q14 | B20: Use IFERROR with VLOOKUP to fetch employee name from Employee_ID in Attendance sheet. Handle errors. | C20: Done | F20: 3 | G20: {=_xlfn.IFS(F20>=4.5,"Excellent",AND(F20>=3.5,F20<=4.4),"Good",F20<3.5,"Needs Improvement")} -> Needs Improvement | I20: 131.08 | J20: 114.66 | K20: =IF(J20>I20,"Over Budget","Within Budget") -> Within Budget | N20: 60126 | O20: =IF(M20<>N20,"Yes","No") -> Yes | Q20: 11.18 | R20: =IF(ISBLANK(Q20),"No","Yes") -> Yes | T20: 5.13 | U20: =IF(T20>10,"High Attrition","No") -> No | W20: EMP0076 | X20: =VLOOKUP(W20,Employees!$A$1:$B$601,2,FALSE) -> Bikash Biswal | Z20: EMP0019 | AA20: =RIGHT(Z20,4) -> 0019 | AC20: Data Science | AD20: =PROPER(AC20) -> Data Science | AF20: Lipsa Behura | AG20: Data Science | AH20: UtkalSoft Technologies | AI20: =_xlfn.CONCAT(AF20,"|",AG20,"|",AH20) -> Lipsa Behura|Data Science|UtkalSoft Technologies | AK20: Lipsa Behura | AL20: =LEFT(AK20,1)&"."&MID(AK20,FIND(" ",AK20)+1,1)&"." -> L.B. | AN20: naukri | AO20: =IF(UPPER(AN20)="linkedin","Linkedln",IF(UPPER(AN20)="naukri","Naukri")) -> Naukri | AQ20: Lipsa Behura | AR20: =IF(ISNUMBER(SEARCH("Mishra",AQ20)),"Mishra","NO") -> NO | AT20: Talent Management | AU20: =LEN(AT20) -> 17 | AW20: =DATEDIF(BI20,TODAY(),"Y") -> 6 | AY20: 08-05-2024 | AZ20: =DATE(RIGHT(AY20,4),MID(AY20,4,2),LEFT(AY20,2)) -> 45420 | BA20: =MONTH(AZ20)&"-"&YEAR(AZ20) -> 5-2024 | BC20: 21-06-2022 | BD20: =DATE(RIGHT(BC20,4),MID(BC20,4,2),LEFT(BC20,2)) -> 44733 | BE20: In Progress | BF20: =IF(AND(BD20<TODAY(),BE20<>"Completed"),"Overdue","On Track") -> Overdue | BH20: 20-02-2020 | BI20: =IF(LEN(LEFT(BH20,FIND("-",BH20)-1))=4,DATE(LEFT(BH20,4),MID(BH20,6,2),RIGHT(BH20,2)),DATE(RIGHT(BH20,4),MID(BH20,4,2),LEFT(BH20,2))) -> 43881 | BJ20: =NETWORKDAYS(BI20,TODAY()) -> 1692 | BL20: =IF(MONTH(BI20)<=3,"Q1","No") -> Q1 | BM20: =DATE(RIGHT(AY20,4),MID(AY20,4,2),LEFT(AY20,2)) -> 45420 | BN20: =IF(LEN(LEFT(BH20,FIND("-",BH20)-1))=4,DATE(LEFT(BH20,4),MID(BH20,6,2),RIGHT(BH20,2)),DATE(RIGHT(BH20,4),MID(BH20,4,2),LEFT(BH20,2))) -> 43881 | BO20: =ABS(BN20-BM20) -> 1539 | BP20: EMP0019 | BQ20: Data Science | BR20: EMP0076 | BS20: ATT00019 | BT20: =VLOOKUP(BR20,$BP$2:$BQ$601,2,FALSE) -> Marketing | BV20: EMP0019 | BW20: Lipsa Behura | BX20: Talent Management | BY20: EMP0282 | BZ20: =VLOOKUP(BY20,$BV$2:$BW$601,2,FALSE) -> Smita Mohapatra | CB20: Chinmaya Mishra | CC20: Lipsa Behura | CD20: Data Scientist | CE20: Brand Manager | CG20: =IFERROR(_xlfn.XLOOKUP(Hiring!A20,Hiring!A20:A419,Hiring!B20:B419,,0),"Not Found") -> Chinmaya Mishra
F21: 4.3 | G21: {=_xlfn.IFS(F21>=4.5,"Excellent",AND(F21>=3.5,F21<=4.4),"Good",F21<3.5,"Needs Improvement")} -> Good | I21: 124.11 | J21: 89.15 | K21: =IF(J21>I21,"Over Budget","Within Budget") -> Within Budget | M21: 58147 | N21: 67215 | O21: =IF(M21<>N21,"Yes","No") -> Yes | Q21: 7.89 | R21: =IF(ISBLANK(Q21),"No","Yes") -> Yes | T21: 4.05 | U21: =IF(T21>10,"High Attrition","No") -> No | W21: EMP0076 | X21: =VLOOKUP(W21,Employees!$A$1:$B$601,2,FALSE) -> Bikash Biswal | Z21: EMP0020 | AA21: =RIGHT(Z21,4) -> 0020 | AC21: Marketing | AD21: =PROPER(AC21) -> Marketing | AF21: Namita Sahu | AG21: Marketing | AH21: NilGiri Digitals | AI21: =_xlfn.CONCAT(AF21,"|",AG21,"|",AH21) -> Namita Sahu|Marketing|NilGiri Digitals | AK21: Namita Sahu | AL21: =LEFT(AK21,1)&"."&MID(AK21,FIND(" ",AK21)+1,1)&"." -> N.S. | AN21: LinkedIn | AO21: =IF(UPPER(AN21)="linkedin","Linkedln",IF(UPPER(AN21)="naukri","Naukri")) -> Linkedln | AQ21: Namita Sahu | AR21: =IF(ISNUMBER(SEARCH("Mishra",AQ21)),"Mishra","NO") -> NO | AT21: IoT Gateway | AU21: =LEN(AT21) -> 11 | AW21: =DATEDIF(BI21,TODAY(),"Y") -> 6 | AY21: 11-09-2023 | AZ21: =DATE(RIGHT(AY21,4),MID(AY21,4,2),LEFT(AY21,2)) -> 45180 | BA21: =MONTH(AZ21)&"-"&YEAR(AZ21) -> 9-2023 | BC21: 22-01-2022 | BD21: =DATE(RIGHT(BC21,4),MID(BC21,4,2),LEFT(BC21,2)) -> 44583 | BE21: In Progress | BF21: =IF(AND(BD21<TODAY(),BE21<>"Completed"),"Overdue","On Track") -> Overdue | BH21: 09-10-2019 | BI21: =IF(LEN(LEFT(BH21,FIND("-",BH21)-1))=4,DATE(LEFT(BH21,4),MID(BH21,6,2),RIGHT(BH21,2)),DATE(RIGHT(BH21,4),MID(BH21,4,2),LEFT(BH21,2))) -> 43747 | BJ21: =NETWORKDAYS(BI21,TODAY()) -> 1788 | BL21: =IF(MONTH(BI21)<=3,"Q1","No") -> No | BM21: =DATE(RIGHT(AY21,4),MID(AY21,4,2),LEFT(AY21,2)) -> 45180 | BN21: =IF(LEN(LEFT(BH21,FIND("-",BH21)-1))=4,DATE(LEFT(BH21,4),MID(BH21,6,2),RIGHT(BH21,2)),DATE(RIGHT(BH21,4),MID(BH21,4,2),LEFT(BH21,2))) -> 43747 | BO21: =ABS(BN21-BM21) -> 1433 | BP21: EMP0020 | BQ21: Marketing | BR21: EMP0076 | BS21: ATT00020 | BT21: =VLOOKUP(BR21,$BP$2:$BQ$601,2,FALSE) -> Marketing | BV21: EMP0020 | BW21: Namita Sahu | BX21: IoT Gateway | BY21: EMP0571 | BZ21: =VLOOKUP(BY21,$BV$2:$BW$601,2,FALSE) -> Satyajit Tripathy | CB21: Dibya Routray | CC21: Namita Sahu | CD21: Digital Marketer | CE21: Not Found | CG21: =IFERROR(_xlfn.XLOOKUP(Hiring!A21,Hiring!A21:A420,Hiring!B21:B420,,0),"Not Found") -> Dibya Routray
A22: SECTION C — TEXT FUNCTIONS | F22: 4.4 | G22: {=_xlfn.IFS(F22>=4.5,"Excellent",AND(F22>=3.5,F22<=4.4),"Good",F22<3.5,"Needs Improvement")} -> Good | I22: 45.9 | J22: 43.67 | K22: =IF(J22>I22,"Over Budget","Within Budget") -> Within Budget | N22: 113954 | O22: =IF(M22<>N22,"Yes","No") -> Yes | Q22: 10.33 | R22: =IF(ISBLANK(Q22),"No","Yes") -> Yes | T22: 3.2 | U22: =IF(T22>10,"High Attrition","No") -> No | W22: EMP0076 | X22: =VLOOKUP(W22,Employees!$A$1:$B$601,2,FALSE) -> Bikash Biswal | Z22: EMP0021 | AA22: =RIGHT(Z22,4) -> 0021 | AC22: DevOps | AD22: =PROPER(AC22) -> Devops | AF22: Sudhansu Choudhury | AG22: DevOps | AH22: TributeAI | AI22: =_xlfn.CONCAT(AF22,"|",AG22,"|",AH22) -> Sudhansu Choudhury|DevOps|TributeAI | AK22: Sudhansu Choudhury | AL22: =LEFT(AK22,1)&"."&MID(AK22,FIND(" ",AK22)+1,1)&"." -> S.C. | AN22: Walk-in | AO22: =IF(UPPER(AN22)="linkedin","Linkedln",IF(UPPER(AN22)="naukri","Naukri")) -> FALSE | AQ22: Sudhansu Choudhury | AR22: =IF(ISNUMBER(SEARCH("Mishra",AQ22)),"Mishra","NO") -> NO | AT22: Mobile Banking App | AU22: =LEN(AT22) -> 18 | AW22: =DATEDIF(BI22,TODAY(),"Y") -> 6 | AY22: 14-05-2024 | AZ22: =DATE(RIGHT(AY22,4),MID(AY22,4,2),LEFT(AY22,2)) -> 45426 | BA22: =MONTH(AZ22)&"-"&YEAR(AZ22) -> 5-2024 | BC22: 28-05-2024 | BD22: =DATE(RIGHT(BC22,4),MID(BC22,4,2),LEFT(BC22,2)) -> 45440 | BE22: In Progress | BF22: =IF(AND(BD22<TODAY(),BE22<>"Completed"),"Overdue","On Track") -> Overdue | BH22: 09-03-2020 | BI22: =IF(LEN(LEFT(BH22,FIND("-",BH22)-1))=4,DATE(LEFT(BH22,4),MID(BH22,6,2),RIGHT(BH22,2)),DATE(RIGHT(BH22,4),MID(BH22,4,2),LEFT(BH22,2))) -> 43899 | BJ22: =NETWORKDAYS(BI22,TODAY()) -> 1680 | BL22: =IF(MONTH(BI22)<=3,"Q1","No") -> Q1 | BM22: =DATE(RIGHT(AY22,4),MID(AY22,4,2),LEFT(AY22,2)) -> 45426 | BN22: =IF(LEN(LEFT(BH22,FIND("-",BH22)-1))=4,DATE(LEFT(BH22,4),MID(BH22,6,2),RIGHT(BH22,2)),DATE(RIGHT(BH22,4),MID(BH22,4,2),LEFT(BH22,2))) -> 43899 | BO22: =ABS(BN22-BM22) -> 1527 | BP22: EMP0021 | BQ22: DevOps | BR22: EMP0076 | BS22: ATT00021 | BT22: =VLOOKUP(BR22,$BP$2:$BQ$601,2,FALSE) -> Marketing | BV22: EMP0021 | BW22: Sudhansu Choudhury | BX22: Mobile Banking App | BY22: EMP0380 | BZ22: =VLOOKUP(BY22,$BV$2:$BW$601,2,FALSE) -> Ranjit Sahoo | CB22: Ankita Prusty | CC22: Sudhansu Choudhury | CD22: Sr DevOps | CE22: Senior QA | CG22: =IFERROR(_xlfn.XLOOKUP(Hiring!A22,Hiring!A22:A421,Hiring!B22:B421,,0),"Not Found") -> Ankita Prusty
A23: Q15 | B23: Extract the numeric part of Employee_ID (e.g., EMP0001 → 0001). Use MID or RIGHT. | C23: Done | F23: 3 | G23: {=_xlfn.IFS(F23>=4.5,"Excellent",AND(F23>=3.5,F23<=4.4),"Good",F23<3.5,"Needs Improvement")} -> Needs Improvement | I23: 82.79 | J23: 80.58 | K23: =IF(J23>I23,"Over Budget","Within Budget") -> Within Budget | M23: 208454 | N23: 183795 | O23: =IF(M23<>N23,"Yes","No") -> Yes | Q23: 7.45 | R23: =IF(ISBLANK(Q23),"No","Yes") -> Yes | T23: 3.76 | U23: =IF(T23>10,"High Attrition","No") -> No | W23: EMP0076 | X23: =VLOOKUP(W23,Employees!$A$1:$B$601,2,FALSE) -> Bikash Biswal | Z23: EMP0022 | AA23: =RIGHT(Z23,4) -> 0022 | AC23: Marketing | AD23: =PROPER(AC23) -> Marketing | AF23: Sudhansu Mohapatra | AG23: Marketing | AH23: OdishaCode Labs | AI23: =_xlfn.CONCAT(AF23,"|",AG23,"|",AH23) -> Sudhansu Mohapatra|Marketing|OdishaCode Labs | AK23: Sudhansu Mohapatra | AL23: =LEFT(AK23,1)&"."&MID(AK23,FIND(" ",AK23)+1,1)&"." -> S.M. | AN23: Job Portal | AO23: =IF(UPPER(AN23)="linkedin","Linkedln",IF(UPPER(AN23)="naukri","Naukri")) -> FALSE | AQ23: Sudhansu Mohapatra | AR23: =IF(ISNUMBER(SEARCH("Mishra",AQ23)),"Mishra","NO") -> NO | AT23: Inventory Tracker | AU23: =LEN(AT23) -> 17 | AW23: =DATEDIF(BI23,TODAY(),"Y") -> 2 | AY23: 26-07-2023 | AZ23: =DATE(RIGHT(AY23,4),MID(AY23,4,2),LEFT(AY23,2)) -> 45133 | BA23: =MONTH(AZ23)&"-"&YEAR(AZ23) -> 7-2023 | BC23: 23-12-2023 | BD23: =DATE(RIGHT(BC23,4),MID(BC23,4,2),LEFT(BC23,2)) -> 45283 | BE23: Under Review | BF23: =IF(AND(BD23<TODAY(),BE23<>"Completed"),"Overdue","On Track") -> Overdue | BH23: 28-02-2024 | BI23: =IF(LEN(LEFT(BH23,FIND("-",BH23)-1))=4,DATE(LEFT(BH23,4),MID(BH23,6,2),RIGHT(BH23,2)),DATE(RIGHT(BH23,4),MID(BH23,4,2),LEFT(BH23,2))) -> 45350 | BJ23: =NETWORKDAYS(BI23,TODAY()) -> 643 | BL23: =IF(MONTH(BI23)<=3,"Q1","No") -> Q1 | BM23: =DATE(RIGHT(AY23,4),MID(AY23,4,2),LEFT(AY23,2)) -> 45133 | BN23: =IF(LEN(LEFT(BH23,FIND("-",BH23)-1))=4,DATE(LEFT(BH23,4),MID(BH23,6,2),RIGHT(BH23,2)),DATE(RIGHT(BH23,4),MID(BH23,4,2),LEFT(BH23,2))) -> 45350 | BO23: =ABS(BN23-BM23) -> 217 | BP23: EMP0022 | BQ23: Marketing | BR23: EMP0076 | BS23: ATT00022 | BT23: =VLOOKUP(BR23,$BP$2:$BQ$601,2,FALSE) -> Marketing | BV23: EMP0022 | BW23: Sudhansu Mohapatra | BX23: Inventory Tracker | BY23: EMP0207 | BZ23: =VLOOKUP(BY23,$BV$2:$BW$601,2,FALSE) -> Amlan Nanda | CB23: Satyajit Pattnaik | CC23: Sudhansu Mohapatra | CD23: Digital Marketer | CE23: Design Lead | CG23: =IFERROR(_xlfn.XLOOKUP(Hiring!A23,Hiring!A23:A422,Hiring!B23:B422,,0),"Not Found") -> Satyajit Pattnaik
A24: Q16 | B24: Standardize the Department column — some values are lowercase. Use PROPER or UPPER. Create a helper column. | C24: Done | F24: 3.9 | G24: {=_xlfn.IFS(F24>=4.5,"Excellent",AND(F24>=3.5,F24<=4.4),"Good",F24<3.5,"Needs Improvement")} -> Good | I24: 98.49 | J24: 96.59 | K24: =IF(J24>I24,"Over Budget","Within Budget") -> Within Budget | N24: 64504 | O24: =IF(M24<>N24,"Yes","No") -> Yes | Q24: 9.82 | R24: =IF(ISBLANK(Q24),"No","Yes") -> Yes | T24: 7.66 | U24: =IF(T24>10,"High Attrition","No") -> No | W24: EMP0076 | X24: =VLOOKUP(W24,Employees!$A$1:$B$601,2,FALSE) -> Bikash Biswal | Z24: EMP0023 | AA24: =RIGHT(Z24,4) -> 0023 | AC24: Marketing | AD24: =PROPER(AC24) -> Marketing | AF24: Barsha Choudhury | AG24: Marketing | AH24: NilGiri Digitals | AI24: =_xlfn.CONCAT(AF24,"|",AG24,"|",AH24) -> Barsha Choudhury|Marketing|NilGiri Digitals | AK24: Barsha Choudhury | AL24: =LEFT(AK24,1)&"."&MID(AK24,FIND(" ",AK24)+1,1)&"." -> B.C. | AN24: Naukri | AO24: =IF(UPPER(AN24)="linkedin","Linkedln",IF(UPPER(AN24)="naukri","Naukri")) -> Naukri | AQ24: Barsha Choudhury | AR24: =IF(ISNUMBER(SEARCH("Mishra",AQ24)),"Mishra","NO") -> NO | AT24: Smart Parking | AU24: =LEN(AT24) -> 13 | AW24: =DATEDIF(BI24,TODAY(),"Y") -> 4 | AY24: 26-11-2023 | AZ24: =DATE(RIGHT(AY24,4),MID(AY24,4,2),LEFT(AY24,2)) -> 45256 | BA24: =MONTH(AZ24)&"-"&YEAR(AZ24) -> 11-2023 | BC24: 21-01-2025 | BD24: =DATE(RIGHT(BC24,4),MID(BC24,4,2),LEFT(BC24,2)) -> 45678 | BE24: Cancelled | BF24: =IF(AND(BD24<TODAY(),BE24<>"Completed"),"Overdue","On Track") -> Overdue | BH24: 22-06-2022 | BI24: =IF(LEN(LEFT(BH24,FIND("-",BH24)-1))=4,DATE(LEFT(BH24,4),MID(BH24,6,2),RIGHT(BH24,2)),DATE(RIGHT(BH24,4),MID(BH24,4,2),LEFT(BH24,2))) -> 44734 | BJ24: =NETWORKDAYS(BI24,TODAY()) -> 1083 | BL24: =IF(MONTH(BI24)<=3,"Q1","No") -> No | BM24: =DATE(RIGHT(AY24,4),MID(AY24,4,2),LEFT(AY24,2)) -> 45256 | BN24: =IF(LEN(LEFT(BH24,FIND("-",BH24)-1))=4,DATE(LEFT(BH24,4),MID(BH24,6,2),RIGHT(BH24,2)),DATE(RIGHT(BH24,4),MID(BH24,4,2),LEFT(BH24,2))) -> 44734 | BO24: =ABS(BN24-BM24) -> 522 | BP24: EMP0023 | BQ24: Marketing | BR24: EMP0076 | BS24: ATT00023 | BT24: =VLOOKUP(BR24,$BP$2:$BQ$601,2,FALSE) -> Marketing | BV24: EMP0023 | BW24: Barsha Choudhury | BX24: Smart Parking | BY24: EMP0463 | BZ24: =VLOOKUP(BY24,$BV$2:$BW$601,2,FALSE) -> Tapas Mishra | CB24: Rahul Nanda | CC24: Barsha Choudhury | CD24: Digital Marketer | CE24: Not Found | CG24: =IFERROR(_xlfn.XLOOKUP(Hiring!A24,Hiring!A24:A423,Hiring!B24:B423,,0),"Not Found") -> Rahul Nanda
A25: Q17 | B25: Create a full label: 'Saurav Mohapatra | Engineering | TechNova Solutions'. Use CONCAT or &. | C25: Done | F25: 4.5 | G25: {=_xlfn.IFS(F25>=4.5,"Excellent",AND(F25>=3.5,F25<=4.4),"Good",F25<3.5,"Needs Improvement")} -> Excellent | I25: 168.31 | J25: 148.69 | K25: =IF(J25>I25,"Over Budget","Within Budget") -> Within Budget | M25: 225137 | N25: 196050 | O25: =IF(M25<>N25,"Yes","No") -> Yes | Q25: 9.05 | R25: =IF(ISBLANK(Q25),"No","Yes") -> Yes | T25: 3.38 | U25: =IF(T25>10,"High Attrition","No") -> No | W25: EMP0076 | X25: =VLOOKUP(W25,Employees!$A$1:$B$601,2,FALSE) -> Bikash Biswal | Z25: EMP0024 | AA25: =RIGHT(Z25,4) -> 0024 | AC25: QA | AD25: =PROPER(AC25) -> Qa | AF25: Smita Tripathy | AG25: QA | AH25: BlueLotus IT | AI25: =_xlfn.CONCAT(AF25,"|",AG25,"|",AH25) -> Smita Tripathy|QA|BlueLotus IT | AK25: Smita Tripathy | AL25: =LEFT(AK25,1)&"."&MID(AK25,FIND(" ",AK25)+1,1)&"." -> S.T. | AN25: Naukri | AO25: =IF(UPPER(AN25)="linkedin","Linkedln",IF(UPPER(AN25)="naukri","Naukri")) -> Naukri | AQ25: Smita Tripathy | AR25: =IF(ISNUMBER(SEARCH("Mishra",AQ25)),"Mishra","NO") -> NO | AT25: ML Fraud Detection | AU25: =LEN(AT25) -> 18 | AW25: =DATEDIF(BI25,TODAY(),"Y") -> 6 | AY25: 05-04-2024 | AZ25: =DATE(RIGHT(AY25,4),MID(AY25,4,2),LEFT(AY25,2)) -> 45387 | BA25: =MONTH(AZ25)&"-"&YEAR(AZ25) -> 4-2024 | BC25: 05-09-2022 | BD25: =DATE(RIGHT(BC25,4),MID(BC25,4,2),LEFT(BC25,2)) -> 44809 | BE25: In Progress | BF25: =IF(AND(BD25<TODAY(),BE25<>"Completed"),"Overdue","On Track") -> Overdue | BH25: 15-12-2019 | BI25: =IF(LEN(LEFT(BH25,FIND("-",BH25)-1))=4,DATE(LEFT(BH25,4),MID(BH25,6,2),RIGHT(BH25,2)),DATE(RIGHT(BH25,4),MID(BH25,4,2),LEFT(BH25,2))) -> 43814 | BJ25: =NETWORKDAYS(BI25,TODAY()) -> 1740 | BL25: =IF(MONTH(BI25)<=3,"Q1","No") -> No | BM25: =DATE(RIGHT(AY25,4),MID(AY25,4,2),LEFT(AY25,2)) -> 45387 | BN25: =IF(LEN(LEFT(BH25,FIND("-",BH25)-1))=4,DATE(LEFT(BH25,4),MID(BH25,6,2),RIGHT(BH25,2)),DATE(RIGHT(BH25,4),MID(BH25,4,2),LEFT(BH25,2))) -> 43814 | BO25: =ABS(BN25-BM25) -> 1573 | BP25: EMP0024 | BQ25: QA | BR25: EMP0076 | BS25: ATT00024 | BT25: =VLOOKUP(BR25,$BP$2:$BQ$601,2,FALSE) -> Marketing | BV25: EMP0024 | BW25: Smita Tripathy | BX25: ML Fraud Detection | BY25: EMP0285 | BZ25: =VLOOKUP(BY25,$BV$2:$BW$601,2,FALSE) -> Barsha Behura | CB25: Rajan Dhal | CC25: Smita Tripathy | CD25: Test Analyst | CE25: BI Developer | CG25: =IFERROR(_xlfn.XLOOKUP(Hiring!A25,Hiring!A25:A424,Hiring!B25:B424,,0),"Not Found") -> Rajan Dhal
A26: Q18 | B26: Extract initials from employee Full_Name (e.g., Saurav Mohapatra → S.M.). Use LEFT + FIND + MID. | C26: Done | F26: 4.9 | G26: {=_xlfn.IFS(F26>=4.5,"Excellent",AND(F26>=3.5,F26<=4.4),"Good",F26<3.5,"Needs Improvement")} -> Excellent | I26: 31.96 | J26: 38.49 | K26: =IF(J26>I26,"Over Budget","Within Budget") -> Over Budget | M26: 66872 | N26: 66622 | O26: =IF(M26<>N26,"Yes","No") -> Yes | Q26: 7.62 | R26: =IF(ISBLANK(Q26),"No","Yes") -> Yes | T26: 4.03 | U26: =IF(T26>10,"High Attrition","No") -> No | W26: EMP0076 | X26: =VLOOKUP(W26,Employees!$A$1:$B$601,2,FALSE) -> Bikash Biswal | Z26: EMP0025 | AA26: =RIGHT(Z26,4) -> 0025 | AC26: HR | AD26: =PROPER(AC26) -> Hr | AF26: Alka Padhi | AG26: HR | AH26: BlueLotus IT | AI26: =_xlfn.CONCAT(AF26,"|",AG26,"|",AH26) -> Alka Padhi|HR|BlueLotus IT | AK26: Alka Padhi | AL26: =LEFT(AK26,1)&"."&MID(AK26,FIND(" ",AK26)+1,1)&"." -> A.P. | AN26: linkedin | AO26: =IF(UPPER(AN26)="linkedin","Linkedln",IF(UPPER(AN26)="naukri","Naukri")) -> Linkedln | AQ26: Alka Padhi | AR26: =IF(ISNUMBER(SEARCH("Mishra",AQ26)),"Mishra","NO") -> NO | AT26: Data Warehouse Migration | AU26: =LEN(AT26) -> 24 | AW26: =DATEDIF(BI26,TODAY(),"Y") -> 7 | AY26: 03-04-2024 | AZ26: =DATE(RIGHT(AY26,4),MID(AY26,4,2),LEFT(AY26,2)) -> 45385 | BA26: =MONTH(AZ26)&"-"&YEAR(AZ26) -> 4-2024 | BC26: 27-03-2024 | BD26: =DATE(RIGHT(BC26,4),MID(BC26,4,2),LEFT(BC26,2)) -> 45378 | BE26: Under Review | BF26: =IF(AND(BD26<TODAY(),BE26<>"Completed"),"Overdue","On Track") -> Overdue | BH26: 18-04-2019 | BI26: =IF(LEN(LEFT(BH26,FIND("-",BH26)-1))=4,DATE(LEFT(BH26,4),MID(BH26,6,2),RIGHT(BH26,2)),DATE(RIGHT(BH26,4),MID(BH26,4,2),LEFT(BH26,2))) -> 43573 | BJ26: =NETWORKDAYS(BI26,TODAY()) -> 1912 | BL26: =IF(MONTH(BI26)<=3,"Q1","No") -> No | BM26: =DATE(RIGHT(AY26,4),MID(AY26,4,2),LEFT(AY26,2)) -> 45385 | BN26: =IF(LEN(LEFT(BH26,FIND("-",BH26)-1))=4,DATE(LEFT(BH26,4),MID(BH26,6,2),RIGHT(BH26,2)),DATE(RIGHT(BH26,4),MID(BH26,4,2),LEFT(BH26,2))) -> 43573 | BO26: =ABS(BN26-BM26) -> 1812 | BP26: EMP0025 | BQ26: HR | BR26: EMP0076 | BS26: ATT00025 | BT26: =VLOOKUP(BR26,$BP$2:$BQ$601,2,FALSE) -> Marketing | BV26: EMP0025 | BW26: Alka Padhi | BX26: Data Warehouse Migration | BY26: EMP0242 | BZ26: =VLOOKUP(BY26,$BV$2:$BW$601,2,FALSE) -> Rajan Behura | CB26: Puspita Dhal | CC26: Alka Padhi | CD26: HR Executive | CE26: QA Lead | CG26: =IFERROR(_xlfn.XLOOKUP(Hiring!A26,Hiring!A26:A425,Hiring!B26:B425,,0),"Not Found") -> Puspita Dhal
A27: Q19 | B27: Standardize the 'Source' column in Hiring sheet (linkedin → LinkedIn, naukri → Naukri). Use IF + UPPER. | C27: Done | F27: 4.1 | G27: {=_xlfn.IFS(F27>=4.5,"Excellent",AND(F27>=3.5,F27<=4.4),"Good",F27<3.5,"Needs Improvement")} -> Good | I27: 111.45 | J27: 106.53 | K27: =IF(J27>I27,"Over Budget","Within Budget") -> Within Budget | M27: 66284 | N27: 60845 | O27: =IF(M27<>N27,"Yes","No") -> Yes | Q27: 7.45 | R27: =IF(ISBLANK(Q27),"No","Yes") -> Yes | T27: 3.16 | U27: =IF(T27>10,"High Attrition","No") -> No | W27: EMP0076 | X27: =VLOOKUP(W27,Employees!$A$1:$B$601,2,FALSE) -> Bikash Biswal | Z27: EMP0026 | AA27: =RIGHT(Z27,4) -> 0026 | AC27: HR | AD27: =PROPER(AC27) -> Hr | AF27: Saurav Routray | AG27: HR | AH27: InfySoft Bhubaneswar | AI27: =_xlfn.CONCAT(AF27,"|",AG27,"|",AH27) -> Saurav Routray|HR|InfySoft Bhubaneswar | AK27: Saurav Routray | AL27: =LEFT(AK27,1)&"."&MID(AK27,FIND(" ",AK27)+1,1)&"." -> S.R. | AN27: Referral | AO27: =IF(UPPER(AN27)="linkedin","Linkedln",IF(UPPER(AN27)="naukri","Naukri")) -> FALSE | AQ27: Saurav Routray | AR27: =IF(ISNUMBER(SEARCH("Mishra",AQ27)),"Mishra","NO") -> NO | AT27: Customer 360 View | AU27: =LEN(AT27) -> 17 | AW27: =DATEDIF(BI27,TODAY(),"Y") -> 5 | AY27: 23-10-2023 | AZ27: =DATE(RIGHT(AY27,4),MID(AY27,4,2),LEFT(AY27,2)) -> 45222 | BA27: =MONTH(AZ27)&"-"&YEAR(AZ27) -> 10-2023 | BC27: 26-10-2024 | BD27: =DATE(RIGHT(BC27,4),MID(BC27,4,2),LEFT(BC27,2)) -> 45591 | BE27: Cancelled | BF27: =IF(AND(BD27<TODAY(),BE27<>"Completed"),"Overdue","On Track") -> Overdue | BH27: 30-08-2020 | BI27: =IF(LEN(LEFT(BH27,FIND("-",BH27)-1))=4,DATE(LEFT(BH27,4),MID(BH27,6,2),RIGHT(BH27,2)),DATE(RIGHT(BH27,4),MID(BH27,4,2),LEFT(BH27,2))) -> 44073 | BJ27: =NETWORKDAYS(BI27,TODAY()) -> 1555 | BL27: =IF(MONTH(BI27)<=3,"Q1","No") -> No | BM27: =DATE(RIGHT(AY27,4),MID(AY27,4,2),LEFT(AY27,2)) -> 45222 | BN27: =IF(LEN(LEFT(BH27,FIND("-",BH27)-1))=4,DATE(LEFT(BH27,4),MID(BH27,6,2),RIGHT(BH27,2)),DATE(RIGHT(BH27,4),MID(BH27,4,2),LEFT(BH27,2))) -> 44073 | BO27: =ABS(BN27-BM27) -> 1149 | BP27: EMP0026 | BQ27: HR | BR27: EMP0076 | BS27: ATT00026 | BT27: =VLOOKUP(BR27,$BP$2:$BQ$601,2,FALSE) -> Marketing | BV27: EMP0026 | BW27: Saurav Routray | BX27: Customer 360 View | BY27: EMP0532 | BZ27: =VLOOKUP(BY27,$BV$2:$BW$601,2,FALSE) -> Ankita Mohapatra | CB27: Ankita Mishra | CC27: Saurav Routray | CD27: HR Executive | CE27: Not Found | CG27: =IFERROR(_xlfn.XLOOKUP(Hiring!A27,Hiring!A27:A426,Hiring!B27:B426,,0),"Not Found") -> Ankita Mishra
A28: Q20 | B28: Find all employees whose surname is 'Mishra'. Use SEARCH or RIGHT in combination with IF. | C28: Done | F28: 3.9 | G28: {=_xlfn.IFS(F28>=4.5,"Excellent",AND(F28>=3.5,F28<=4.4),"Good",F28<3.5,"Needs Improvement")} -> Good | I28: 183.02 | J28: 236.49 | K28: =IF(J28>I28,"Over Budget","Within Budget") -> Over Budget | M28: 117989 | N28: 129397 | O28: =IF(M28<>N28,"Yes","No") -> Yes | Q28: 9.31 | R28: =IF(ISBLANK(Q28),"No","Yes") -> Yes | T28: 28.57 | U28: =IF(T28>10,"High Attrition","No") -> High Attrition | W28: EMP0076 | X28: =VLOOKUP(W28,Employees!$A$1:$B$601,2,FALSE) -> Bikash Biswal | Z28: EMP0027 | AA28: =RIGHT(Z28,4) -> 0027 | AC28: Product | AD28: =PROPER(AC28) -> Product | AF28: Ranjit Dhal | AG28: Product | AH28: NilGiri Digitals | AI28: =_xlfn.CONCAT(AF28,"|",AG28,"|",AH28) -> Ranjit Dhal|Product|NilGiri Digitals | AK28: Ranjit Dhal | AL28: =LEFT(AK28,1)&"."&MID(AK28,FIND(" ",AK28)+1,1)&"." -> R.D. | AN28: Job Portal | AO28: =IF(UPPER(AN28)="linkedin","Linkedln",IF(UPPER(AN28)="naukri","Naukri")) -> FALSE | AQ28: Ranjit Dhal | AR28: =IF(ISNUMBER(SEARCH("Mishra",AQ28)),"Mishra","NO") -> NO | AT28: LMS Portal | AU28: =LEN(AT28) -> 10 | AW28: =DATEDIF(BI28,TODAY(),"Y") -> 7 | AY28: 21-09-2023 | AZ28: =DATE(RIGHT(AY28,4),MID(AY28,4,2),LEFT(AY28,2)) -> 45190 | BA28: =MONTH(AZ28)&"-"&YEAR(AZ28) -> 9-2023 | BC28: 01-01-2023 | BD28: =DATE(RIGHT(BC28,4),MID(BC28,4,2),LEFT(BC28,2)) -> 44927 | BE28: Under Review | BF28: =IF(AND(BD28<TODAY(),BE28<>"Completed"),"Overdue","On Track") -> Overdue | BH28: 09-04-2019 | BI28: =IF(LEN(LEFT(BH28,FIND("-",BH28)-1))=4,DATE(LEFT(BH28,4),MID(BH28,6,2),RIGHT(BH28,2)),DATE(RIGHT(BH28,4),MID(BH28,4,2),LEFT(BH28,2))) -> 43564 | BJ28: =NETWORKDAYS(BI28,TODAY()) -> 1919 | BL28: =IF(MONTH(BI28)<=3,"Q1","No") -> No | BM28: =DATE(RIGHT(AY28,4),MID(AY28,4,2),LEFT(AY28,2)) -> 45190 | BN28: =IF(LEN(LEFT(BH28,FIND("-",BH28)-1))=4,DATE(LEFT(BH28,4),MID(BH28,6,2),RIGHT(BH28,2)),DATE(RIGHT(BH28,4),MID(BH28,4,2),LEFT(BH28,2))) -> 43564 | BO28: =ABS(BN28-BM28) -> 1626 | BP28: EMP0027 | BQ28: Product | BR28: EMP0076 | BS28: ATT00027 | BT28: =VLOOKUP(BR28,$BP$2:$BQ$601,2,FALSE) -> Marketing | BV28: EMP0027 | BW28: Ranjit Dhal | BX28: LMS Portal | BY28: EMP0599 | BZ28: =VLOOKUP(BY28,$BV$2:$BW$601,2,FALSE) -> Alka Routray | CB28: Namita Biswal | CC28: Ranjit Dhal | CD28: Product Owner | CE28: Not Found | CG28: =IFERROR(_xlfn.XLOOKUP(Hiring!A28,Hiring!A28:A427,Hiring!B28:B427,,0),"Not Found") -> Namita Biswal
A29: Q21 | B29: Count characters in Project_Name to identify unusually short names. Use LEN. | C29: Done | F29: 2.8 | G29: {=_xlfn.IFS(F29>=4.5,"Excellent",AND(F29>=3.5,F29<=4.4),"Good",F29<3.5,"Needs Improvement")} -> Needs Improvement | I29: 138.96 | J29: 163.14 | K29: =IF(J29>I29,"Over Budget","Within Budget") -> Over Budget | N29: 199530 | O29: =IF(M29<>N29,"Yes","No") -> Yes | Q29: 8.44 | R29: =IF(ISBLANK(Q29),"No","Yes") -> Yes | T29: 2.02 | U29: =IF(T29>10,"High Attrition","No") -> No | W29: EMP0076 | X29: =VLOOKUP(W29,Employees!$A$1:$B$601,2,FALSE) -> Bikash Biswal | Z29: EMP0028 | AA29: =RIGHT(Z29,4) -> 0028 | AC29: Product | AD29: =PROPER(AC29) -> Product | AF29: Soumya Senapati | AG29: Product | AH29: SilverByte Systems | AI29: =_xlfn.CONCAT(AF29,"|",AG29,"|",AH29) -> Soumya Senapati|Product|SilverByte Systems | AK29: Soumya Senapati | AL29: =LEFT(AK29,1)&"."&MID(AK29,FIND(" ",AK29)+1,1)&"." -> S.S. | AN29: Campus | AO29: =IF(UPPER(AN29)="linkedin","Linkedln",IF(UPPER(AN29)="naukri","Naukri")) -> FALSE | AQ29: Soumya Senapati | AR29: =IF(ISNUMBER(SEARCH("Mishra",AQ29)),"Mishra","NO") -> NO | AT29: Talent Management | AU29: =LEN(AT29) -> 17 | AW29: =DATEDIF(BI29,TODAY(),"Y") -> 6 | AY29: 30-11-2024 | AZ29: =DATE(RIGHT(AY29,4),MID(AY29,4,2),LEFT(AY29,2)) -> 45626 | BA29: =MONTH(AZ29)&"-"&YEAR(AZ29) -> 11-2024 | BC29: 12-04-2023 | BD29: =DATE(RIGHT(BC29,4),MID(BC29,4,2),LEFT(BC29,2)) -> 45028 | BE29: On Hold | BF29: =IF(AND(BD29<TODAY(),BE29<>"Completed"),"Overdue","On Track") -> Overdue | BH29: 05-02-2020 | BI29: =IF(LEN(LEFT(BH29,FIND("-",BH29)-1))=4,DATE(LEFT(BH29,4),MID(BH29,6,2),RIGHT(BH29,2)),DATE(RIGHT(BH29,4),MID(BH29,4,2),LEFT(BH29,2))) -> 43866 | BJ29: =NETWORKDAYS(BI29,TODAY()) -> 1703 | BL29: =IF(MONTH(BI29)<=3,"Q1","No") -> Q1 | BM29: =DATE(RIGHT(AY29,4),MID(AY29,4,2),LEFT(AY29,2)) -> 45626 | BN29: =IF(LEN(LEFT(BH29,FIND("-",BH29)-1))=4,DATE(LEFT(BH29,4),MID(BH29,6,2),RIGHT(BH29,2)),DATE(RIGHT(BH29,4),MID(BH29,4,2),LEFT(BH29,2))) -> 43866 | BO29: =ABS(BN29-BM29) -> 1760 | BP29: EMP0028 | BQ29: Product | BR29: EMP0076 | BS29: ATT00028 | BT29: =VLOOKUP(BR29,$BP$2:$BQ$601,2,FALSE) -> Marketing | BV29: EMP0028 | BW29: Soumya Senapati | BX29: Talent Management | BY29: EMP0464 | BZ29: =VLOOKUP(BY29,$BV$2:$BW$601,2,FALSE) -> Barsha Pattnaik | CB29: Ranjit Parida | CC29: Soumya Senapati | CD29: Product Owner | CE29: Product Manager | CG29: =IFERROR(_xlfn.XLOOKUP(Hiring!A29,Hiring!A29:A428,Hiring!B29:B428,,0),"Not Found") -> Ranjit Parida
F30: 4.7 | G30: {=_xlfn.IFS(F30>=4.5,"Excellent",AND(F30>=3.5,F30<=4.4),"Good",F30<3.5,"Needs Improvement")} -> Excellent | I30: 34.36 | J30: 35.61 | K30: =IF(J30>I30,"Over Budget","Within Budget") -> Over Budget | M30: 185498 | N30: 169961 | O30: =IF(M30<>N30,"Yes","No") -> Yes | Q30: 7.26 | R30: =IF(ISBLANK(Q30),"No","Yes") -> Yes | T30: 3.06 | U30: =IF(T30>10,"High Attrition","No") -> No | W30: EMP0076 | X30: =VLOOKUP(W30,Employees!$A$1:$B$601,2,FALSE) -> Bikash Biswal | Z30: EMP0029 | AA30: =RIGHT(Z30,4) -> 0029 | AC30: QA | AD30: =PROPER(AC30) -> Qa | AF30: Dibya Senapati | AG30: QA | AH30: CoastalDev Studio | AI30: =_xlfn.CONCAT(AF30,"|",AG30,"|",AH30) -> Dibya Senapati|QA|CoastalDev Studio | AK30: Dibya Senapati | AL30: =LEFT(AK30,1)&"."&MID(AK30,FIND(" ",AK30)+1,1)&"." -> D.S. | AN30: Naukri | AO30: =IF(UPPER(AN30)="linkedin","Linkedln",IF(UPPER(AN30)="naukri","Naukri")) -> Naukri | AQ30: Dibya Senapati | AR30: =IF(ISNUMBER(SEARCH("Mishra",AQ30)),"Mishra","NO") -> NO | AT30: Analytics Dashboard | AU30: =LEN(AT30) -> 19 | AW30: =DATEDIF(BI30,TODAY(),"Y") -> 6 | AY30: 24-09-2024 | AZ30: =DATE(RIGHT(AY30,4),MID(AY30,4,2),LEFT(AY30,2)) -> 45559 | BA30: =MONTH(AZ30)&"-"&YEAR(AZ30) -> 9-2024 | BC30: 10-08-2021 | BD30: =DATE(RIGHT(BC30,4),MID(BC30,4,2),LEFT(BC30,2)) -> 44418 | BE30: Under Review | BF30: =IF(AND(BD30<TODAY(),BE30<>"Completed"),"Overdue","On Track") -> Overdue | BH30: 10-11-2019 | BI30: =IF(LEN(LEFT(BH30,FIND("-",BH30)-1))=4,DATE(LEFT(BH30,4),MID(BH30,6,2),RIGHT(BH30,2)),DATE(RIGHT(BH30,4),MID(BH30,4,2),LEFT(BH30,2))) -> 43779 | BJ30: =NETWORKDAYS(BI30,TODAY()) -> 1765 | BL30: =IF(MONTH(BI30)<=3,"Q1","No") -> No | BM30: =DATE(RIGHT(AY30,4),MID(AY30,4,2),LEFT(AY30,2)) -> 45559 | BN30: =IF(LEN(LEFT(BH30,FIND("-",BH30)-1))=4,DATE(LEFT(BH30,4),MID(BH30,6,2),RIGHT(BH30,2)),DATE(RIGHT(BH30,4),MID(BH30,4,2),LEFT(BH30,2))) -> 43779 | BO30: =ABS(BN30-BM30) -> 1780 | BP30: EMP0029 | BQ30: QA | BR30: EMP0076 | BS30: ATT00029 | BT30: =VLOOKUP(BR30,$BP$2:$BQ$601,2,FALSE) -> Marketing | BV30: EMP0029 | BW30: Dibya Senapati | BX30: Analytics Dashboard | BY30: EMP0168 | BZ30: =VLOOKUP(BY30,$BV$2:$BW$601,2,FALSE) -> Soumya Tripathy | CB30: Namita Behura | CC30: Dibya Senapati | CD30: QA Engineer | CE30: Not Found | CG30: =IFERROR(_xlfn.XLOOKUP(Hiring!A30,Hiring!A30:A429,Hiring!B30:B429,,0),"Not Found") -> Namita Behura
A31: SECTION D — DATE FUNCTIONS | F31: 3.1 | G31: {=_xlfn.IFS(F31>=4.5,"Excellent",AND(F31>=3.5,F31<=4.4),"Good",F31<3.5,"Needs Improvement")} -> Needs Improvement | I31: 66.93 | J31: 50.48 | K31: =IF(J31>I31,"Over Budget","Within Budget") -> Within Budget | M31: 125277 | N31: 131761 | O31: =IF(M31<>N31,"Yes","No") -> Yes | Q31: 10.71 | R31: =IF(ISBLANK(Q31),"No","Yes") -> Yes | T31: 15 | U31: =IF(T31>10,"High Attrition","No") -> High Attrition | W31: EMP0076 | X31: =VLOOKUP(W31,Employees!$A$1:$B$601,2,FALSE) -> Bikash Biswal | Z31: EMP0030 | AA31: =RIGHT(Z31,4) -> 0030 | AC31: QA | AD31: =PROPER(AC31) -> Qa | AF31: Puspita Mohapatra | AG31: QA | AH31: CoastalDev Studio | AI31: =_xlfn.CONCAT(AF31,"|",AG31,"|",AH31) -> Puspita Mohapatra|QA|CoastalDev Studio | AK31: Puspita Mohapatra | AL31: =LEFT(AK31,1)&"."&MID(AK31,FIND(" ",AK31)+1,1)&"." -> P.M. | AN31: Job Portal | AO31: =IF(UPPER(AN31)="linkedin","Linkedln",IF(UPPER(AN31)="naukri","Naukri")) -> FALSE | AQ31: Puspita Mohapatra | AR31: =IF(ISNUMBER(SEARCH("Mishra",AQ31)),"Mishra","NO") -> NO | AT31: ERP Implementation | AU31: =LEN(AT31) -> 18 | AW31: =DATEDIF(BI31,TODAY(),"Y") -> 3 | AY31: 17-06-2023 | AZ31: =DATE(RIGHT(AY31,4),MID(AY31,4,2),LEFT(AY31,2)) -> 45094 | BA31: =MONTH(AZ31)&"-"&YEAR(AZ31) -> 6-2023 | BC31: 12-12-2024 | BD31: =DATE(RIGHT(BC31,4),MID(BC31,4,2),LEFT(BC31,2)) -> 45638 | BE31: Under Review | BF31: =IF(AND(BD31<TODAY(),BE31<>"Completed"),"Overdue","On Track") -> Overdue | BH31: 09-11-2022 | BI31: =IF(LEN(LEFT(BH31,FIND("-",BH31)-1))=4,DATE(LEFT(BH31,4),MID(BH31,6,2),RIGHT(BH31,2)),DATE(RIGHT(BH31,4),MID(BH31,4,2),LEFT(BH31,2))) -> 44874 | BJ31: =NETWORKDAYS(BI31,TODAY()) -> 983 | BL31: =IF(MONTH(BI31)<=3,"Q1","No") -> No | BM31: =DATE(RIGHT(AY31,4),MID(AY31,4,2),LEFT(AY31,2)) -> 45094 | BN31: =IF(LEN(LEFT(BH31,FIND("-",BH31)-1))=4,DATE(LEFT(BH31,4),MID(BH31,6,2),RIGHT(BH31,2)),DATE(RIGHT(BH31,4),MID(BH31,4,2),LEFT(BH31,2))) -> 44874 | BO31: =ABS(BN31-BM31) -> 220 | BP31: EMP0030 | BQ31: QA | BR31: EMP0076 | BS31: ATT00030 | BT31: =VLOOKUP(BR31,$BP$2:$BQ$601,2,FALSE) -> Marketing | BV31: EMP0030 | BW31: Puspita Mohapatra | BX31: ERP Implementation | BY31: EMP0391 | BZ31: =VLOOKUP(BY31,$BV$2:$BW$601,2,FALSE) -> Priyanka Samal | CB31: Soumya Prusty | CC31: Puspita Mohapatra | CD31: QA Engineer | CE31: Sales Manager | CG31: =IFERROR(_xlfn.XLOOKUP(Hiring!A31,Hiring!A31:A430,Hiring!B31:B430,,0),"Not Found") -> Soumya Prusty
A32: Q22 | B32: Calculate tenure (in years) for each employee from their Joining_Date to today. Use DATEDIF. | C32: Done | F32: 2.3 | G32: {=_xlfn.IFS(F32>=4.5,"Excellent",AND(F32>=3.5,F32<=4.4),"Good",F32<3.5,"Needs Improvement")} -> Needs Improvement | I32: 196.41 | J32: 248.34 | K32: =IF(J32>I32,"Over Budget","Within Budget") -> Over Budget | M32: 193212 | N32: 180507 | O32: =IF(M32<>N32,"Yes","No") -> Yes | Q32: 8.59 | R32: =IF(ISBLANK(Q32),"No","Yes") -> Yes | T32: 25 | U32: =IF(T32>10,"High Attrition","No") -> High Attrition | W32: EMP0076 | X32: =VLOOKUP(W32,Employees!$A$1:$B$601,2,FALSE) -> Bikash Biswal | Z32: EMP0031 | AA32: =RIGHT(Z32,4) -> 0031 | AC32: DevOps | AD32: =PROPER(AC32) -> Devops | AF32: Barsha Mohapatra | AG32: DevOps | AH32: SilverByte Systems | AI32: =_xlfn.CONCAT(AF32,"|",AG32,"|",AH32) -> Barsha Mohapatra|DevOps|SilverByte Systems | AK32: Barsha Mohapatra | AL32: =LEFT(AK32,1)&"."&MID(AK32,FIND(" ",AK32)+1,1)&"." -> B.M. | AN32: naukri | AO32: =IF(UPPER(AN32)="linkedin","Linkedln",IF(UPPER(AN32)="naukri","Naukri")) -> Naukri | AQ32: Barsha Mohapatra | AR32: =IF(ISNUMBER(SEARCH("Mishra",AQ32)),"Mishra","NO") -> NO | AT32: Mobile Banking App | AU32: =LEN(AT32) -> 18 | AW32: =DATEDIF(BI32,TODAY(),"Y") -> 6 | AY32: 02-04-2023 | AZ32: =DATE(RIGHT(AY32,4),MID(AY32,4,2),LEFT(AY32,2)) -> 45018 | BA32: =MONTH(AZ32)&"-"&YEAR(AZ32) -> 4-2023 | BC32: 28-08-2021 | BD32: =DATE(RIGHT(BC32,4),MID(BC32,4,2),LEFT(BC32,2)) -> 44436 | BE32: On Hold | BF32: =IF(AND(BD32<TODAY(),BE32<>"Completed"),"Overdue","On Track") -> Overdue | BH32: 25-11-2019 | BI32: =IF(LEN(LEFT(BH32,FIND("-",BH32)-1))=4,DATE(LEFT(BH32,4),MID(BH32,6,2),RIGHT(BH32,2)),DATE(RIGHT(BH32,4),MID(BH32,4,2),LEFT(BH32,2))) -> 43794 | BJ32: =NETWORKDAYS(BI32,TODAY()) -> 1755 | BL32: =IF(MONTH(BI32)<=3,"Q1","No") -> No | BM32: =DATE(RIGHT(AY32,4),MID(AY32,4,2),LEFT(AY32,2)) -> 45018 | BN32: =IF(LEN(LEFT(BH32,FIND("-",BH32)-1))=4,DATE(LEFT(BH32,4),MID(BH32,6,2),RIGHT(BH32,2)),DATE(RIGHT(BH32,4),MID(BH32,4,2),LEFT(BH32,2))) -> 43794 | BO32: =ABS(BN32-BM32) -> 1224 | BP32: EMP0031 | BQ32: DevOps | BR32: EMP0076 | BS32: ATT00031 | BT32: =VLOOKUP(BR32,$BP$2:$BQ$601,2,FALSE) -> Marketing | BV32: EMP0031 | BW32: Barsha Mohapatra | BX32: Mobile Banking App | BY32: EMP0118 | BZ32: =VLOOKUP(BY32,$BV$2:$BW$601,2,FALSE) -> Satyajit Mishra | CB32: Nirmal Mishra | CC32: Barsha Mohapatra | CD32: Cloud Architect | CE32: Content Strategist | CG32: =IFERROR(_xlfn.XLOOKUP(Hiring!A32,Hiring!A32:A431,Hiring!B32:B431,,0),"Not Found") -> Nirmal Mishra
A33: Q23 | B33: Extract Month and Year from Interview_Date in Hiring sheet. | C33: Done | F33: 2.2 | G33: {=_xlfn.IFS(F33>=4.5,"Excellent",AND(F33>=3.5,F33<=4.4),"Good",F33<3.5,"Needs Improvement")} -> Needs Improvement | I33: 77.56 | J33: 77.32 | K33: =IF(J33>I33,"Over Budget","Within Budget") -> Within Budget | M33: 151325 | N33: 158520 | O33: =IF(M33<>N33,"Yes","No") -> Yes | Q33: 9.27 | R33: =IF(ISBLANK(Q33),"No","Yes") -> Yes | T33: 9.09 | U33: =IF(T33>10,"High Attrition","No") -> No | W33: EMP0076 | X33: =VLOOKUP(W33,Employees!$A$1:$B$601,2,FALSE) -> Bikash Biswal | Z33: EMP0032 | AA33: =RIGHT(Z33,4) -> 0032 | AC33: QA | AD33: =PROPER(AC33) -> Qa | AF33: Satyajit Mahapatra | AG33: QA | AH33: SilverByte Systems | AI33: =_xlfn.CONCAT(AF33,"|",AG33,"|",AH33) -> Satyajit Mahapatra|QA|SilverByte Systems | AK33: Satyajit Mahapatra | AL33: =LEFT(AK33,1)&"."&MID(AK33,FIND(" ",AK33)+1,1)&"." -> S.M. | AN33: Referral | AO33: =IF(UPPER(AN33)="linkedin","Linkedln",IF(UPPER(AN33)="naukri","Naukri")) -> FALSE | AQ33: Satyajit Mahapatra | AR33: =IF(ISNUMBER(SEARCH("Mishra",AQ33)),"Mishra","NO") -> NO | AT33: DigitalBank Portal | AU33: =LEN(AT33) -> 18 | AW33: =DATEDIF(BI33,TODAY(),"Y") -> 8 | AY33: 10-03-2023 | AZ33: =DATE(RIGHT(AY33,4),MID(AY33,4,2),LEFT(AY33,2)) -> 44995 | BA33: =MONTH(AZ33)&"-"&YEAR(AZ33) -> 3-2023 | BC33: 28-09-2023 | BD33: =DATE(RIGHT(BC33,4),MID(BC33,4,2),LEFT(BC33,2)) -> 45197 | BE33: Cancelled | BF33: =IF(AND(BD33<TODAY(),BE33<>"Completed"),"Overdue","On Track") -> Overdue | BH33: 18-02-2018 | BI33: =IF(LEN(LEFT(BH33,FIND("-",BH33)-1))=4,DATE(LEFT(BH33,4),MID(BH33,6,2),RIGHT(BH33,2)),DATE(RIGHT(BH33,4),MID(BH33,4,2),LEFT(BH33,2))) -> 43149 | BJ33: =NETWORKDAYS(BI33,TODAY()) -> 2215 | BL33: =IF(MONTH(BI33)<=3,"Q1","No") -> Q1 | BM33: =DATE(RIGHT(AY33,4),MID(AY33,4,2),LEFT(AY33,2)) -> 44995 | BN33: =IF(LEN(LEFT(BH33,FIND("-",BH33)-1))=4,DATE(LEFT(BH33,4),MID(BH33,6,2),RIGHT(BH33,2)),DATE(RIGHT(BH33,4),MID(BH33,4,2),LEFT(BH33,2))) -> 43149 | BO33: =ABS(BN33-BM33) -> 1846 | BP33: EMP0032 | BQ33: QA | BR33: EMP0076 | BS33: ATT00032 | BT33: =VLOOKUP(BR33,$BP$2:$BQ$601,2,FALSE) -> Marketing | BV33: EMP0032 | BW33: Satyajit Mahapatra | BX33: DigitalBank Portal | BY33: EMP0196 | BZ33: =VLOOKUP(BY33,$BV$2:$BW$601,2,FALSE) -> Tanmay Choudhury | CB33: Subhasree Parida | CC33: Satyajit Mahapatra | CD33: QA Lead | CE33: HR Manager | CG33: =IFERROR(_xlfn.XLOOKUP(Hiring!A33,Hiring!A33:A432,Hiring!B33:B432,,0),"Not Found") -> Subhasree Parida
A34: Q24 | B34: Find projects that are overdue: Deadline has passed but Status ≠ 'Completed'. Use TODAY() + IF. | C34: Done | F34: 4.8 | G34: {=_xlfn.IFS(F34>=4.5,"Excellent",AND(F34>=3.5,F34<=4.4),"Good",F34<3.5,"Needs Improvement")} -> Excellent | I34: 38.8 | J34: 34.66 | K34: =IF(J34>I34,"Over Budget","Within Budget") -> Within Budget | M34: 129695 | N34: 125983 | O34: =IF(M34<>N34,"Yes","No") -> Yes | Q34: 7.4 | R34: =IF(ISBLANK(Q34),"No","Yes") -> Yes | T34: 2.27 | U34: =IF(T34>10,"High Attrition","No") -> No | W34: EMP0076 | X34: =VLOOKUP(W34,Employees!$A$1:$B$601,2,FALSE) -> Bikash Biswal | Z34: EMP0033 | AA34: =RIGHT(Z34,4) -> 0033 | AC34: Engineering | AD34: =PROPER(AC34) -> Engineering | AF34: Priyanka Ratha | AG34: Engineering | AH34: InfySoft Bhubaneswar | AI34: =_xlfn.CONCAT(AF34,"|",AG34,"|",AH34) -> Priyanka Ratha|Engineering|InfySoft Bhubaneswar | AK34: Priyanka Ratha | AL34: =LEFT(AK34,1)&"."&MID(AK34,FIND(" ",AK34)+1,1)&"." -> P.R. | AN34: Campus | AO34: =IF(UPPER(AN34)="linkedin","Linkedln",IF(UPPER(AN34)="naukri","Naukri")) -> FALSE | AQ34: Priyanka Ratha | AR34: =IF(ISNUMBER(SEARCH("Mishra",AQ34)),"Mishra","NO") -> NO | AT34: Talent Management | AU34: =LEN(AT34) -> 17 | AW34: =DATEDIF(BI34,TODAY(),"Y") -> 2 | AY34: 21-05-2023 | AZ34: =DATE(RIGHT(AY34,4),MID(AY34,4,2),LEFT(AY34,2)) -> 45067 | BA34: =MONTH(AZ34)&"-"&YEAR(AZ34) -> 5-2023 | BC34: 14-05-2024 | BD34: =DATE(RIGHT(BC34,4),MID(BC34,4,2),LEFT(BC34,2)) -> 45426 | BE34: On Hold | BF34: =IF(AND(BD34<TODAY(),BE34<>"Completed"),"Overdue","On Track") -> Overdue | BH34: 22-02-2024 | BI34: =IF(LEN(LEFT(BH34,FIND("-",BH34)-1))=4,DATE(LEFT(BH34,4),MID(BH34,6,2),RIGHT(BH34,2)),DATE(RIGHT(BH34,4),MID(BH34,4,2),LEFT(BH34,2))) -> 45344 | BJ34: =NETWORKDAYS(BI34,TODAY()) -> 647 | BL34: =IF(MONTH(BI34)<=3,"Q1","No") -> Q1 | BM34: =DATE(RIGHT(AY34,4),MID(AY34,4,2),LEFT(AY34,2)) -> 45067 | BN34: =IF(LEN(LEFT(BH34,FIND("-",BH34)-1))=4,DATE(LEFT(BH34,4),MID(BH34,6,2),RIGHT(BH34,2)),DATE(RIGHT(BH34,4),MID(BH34,4,2),LEFT(BH34,2))) -> 45344 | BO34: =ABS(BN34-BM34) -> 277 | BP34: EMP0033 | BQ34: Engineering | BR34: EMP0076 | BS34: ATT00033 | BT34: =VLOOKUP(BR34,$BP$2:$BQ$601,2,FALSE) -> Marketing | BV34: EMP0033 | BW34: Priyanka Ratha | BX34: Talent Management | BY34: EMP0251 | BZ34: =VLOOKUP(BY34,$BV$2:$BW$601,2,FALSE) -> Nirmal Samal | CB34: Debasmita Mohapatra | CC34: Priyanka Ratha | CD34: Tech Lead | CE34: Not Found | CG34: =IFERROR(_xlfn.XLOOKUP(Hiring!A34,Hiring!A34:A433,Hiring!B34:B433,,0),"Not Found") -> Debasmita Mohapatra
A35: Q25 | B35: Calculate working days each employee has been with the company. Use NETWORKDAYS. | C35: Done | F35: 3.8 | G35: {=_xlfn.IFS(F35>=4.5,"Excellent",AND(F35>=3.5,F35<=4.4),"Good",F35<3.5,"Needs Improvement")} -> Good | I35: 106.16 | J35: 85.86 | K35: =IF(J35>I35,"Over Budget","Within Budget") -> Within Budget | M35: 117799 | N35: 103827 | O35: =IF(M35<>N35,"Yes","No") -> Yes | Q35: 6.6 | R35: =IF(ISBLANK(Q35),"No","Yes") -> Yes | T35: 5.21 | U35: =IF(T35>10,"High Attrition","No") -> No | W35: EMP0076 | X35: =VLOOKUP(W35,Employees!$A$1:$B$601,2,FALSE) -> Bikash Biswal | Z35: EMP0034 | AA35: =RIGHT(Z35,4) -> 0034 | AC35: Sales | AD35: =PROPER(AC35) -> Sales | AF35: Chinmaya Prusty | AG35: Sales | AH35: InfySoft Bhubaneswar | AI35: =_xlfn.CONCAT(AF35,"|",AG35,"|",AH35) -> Chinmaya Prusty|Sales|InfySoft Bhubaneswar | AK35: Chinmaya Prusty | AL35: =LEFT(AK35,1)&"."&MID(AK35,FIND(" ",AK35)+1,1)&"." -> C.P. | AN35: LinkedIn | AO35: =IF(UPPER(AN35)="linkedin","Linkedln",IF(UPPER(AN35)="naukri","Naukri")) -> Linkedln | AQ35: Chinmaya Prusty | AR35: =IF(ISNUMBER(SEARCH("Mishra",AQ35)),"Mishra","NO") -> NO | AT35: AI Chatbot | AU35: =LEN(AT35) -> 10 | AW35: =DATEDIF(BI35,TODAY(),"Y") -> 6 | AY35: 26-12-2024 | AZ35: =DATE(RIGHT(AY35,4),MID(AY35,4,2),LEFT(AY35,2)) -> 45652 | BA35: =MONTH(AZ35)&"-"&YEAR(AZ35) -> 12-2024 | BC35: 23-01-2024 | BD35: =DATE(RIGHT(BC35,4),MID(BC35,4,2),LEFT(BC35,2)) -> 45314 | BE35: Under Review | BF35: =IF(AND(BD35<TODAY(),BE35<>"Completed"),"Overdue","On Track") -> Overdue | BH35: 19-07-2020 | BI35: =IF(LEN(LEFT(BH35,FIND("-",BH35)-1))=4,DATE(LEFT(BH35,4),MID(BH35,6,2),RIGHT(BH35,2)),DATE(RIGHT(BH35,4),MID(BH35,4,2),LEFT(BH35,2))) -> 44031 | BJ35: =NETWORKDAYS(BI35,TODAY()) -> 1585 | BL35: =IF(MONTH(BI35)<=3,"Q1","No") -> No | BM35: =DATE(RIGHT(AY35,4),MID(AY35,4,2),LEFT(AY35,2)) -> 45652 | BN35: =IF(LEN(LEFT(BH35,FIND("-",BH35)-1))=4,DATE(LEFT(BH35,4),MID(BH35,6,2),RIGHT(BH35,2)),DATE(RIGHT(BH35,4),MID(BH35,4,2),LEFT(BH35,2))) -> 44031 | BO35: =ABS(BN35-BM35) -> 1621 | BP35: EMP0034 | BQ35: Sales | BR35: EMP0076 | BS35: ATT00034 | BT35: =VLOOKUP(BR35,$BP$2:$BQ$601,2,FALSE) -> Marketing | BV35: EMP0034 | BW35: Chinmaya Prusty | BX35: AI Chatbot | BY35: EMP0239 | BZ35: =VLOOKUP(BY35,$BV$2:$BW$601,2,FALSE) -> Alka Pattnaik | CB35: Ipsita Behura | CC35: Chinmaya Prusty | CD35: Account Manager | CE35: HR Manager | CG35: =IFERROR(_xlfn.XLOOKUP(Hiring!A35,Hiring!A35:A434,Hiring!B35:B434,,0),"Not Found") -> Ipsita Behura
A36: Q26 | B36: Find employees who joined in Q1 (Jan–Mar) of any year. Use MONTH() + IF. | C36: Done | F36: 4.9 | G36: {=_xlfn.IFS(F36>=4.5,"Excellent",AND(F36>=3.5,F36<=4.4),"Good",F36<3.5,"Needs Improvement")} -> Excellent | I36: 109.16 | J36: 92.25 | K36: =IF(J36>I36,"Over Budget","Within Budget") -> Within Budget | N36: 131980 | O36: =IF(M36<>N36,"Yes","No") -> Yes | Q36: 9.48 | R36: =IF(ISBLANK(Q36),"No","Yes") -> Yes | T36: 31.75 | U36: =IF(T36>10,"High Attrition","No") -> High Attrition | W36: EMP0076 | X36: =VLOOKUP(W36,Employees!$A$1:$B$601,2,FALSE) -> Bikash Biswal | Z36: EMP0035 | AA36: =RIGHT(Z36,4) -> 0035 | AC36: Data Science | AD36: =PROPER(AC36) -> Data Science | AF36: Tanmay Padhi | AG36: Data Science | AH36: TechNova Solutions | AI36: =_xlfn.CONCAT(AF36,"|",AG36,"|",AH36) -> Tanmay Padhi|Data Science|TechNova Solutions | AK36: Tanmay Padhi | AL36: =LEFT(AK36,1)&"."&MID(AK36,FIND(" ",AK36)+1,1)&"." -> T.P. | AN36: naukri | AO36: =IF(UPPER(AN36)="linkedin","Linkedln",IF(UPPER(AN36)="naukri","Naukri")) -> Naukri | AQ36: Tanmay Padhi | AR36: =IF(ISNUMBER(SEARCH("Mishra",AQ36)),"Mishra","NO") -> NO | AT36: Fleet Management | AU36: =LEN(AT36) -> 16 | AW36: =DATEDIF(BI36,TODAY(),"Y") -> 3 | AY36: 09-04-2024 | AZ36: =DATE(RIGHT(AY36,4),MID(AY36,4,2),LEFT(AY36,2)) -> 45391 | BA36: =MONTH(AZ36)&"-"&YEAR(AZ36) -> 4-2024 | BC36: 22-06-2022 | BD36: =DATE(RIGHT(BC36,4),MID(BC36,4,2),LEFT(BC36,2)) -> 44734 | BE36: Cancelled | BF36: =IF(AND(BD36<TODAY(),BE36<>"Completed"),"Overdue","On Track") -> Overdue | BH36: 05-02-2023 | BI36: =IF(LEN(LEFT(BH36,FIND("-",BH36)-1))=4,DATE(LEFT(BH36,4),MID(BH36,6,2),RIGHT(BH36,2)),DATE(RIGHT(BH36,4),MID(BH36,4,2),LEFT(BH36,2))) -> 44962 | BJ36: =NETWORKDAYS(BI36,TODAY()) -> 920 | BL36: =IF(MONTH(BI36)<=3,"Q1","No") -> Q1 | BM36: =DATE(RIGHT(AY36,4),MID(AY36,4,2),LEFT(AY36,2)) -> 45391 | BN36: =IF(LEN(LEFT(BH36,FIND("-",BH36)-1))=4,DATE(LEFT(BH36,4),MID(BH36,6,2),RIGHT(BH36,2)),DATE(RIGHT(BH36,4),MID(BH36,4,2),LEFT(BH36,2))) -> 44962 | BO36: =ABS(BN36-BM36) -> 429 | BP36: EMP0035 | BQ36: Data Science | BR36: EMP0076 | BS36: ATT00035 | BT36: =VLOOKUP(BR36,$BP$2:$BQ$601,2,FALSE) -> Marketing | BV36: EMP0035 | BW36: Tanmay Padhi | BX36: Fleet Management | BY36: EMP0529 | BZ36: =VLOOKUP(BY36,$BV$2:$BW$601,2,FALSE) -> Subhasree Prusty | CB36: Lipsa Tripathy | CC36: Tanmay Padhi | CD36: Data Analyst | CE36: Not Found | CG36: =IFERROR(_xlfn.XLOOKUP(Hiring!A36,Hiring!A36:A435,Hiring!B36:B435,,0),"Not Found") -> Lipsa Tripathy
A37: Q27 | B37: Calculate the gap between Interview_Date and Joining_Date for placed candidates. Use DATEDIF. | C37: Done | F37: 2.4 | G37: {=_xlfn.IFS(F37>=4.5,"Excellent",AND(F37>=3.5,F37<=4.4),"Good",F37<3.5,"Needs Improvement")} -> Needs Improvement | I37: 82.32 | J37: 97.59 | K37: =IF(J37>I37,"Over Budget","Within Budget") -> Over Budget | M37: 91424 | N37: 83588 | O37: =IF(M37<>N37,"Yes","No") -> Yes | Q37: 11.49 | R37: =IF(ISBLANK(Q37),"No","Yes") -> Yes | T37: 10.06 | U37: =IF(T37>10,"High Attrition","No") -> High Attrition | W37: EMP0076 | X37: =VLOOKUP(W37,Employees!$A$1:$B$601,2,FALSE) -> Bikash Biswal | Z37: EMP0036 | AA37: =RIGHT(Z37,4) -> 0036 | AC37: Finance | AD37: =PROPER(AC37) -> Finance | AF37: Saurav Biswal | AG37: Finance | AH37: InfySoft Bhubaneswar | AI37: =_xlfn.CONCAT(AF37,"|",AG37,"|",AH37) -> Saurav Biswal|Finance|InfySoft Bhubaneswar | AK37: Saurav Biswal | AL37: =LEFT(AK37,1)&"."&MID(AK37,FIND(" ",AK37)+1,1)&"." -> S.B. | AN37: naukri | AO37: =IF(UPPER(AN37)="linkedin","Linkedln",IF(UPPER(AN37)="naukri","Naukri")) -> Naukri | AQ37: Saurav Biswal | AR37: =IF(ISNUMBER(SEARCH("Mishra",AQ37)),"Mishra","NO") -> NO | AT37: DigitalBank Portal | AU37: =LEN(AT37) -> 18 | AW37: =DATEDIF(BI37,TODAY(),"Y") -> 7 | AY37: 18-04-2024 | AZ37: =DATE(RIGHT(AY37,4),MID(AY37,4,2),LEFT(AY37,2)) -> 45400 | BA37: =MONTH(AZ37)&"-"&YEAR(AZ37) -> 4-2024 | BC37: 06-07-2023 | BD37: =DATE(RIGHT(BC37,4),MID(BC37,4,2),LEFT(BC37,2)) -> 45113 | BE37: Cancelled | BF37: =IF(AND(BD37<TODAY(),BE37<>"Completed"),"Overdue","On Track") -> Overdue | BH37: 16-09-2018 | BI37: =IF(LEN(LEFT(BH37,FIND("-",BH37)-1))=4,DATE(LEFT(BH37,4),MID(BH37,6,2),RIGHT(BH37,2)),DATE(RIGHT(BH37,4),MID(BH37,4,2),LEFT(BH37,2))) -> 43359 | BJ37: =NETWORKDAYS(BI37,TODAY()) -> 2065 | BL37: =IF(MONTH(BI37)<=3,"Q1","No") -> No | BM37: =DATE(RIGHT(AY37,4),MID(AY37,4,2),LEFT(AY37,2)) -> 45400 | BN37: =IF(LEN(LEFT(BH37,FIND("-",BH37)-1))=4,DATE(LEFT(BH37,4),MID(BH37,6,2),RIGHT(BH37,2)),DATE(RIGHT(BH37,4),MID(BH37,4,2),LEFT(BH37,2))) -> 43359 | BO37: =ABS(BN37-BM37) -> 2041 | BP37: EMP0036 | BQ37: Finance | BR37: EMP0076 | BS37: ATT00036 | BT37: =VLOOKUP(BR37,$BP$2:$BQ$601,2,FALSE) -> Marketing | BV37: EMP0036 | BW37: Saurav Biswal | BX37: DigitalBank Portal | BY37: EMP0321 | BZ37: =VLOOKUP(BY37,$BV$2:$BW$601,2,FALSE) -> Bikash Parida | CB37: Rajan Routray | CC37: Saurav Biswal | CD37: Finance Analyst | CE37: UI Designer | CG37: =IFERROR(_xlfn.XLOOKUP(Hiring!A37,Hiring!A37:A436,Hiring!B37:B436,,0),"Not Found") -> Rajan Routray
F38: 3.1 | G38: {=_xlfn.IFS(F38>=4.5,"Excellent",AND(F38>=3.5,F38<=4.4),"Good",F38<3.5,"Needs Improvement")} -> Needs Improvement | I38: 55.06 | J38: 57.15 | K38: =IF(J38>I38,"Over Budget","Within Budget") -> Over Budget | M38: 125731 | N38: 139840 | O38: =IF(M38<>N38,"Yes","No") -> Yes | Q38: 9.13 | R38: =IF(ISBLANK(Q38),"No","Yes") -> Yes | T38: 4.86 | U38: =IF(T38>10,"High Attrition","No") -> No | W38: EMP0076 | X38: =VLOOKUP(W38,Employees!$A$1:$B$601,2,FALSE) -> Bikash Biswal | Z38: EMP0037 | AA38: =RIGHT(Z38,4) -> 0037 | AC38: Marketing | AD38: =PROPER(AC38) -> Marketing | AF38: Saurav Nanda | AG38: Marketing | AH38: InfySoft Bhubaneswar | AI38: =_xlfn.CONCAT(AF38,"|",AG38,"|",AH38) -> Saurav Nanda|Marketing|InfySoft Bhubaneswar | AK38: Saurav Nanda | AL38: =LEFT(AK38,1)&"."&MID(AK38,FIND(" ",AK38)+1,1)&"." -> S.N. | AN38: LinkedIn | AO38: =IF(UPPER(AN38)="linkedin","Linkedln",IF(UPPER(AN38)="naukri","Naukri")) -> Linkedln | AQ38: Saurav Nanda | AR38: =IF(ISNUMBER(SEARCH("Mishra",AQ38)),"Mishra","NO") -> NO | AT38: Analytics Dashboard | AU38: =LEN(AT38) -> 19 | AW38: =DATEDIF(BI38,TODAY(),"Y") -> 7 | AY38: 24-10-2024 | AZ38: =DATE(RIGHT(AY38,4),MID(AY38,4,2),LEFT(AY38,2)) -> 45589 | BA38: =MONTH(AZ38)&"-"&YEAR(AZ38) -> 10-2024 | BC38: 16-06-2023 | BD38: =DATE(RIGHT(BC38,4),MID(BC38,4,2),LEFT(BC38,2)) -> 45093 | BE38: Completed | BF38: =IF(AND(BD38<TODAY(),BE38<>"Completed"),"Overdue","On Track") -> On Track | BH38: 21-09-2018 | BI38: =IF(LEN(LEFT(BH38,FIND("-",BH38)-1))=4,DATE(LEFT(BH38,4),MID(BH38,6,2),RIGHT(BH38,2)),DATE(RIGHT(BH38,4),MID(BH38,4,2),LEFT(BH38,2))) -> 43364 | BJ38: =NETWORKDAYS(BI38,TODAY()) -> 2061 | BL38: =IF(MONTH(BI38)<=3,"Q1","No") -> No | BM38: =DATE(RIGHT(AY38,4),MID(AY38,4,2),LEFT(AY38,2)) -> 45589 | BN38: =IF(LEN(LEFT(BH38,FIND("-",BH38)-1))=4,DATE(LEFT(BH38,4),MID(BH38,6,2),RIGHT(BH38,2)),DATE(RIGHT(BH38,4),MID(BH38,4,2),LEFT(BH38,2))) -> 43364 | BO38: =ABS(BN38-BM38) -> 2225 | BP38: EMP0037 | BQ38: Marketing | BR38: EMP0076 | BS38: ATT00037 | BT38: =VLOOKUP(BR38,$BP$2:$BQ$601,2,FALSE) -> Marketing | BV38: EMP0037 | BW38: Saurav Nanda | BX38: Analytics Dashboard | BY38: EMP0390 | BZ38: =VLOOKUP(BY38,$BV$2:$BW$601,2,FALSE) -> Soumya Mohapatra | CB38: Subhasree Padhi | CC38: Saurav Nanda | CD38: Content Strategist | CE38: Associate PM | CG38: =IFERROR(_xlfn.XLOOKUP(Hiring!A38,Hiring!A38:A437,Hiring!B38:B437,,0),"Not Found") -> Subhasree Padhi
A39: SECTION E — LOOKUP FUNCTIONS | F39: 4.7 | G39: {=_xlfn.IFS(F39>=4.5,"Excellent",AND(F39>=3.5,F39<=4.4),"Good",F39<3.5,"Needs Improvement")} -> Excellent | I39: 19.87 | J39: 16.01 | K39: =IF(J39>I39,"Over Budget","Within Budget") -> Within Budget | M39: 89054 | N39: 100081 | O39: =IF(M39<>N39,"Yes","No") -> Yes | Q39: 9.89 | R39: =IF(ISBLANK(Q39),"No","Yes") -> Yes | T39: 8.81 | U39: =IF(T39>10,"High Attrition","No") -> No | W39: EMP0076 | X39: =VLOOKUP(W39,Employees!$A$1:$B$601,2,FALSE) -> Bikash Biswal | Z39: EMP0038 | AA39: =RIGHT(Z39,4) -> 0038 | AC39: QA | AD39: =PROPER(AC39) -> Qa | AF39: Alka Nanda | AG39: QA | AH39: KalingaTech Pvt Ltd | AI39: =_xlfn.CONCAT(AF39,"|",AG39,"|",AH39) -> Alka Nanda|QA|KalingaTech Pvt Ltd | AK39: Alka Nanda | AL39: =LEFT(AK39,1)&"."&MID(AK39,FIND(" ",AK39)+1,1)&"." -> A.N. | AN39: Referral | AO39: =IF(UPPER(AN39)="linkedin","Linkedln",IF(UPPER(AN39)="naukri","Naukri")) -> FALSE | AQ39: Alka Nanda | AR39: =IF(ISNUMBER(SEARCH("Mishra",AQ39)),"Mishra","NO") -> NO | AT39: Fleet Management | AU39: =LEN(AT39) -> 16 | AW39: =DATEDIF(BI39,TODAY(),"Y") -> 3 | AY39: 06-07-2024 | AZ39: =DATE(RIGHT(AY39,4),MID(AY39,4,2),LEFT(AY39,2)) -> 45479 | BA39: =MONTH(AZ39)&"-"&YEAR(AZ39) -> 7-2024 | BC39: 28-06-2024 | BD39: =DATE(RIGHT(BC39,4),MID(BC39,4,2),LEFT(BC39,2)) -> 45471 | BE39: On Hold | BF39: =IF(AND(BD39<TODAY(),BE39<>"Completed"),"Overdue","On Track") -> Overdue | BH39: 07-12-2022 | BI39: =IF(LEN(LEFT(BH39,FIND("-",BH39)-1))=4,DATE(LEFT(BH39,4),MID(BH39,6,2),RIGHT(BH39,2)),DATE(RIGHT(BH39,4),MID(BH39,4,2),LEFT(BH39,2))) -> 44902 | BJ39: =NETWORKDAYS(BI39,TODAY()) -> 963 | BL39: =IF(MONTH(BI39)<=3,"Q1","No") -> No | BM39: =DATE(RIGHT(AY39,4),MID(AY39,4,2),LEFT(AY39,2)) -> 45479 | BN39: =IF(LEN(LEFT(BH39,FIND("-",BH39)-1))=4,DATE(LEFT(BH39,4),MID(BH39,6,2),RIGHT(BH39,2)),DATE(RIGHT(BH39,4),MID(BH39,4,2),LEFT(BH39,2))) -> 44902 | BO39: =ABS(BN39-BM39) -> 577 | BP39: EMP0038 | BQ39: QA | BR39: EMP0076 | BS39: ATT00038 | BT39: =VLOOKUP(BR39,$BP$2:$BQ$601,2,FALSE) -> Marketing | BV39: EMP0038 | BW39: Alka Nanda | BX39: Fleet Management | BY39: EMP0010 | BZ39: =VLOOKUP(BY39,$BV$2:$BW$601,2,FALSE) -> Sudhansu Dhal | CB39: Amlan Biswal | CC39: Alka Nanda | CD39: Test Analyst | CE39: Junior Developer | CG39: =IFERROR(_xlfn.XLOOKUP(Hiring!A39,Hiring!A39:A438,Hiring!B39:B438,,0),"Not Found") -> Amlan Biswal
A40: Q28 | B40: For each Attendance record, fetch the Employee's Department using VLOOKUP (from Employees sheet). | C40: Done | F40: 3.4 | G40: {=_xlfn.IFS(F40>=4.5,"Excellent",AND(F40>=3.5,F40<=4.4),"Good",F40<3.5,"Needs Improvement")} -> Needs Improvement | I40: 52.99 | J40: 49.34 | K40: =IF(J40>I40,"Over Budget","Within Budget") -> Within Budget | M40: 0 | N40: 0 | O40: =IF(M40<>N40,"Yes","No") -> No | Q40: 7.43 | R40: =IF(ISBLANK(Q40),"No","Yes") -> Yes | T40: 8.11 | U40: =IF(T40>10,"High Attrition","No") -> No | W40: EMP0076 | X40: =VLOOKUP(W40,Employees!$A$1:$B$601,2,FALSE) -> Bikash Biswal | Z40: EMP0039 | AA40: =RIGHT(Z40,4) -> 0039 | AC40: DevOps | AD40: =PROPER(AC40) -> Devops | AF40: Puspita Nanda | AG40: DevOps | AH40: InfySoft Bhubaneswar | AI40: =_xlfn.CONCAT(AF40,"|",AG40,"|",AH40) -> Puspita Nanda|DevOps|InfySoft Bhubaneswar | AK40: Puspita Nanda | AL40: =LEFT(AK40,1)&"."&MID(AK40,FIND(" ",AK40)+1,1)&"." -> P.N. | AN40: Campus | AO40: =IF(UPPER(AN40)="linkedin","Linkedln",IF(UPPER(AN40)="naukri","Naukri")) -> FALSE | AQ40: Puspita Nanda | AR40: =IF(ISNUMBER(SEARCH("Mishra",AQ40)),"Mishra","NO") -> NO | AT40: Smart Grid System | AU40: =LEN(AT40) -> 17 | AW40: =DATEDIF(BI40,TODAY(),"Y") -> 5 | AY40: 05-01-2024 | AZ40: =DATE(RIGHT(AY40,4),MID(AY40,4,2),LEFT(AY40,2)) -> 45296 | BA40: =MONTH(AZ40)&"-"&YEAR(AZ40) -> 1-2024 | BC40: 18-09-2021 | BD40: =DATE(RIGHT(BC40,4),MID(BC40,4,2),LEFT(BC40,2)) -> 44457 | BE40: On Hold | BF40: =IF(AND(BD40<TODAY(),BE40<>"Completed"),"Overdue","On Track") -> Overdue | BH40: 15-06-2021 | BI40: =IF(LEN(LEFT(BH40,FIND("-",BH40)-1))=4,DATE(LEFT(BH40,4),MID(BH40,6,2),RIGHT(BH40,2)),DATE(RIGHT(BH40,4),MID(BH40,4,2),LEFT(BH40,2))) -> 44362 | BJ40: =NETWORKDAYS(BI40,TODAY()) -> 1349 | BL40: =IF(MONTH(BI40)<=3,"Q1","No") -> No | BM40: =DATE(RIGHT(AY40,4),MID(AY40,4,2),LEFT(AY40,2)) -> 45296 | BN40: =IF(LEN(LEFT(BH40,FIND("-",BH40)-1))=4,DATE(LEFT(BH40,4),MID(BH40,6,2),RIGHT(BH40,2)),DATE(RIGHT(BH40,4),MID(BH40,4,2),LEFT(BH40,2))) -> 44362 | BO40: =ABS(BN40-BM40) -> 934 | BP40: EMP0039 | BQ40: DevOps | BR40: EMP0076 | BS40: ATT00039 | BT40: =VLOOKUP(BR40,$BP$2:$BQ$601,2,FALSE) -> Marketing | BV40: EMP0039 | BW40: Puspita Nanda | BX40: Smart Grid System | BY40: EMP0429 | BZ40: =VLOOKUP(BY40,$BV$2:$BW$601,2,FALSE) -> Sangita Parida | CB40: Subhasree Sahu | CC40: Puspita Nanda | CD40: Cloud Architect | CE40: Not Found | CG40: =IFERROR(_xlfn.XLOOKUP(Hiring!A40,Hiring!A40:A439,Hiring!B40:B439,,0),"Not Found") -> Subhasree Sahu
A41: Q29 | B41: For each Project, fetch the Lead Employee's Name using XLOOKUP (from Employees sheet). | C41: Done | F41: 2.9 | G41: {=_xlfn.IFS(F41>=4.5,"Excellent",AND(F41>=3.5,F41<=4.4),"Good",F41<3.5,"Needs Improvement")} -> Needs Improvement | I41: 38.03 | J41: 31.61 | K41: =IF(J41>I41,"Over Budget","Within Budget") -> Within Budget | M41: 192973 | N41: 184893 | O41: =IF(M41<>N41,"Yes","No") -> Yes | Q41: 6.68 | R41: =IF(ISBLANK(Q41),"No","Yes") -> Yes | T41: 29.85 | U41: =IF(T41>10,"High Attrition","No") -> High Attrition | W41: EMP0076 | X41: =VLOOKUP(W41,Employees!$A$1:$B$601,2,FALSE) -> Bikash Biswal | Z41: EMP0040 | AA41: =RIGHT(Z41,4) -> 0040 | AC41: Marketing | AD41: =PROPER(AC41) -> Marketing | AF41: Chinmaya Biswal | AG41: Marketing | AH41: KalingaTech Pvt Ltd | AI41: =_xlfn.CONCAT(AF41,"|",AG41,"|",AH41) -> Chinmaya Biswal|Marketing|KalingaTech Pvt Ltd | AK41: Chinmaya Biswal | AL41: =LEFT(AK41,1)&"."&MID(AK41,FIND(" ",AK41)+1,1)&"." -> C.B. | AN41: Campus | AO41: =IF(UPPER(AN41)="linkedin","Linkedln",IF(UPPER(AN41)="naukri","Naukri")) -> FALSE | AQ41: Chinmaya Biswal | AR41: =IF(ISNUMBER(SEARCH("Mishra",AQ41)),"Mishra","NO") -> NO | AT41: Inventory Tracker | AU41: =LEN(AT41) -> 17 | AW41: =DATEDIF(BI41,TODAY(),"Y") -> 3 | AY41: 19-10-2024 | AZ41: =DATE(RIGHT(AY41,4),MID(AY41,4,2),LEFT(AY41,2)) -> 45584 | BA41: =MONTH(AZ41)&"-"&YEAR(AZ41) -> 10-2024 | BC41: 09-02-2022 | BD41: =DATE(RIGHT(BC41,4),MID(BC41,4,2),LEFT(BC41,2)) -> 44601 | BE41: In Progress | BF41: =IF(AND(BD41<TODAY(),BE41<>"Completed"),"Overdue","On Track") -> Overdue | BH41: 10-08-2023 | BI41: =IF(LEN(LEFT(BH41,FIND("-",BH41)-1))=4,DATE(LEFT(BH41,4),MID(BH41,6,2),RIGHT(BH41,2)),DATE(RIGHT(BH41,4),MID(BH41,4,2),LEFT(BH41,2))) -> 45148 | BJ41: =NETWORKDAYS(BI41,TODAY()) -> 787 | BL41: =IF(MONTH(BI41)<=3,"Q1","No") -> No | BM41: =DATE(RIGHT(AY41,4),MID(AY41,4,2),LEFT(AY41,2)) -> 45584 | BN41: =IF(LEN(LEFT(BH41,FIND("-",BH41)-1))=4,DATE(LEFT(BH41,4),MID(BH41,6,2),RIGHT(BH41,2)),DATE(RIGHT(BH41,4),MID(BH41,4,2),LEFT(BH41,2))) -> 45148 | BO41: =ABS(BN41-BM41) -> 436 | BP41: EMP0040 | BQ41: Marketing | BR41: EMP0076 | BS41: ATT00040 | BT41: =VLOOKUP(BR41,$BP$2:$BQ$601,2,FALSE) -> Marketing | BV41: EMP0040 | BW41: Chinmaya Biswal | BX41: Inventory Tracker | BY41: EMP0279 | BZ41: =VLOOKUP(BY41,$BV$2:$BW$601,2,FALSE) -> Tanmay Mishra | CB41: Lipsa Prusty | CC41: Chinmaya Biswal | CD41: Digital Marketer | CE41: Software Engineer | CG41: =IFERROR(_xlfn.XLOOKUP(Hiring!A41,Hiring!A41:A440,Hiring!B41:B440,,0),"Not Found") -> Lipsa Prusty
A42: Q30 | B42: Use INDEX-MATCH to find which Company employs the highest-paid employee. | C42: =INDEX(Employees!G2:G601,MATCH(MAX(Employees!I2:I601),Employees!I2:I601,0)) -> OdishaCode Labs | F42: 3.1 | G42: {=_xlfn.IFS(F42>=4.5,"Excellent",AND(F42>=3.5,F42<=4.4),"Good",F42<3.5,"Needs Improvement")} -> Needs Improvement | I42: 93.95 | J42: 94.74 | K42: =IF(J42>I42,"Over Budget","Within Budget") -> Over Budget | N42: 94557 | O42: =IF(M42<>N42,"Yes","No") -> Yes | Q42: 9.43 | R42: =IF(ISBLANK(Q42),"No","Yes") -> Yes | T42: 2.6 | U42: =IF(T42>10,"High Attrition","No") -> No | W42: EMP0076 | X42: =VLOOKUP(W42,Employees!$A$1:$B$601,2,FALSE) -> Bikash Biswal | Z42: EMP0041 | AA42: =RIGHT(Z42,4) -> 0041 | AC42: DevOps | AD42: =PROPER(AC42) -> Devops | AF42: Sangita Ratha | AG42: DevOps | AH42: SambalpurNet | AI42: =_xlfn.CONCAT(AF42,"|",AG42,"|",AH42) -> Sangita Ratha|DevOps|SambalpurNet | AK42: Sangita Ratha | AL42: =LEFT(AK42,1)&"."&MID(AK42,FIND(" ",AK42)+1,1)&"." -> S.R. | AN42: linkedin | AO42: =IF(UPPER(AN42)="linkedin","Linkedln",IF(UPPER(AN42)="naukri","Naukri")) -> Linkedln | AQ42: Sangita Ratha | AR42: =IF(ISNUMBER(SEARCH("Mishra",AQ42)),"Mishra","NO") -> NO | AT42: ML Fraud Detection | AU42: =LEN(AT42) -> 18 | AW42: =DATEDIF(BI42,TODAY(),"Y") -> 6 | AY42: 19-07-2024 | AZ42: =DATE(RIGHT(AY42,4),MID(AY42,4,2),LEFT(AY42,2)) -> 45492 | BA42: =MONTH(AZ42)&"-"&YEAR(AZ42) -> 7-2024 | BC42: 12-11-2022 | BD42: =DATE(RIGHT(BC42,4),MID(BC42,4,2),LEFT(BC42,2)) -> 44877 | BE42: Cancelled | BF42: =IF(AND(BD42<TODAY(),BE42<>"Completed"),"Overdue","On Track") -> Overdue | BH42: 20-09-2019 | BI42: =IF(LEN(LEFT(BH42,FIND("-",BH42)-1))=4,DATE(LEFT(BH42,4),MID(BH42,6,2),RIGHT(BH42,2)),DATE(RIGHT(BH42,4),MID(BH42,4,2),LEFT(BH42,2))) -> 43728 | BJ42: =NETWORKDAYS(BI42,TODAY()) -> 1801 | BL42: =IF(MONTH(BI42)<=3,"Q1","No") -> No | BM42: =DATE(RIGHT(AY42,4),MID(AY42,4,2),LEFT(AY42,2)) -> 45492 | BN42: =IF(LEN(LEFT(BH42,FIND("-",BH42)-1))=4,DATE(LEFT(BH42,4),MID(BH42,6,2),RIGHT(BH42,2)),DATE(RIGHT(BH42,4),MID(BH42,4,2),LEFT(BH42,2))) -> 43728 | BO42: =ABS(BN42-BM42) -> 1764 | BP42: EMP0041 | BQ42: DevOps | BR42: EMP0076 | BS42: ATT00041 | BT42: =VLOOKUP(BR42,$BP$2:$BQ$601,2,FALSE) -> Marketing | BV42: EMP0041 | BW42: Sangita Ratha | BX42: ML Fraud Detection | BY42: EMP0096 | BZ42: =VLOOKUP(BY42,$BV$2:$BW$601,2,FALSE) -> Prasant Mahapatra | CB42: Namita Tripathy | CC42: Sangita Ratha | CD42: SRE | CE42: Associate PM | CG42: =IFERROR(_xlfn.XLOOKUP(Hiring!A42,Hiring!A42:A441,Hiring!B42:B441,,0),"Not Found") -> Namita Tripathy
A43: Q31 | B43: Fetch the Designation of each employee who appears in the Hiring sheet as a candidate. | C43: Done | F43: 2.6 | G43: {=_xlfn.IFS(F43>=4.5,"Excellent",AND(F43>=3.5,F43<=4.4),"Good",F43<3.5,"Needs Improvement")} -> Needs Improvement | I43: 183.85 | J43: 234.02 | K43: =IF(J43>I43,"Over Budget","Within Budget") -> Over Budget | M43: 144200 | N43: 145379 | O43: =IF(M43<>N43,"Yes","No") -> Yes | Q43: 6.83 | R43: =IF(ISBLANK(Q43),"No","Yes") -> Yes | T43: 4.53 | U43: =IF(T43>10,"High Attrition","No") -> No | W43: EMP0076 | X43: =VLOOKUP(W43,Employees!$A$1:$B$601,2,FALSE) -> Bikash Biswal | Z43: EMP0042 | AA43: =RIGHT(Z43,4) -> 0042 | AC43: Engineering | AD43: =PROPER(AC43) -> Engineering | AF43: Sangita Jena | AG43: Engineering | AH43: NilGiri Digitals | AI43: =_xlfn.CONCAT(AF43,"|",AG43,"|",AH43) -> Sangita Jena|Engineering|NilGiri Digitals | AK43: Sangita Jena | AL43: =LEFT(AK43,1)&"."&MID(AK43,FIND(" ",AK43)+1,1)&"." -> S.J. | AN43: Referral | AO43: =IF(UPPER(AN43)="linkedin","Linkedln",IF(UPPER(AN43)="naukri","Naukri")) -> FALSE | AQ43: Sangita Jena | AR43: =IF(ISNUMBER(SEARCH("Mishra",AQ43)),"Mishra","NO") -> NO | AT43: E-Commerce Platform | AU43: =LEN(AT43) -> 19 | AW43: =DATEDIF(BI43,TODAY(),"Y") -> 4 | AY43: 29-07-2024 | AZ43: =DATE(RIGHT(AY43,4),MID(AY43,4,2),LEFT(AY43,2)) -> 45502 | BA43: =MONTH(AZ43)&"-"&YEAR(AZ43) -> 7-2024 | BC43: 22-08-2024 | BD43: =DATE(RIGHT(BC43,4),MID(BC43,4,2),LEFT(BC43,2)) -> 45526 | BE43: In Progress | BF43: =IF(AND(BD43<TODAY(),BE43<>"Completed"),"Overdue","On Track") -> Overdue | BH43: 04-12-2021 | BI43: =IF(LEN(LEFT(BH43,FIND("-",BH43)-1))=4,DATE(LEFT(BH43,4),MID(BH43,6,2),RIGHT(BH43,2)),DATE(RIGHT(BH43,4),MID(BH43,4,2),LEFT(BH43,2))) -> 44534 | BJ43: =NETWORKDAYS(BI43,TODAY()) -> 1225 | BL43: =IF(MONTH(BI43)<=3,"Q1","No") -> No | BM43: =DATE(RIGHT(AY43,4),MID(AY43,4,2),LEFT(AY43,2)) -> 45502 | BN43: =IF(LEN(LEFT(BH43,FIND("-",BH43)-1))=4,DATE(LEFT(BH43,4),MID(BH43,6,2),RIGHT(BH43,2)),DATE(RIGHT(BH43,4),MID(BH43,4,2),LEFT(BH43,2))) -> 44534 | BO43: =ABS(BN43-BM43) -> 968 | BP43: EMP0042 | BQ43: Engineering | BR43: EMP0076 | BS43: ATT00042 | BT43: =VLOOKUP(BR43,$BP$2:$BQ$601,2,FALSE) -> Marketing | BV43: EMP0042 | BW43: Sangita Jena | BX43: E-Commerce Platform | BY43: EMP0337 | BZ43: =VLOOKUP(BY43,$BV$2:$BW$601,2,FALSE) -> Subhasree Parida | CB43: Lipsa Mohapatra | CC43: Sangita Jena | CD43: Senior Developer | CE43: Not Found | CG43: =IFERROR(_xlfn.XLOOKUP(Hiring!A43,Hiring!A43:A442,Hiring!B43:B442,,0),"Not Found") -> Lipsa Mohapatra
A44: Q32 | B44: Use XLOOKUP with IFERROR to find a Candidate by ID. Return 'Not Found' if not present. | C44: Done | F44: 3.3 | G44: {=_xlfn.IFS(F44>=4.5,"Excellent",AND(F44>=3.5,F44<=4.4),"Good",F44<3.5,"Needs Improvement")} -> Needs Improvement | I44: 23.27 | J44: 20.03 | K44: =IF(J44>I44,"Over Budget","Within Budget") -> Within Budget | N44: 155745 | O44: =IF(M44<>N44,"Yes","No") -> Yes | Q44: 10.26 | R44: =IF(ISBLANK(Q44),"No","Yes") -> Yes | T44: 3.83 | U44: =IF(T44>10,"High Attrition","No") -> No | W44: EMP0076 | X44: =VLOOKUP(W44,Employees!$A$1:$B$601,2,FALSE) -> Bikash Biswal | Z44: EMP0043 | AA44: =RIGHT(Z44,4) -> 0043 | AC44: Data Science | AD44: =PROPER(AC44) -> Data Science | AF44: Rahul Ratha | AG44: Data Science | AH44: TributeAI | AI44: =_xlfn.CONCAT(AF44,"|",AG44,"|",AH44) -> Rahul Ratha|Data Science|TributeAI | AK44: Rahul Ratha | AL44: =LEFT(AK44,1)&"."&MID(AK44,FIND(" ",AK44)+1,1)&"." -> R.R. | AN44: LinkedIn | AO44: =IF(UPPER(AN44)="linkedin","Linkedln",IF(UPPER(AN44)="naukri","Naukri")) -> Linkedln | AQ44: Rahul Ratha | AR44: =IF(ISNUMBER(SEARCH("Mishra",AQ44)),"Mishra","NO") -> NO | AT44: Talent Management | AU44: =LEN(AT44) -> 17 | AW44: =DATEDIF(BI44,TODAY(),"Y") -> 6 | AY44: 29-09-2023 | AZ44: =DATE(RIGHT(AY44,4),MID(AY44,4,2),LEFT(AY44,2)) -> 45198 | BA44: =MONTH(AZ44)&"-"&YEAR(AZ44) -> 9-2023 | BC44: 04-08-2023 | BD44: =DATE(RIGHT(BC44,4),MID(BC44,4,2),LEFT(BC44,2)) -> 45142 | BE44: Cancelled | BF44: =IF(AND(BD44<TODAY(),BE44<>"Completed"),"Overdue","On Track") -> Overdue | BH44: 18-01-2020 | BI44: =IF(LEN(LEFT(BH44,FIND("-",BH44)-1))=4,DATE(LEFT(BH44,4),MID(BH44,6,2),RIGHT(BH44,2)),DATE(RIGHT(BH44,4),MID(BH44,4,2),LEFT(BH44,2))) -> 43848 | BJ44: =NETWORKDAYS(BI44,TODAY()) -> 1715 | BL44: =IF(MONTH(BI44)<=3,"Q1","No") -> Q1 | BM44: =DATE(RIGHT(AY44,4),MID(AY44,4,2),LEFT(AY44,2)) -> 45198 | BN44: =IF(LEN(LEFT(BH44,FIND("-",BH44)-1))=4,DATE(LEFT(BH44,4),MID(BH44,6,2),RIGHT(BH44,2)),DATE(RIGHT(BH44,4),MID(BH44,4,2),LEFT(BH44,2))) -> 43848 | BO44: =ABS(BN44-BM44) -> 1350 | BP44: EMP0043 | BQ44: Data Science | BR44: EMP0076 | BS44: ATT00043 | BT44: =VLOOKUP(BR44,$BP$2:$BQ$601,2,FALSE) -> Marketing | BV44: EMP0043 | BW44: Rahul Ratha | BX44: Talent Management | BY44: EMP0180 | BZ44: =VLOOKUP(BY44,$BV$2:$BW$601,2,FALSE) -> Abhishek Pattnaik | CB44: Sangita Parida | CC44: Rahul Ratha | CD44: Data Analyst | CE44: ML Engineer | CG44: =IFERROR(_xlfn.XLOOKUP(Hiring!A44,Hiring!A44:A443,Hiring!B44:B443,,0),"Not Found") -> Sangita Parida
F45: 2.7 | G45: {=_xlfn.IFS(F45>=4.5,"Excellent",AND(F45>=3.5,F45<=4.4),"Good",F45<3.5,"Needs Improvement")} -> Needs Improvement | I45: 59.86 | J45: 42.4 | K45: =IF(J45>I45,"Over Budget","Within Budget") -> Within Budget | N45: 195587 | O45: =IF(M45<>N45,"Yes","No") -> Yes | Q45: 9.65 | R45: =IF(ISBLANK(Q45),"No","Yes") -> Yes | T45: 5.6 | U45: =IF(T45>10,"High Attrition","No") -> No | W45: EMP0061 | X45: =VLOOKUP(W45,Employees!$A$1:$B$601,2,FALSE) -> Aditya Prusty | Z45: EMP0044 | AA45: =RIGHT(Z45,4) -> 0044 | AC45: HR | AD45: =PROPER(AC45) -> Hr | AF45: Nirmal Padhi | AG45: HR | AH45: OdishaCode Labs | AI45: =_xlfn.CONCAT(AF45,"|",AG45,"|",AH45) -> Nirmal Padhi|HR|OdishaCode Labs | AK45: Nirmal Padhi | AL45: =LEFT(AK45,1)&"."&MID(AK45,FIND(" ",AK45)+1,1)&"." -> N.P. | AN45: naukri | AO45: =IF(UPPER(AN45)="linkedin","Linkedln",IF(UPPER(AN45)="naukri","Naukri")) -> Naukri | AQ45: Nirmal Padhi | AR45: =IF(ISNUMBER(SEARCH("Mishra",AQ45)),"Mishra","NO") -> NO | AT45: Supply Chain Optimizer | AU45: =LEN(AT45) -> 22 | AW45: =DATEDIF(BI45,TODAY(),"Y") -> 6 | AY45: 03-08-2023 | AZ45: =DATE(RIGHT(AY45,4),MID(AY45,4,2),LEFT(AY45,2)) -> 45141 | BA45: =MONTH(AZ45)&"-"&YEAR(AZ45) -> 8-2023 | BC45: 08-05-2022 | BD45: =DATE(RIGHT(BC45,4),MID(BC45,4,2),LEFT(BC45,2)) -> 44689 | BE45: On Hold | BF45: =IF(AND(BD45<TODAY(),BE45<>"Completed"),"Overdue","On Track") -> Overdue | BH45: 2020-05-30 | BI45: =IF(LEN(LEFT(BH45,FIND("-",BH45)-1))=4,DATE(LEFT(BH45,4),MID(BH45,6,2),RIGHT(BH45,2)),DATE(RIGHT(BH45,4),MID(BH45,4,2),LEFT(BH45,2))) -> 43981 | BJ45: =NETWORKDAYS(BI45,TODAY()) -> 1620 | BL45: =IF(MONTH(BI45)<=3,"Q1","No") -> No | BM45: =DATE(RIGHT(AY45,4),MID(AY45,4,2),LEFT(AY45,2)) -> 45141 | BN45: =IF(LEN(LEFT(BH45,FIND("-",BH45)-1))=4,DATE(LEFT(BH45,4),MID(BH45,6,2),RIGHT(BH45,2)),DATE(RIGHT(BH45,4),MID(BH45,4,2),LEFT(BH45,2))) -> 43981 | BO45: =ABS(BN45-BM45) -> 1160 | BP45: EMP0044 | BQ45: HR | BR45: EMP0061 | BS45: ATT00044 | BT45: =VLOOKUP(BR45,$BP$2:$BQ$601,2,FALSE) -> Product | BV45: EMP0044 | BW45: Nirmal Padhi | BX45: Supply Chain Optimizer | BY45: EMP0499 | BZ45: =VLOOKUP(BY45,$BV$2:$BW$601,2,FALSE) -> Puspita Prusty | CB45: Debasmita Parida | CC45: Nirmal Padhi | CD45: HR Manager | CE45: Not Found | CG45: =IFERROR(_xlfn.XLOOKUP(Hiring!A45,Hiring!A45:A444,Hiring!B45:B444,,0),"Not Found") -> Debasmita Parida
