Workbook

Sheet Branches
A1: Branch_ID | B1: Branch_Name | C1: Manager | D1: Region | E1: State | F1: Target_Revenue_Lakhs | G1: Established_Year
A2: BR001 | B2: Bhubaneswar Main | C2: Rajesh Kumar | D2: North | E2: Jharkhand | F2: 209.86 | G2: 2012
A3: BR002 | B3: Cuttack Central | C3: Priya Mohanty | D3: North | E3: Chhattisgarh | F3: 105.8 | G3: 2007
A4: BR003 | B4: Rourkela Industrial | C4: Suresh Panda | D4: North | E4: Odisha | F4: 197.62 | G4: 2007
A5: BR004 | B5: Puri Tourism | C5: Anita Das | D5: Central | E5: Chhattisgarh | F5: 104.66 | G5: 2005
A6: BR005 | B6: Sambalpur Regional | C6: Bikash Nayak | D6: Central | E6: Andhra Pradesh | F6: 190.31 | G6: 2012
A7: BR006 | B7: Berhampur South | C7: Sunita Sahu | D7: East | E7: Odisha | F7: 162.3 | G7: 2010
A8: BR007 | B8: Balasore North | C8: Ramesh Behera | D8: East | E8: Jharkhand | F8: 224.53 | G8: 2009
A9: BR008 | B9: Angul Mining | C9: Kavita Rath | D9: East | E9: Odisha | F9: 103.83 | G9: 2007
A10: BR009 | B10: Jharsuguda Energy | C10: Deepak Mishra | D10: East | E10: Jharkhand | F10: 144.98 | G10: 2013
A11: BR010 | B11: Dhenkanal Rural | C11: Pooja Tripathi | D11: West | E11: Chhattisgarh | F11: 251.78 | G11: 2008

Sheet Customers
A1: Customer_ID | B1: Name | C1: Gender | D1: City | E1: Occupation | F1: Annual_Income_Lakhs | G1: Credit_Score | H1: Joining_Date | I1: Age | J1: Loan_History_Count
A2: CUST0001 | B2: Mira Pradhan | C2: Male | D2: Dhenkanal | E2: retired | F2: 43.5 | G2: 585 | H2: 22-07-2020 | I2: 40 | J2: 0
A3: CUST0002 | B3: Sita Rath | C3: Male | D3: Balasore | E3: Government Employee | F3: 20.15 | G3: 657 | H3: 20-10-2018 | I3: 60 | J3: 5
A4: CUST0003 | B4: Kavita Rout | C4: female | D4: Sambalpur | E4: Government Employee | F4: 49.51 | G4: 835 | H4: 21-08-2021 | I4: 25 | J4: 1
A5: CUST0004 | B5: Ashok Mohanty | C5: M | D5: Balasore | E5: Salaried | F5: 47.32 | G5: 711 | H5: 07-08-2023 | I5: 47 | J5: 5
A6: CUST0005 | B6: Arjun Nayak | C6: M | D6: Rourkela | E6: retired | F6: 15.35 | G6: 848 | H6: 17-06-2020 | I6: 30 | J6: 4
A7: CUST0006 | B7: Nisha Das | C7: Male | D7: Cuttack | E7: retired | F7: 34.98 | G7: 747 | H7: 02-04-2023 | I7: 55 | J7: 2
A8: CUST0007 | B8: Seema Kumar | C8: female | D8: Cuttack | E8: retired | F8: 38.29 | G8: 724 | H8: 16-11-2022 | I8: 32 | J8: 3
A9: CUST0008 | B9: Amit Mishra | C9: male | D9: Rourkela | E9: Salaried | F9: 17.03 | G9: 861 | H9: 12-03-2022 | I9: 32 | J9: 4
A10: CUST0009 | B10: Prakash Swain | C10: Male | D10: Jharsuguda | E10: Government Employee | G10: 707 | H10: 13-09-2020 | I10: 58 | J10: 0
A11: CUST0010 | B11: Ravi Dash | C11: Male | D11: Dhenkanal | E11: Self-Employed | F11: 47.5 | G11: 820 | H11: 30-09-2022 | I11: 35 | J11: 4
A12: CUST0011 | B12: Prakash Behera | C12: female | D12: Berhampur | E12: retired | F12: 23.59 | G12: 611 | H12: 20-09-2018 | I12: 43 | J12: 0
A13: CUST0012 | B13: Vijay Rout | C13: Female | D13: Jharsuguda | E13: Salaried | F13: 32.66 | G13: 566 | H13: 18-10-2018 | I13: 54 | J13: 1
A14: CUST0013 | B14: Bikash Dash | C14: Female | D14: Dhenkanal | E14: retired | F14: 29.84 | G14: 792 | H14: 19-02-2020 | I14: 28 | J14: 0
A15: CUST0014 | B15: Rekha Patnaik | C15: M | D15: Balasore | E15: Government Employee | F15: 5.55 | G15: 880 | H15: 08-07-2022 | I15: 43 | J15: 0
A16: CUST0015 | B16: Anita Behera | C16: Female | D16: Dhenkanal | E16: Self-Employed | F16: 16.09 | G16: 588 | H16: 04-03-2024 | I16: 28 | J16: 0
A17: CUST0016 | B17: Manoj Rout | C17: Male | D17: Cuttack | E17: Self-Employed | F17: 25.62 | G17: 580 | H17: 09-01-2018 | I17: 46 | J17: 2
A18: CUST0017 | B18: Mira Sethi | C18: M | D18: Balasore | E18: retired | F18: 10.28 | G18: 579 | H18: 30-01-2024 | I18: 25 | J18: 5
A19: CUST0018 | B19: Deepak Mohanty | C19: Male | D19: Jharsuguda | E19: Freelancer | F19: 27.96 | G19: 810 | H19: 01-02-2020 | I19: 26 | J19: 4
A20: CUST0019 | B20: Ravi Rath | C20: F | D20: Cuttack | E20: Self-Employed | F20: 4.87 | G20: 886 | H20: 12-11-2023 | I20: 42 | J20: 2
A21: CUST0020 | B21: Suresh Sahoo | C21: Female | D21: Berhampur | E21: Self-Employed | F21: 17.1 | G21: 587 | H21: 2024/12/19 | I21: 58 | J21: 0
A22: CUST0021 | B22: Ravi Rout | C22: Female | D22: Dhenkanal | E22: Self-Employed | F22: 44.4 | G22: 739 | H22: 30-11-2022 | I22: 56 | J22: 5
... A24: CUST0023 | B24: Bikash Tripathi | C24: male | D24: Sambalpur | E24: Self-Employed | F24: 43.09 | G24: 678 | H24: 28-07-2018 | I24: 27 | J24: 5
A25: CUST0024 | B25: Lata Mishra | D25: Bhubaneswar | E25: Self-Employed | F25: 15.31 | G25: 832 | H25: 16-04-2024 | I25: 22 | J25: 0
A26: CUST0025 | B26: Ravi Nayak | C26: male | D26: Bhubaneswar | E26: Freelancer | F26: 23.2 | H26: 13-06-2018 | I26: 44 | J26: 1
A27: CUST0026 | B27: Rekha Rath | C27: female | D27: Cuttack | E27: Freelancer | F27: 22.1 | G27: 629 | H27: 27-08-2020 | I27: 32 | J27: 1
A28: CUST0027 | B28: Dilip Patnaik | C28: Male | D28: Rourkela | E28: Government Employee | F28: 43.61 | G28: 686 | H28: 19-03-2019 | I28: 46 | J28: 0
A29: CUST0028 | B29: Sita Dash | C29: Female | D29: Sambalpur | E29: Business Owner | F29: 40.38 | G29: 562 | H29: 21-06-2022 | I29: 43 | J29: 2
A30: CUST0029 | B30: Sita Das | C30: M | D30: Puri | E30: Government Employee | F30: 42.65 | G30: 564 | H30: 05-12-2020 | I30: 33 | J30: 4
A31: CUST0030 | B31: Bikash Mohanty | C31: Male | D31: Jharsuguda | E31: Business Owner | F31: 17.74 | G31: 811 | H31: 19-06-2024 | I31: 34 | J31: 2
A32: CUST0031 | B32: Priya Patnaik | C32: Male | D32: Dhenkanal | E32: retired | F32: 37.87 | G32: 736 | H32: 14-09-2021 | I32: 61 | J32: 2
A33: CUST0032 | B33: Rekha Panda | C33: female | D33: Berhampur | E33: Business Owner | F33: 18.33 | G33: 833 | H33: 19-09-2022 | I33: 64 | J33: 3
A34: CUST0033 | B34: Rekha Sahu | C34: male | D34: Jharsuguda | E34: Government Employee | F34: 3.02 | G34: 770 | H34: 20-10-2024 | I34: 63 | J34: 2
A35: CUST0034 | B35: Arjun Sethi | C35: F | D35: Bhubaneswar | E35: Freelancer | F35: 45.36 | G35: 636 | H35: 08-03-2021 | I35: 54 | J35: 5
A36: CUST0035 | B36: Manoj Barik | C36: M | D36: Cuttack | E36: retired | F36: 40.91 | G36: 573 | H36: 01-05-2023 | I36: 61 | J36: 0
A37: CUST0036 | B37: Arjun Patnaik | C37: female | D37: Jharsuguda | E37: retired | F37: 26.24 | G37: 885 | H37: 13-03-2019 | I37: 49 | J37: 1
A38: CUST0037 | B38: Kavita Swain | C38: F | D38: Bhubaneswar | E38: Self-Employed | F38: 8.7 | G38: 787 | H38: 08-04-2024 | I38: 60 | J38: 2
... A45: CUST0044 | B45: Bikash Pradhan | C45: M | D45: Sambalpur | E45: Business Owner | F45: 44.34 | G45: 765 | H45: 02-12-2018 | I45: 52 | J45: 0
A46: CUST0045 | B46: Mamata Rout | C46: Male | D46: Puri | E46: retired | F46: 47.99 | H46: 09-10-2020 | I46: 34 | J46: 0
A47: CUST0046 | B47: Puja Nayak | C47: Female | D47: Rourkela | E47: retired | F47: 47.54 | G47: 681 | H47: 19-11-2019 | I47: 60 | J47: 4
A48: CUST0047 | B48: Mamata Panda | C48: Female | D48: Berhampur | E48: Freelancer | G48: 896 | H48: 18-03-2022 | I48: 47 | J48: 5
A49: CUST0048 | B49: Suresh Das | C49: male | D49: Cuttack | E49: Salaried | F49: 17.17 | G49: 611 | H49: 07-05-2024 | I49: 24 | J49: 2
A50: CUST0049 | B50: Seema Patnaik | C50: female | D50: Puri | E50: Freelancer | F50: 3.59 | G50: 800 | H50: 23-01-2022 | I50: 62 | J50: 3
A51: CUST0050 | B51: Ganesh Nayak | C51: F | D51: Rourkela | E51: retired | F51: 40.99 | G51: 797 | H51: 23-08-2024 | I51: 39 | J51: 2
A52: CUST0051 | B52: Sita Rath | C52: Male | D52: Berhampur | E52: Self-Employed | F52: 29.78 | G52: 722 | H52: 24-08-2021 | I52: 33 | J52: 3
A53: CUST0052 | B53: Suresh Biswal | C53: M | D53: Puri | E53: Freelancer | F53: 15.98 | H53: 17-12-2018 | I53: 37 | J53: 5
A54: CUST0053 | B54: Lata Dash | C54: male | D54: Sambalpur | E54: retired | F54: 24.06 | H54: 15-07-2022 | I54: 37 | J54: 2
A55: CUST0054 | B55: Rekha Mallick | C55: M | D55: Angul | E55: Freelancer | F55: 49.84 | G55: 730 | H55: 14-01-2021 | I55: 41 | J55: 2
A56: CUST0055 | B56: Anita Panda | C56: female | D56: Sambalpur | E56: Salaried | F56: 47.69 | G56: 648 | H56: 07-06-2023 | I56: 39 | J56: 5
A57: CUST0056 | B57: Vijay Swain | C57: male | D57: Berhampur | E57: Self-Employed | F57: 19.96 | G57: 823 | H57: 06-07-2018 | I57: 25 | J57: 4
A58: CUST0057 | B58: Pooja Nayak | C58: female | D58: Angul | E58: Salaried | F58: 25.06 | G58: 644 | H58: 31-10-2020 | I58: 52 | J58: 0
A59: CUST0058 | B59: Ashok Das | C59: F | D59: Angul | E59: Freelancer | F59: 5.52 | G59: 838 | H59: 15-12-2018 | I59: 37 | J59: 0
A60: CUST0059 | B60: Seema Patnaik | C60: male | D60: Jharsuguda | E60: Self-Employed | F60: 20.88 | G60: 702 | H60: 23-10-2022 | I60: 41 | J60: 4
A61: CUST0060 | B61: Puja Mohanty | C61: male | D61: Cuttack | E61: Self-Employed | F61: 15.44 | G61: 672 | H61: 04-11-2018 | I61: 32 | J61: 0
A62: CUST0061 | B62: Lata Sethi | C62: female | D62: Jharsuguda | E62: Business Owner | F62: 16.54 | G62: 782 | H62: 14-08-2020 | I62: 38 | J62: 5
A63: CUST0062 | B63: Vijay Behera | C63: F | D63: Cuttack | E63: Self-Employed | F63: 45.7 | G63: 586 | H63: 13-06-2021 | I63: 60 | J63: 5
A64: CUST0063 | B64: Ashok Mallick | C64: M | D64: Angul | E64: Government Employee | F64: 35.89 | G64: 806 | H64: 29-11-2022 | I64: 27 | J64: 4
A65: CUST0064 | B65: Priya Patnaik | C65: female | D65: Puri | E65: Business Owner | G65: 895 | H65: 14-06-2024 | I65: 59 | J65: 0
A66: CUST0065 | B66: Prakash Mishra | C66: male | D66: Bhubaneswar | E66: Government Employee | F66: 23.78 | G66: 849 | H66: 08-07-2023 | I66: 27 | J66: 3
A67: CUST0066 | B67: Meena Patnaik | C67: M | D67: Puri | E67: Self-Employed | F67: 35.6 | G67: 755 | H67: 03-03-2024 | I67: 24 | J67: 3
A68: CUST0067 | B68: Ravi Sahoo | C68: M | D68: Puri | E68: Government Employee | F68: 41.77 | H68: 08-03-2023 | I68: 48 | J68: 0
A69: CUST0068 | B69: Suresh Swain | C69: M | D69: Jharsuguda | E69: retired | F69: 5.43 | G69: 617 | H69: 30-11-2022 | I69: 53 | J69: 0
A70: CUST0069 | B70: Amit Barik | C70: Female | D70: Cuttack | E70: Business Owner | F70: 28.96 | G70: 608 | H70: 27-04-2019 | I70: 63 | J70: 1
A71: CUST0070 | B71: Nisha Tripathi | C71: male | D71: Cuttack | E71: Government Employee | F71: 49.07 | G71: 832 | H71: 20-02-2020 | I71: 60 | J71: 4
A72: CUST0071 | B72: Mamata Nayak | C72: Male | D72: Berhampur | E72: Business Owner | F72: 26.86 | G72: 694 | H72: 01-08-2024 | I72: 59 | J72: 5
A73: CUST0072 | B73: Nisha Nayak | C73: F | D73: Dhenkanal | E73: Business Owner | F73: 38.86 | G73: 714 | H73: 05-09-2020 | I73: 58 | J73: 3
A74: CUST0073 | B74: Anita Patnaik | C74: Male | D74: Puri | E74: retired | F74: 20.92 | G74: 883 | H74: 22-07-2023 | I74: 24 | J74: 1
A75: CUST0074 | B75: Rohit Mallick | C75: M | D75: Cuttack | E75: Salaried | F75: 24.48 | G75: 759 | H75: 25-09-2019 | I75: 26 | J75: 3
A76: CUST0075 | B76: Suman Mishra | C76: M | D76: Jharsuguda | E76: retired | F76: 18.44 | G76: 823 | H76: 21-07-2021 | I76: 62 | J76: 5
A77: CUST0076 | B77: Dilip Dash | C77: male | D77: Bhubaneswar | E77: Salaried | F77: 35.17 | G77: 666 | H77: 13-11-2022 | I77: 28 | J77: 5
A78: CUST0077 | B78: Ganesh Panda | C78: F | D78: Rourkela | E78: Salaried | F78: 40.42 | G78: 741 | H78: 27-09-2020 | I78: 55 | J78: 3
A79: CUST0078 | B79: Vijay Sahu | C79: Female | D79: Rourkela | E79: Freelancer | F79: 32.13 | G79: 848 | H79: 04-03-2023 | I79: 62 | J79: 2
A80: CUST0079 | B80: Arjun Mishra | C80: female | D80: Bhubaneswar | E80: Business Owner | F80: 10.42 | G80: 726 | H80: 10-05-2021 | I80: 62 | J80: 3
... A82: CUST0081 | B82: Sanjay Mishra | C82: Male | D82: Jharsuguda | E82: Freelancer | F82: 42.14 | G82: 667 | H82: 14-12-2021 | I82: 36 | J82: 5
A83: CUST0082 | B83: Suresh Barik | C83: M | D83: Bhubaneswar | E83: retired | F83: 32.49 | H83: 17-05-2018 | I83: 59 | J83: 2
A84: CUST0083 | B84: Mamata Nayak | C84: Male | D84: Berhampur | E84: retired | F84: 12.44 | G84: 737 | H84: 21-01-2021 | I84: 32 | J84: 2
A85: CUST0084 | B85: Mira Dash | C85: M | D85: Cuttack | E85: Salaried | F85: 6.54 | G85: 665 | H85: 16-06-2022 | I85: 57 | J85: 2
A86: CUST0085 | B86: Ravi Pradhan | C86: Male | D86: Berhampur | E86: Salaried | F86: 34.62 | G86: 849 | H86: 02-03-2022 | I86: 28 | J86: 5
A87: CUST0086 | B87: Anita Dash | C87: Male | D87: Jharsuguda | E87: Business Owner | F87: 13.4 | G87: 787 | H87: 22-05-2021 | I87: 63 | J87: 3
A88: CUST0087 | B88: Sunita Nayak | C88: Male | D88: Bhubaneswar | E88: Government Employee | F88: 14.04 | G88: 748 | H88: 22-01-2024 | I88: 48 | J88: 4
A89: CUST0088 | B89: Mamata Nayak | C89: F | D89: Bhubaneswar | E89: Government Employee | F89: 47.14 | G89: 739 | H89: 27-12-2022 | I89: 37 | J89: 2
A90: CUST0089 | B90: Sunita Biswal | C90: male | D90: Bhubaneswar | E90: Salaried | F90: 11.92 | G90: 782 | H90: 18-05-2020 | I90: 63 | J90: 5
A91: CUST0090 | B91: Puja Kumar | C91: Male | D91: Puri | E91: Self-Employed | F91: 12.64 | G91: 833 | H91: 03-06-2020 | I91: 36 | J91: 2
A92: CUST0091 | B92: Prakash Nayak | C92: male | D92: Bhubaneswar | E92: Self-Employed | F92: 28.39 | G92: 606 | H92: 16-04-2018 | I92: 30 | J92: 0
A93: CUST0092 | B93: Meena Rath | C93: male | D93: Puri | E93: Self-Employed | F93: 8.96 | G93: 608 | H93: 05-05-2023 | I93: 50 | J93: 2
A94: CUST0093 | B94: Rohit Mallick | C94: Male | D94: Angul | E94: Self-Employed | F94: 5.04 | G94: 887 | H94: 20-02-2023 | I94: 63 | J94: 0
A95: CUST0094 | B95: Priya Dash | C95: F | D95: Balasore | E95: Government Employee | F95: 23.85 | G95: 714 | H95: 27-09-2018 | I95: 30 | J95: 2
... A113: CUST0112 | B113: Rohit Pradhan | C113: F | D113: Jharsuguda | E113: retired | F113: 24.14 | G113: 883 | H113: 14-10-2024 | I113: 52 | J113: 4
A114: CUST0113 | B114: Rajesh Mohanty | C114: F | D114: Cuttack | E114: retired | F114: 33.37 | H114: 05-12-2022 | I114: 55 | J114: 4
A115: CUST0114 | B115: Puja Sahu | C115: M | D115: Puri | E115: Government Employee | F115: 18.9 | G115: 873 | H115: 27-09-2018 | I115: 43 | J115: 0
A116: CUST0115 | B116: Seema Pradhan | C116: M | D116: Berhampur | E116: Self-Employed | F116: 30.39 | G116: 729 | H116: 25-05-2022 | I116: 30 | J116: 4
A117: CUST0116 | B117: Ganesh Das | C117: M | D117: Dhenkanal | E117: retired | F117: 41.22 | G117: 900 | H117: 18-01-2019 | I117: 63 | J117: 5
A118: CUST0117 | B118: Lata Swain | C118: M | D118: Bhubaneswar | E118: Business Owner | F118: 13.07 | G118: 798 | H118: 18-07-2019 | I118: 31 | J118: 0
A119: CUST0118 | B119: Pooja Panda | C119: male | D119: Dhenkanal | E119: Salaried | F119: 44.19 | G119: 855 | H119: 27-10-2019 | I119: 33 | J119: 5
A120: CUST0119 | B120: Prakash Barik | C120: Female | D120: Cuttack | E120: Salaried | F120: 34.79 | G120: 777 | H120: 13-01-2023 | I120: 36 | J120: 4
A121: CUST0120 | B121: Anita Tripathi | C121: F | D121: Sambalpur | E121: retired | F121: 49.27 | G121: 694 | H121: 22-08-2023 | I121: 55 | J121: 3
A122: CUST0121 | B122: Kavita Behera | C122: male | D122: Rourkela | E122: Salaried | F122: 44.08 | G122: 602 | H122: 15-10-2023 | I122: 29 | J122: 2
A123: CUST0122 | B123: Ravi Sahu | C123: M | D123: Angul | E123: Self-Employed | F123: 7.31 | G123: 780 | H123: 20-04-2018 | I123: 48 | J123: 0
A124: CUST0123 | B124: Sanjay Swain | C124: M | D124: Sambalpur | E124: Salaried | F124: 4.32 | G124: 882 | H124: 22-08-2019 | I124: 30 | J124: 0
A125: CUST0124 | B125: Pooja Dash | C125: female | D125: Rourkela | E125: Government Employee | F125: 45.58 | H125: 05-09-2019 | I125: 57 | J125: 5
...

Sheet Sheet3
A1: Customer_ID | B1: Name | C1: Gender | D1: City | E1: Occupation | F1: Annual_Income_Lakhs | G1: Credit_Score | H1: Joining_Date | I1: Age | J1: Loan_History_Count | K1: Loan_Amount_Lakhs
A2: CUST0001 | B2: Mira Pradhan | C2: Male | D2: Dhenkanal | E2: retired | F2: 43.5 | G2: 585 | H2: 22-07-2020 | I2: 40 | J2: 0 | K2: 73.8
A3: CUST0002 | B3: Sita Rath | C3: Male | D3: Balasore | E3: Government Employee | F3: 20.15 | G3: 657 | H3: 20-10-2018 | I3: 60 | J3: 5 | K3: 47.65
A4: CUST0003 | B4: Kavita Rout | C4: female | D4: Sambalpur | E4: Government Employee | F4: 49.51 | G4: 835 | H4: 21-08-2021 | I4: 25 | J4: 1 | K4: 58.02
A5: CUST0004 | B5: Ashok Mohanty | C5: M | D5: Balasore | E5: Salaried | F5: 47.32 | G5: 711 | H5: 07-08-2023 | I5: 47 | J5: 5 | K5: 25.12
A6: CUST0005 | B6: Arjun Nayak | C6: M | D6: Rourkela | E6: retired | F6: 15.35 | G6: 848 | H6: 17-06-2020 | I6: 30 | J6: 4 | K6: 80.93
A7: CUST0006 | B7: Nisha Das | C7: Male | D7: Cuttack | E7: retired | F7: 34.98 | G7: 747 | H7: 02-04-2023 | I7: 55 | J7: 2 | K7: 82.82
A8: CUST0007 | B8: Seema Kumar | C8: female | D8: Cuttack | E8: retired | F8: 38.29 | G8: 724 | H8: 16-11-2022 | I8: 32 | J8: 3 | K8: 66.27
A9: CUST0008 | B9: Amit Mishra | C9: male | D9: Rourkela | E9: Salaried | F9: 17.03 | G9: 861 | H9: 12-03-2022 | I9: 32 | J9: 4 | K9: 62.07
A10: CUST0009 | B10: Prakash Swain | C10: Male | D10: Jharsuguda | E10: Government Employee | G10: 707 | H10: 13-09-2020 | I10: 58 | J10: 0 | K10: 33.27
A11: CUST0010 | B11: Ravi Dash | C11: Male | D11: Dhenkanal | E11: Self-Employed | F11: 47.5 | G11: 820 | H11: 30-09-2022 | I11: 35 | J11: 4 | K11: 48.96
A12: CUST0011 | B12: Prakash Behera | C12: female | D12: Berhampur | E12: retired | F12: 23.59 | G12: 611 | H12: 20-09-2018 | I12: 43 | J12: 0 | K12: 69.53
A13: CUST0012 | B13: Vijay Rout | C13: Female | D13: Jharsuguda | E13: Salaried | F13: 32.66 | G13: 566 | H13: 18-10-2018 | I13: 54 | J13: 1 | K13: 85.65
A14: CUST0013 | B14: Bikash Dash | C14: Female | D14: Dhenkanal | E14: retired | F14: 29.84 | G14: 792 | H14: 19-02-2020 | I14: 28 | J14: 0 | K14: 89.29
A15: CUST0014 | B15: Rekha Patnaik | C15: M | D15: Balasore | E15: Government Employee | F15: 5.55 | G15: 880 | H15: 08-07-2022 | I15: 43 | J15: 0 | K15: 24.81
A16: CUST0015 | B16: Anita Behera | C16: Female | D16: Dhenkanal | E16: Self-Employed | F16: 16.09 | G16: 588 | H16: 04-03-2024 | I16: 28 | J16: 0 | K16: 85.93
A17: CUST0016 | B17: Manoj Rout | C17: Male | D17: Cuttack | E17: Self-Employed | F17: 25.62 | G17: 580 | H17: 09-01-2018 | I17: 46 | J17: 2 | K17: 53.56
A18: CUST0017 | B18: Mira Sethi | C18: M | D18: Balasore | E18: retired | F18: 10.28 | G18: 579 | H18: 30-01-2024 | I18: 25 | J18: 5 | K18: 37.19
A19: CUST0018 | B19: Deepak Mohanty | C19: Male | D19: Jharsuguda | E19: Freelancer | F19: 27.96 | G19: 810 | H19: 01-02-2020 | I19: 26 | J19: 4 | K19: 75.56
A20: CUST0019 | B20: Ravi Rath | C20: F | D20: Cuttack | E20: Self-Employed | F20: 4.87 | G20: 886 | H20: 12-11-2023 | I20: 42 | J20: 2 | K20: 68.15
A21: CUST0020 | B21: Suresh Sahoo | C21: Female | D21: Berhampur | E21: Self-Employed | F21: 17.1 | G21: 587 | H21: 2024/12/19 | I21: 58 | J21: 0 | K21: 70.01
A22: CUST0021 | B22: Ravi Rout | C22: Female | D22: Dhenkanal | E22: Self-Employed | F22: 44.4 | G22: 739 | H22: 30-11-2022 | I22: 56 | J22: 5 | K22: 83.66
... A25: CUST0024 | B25: Lata Mishra | C25: Male | D25: Bhubaneswar | E25: Self-Employed | F25: 15.31 | G25: 832 | H25: 16-04-2024 | I25: 22 | J25: 0 | K25: 13.03
A26: CUST0025 | B26: Ravi Nayak | C26: male | D26: Bhubaneswar | E26: Freelancer | F26: 23.2 | H26: 13-06-2018 | I26: 44 | J26: 1 | K26: 67.02
A27: CUST0026 | B27: Rekha Rath | C27: female | D27: Cuttack | E27: Freelancer | F27: 22.1 | G27: 629 | H27: 27-08-2020 | I27: 32 | J27: 1 | K27: 62.13
A28: CUST0027 | B28: Dilip Patnaik | C28: Male | D28: Rourkela | E28: Government Employee | F28: 43.61 | G28: 686 | H28: 19-03-2019 | I28: 46 | J28: 0 | K28: 20.25
A29: CUST0028 | B29: Sita Dash | C29: Female | D29: Sambalpur | E29: Business Owner | F29: 40.38 | G29: 562 | H29: 21-06-2022 | I29: 43 | J29: 2 | K29: 22.35
A30: CUST0029 | B30: Sita Das | C30: M | D30: Puri | E30: Government Employee | F30: 42.65 | G30: 564 | H30: 05-12-2020 | I30: 33 | J30: 4 | K30: 47.99
A31: CUST0030 | B31: Bikash Mohanty | C31: Male | D31: Jharsuguda | E31: Business Owner | F31: 17.74 | G31: 811 | H31: 19-06-2024 | I31: 34 | J31: 2 | K31: 19.41
A32: CUST0031 | B32: Priya Patnaik | C32: Male | D32: Dhenkanal | E32: retired | F32: 37.87 | G32: 736 | H32: 14-09-2021 | I32: 61 | J32: 2 | K32: 83.59
A33: CUST0032 | B33: Rekha Panda | C33: female | D33: Berhampur | E33: Business Owner | F33: 18.33 | G33: 833 | H33: 19-09-2022 | I33: 64 | J33: 3 | K33: 56.99
A34: CUST0033 | B34: Rekha Sahu | C34: male | D34: Jharsuguda | E34: Government Employee | F34: 3.02 | G34: 770 | H34: 20-10-2024 | I34: 63 | J34: 2 | K34: 27.99
A35: CUST0034 | B35: Arjun Sethi | C35: F | D35: Bhubaneswar | E35: Freelancer | F35: 45.36 | G35: 636 | H35: 08-03-2021 | I35: 54 | J35: 5 | K35: 82.86
A36: CUST0035 | B36: Manoj Barik | C36: M | D36: Cuttack | E36: retired | F36: 40.91 | G36: 573 | H36: 01-05-2023 | I36: 61 | J36: 0 | K36: 92.17
A37: CUST0036 | B37: Arjun Patnaik | C37: female | D37: Jharsuguda | E37: retired | F37: 26.24 | G37: 885 | H37: 13-03-2019 | I37: 49 | J37: 1 | K37: 82.07
A38: CUST0037 | B38: Kavita Swain | C38: F | D38: Bhubaneswar | E38: Self-Employed | F38: 8.7 | G38: 787 | H38: 08-04-2024 | I38: 60 | J38: 2 | K38: 15.09
... A45: CUST0044 | B45: Bikash Pradhan | C45: M | D45: Sambalpur | E45: Business Owner | F45: 44.34 | G45: 765 | H45: 02-12-2018 | I45: 52 | J45: 0 | K45: 40.09
A46: CUST0045 | B46: Mamata Rout | C46: Male | D46: Puri | E46: retired | F46: 47.99 | H46: 09-10-2020 | I46: 34 | J46: 0 | K46: 50.41
A47: CUST0046 | B47: Puja Nayak | C47: Female | D47: Rourkela | E47: retired | F47: 47.54 | G47: 681 | H47: 19-11-2019 | I47: 60 | J47: 4 | K47: 63.21
A48: CUST0047 | B48: Mamata Panda | C48: Female | D48: Berhampur | E48: Freelancer | G48: 896 | H48: 18-03-2022 | I48: 47 | J48: 5 | K48: 76.26
A49: CUST0048 | B49: Suresh Das | C49: male | D49: Cuttack | E49: Salaried | F49: 17.17 | G49: 611 | H49: 07-05-2024 | I49: 24 | J49: 2 | K49: 99.08
A50: CUST0049 | B50: Seema Patnaik | C50: female | D50: Puri | E50: Freelancer | F50: 3.59 | G50: 800 | H50: 23-01-2022 | I50: 62 | J50: 3 | K50: 31.93
A51: CUST0050 | B51: Ganesh Nayak | C51: F | D51: Rourkela | E51: retired | F51: 40.99 | G51: 797 | H51: 23-08-2024 | I51: 39 | J51: 2 | K51: 67.97
A52: CUST0051 | B52: Sita Rath | C52: Male | D52: Berhampur | E52: Self-Employed | F52: 29.78 | G52: 722 | H52: 24-08-2021 | I52: 33 | J52: 3 | K52: 35.17
A53: CUST0052 | B53: Suresh Biswal | C53: M | D53: Puri | E53: Freelancer | F53: 15.98 | H53: 17-12-2018 | I53: 37 | J53: 5 | K53: 54.3
A54: CUST0053 | B54: Lata Dash | C54: male | D54: Sambalpur | E54: retired | F54: 24.06 | H54: 15-07-2022 | I54: 37 | J54: 2 | K54: 10.67
A55: CUST0054 | B55: Rekha Mallick | C55: M | D55: Angul | E55: Freelancer | F55: 49.84 | G55: 730 | H55: 14-01-2021 | I55: 41 | J55: 2 | K55: 29.45
A56: CUST0055 | B56: Anita Panda | C56: female | D56: Sambalpur | E56: Salaried | F56: 47.69 | G56: 648 | H56: 07-06-2023 | I56: 39 | J56: 5 | K56: 43.28
A57: CUST0056 | B57: Vijay Swain | C57: male | D57: Berhampur | E57: Self-Employed | F57: 19.96 | G57: 823 | H57: 06-07-2018 | I57: 25 | J57: 4 | K57: 70.63
A58: CUST0057 | B58: Pooja Nayak | C58: female | D58: Angul | E58: Salaried | F58: 25.06 | G58: 644 | H58: 31-10-2020 | I58: 52 | J58: 0 | K58: 37.06
A59: CUST0058 | B59: Ashok Das | C59: F | D59: Angul | E59: Freelancer | F59: 5.52 | G59: 838 | H59: 15-12-2018 | I59: 37 | J59: 0 | K59: 26.39
A60: CUST0059 | B60: Seema Patnaik | C60: male | D60: Jharsuguda | E60: Self-Employed | F60: 20.88 | G60: 702 | H60: 23-10-2022 | I60: 41 | J60: 4 | K60: 28
A61: CUST0060 | B61: Puja Mohanty | C61: male | D61: Cuttack | E61: Self-Employed | F61: 15.44 | G61: 672 | H61: 04-11-2018 | I61: 32 | J61: 0 | K61: 86.85
A62: CUST0061 | B62: Lata Sethi | C62: female | D62: Jharsuguda | E62: Business Owner | F62: 16.54 | G62: 782 | H62: 14-08-2020 | I62: 38 | J62: 5 | K62: 50.15
A63: CUST0062 | B63: Vijay Behera | C63: F | D63: Cuttack | E63: Self-Employed | F63: 45.7 | G63: 586 | H63: 13-06-2021 | I63: 60 | J63: 5 | K63: 44.51
A64: CUST0063 | B64: Ashok Mallick | C64: M | D64: Angul | E64: Government Employee | F64: 35.89 | G64: 806 | H64: 29-11-2022 | I64: 27 | J64: 4 | K64: 37.41
A65: CUST0064 | B65: Priya Patnaik | C65: female | D65: Puri | E65: Business Owner | G65: 895 | H65: 14-06-2024 | I65: 59 | J65: 0 | K65: 85.91
A66: CUST0065 | B66: Prakash Mishra | C66: male | D66: Bhubaneswar | E66: Government Employee | F66: 23.78 | G66: 849 | H66: 08-07-2023 | I66: 27 | J66: 3 | K66: 86.78
A67: CUST0066 | B67: Meena Patnaik | C67: M | D67: Puri | E67: Self-Employed | F67: 35.6 | G67: 755 | H67: 03-03-2024 | I67: 24 | J67: 3 | K67: 42.67
A68: CUST0067 | B68: Ravi Sahoo | C68: M | D68: Puri | E68: Government Employee | F68: 41.77 | H68: 08-03-2023 | I68: 48 | J68: 0 | K68: 31.25
A69: CUST0068 | B69: Suresh Swain | C69: M | D69: Jharsuguda | E69: retired | F69: 5.43 | G69: 617 | H69: 30-11-2022 | I69: 53 | J69: 0 | K69: 59.71
A70: CUST0069 | B70: Amit Barik | C70: Female | D70: Cuttack | E70: Business Owner | F70: 28.96 | G70: 608 | H70: 27-04-2019 | I70: 63 | J70: 1 | K70: 90.78
A71: CUST0070 | B71: Nisha Tripathi | C71: male | D71: Cuttack | E71: Government Employee | F71: 49.07 | G71: 832 | H71: 20-02-2020 | I71: 60 | J71: 4 | K71: 72.14
A72: CUST0071 | B72: Mamata Nayak | C72: Male | D72: Berhampur | E72: Business Owner | F72: 26.86 | G72: 694 | H72: 01-08-2024 | I72: 59 | J72: 5 | K72: 38.83
A73: CUST0072 | B73: Nisha Nayak | C73: F | D73: Dhenkanal | E73: Business Owner | F73: 38.86 | G73: 714 | H73: 05-09-2020 | I73: 58 | J73: 3 | K73: 58.71
A74: CUST0073 | B74: Anita Patnaik | C74: Male | D74: Puri | E74: retired | F74: 20.92 | G74: 883 | H74: 22-07-2023 | I74: 24 | J74: 1 | K74: 58.47
A75: CUST0074 | B75: Rohit Mallick | C75: M | D75: Cuttack | E75: Salaried | F75: 24.48 | G75: 759 | H75: 25-09-2019 | I75: 26 | J75: 3 | K75: 36.7
A76: CUST0075 | B76: Suman Mishra | C76: M | D76: Jharsuguda | E76: retired | F76: 18.44 | G76: 823 | H76: 21-07-2021 | I76: 62 | J76: 5 | K76: 80.02
A77: CUST0076 | B77: Dilip Dash | C77: male | D77: Bhubaneswar | E77: Salaried | F77: 35.17 | G77: 666 | H77: 13-11-2022 | I77: 28 | J77: 5 | K77: 98.89
A78: CUST0077 | B78: Ganesh Panda | C78: F | D78: Rourkela | E78: Salaried | F78: 40.42 | G78: 741 | H78: 27-09-2020 | I78: 55 | J78: 3 | K78: 89.2
A79: CUST0078 | B79: Vijay Sahu | C79: Female | D79: Rourkela | E79: Freelancer | F79: 32.13 | G79: 848 | H79: 04-03-2023 | I79: 62 | J79: 2 | K79: 98.15
A80: CUST0079 | B80: Arjun Mishra | C80: female | D80: Bhubaneswar | E80: Business Owner | F80: 10.42 | G80: 726 | H80: 10-05-2021 | I80: 62 | J80: 3 | K80: 33.61
... A82: CUST0081 | B82: Sanjay Mishra | C82: Male | D82: Jharsuguda | E82: Freelancer | F82: 42.14 | G82: 667 | H82: 14-12-2021 | I82: 36 | J82: 5 | K82: 90.47
A83: CUST0082 | B83: Suresh Barik | C83: M | D83: Bhubaneswar | E83: retired | F83: 32.49 | H83: 17-05-2018 | I83: 59 | J83: 2 | K83: 61.77
A84: CUST0083 | B84: Mamata Nayak | C84: Male | D84: Berhampur | E84: retired | F84: 12.44 | G84: 737 | H84: 21-01-2021 | I84: 32 | J84: 2 | K84: 44.3
A85: CUST0084 | B85: Mira Dash | C85: M | D85: Cuttack | E85: Salaried | F85: 6.54 | G85: 665 | H85: 16-06-2022 | I85: 57 | J85: 2 | K85: 11.53
A86: CUST0085 | B86: Ravi Pradhan | C86: Male | D86: Berhampur | E86: Salaried | F86: 34.62 | G86: 849 | H86: 02-03-2022 | I86: 28 | J86: 5 | K86: 67.71
A87: CUST0086 | B87: Anita Dash | C87: Male | D87: Jharsuguda | E87: Business Owner | F87: 13.4 | G87: 787 | H87: 22-05-2021 | I87: 63 | J87: 3 | K87: 65.32
A88: CUST0087 | B88: Sunita Nayak | C88: Male | D88: Bhubaneswar | E88: Government Employee | F88: 14.04 | G88: 748 | H88: 22-01-2024 | I88: 48 | J88: 4 | K88: 58.29
A89: CUST0088 | B89: Mamata Nayak | C89: F | D89: Bhubaneswar | E89: Government Employee | F89: 47.14 | G89: 739 | H89: 27-12-2022 | I89: 37 | J89: 2 | K89: 42.3
A90: CUST0089 | B90: Sunita Biswal | C90: male | D90: Bhubaneswar | E90: Salaried | F90: 11.92 | G90: 782 | H90: 18-05-2020 | I90: 63 | J90: 5 | K90: 59.18
A91: CUST0090 | B91: Puja Kumar | C91: Male | D91: Puri | E91: Self-Employed | F91: 12.64 | G91: 833 | H91: 03-06-2020 | I91: 36 | J91: 2 | K91: 21.51
A92: CUST0091 | B92: Prakash Nayak | C92: male | D92: Bhubaneswar | E92: Self-Employed | F92: 28.39 | G92: 606 | H92: 16-04-2018 | I92: 30 | J92: 0 | K92: 99.93
A93: CUST0092 | B93: Meena Rath | C93: male | D93: Puri | E93: Self-Employed | F93: 8.96 | G93: 608 | H93: 05-05-2023 | I93: 50 | J93: 2 | K93: 77.17
A94: CUST0093 | B94: Rohit Mallick | C94: Male | D94: Angul | E94: Self-Employed | F94: 5.04 | G94: 887 | H94: 20-02-2023 | I94: 63 | J94: 0 | K94: 78.43
A95: CUST0094 | B95: Priya Dash | C95: F | D95: Balasore | E95: Government Employee | F95: 23.85 | G95: 714 | H95: 27-09-2018 | I95: 30 | J95: 2 | K95: 87.18
... A113: CUST0112 | B113: Rohit Pradhan | C113: F | D113: Jharsuguda | E113: retired | F113: 24.14 | G113: 883 | H113: 14-10-2024 | I113: 52 | J113: 4 | K113: 24.14
A114: CUST0113 | B114: Rajesh Mohanty | C114: F | D114: Cuttack | E114: retired | F114: 33.37 | H114: 05-12-2022 | I114: 55 | J114: 4 | K114: 98.55
A115: CUST0114 | B115: Puja Sahu | C115: M | D115: Puri | E115: Government Employee | F115: 18.9 | G115: 873 | H115: 27-09-2018 | I115: 43 | J115: 0 | K115: 28.06
A116: CUST0115 | B116: Seema Pradhan | C116: M | D116: Berhampur | E116: Self-Employed | F116: 30.39 | G116: 729 | H116: 25-05-2022 | I116: 30 | J116: 4 | K116: 56.09
A117: CUST0116 | B117: Ganesh Das | C117: M | D117: Dhenkanal | E117: retired | F117: 41.22 | G117: 900 | H117: 18-01-2019 | I117: 63 | J117: 5 | K117: 95.94
A118: CUST0117 | B118: Lata Swain | C118: M | D118: Bhubaneswar | E118: Business Owner | F118: 13.07 | G118: 798 | H118: 18-07-2019 | I118: 31 | J118: 0 | K118: 78.94
A119: CUST0118 | B119: Pooja Panda | C119: male | D119: Dhenkanal | E119: Salaried | F119: 44.19 | G119: 855 | H119: 27-10-2019 | I119: 33 | J119: 5 | K119: 93.69
A120: CUST0119 | B120: Prakash Barik | C120: Female | D120: Cuttack | E120: Salaried | F120: 34.79 | G120: 777 | H120: 13-01-2023 | I120: 36 | J120: 4 | K120: 28.79
A121: CUST0120 | B121: Anita Tripathi | C121: F | D121: Sambalpur | E121: retired | F121: 49.27 | G121: 694 | H121: 22-08-2023 | I121: 55 | J121: 3 | K121: 56.45
A122: CUST0121 | B122: Kavita Behera | C122: male | D122: Rourkela | E122: Salaried | F122: 44.08 | G122: 602 | H122: 15-10-2023 | I122: 29 | J122: 2 | K122: 91.92
A123: CUST0122 | B123: Ravi Sahu | C123: M | D123: Angul | E123: Self-Employed | F123: 7.31 | G123: 780 | H123: 20-04-2018 | I123: 48 | J123: 0 | K123: 33.59
A124: CUST0123 | B124: Sanjay Swain | C124: M | D124: Sambalpur | E124: Salaried | F124: 4.32 | G124: 882 | H124: 22-08-2019 | I124: 30 | J124: 0 | K124: 79.62
A125: CUST0124 | B125: Pooja Dash | C125: female | D125: Rourkela | E125: Government Employee | F125: 45.58 | H125: 05-09-2019 | I125: 57 | J125: 5 | K125: 39.01
A126: CUST0125 | B126: Puja Swain | C126: F | D126: Cuttack | E126: Self-Employed | F126: 5.24 | G126: 868 | H126: 31-03-2019 | I126: 53 | J126: 4 | K126: 90.53
...

Sheet Sheet21
A1: Payment_Status | B1: Defaulted
A3: Region | B3: Count of Transaction_ID
A4: Central | B4: 76
A5: East | B5: 67
A6: North | B6: 75
A7: South | B7: 72
A8: West | B8: 69
A9: Grand Total | B9: 359

Sheet Transitions
A1: Transaction_ID | B1: Customer_ID | C1: Branch_ID | D1: Region | E1: Product | F1: Loan_Type | G1: Loan_Amount_Lakhs | H1: Interest_Rate_Pct | I1: Processing_Fee_Lakhs | J1: EMI_Monthly | K1: Payment_Status | L1: Credit_Score | M1: Approval_Status | O1: Transaction_Date | P1: Transaction_Date | Q1: Disbursal_Date | R1: Tenure_Months | S1: Outstanding_Balance
A2: TXN00001 | B2: CUST0184 | C2: BR008 | D2: North | E2: Business Loan | F2: Unsecured | G2: 73.8 | H2: 9.62 | I2: 1.1658 | J2: 1.8583 | K2: Partially Paid | L2: 557 | M2: approved | N2: =PROPER(M2) -> Approved | O2: 10-05-2022 | P2: 10-05-2022 | Q2: 23-05-2022 | R2: 48 | S2: 41.29
A3: TXN00002 | B3: CUST0428 | C3: BR008 | D3: North | E3: Home Loan | F3: Unsecured | G3: 6.55 | H3: 7.97 | I3: 0.0444 | J3: 0.0547 | K3: Partially Paid | L3: 600 | M3: Rejected | N3: =PROPER(M3) -> Rejected | O3: 02-11-2022 | P3: 02-11-2022 | R3: 240 | S3: 4.78
A4: TXN00003 | B4: CUST0377 | C4: BR003 | D4: West | E4: Business Loan | F4: Secured | G4: 47.65 | H4: 8 | I4: 0.7395 | J4: 1.4932 | K4: Paid | L4: 690 | M4: Rejected | N4: =PROPER(M4) -> Rejected | O4: 13-04-2022 | P4: 13-04-2022 | R4: 36 | S4: 0
A5: TXN00004 | B5: CUST0050 | C5: BR008 | D5: Central | E5: Personal Loan | F5: Semi-Secured | G5: 7.33 | H5: 8.76 | I5: 0.1021 | J5: 0.1816 | K5: Paid | L5: 797 | M5: Rejected | N5: =PROPER(M5) -> Rejected | O5: 22-05-2024 | P5: 22-05-2024 | R5: 48 | S5: 0
A6: TXN00005 | B6: CUST0378 | C6: BR007 | D6: East | E6: Home Loan | F6: Semi-Secured | G6: 58.02 | H6: 16.7 | I6: 0.9803 | J6: 5.2834 | K6: Defaulted | L6: 751 | M6: Rejected | N6: =PROPER(M6) -> Rejected | O6: 19-11-2023 | P6: 19-11-2023 | R6: 12 | S6: 8.92
A7: TXN00006 | B7: CUST0087 | C7: BR006 | D7: Central | E7: Personal Loan | F7: Unsecured | G7: 25.12 | H7: 8.97 | I7: 0.4237 | J7: 0.3178 | K7: Pending | L7: 748 | M7: Approved | N7: =PROPER(M7) -> Approved | O7: 24-09-2024 | P7: 24-09-2024 | Q7: 26-09-2024 | R7: 120 | S7: 2.65
A8: TXN00007 | B8: CUST0334 | C8: BR010 | D8: East | E8: Education Loan | F8: Semi-Secured | G8: 80.93 | H8: 15.12 | I8: 0.6549 | J8: 1.9304 | K8: Defaulted | L8: 866 | M8: approved | N8: =PROPER(M8) -> Approved | O8: 23-04-2024 | P8: 23-04-2024 | Q8: 27-04-2024 | R8: 60 | S8: 72.62
A9: TXN00008 | B9: CUST0093 | C9: BR008 | D9: Central | E9: Home Loan | F9: Semi-Secured | G9: 82.82 | H9: 12.11 | I9: 1.1069 | J9: 2.1854 | K9: Paid | L9: 887 | M9: APPROVED | N9: =PROPER(M9) -> Approved | O9: 15-07-2022 | P9: 15-07-2022 | Q9: 25-07-2022 | R9: 48 | S9: 0
A10: TXN00009 | B10: CUST0277 | C10: BR009 | D10: South | E10: Education Loan | F10: Semi-Secured | G10: 66.27 | H10: 9.63 | I10: 1.1232 | J10: 0.6972 | K10: Partially Paid | L10: 793 | M10: Rejected | N10: =PROPER(M10) -> Rejected | O10: 24-11-2022 | P10: 24-11-2022 | R10: 180 | S10: 44.38
A11: TXN00010 | B11: CUST0146 | C11: BR004 | D11: West | E11: Auto Loan | F11: Unsecured | G11: 62.07 | H11: 12.48 | I11: 0.4076 | J11: 5.5288 | K11: Defaulted | L11: 713 | M11: Rejected | N11: =PROPER(M11) -> Rejected | O11: 20-11-2022 | P11: 20-11-2022 | R11: 12 | S11: 47.65
A12: TXN00011 | B12: CUST0459 | C12: BR004 | D12: West | E12: Gold Loan | F12: Semi-Secured | G12: 33.27 | H12: 14.95 | I12: 0.3289 | J12: 1.6124 | K12: Overdue | L12: 639 | M12: Rejected | N12: =PROPER(M12) -> Rejected | O12: 20-07-2022 | P12: 20-07-2022 | R12: 24 | S12: 10.03
A13: TXN00012 | B13: CUST0457 | C13: BR004 | D13: North | E13: Education Loan | F13: Semi-Secured | G13: 48.96 | H13: 9.09 | I13: 0.9262 | J13: 0.4992 | K13: Pending | L13: 731 | M13: approved | N13: =PROPER(M13) -> Approved | O13: 04-02-2024 | P13: 04-02-2024 | Q13: 07-02-2024 | R13: 180 | S13: 23.95
A14: TXN00013 | B14: CUST0139 | C14: BR004 | D14: East | E14: Personal Loan | F14: Secured | G14: 69.53 | H14: 9 | I14: 1.2359 | J14: 0.7052 | K14: Partially Paid | L14: 738 | M14: Rejected | N14: =PROPER(M14) -> Rejected | O14: 05-12-2023 | P14: 05-12-2023 | R14: 180 | S14: 19.95
A15: TXN00014 | B15: CUST0407 | C15: BR010 | D15: South | E15: Gold Loan | F15: Semi-Secured | G15: 85.65 | H15: 16.93 | I15: 1.0568 | J15: 2.4683 | K15: Defaulted | L15: 863 | M15: approved | N15: =PROPER(M15) -> Approved | O15: 05-08-2024 | P15: 05-08-2024 | Q15: 10-08-2024 | R15: 48 | S15: 9.62
A16: TXN00015 | B16: CUST0127 | C16: BR006 | D16: West | E16: Gold Loan | F16: Secured | G16: 89.29 | H16: 9.14 | I16: 1.2148 | J16: 7.8143 | K16: Partially Paid | L16: 560 | M16: Approved | N16: =PROPER(M16) -> Approved | O16: 24-03-2022 | P16: 24-03-2022 | Q16: 01-04-2022 | R16: 12 | S16: 64.6
A17: TXN00016 | B17: CUST0202 | C17: BR008 | D17: North | E17: Education Loan | F17: Unsecured | G17: 24.81 | H17: 7.64 | I17: 0.3964 | J17: 0.6015 | L17: 582 | M17: Under Review | N17: =PROPER(M17) -> Under Review | O17: 29-08-2023 | P17: 29-08-2023 | R17: 48 | S17: 7.52
A18: TXN00017 | B18: CUST0343 | C18: BR005 | D18: South | E18: Business Loan | F18: Unsecured | G18: 85.93 | H18: 7.77 | I18: 1.0159 | J18: 2.6836 | L18: 649 | M18: Rejected | N18: =PROPER(M18) -> Rejected | O18: 29-01-2024 | P18: 29-01-2024 | R18: 36 | S18: 54.38
A19: TXN00018 | B19: CUST0322 | C19: BR002 | D19: West | E19: Business Loan | F19: Unsecured | G19: 53.56 | H19: 15.78 | I19: 0.8286 | J19: 0.7363 | K19: Defaulted | L19: 849 | M19: Rejected | N19: =PROPER(M19) -> Rejected | O19: 15-06-2022 | P19: 15-06-2022 | R19: 240 | S19: 33.6
A20: TXN00019 | B20: CUST0264 | C20: BR006 | D20: North | E20: Home Loan | F20: Unsecured | G20: 37.19 | H20: 11.52 | I20: 0.2837 | J20: 0.3971 | K20: Paid | L20: 580 | M20: APPROVED | N20: =PROPER(M20) -> Approved | O20: 24-02-2023 | P20: 24-02-2023 | Q20: 27-02-2023 | R20: 240 | S20: 0
A21: TXN00020 | B21: CUST0059 | C21: BR008 | D21: Central | E21: Business Loan | F21: Secured | G21: 75.56 | H21: 11.03 | I21: 1.3955 | J21: 0.7815 | K21: Partially Paid | L21: 702 | M21: Under Review | N21: =PROPER(M21) -> Under Review | O21: 22-04-2022 | P21: 22-04-2022 | R21: 240 | S21: 11.63
A22: TXN00021 | B22: CUST0270 | C22: BR002 | D22: West | E22: Business Loan | F22: Semi-Secured | G22: 68.15 | H22: 10.71 | I22: 0.9755 | J22: 3.1672 | K22: Pending | L22: 845 | M22: approved | N22: =PROPER(M22) -> Approved | O22: 28-06-2022 | P22: 28-06-2022 | Q22: 30-06-2022 | R22: 24 | S22: 29.45
A23: TXN00022 | B23: CUST0040 | C23: BR002 | D23: South | E23: Auto Loan | F23: Secured | G23: 70.01 | H23: 17.12 | I23: 0.8969 | J23: 6.3892 | K23: Overdue | L23: 788 | M23: approved | N23: =PROPER(M23) -> Approved | O23: 28-09-2022 | P23: 28-09-2022 | Q23: 06-10-2022 | R23: 12 | S23: 27.63
A24: TXN00023 | B24: CUST0150 | C24: BR004 | D24: North | E24: Home Loan | F24: Secured | G24: 83.66 | H24: 11.19 | I24: 1.1445 | J24: 1.4408 | K24: Partially Paid | L24: 853 | M24: Rejected | N24: =PROPER(M24) -> Rejected | O24: 21-12-2024 | P24: 21-12-2024 | R24: 84 | S24: 68.23
A25: TXN00024 | B25: CUST0068 | C25: BR005 | D25: South | E25: Auto Loan | F25: Secured | G25: 48.94 | H25: 15.97 | I25: 0.2794 | J25: 0.9712 | K25: Overdue | L25: 617 | M25: approved | N25: =PROPER(M25) -> Approved | O25: 07-12-2022 | P25: 07-12-2022 | Q25: 17-12-2022 | R25: 84 | S25: 43.34
A26: TXN00025 | B26: CUST0499 | C26: BR003 | D26: South | E26: Personal Loan | F26: Secured | G26: 12.57 | H26: 13.82 | I26: 0.146 | J26: 0.2343 | K26: Pending | L26: 881 | M26: Rejected | N26: =PROPER(M26) -> Rejected | O26: 13-03-2022 | P26: 13-03-2022 | R26: 84 | S26: 8.37
A27: TXN00026 | B27: CUST0230 | C27: BR009 | D27: South | E27: Gold Loan | F27: Unsecured | G27: 13.03 | H27: 17.74 | I27: 0.2154 | J27: 0.2074 | K27: Overdue | L27: 706 | M27: Rejected | N27: =PROPER(M27) -> Rejected | O27: 09-01-2022 | P27: 09-01-2022 | R27: 180 | S27: 12.05
A28: TXN00027 | B28: CUST0332 | C28: BR005 | D28: West | E28: Auto Loan | F28: Semi-Secured | G28: 67.02 | H28: 15.51 | I28: 1.2623 | J28: 1.3125 | K28: Paid | L28: 855 | M28: Rejected | N28: =PROPER(M28) -> Rejected | O28: 07-09-2024 | P28: 07-09-2024 | R28: 84 | S28: 0
A29: TXN00028 | B29: CUST0283 | C29: BR002 | D29: East | E29: Home Loan | F29: Unsecured | G29: 62.13 | H29: 11.43 | I29: 0.6148 | J29: 1.6188 | L29: 740 | M29: APPROVED | N29: =PROPER(M29) -> Approved | O29: 31-03-2023 | P29: 31-03-2023 | Q29: 13-04-2023 | R29: 48 | S29: 55.63
A30: TXN00029 | B30: CUST0276 | C30: BR008 | D30: North | E30: Gold Loan | F30: Unsecured | G30: 20.25 | H30: 14.16 | I30: 0.3878 | J30: 0.3813 | K30: Partially Paid | L30: 891 | M30: Rejected | N30: =PROPER(M30) -> Rejected | O30: 25-05-2024 | P30: 25-05-2024 | R30: 84 | S30: 8.39
A31: TXN00030 | B31: CUST0180 | C31: BR005 | D31: West | E31: Gold Loan | F31: Secured | G31: 22.35 | H31: 15.66 | I31: 0.2511 | J31: 0.323 | K31: Overdue | L31: 639 | M31: Rejected | N31: =PROPER(M31) -> Rejected | O31: 18-05-2024 | P31: 18-05-2024 | R31: 180 | S31: 16.08
A32: TXN00031 | B32: CUST0307 | C32: BR002 | D32: South | E32: Personal Loan | F32: Unsecured | G32: 47.99 | H32: 18.35 | I32: 0.2875 | J32: 0.8756 | K32: Paid | L32: 830 | M32: Approved | N32: =PROPER(M32) -> Approved | O32: 18-04-2024 | P32: 18-04-2024 | Q32: 29-04-2024 | R32: 120 | S32: 0
A33: TXN00032 | B33: CUST0285 | C33: BR008 | D33: Central | E33: Personal Loan | F33: Secured | G33: 19.41 | H33: 13.59 | I33: 0.1093 | J33: 0.4475 | L33: 578 | M33: Under Review | N33: =PROPER(M33) -> Under Review | O33: 08-10-2024 | P33: 08-10-2024 | R33: 60 | S33: 11.17
A34: TXN00033 | B34: CUST0002 | C34: BR003 | D34: East | E34: Auto Loan | F34: Semi-Secured | G34: 83.59 | H34: 14.69 | I34: 1.5372 | J34: 1.3328 | K34: Pending | L34: 657 | M34: approved | N34: =PROPER(M34) -> Approved | O34: 17-05-2023 | P34: 17-05-2023 | Q34: 18-05-2023 | R34: 120 | S34: 16.84
A35: TXN00034 | B35: CUST0035 | C35: BR010 | D35: East | E35: Gold Loan | F35: Unsecured | G35: 56.99 | H35: 14.41 | I35: 0.6919 | J35: 2.7473 | K35: Overdue | L35: 573 | M35: APPROVED | N35: =PROPER(M35) -> Approved | O35: 05-02-2022 | P35: 05-02-2022 | Q35: 19-02-2022 | R35: 24 | S35: 18.27
A36: TXN00035 | B36: CUST0237 | C36: BR003 | D36: East | E36: Personal Loan | F36: Secured | G36: 27.99 | H36: 17.53 | I36: 0.2894 | J36: 0.7036 | K36: Overdue | L36: 841 | M36: APPROVED | N36: =PROPER(M36) -> Approved | O36: 07-06-2022 | P36: 07-06-2022 | Q36: 16-06-2022 | R36: 60 | S36: 7.41
A37: TXN00036 | B37: CUST0307 | C37: BR003 | D37: Central | E37: Auto Loan | F37: Unsecured | G37: 82.86 | H37: 10.81 | I37: 1.2662 | J37: 1.4105 | K37: Paid | L37: 830 | M37: APPROVED | N37: =PROPER(M37) -> Approved | O37: 22-12-2023 | P37: 22-12-2023 | Q37: 05-01-2024 | R37: 84 | S37: 0
A38: TXN00037 | B38: CUST0145 | C38: BR006 | D38: West | E38: Education Loan | F38: Unsecured | G38: 92.17 | H38: 9.9 | I38: 1.1568 | J38: 2.3332 | K38: Defaulted | L38: 704 | M38: APPROVED | N38: =PROPER(M38) -> Approved | O38: 12-12-2024 | P38: 12-12-2024 | Q38: 26-12-2024 | R38: 48 | S38: 50.9
A39: TXN00038 | B39: CUST0059 | C39: BR007 | D39: West | E39: Home Loan | F39: Secured | G39: 82.07 | H39: 12.77 | I39: 0.7939 | J39: 1.4828 | K39: Pending | L39: 702 | M39: approved | N39: =PROPER(M39) -> Approved | O39: 07-12-2024 | P39: 07-12-2024 | Q39: 20-12-2024 | R39: 84 | S39: 75.88
A40: TXN00039 | B40: CUST0382 | C40: BR002 | D40: South | E40: Personal Loan | F40: Semi-Secured | G40: 15.09 | H40: 8.88 | I40: 0.1049 | J40: 0.6886 | K40: Partially Paid | L40: 837 | M40: Rejected | N40: =PROPER(M40) -> Rejected | O40: 17-08-2022 | P40: 17-08-2022 | R40: 24 | S40: 2.51
A41: TXN00040 | B41: CUST0022 | C41: BR004 | D41: North | E41: Home Loan | F41: Semi-Secured | G41: 51.83 | H41: 8.81 | I41: 0.4559 | J41: 2.3633 | K41: Overdue | L41: 618 | M41: Rejected | N41: =PROPER(M41) -> Rejected | O41: 22-01-2022 | P41: 22-01-2022 | R41: 24 | S41: 38.43
A42: TXN00041 | B42: CUST0106 | C42: BR010 | D42: South | E42: Personal Loan | F42: Semi-Secured | G42: 35.8 | H42: 16.8 | I42: 0.6848 | J42: 0.7275 | K42: Overdue | L42: 877 | M42: Rejected | N42: =PROPER(M42) -> Rejected | O42: 22-10-2024 | P42: 22-10-2024 | R42: 84 | S42: 27.34
A43: TXN00042 | B43: CUST0035 | C43: BR002 | D43: Central | E43: Home Loan | F43: Semi-Secured | G43: 22.48 | H43: 10.6 | I43: 0.4164 | J43: 0.2259 | K43: Paid | L43: 573 | M43: Rejected | N43: =PROPER(M43) -> Rejected | O43: 22-07-2022 | P43: 22-07-2022 | R43: 240 | S43: 0
A44: TXN00043 | B44: CUST0436 | C44: BR008 | D44: East | E44: Business Loan | F44: Semi-Secured | G44: 19.33 | H44: 8.68 | I44: 0.3387 | J44: 0.2415 | K44: Partially Paid | L44: 859 | M44: Rejected | N44: =PROPER(M44) -> Rejected | O44: 19-11-2024 | P44: 19-11-2024 | R44: 120 | S44: 5.67
A45: TXN00044 | B45: CUST0064 | C45: BR008 | D45: North | E45: Gold Loan | F45: Secured | G45: 50.09 | H45: 10.67 | I45: 0.793 | J45: 2.3269 | K45: Overdue | L45: 895 | M45: approved | N45: =PROPER(M45) -> Approved | O45: 25-08-2022 | P45: 25-08-2022 | Q45: 01-09-2022 | R45: 24 | S45: 17.08
A46: TXN00045 | B46: CUST0500 | C46: BR008 | D46: South | E46: Gold Loan | F46: Unsecured | G46: 29.77 | H46: 9.58 | I46: 0.1799 | J46: 0.3123 | K46: Overdue | L46: 703 | M46: Rejected | N46: =PROPER(M46) -> Rejected | O46: 27-01-2022 | P46: 27-01-2022 | R46: 180 | S46: 28.25
A47: TXN00046 | B47: CUST0225 | C47: BR009 | D47: North | E47: Home Loan | F47: Secured | G47: 40.09 | H47: 18.25 | I47: 0.6463 | J47: 1.4544 | K47: Paid | L47: 677 | M47: Under Review | N47: =PROPER(M47) -> Under Review | O47: 12-02-2023 | P47: 12-02-2023 | R47: 36 | S47: 0
A48: TXN00047 | B48: CUST0207 | C48: BR002 | D48: South | E48: Education Loan | F48: Semi-Secured | G48: 50.41 | H48: 15.93 | I48: 0.7009 | J48: 0.8422 | K48: Overdue | L48: 887 | M48: approved | N48: =PROPER(M48) -> Approved | O48: 08-04-2024 | P48: 08-04-2024 | Q48: 16-04-2024 | R48: 120 | S48: 26.95
A49: TXN00048 | B49: CUST0063 | C49: BR005 | D49: West | E49: Education Loan | F49: Secured | G49: 63.21 | H49: 8.6 | I49: 0.3662 | J49: 2.8761 | K49: Partially Paid | L49: 806 | M49: Rejected | N49: =PROPER(M49) -> Rejected | O49: 24-02-2022 | P49: 24-02-2022 | R49: 24 | S49: 58.55
A50: TXN00049 | B50: CUST0079 | C50: BR005 | D50: Central | E50: Gold Loan | F50: Secured | G50: 76.26 | H50: 13.22 | I50: 0.9443 | J50: 0.9759 | K50: Pending | L50: 726 | M50: Under Review | N50: =PROPER(M50) -> Under Review | O50: 16-10-2024 | P50: 16-10-2024 | R50: 180 | S50: 39.4
A51: TXN00050 | B51: CUST0441 | C51: BR009 | D51: Central | E51: Home Loan | F51: Secured | G51: 99.08 | H51: 8.81 | I51: 1.1644 | J51: 1.2449 | K51: Partially Paid | L51: 814 | M51: approved | N51: =PROPER(M51) -> Approved | O51: 15-03-2022 | P51: 15-03-2022 | Q51: 16-03-2022 | R51: 120 | S51: 24.8
A52: TXN00051 | B52: CUST0453 | C52: BR003 | D52: West | E52: Education Loan | F52: Secured | G52: 31.93 | H52: 15.9 | I52: 0.4321 | J52: 0.4667 | K52: Defaulted | L52: 900 | M52: APPROVED | N52: =PROPER(M52) -> Approved | O52: 20-08-2024 | P52: 20-08-2024 | Q52: 28-08-2024 | R52: 180 | S52: 18.45
A53: TXN00052 | B53: CUST0135 | C53: BR008 | D53: Central | E53: Education Loan | F53: Semi-Secured | G53: 67.97 | H53: 10.63 | I53: 0.4025 | J53: 5.9956 | K53: Pending | L53: 897 | M53: Under Review | N53: =PROPER(M53) -> Under Review | O53: 16-12-2023 | P53: 16-12-2023 | R53: 12 | S53: 53.57
A54: TXN00053 | B54: CUST0321 | C54: BR006 | D54: West | E54: Home Loan | F54: Unsecured | G54: 35.17 | H54: 11.36 | I54: 0.5247 | J54: 0.9151 | K54: Pending | L54: 894 | M54: Rejected | N54: =PROPER(M54) -> Rejected | O54: 02-10-2023 | P54: 02-10-2023 | R54: 48 | S54: 21.23
A55: TXN00054 | B55: CUST0157 | C55: BR002 | D55: East | E55: Personal Loan | F55: Secured | G55: 54.3 | H55: 14.74 | I55: 0.6156 | J55: 0.7046 | K55: Partially Paid | L55: 837 | M55: Under Review | N55: =PROPER(M55) -> Under Review | O55: 11-02-2022 | P55: 11-02-2022 | R55: 240 | S55: 37.55
A56: TXN00055 | B56: CUST0194 | C56: BR010 | D56: West | E56: Auto Loan | F56: Semi-Secured | G56: 10.67 | H56: 15.1 | I56: 0.0863 | J56: 0.1501 | K56: Defaulted | L56: 719 | M56: Rejected | N56: =PROPER(M56) -> Rejected | O56: 27-11-2023 | P56: 27-11-2023 | R56: 180 | S56: 2.58
A57: TXN00056 | B57: CUST0104 | C57: BR008 | D57: North | E57: Gold Loan | F57: Secured | G57: 29.45 | H57: 18.46 | I57: 0.3248 | J57: 0.8722 | K57: Defaulted | L57: 654 | M57: Rejected | N57: =PROPER(M57) -> Rejected | O57: 08-07-2022 | P57: 08-07-2022 | R57: 48 | S57: 20.91
A58: TXN00057 | B58: CUST0140 | C58: BR002 | D58: Central | E58: Gold Loan | F58: Unsecured | G58: 43.28 | H58: 8.34 | I58: 0.7512 | J58: 0.3712 | K58: Overdue | L58: 844 | M58: approved | N58: =PROPER(M58) -> Approved | O58: 04-10-2023 | P58: 04-10-2023 | Q58: 08-10-2023 | R58: 240 | S58: 19.57
A59: TXN00058 | B59: CUST0344 | C59: BR009 | D59: South | E59: Home Loan | F59: Semi-Secured | G59: 70.63 | H59: 13.85 | I59: 0.5788 | J59: 0.9335 | K59: Overdue | L59: 719 | M59: Rejected | N59: =PROPER(M59) -> Rejected | O59: 27-12-2024 | P59: 27-12-2024 | R59: 180 | S59: 55.63
A60: TXN00059 | B60: CUST0479 | C60: BR010 | D60: North | E60: Gold Loan | F60: Secured | G60: 37.06 | H60: 9.16 | I60: 0.5663 | J60: 0.7722 | K60: Partially Paid | L60: 767 | M60: approved | N60: =PROPER(M60) -> Approved | O60: 15-10-2023 | P60: 15-10-2023 | Q60: 29-10-2023 | R60: 60 | S60: 29.86
A61: TXN00060 | B61: CUST0212 | C61: BR005 | D61: East | E61: Business Loan | F61: Secured | G61: 26.39 | H61: 11.96 | I61: 0.1769 | J61: 0.6944 | K61: Paid | L61: 713 | M61: Rejected | N61: =PROPER(M61) -> Rejected | O61: 28-09-2023 | P61: 28-09-2023 | R61: 48 | S61: 0
A62: TXN00061 | B62: CUST0224 | C62: BR007 | D62: North | E62: Personal Loan | F62: Secured | G62: 28 | H62: 16.19 | I62: 0.2567 | J62: 0.3935 | L62: 699 | M62: Rejected | N62: =PROPER(M62) -> Rejected | O62: 28-03-2022 | P62: 28-03-2022 | R62: 240 | S62: 25.74
A63: TXN00062 | B63: CUST0441 | C63: BR002 | D63: East | E63: Gold Loan | F63: Unsecured | G63: 86.85 | H63: 11.98 | I63: 0.9077 | J63: 4.0875 | K63: Partially Paid | L63: 814 | M63: Rejected | N63: =PROPER(M63) -> Rejected | O63: 15-10-2022 | P63: 15-10-2022 | R63: 24 | S63: 26.11
A64: TXN00063 | B64: CUST0062 | C64: BR009 | D64: Central | E64: Gold Loan | F64: Unsecured | G64: 50.15 | H64: 14.1 | I64: 0.8324 | J64: 0.9426 | K64: Overdue | L64: 586 | M64: APPROVED | N64: =PROPER(M64) -> Approved | O64: 09-03-2024 | P64: 09-03-2024 | Q64: 22-03-2024 | R64: 84 | S64: 36.92
A65: TXN00064 | B65: CUST0074 | C65: BR002 | D65: South | E65: Personal Loan | F65: Unsecured | G65: 44.51 | H65: 13.98 | I65: 0.5499 | J65: 0.8336 | K65: Paid | L65: 759 | M65: Under Review | N65: =PROPER(M65) -> Under Review | O65: 17-05-2024 | P65: 17-05-2024 | R65: 84 | S65: 0
A66: TXN00065 | B66: CUST0143 | C66: BR003 | D66: East | E66: Education Loan | F66: Semi-Secured | G66: 37.41 | H66: 14.6 | I66: 0.695 | J66: 3.3695 | K66: Paid | L66: 878 | M66: Rejected | N66: =PROPER(M66) -> Rejected | O66: 06-05-2023 | P66: 06-05-2023 | R66: 12 | S66: 0
A67: TXN00066 | B67: CUST0328 | C67: BR006 | D67: North | E67: Gold Loan | F67: Secured | G67: 85.91 | H67: 17.51 | I67: 0.936 | J67: 2.1587 | K67: Overdue | L67: 837 | M67: Approved | N67: =PROPER(M67) -> Approved | O67: 28-04-2023 | P67: 28-04-2023 | Q67: 03-05-2023 | R67: 60 | S67: 23.95
A68: TXN00067 | B68: CUST0324 | C68: BR006 | D68: West | E68: Home Loan | F68: Unsecured | G68: 86.78 | H68: 17.85 | I68: 1.0471 | J68: 1.5553 | K68: Overdue | L68: 703 | M68: Rejected | N68: =PROPER(M68) -> Rejected | O68: 15-05-2024 | P68: 15-05-2024 | R68: 120 | S68: 73.35
A69: TXN00068 | B69: CUST0358 | C69: BR005 | D69: Central | E69: Home Loan | F69: Unsecured | G69: 42.67 | H69: 13.53 | I69: 0.4225 | J69: 3.8218 | K69: Paid | L69: 855 | M69: Rejected | N69: =PROPER(M69) -> Rejected | O69: 12-01-2023 | P69: 12-01-2023 | R69: 12 | S69: 0
A70: TXN00069 | B70: CUST0070 | C70: BR001 | D70: West | E70: Personal Loan | F70: Semi-Secured | G70: 31.25 | H70: 8.72 | I70: 0.2733 | J70: 0.9897 | K70: Defaulted | L70: 832 | M70: Rejected | N70: =PROPER(M70) -> Rejected | O70: 20-04-2024 | P70: 20-04-2024 | R70: 36 | S70: 24.18
A71: TXN00070 | B71: CUST0377 | C71: BR003 | D71: East | E71: Personal Loan | F71: Semi-Secured | G71: 59.71 | H71: 10.6 | I71: 0.3741 | J71: 1.0099 | K71: Pending | L71: 690 | M71: approved | N71: =PROPER(M71) -> Approved | O71: 12-02-2024 | P71: 12-02-2024 | Q71: 26-02-2024 | R71: 84 | S71: 50.85
A72: TXN00071 | B72: CUST0473 | C72: BR009 | D72: Central | E72: Business Loan | F72: Secured | G72: 90.78 | H72: 9.68 | I72: 1.4088 | J72: 2.9156 | K72: Paid | L72: 755 | M72: APPROVED | N72: =PROPER(M72) -> Approved | O72: 28-05-2024 | P72: 28-05-2024 | Q72: 07-06-2024 | R72: 36 | S72: 0
A73: TXN00072 | B73: CUST0189 | C73: BR003 | D73: Central | E73: Home Loan | F73: Secured | G73: 72.14 | H73: 17.62 | I73: 0.8517 | J73: 1.1421 | K73: Paid | L73: 580 | M73: Rejected | N73: =PROPER(M73) -> Rejected | O73: 21-02-2023 | P73: 21-02-2023 | R73: 180 | S73: 0
A74: TXN00073 | B74: CUST0401 | C74: BR005 | D74: East | E74: Business Loan | F74: Unsecured | G74: 38.83 | H74: 9.77 | I74: 0.3197 | J74: 0.8206 | K74: Pending | L74: 764 | M74: Rejected | N74: =PROPER(M74) -> Rejected | O74: 16-04-2024 | P74: 16-04-2024 | R74: 60 | S74: 30.04
A75: TXN00074 | B75: CUST0121 | C75: BR010 | D75: West | E75: Personal Loan | F75: Unsecured | G75: 58.71 | H75: 8.44 | I75: 0.7065 | J75: 0.928 | K75: Partially Paid | L75: 602 | M75: Rejected | N75: =PROPER(M75) -> Rejected | O75: 11-03-2023 | P75: 11-03-2023 | R75: 84 | S75: 41.47
A76: TXN00075 | B76: CUST0132 | C76: BR002 | D76: North | E76: Gold Loan | F76: Secured | G76: 6.16 | H76: 12.68 | I76: 0.0635 | J76: 0.5493 | K76: Paid | L76: 642 | M76: Under Review | N76: =PROPER(M76) -> Under Review | O76: 30-10-2024 | P76: 30-10-2024 | R76: 12 | S76: 0
A77: TXN00076 | B77: CUST0203 | C77: BR006 | D77: South | E77: Gold Loan | F77: Secured | G77: 58.47 | H77: 13.04 | I77: 1.1083 | J77: 0.7413 | K77: Pending | L77: 604 | M77: Approved | N77: =PROPER(M77) -> Approved | O77: 12-10-2023 | P77: 12-10-2023 | Q77: 24-10-2023 | R77: 180 | S77: 32.21
A78: TXN00077 | B78: CUST0023 | C78: BR003 | D78: West | E78: Auto Loan | F78: Semi-Secured | G78: 36.7 | H78: 17.43 | I78: 0.3284 | J78: 0.9206 | K78: Defaulted | L78: 678 | M78: Under Review | N78: =PROPER(M78) -> Under Review | O78: 11-06-2024 | P78: 11-06-2024 | R78: 60 | S78: 31.52
A79: TXN00078 | B79: CUST0392 | C79: BR003 | D79: Central | E79: Business Loan | F79: Semi-Secured | G79: 80.02 | H79: 9.13 | I79: 0.676 | J79: 7.0027 | K79: Partially Paid | L79: 794 | M79: Under Review | N79: =PROPER(M79) -> Under Review | O79: 01-12-2022 | P79: 01-12-2022 | R79: 12 | S79: 56.02
A80: TXN00079 | B80: CUST0475 | C80: BR008 | D80: North | E80: Education Loan | F80: Unsecured | G80: 98.89 | H80: 12.54 | I80: 0.6613 | J80: 3.3101 | K80: Paid | L80: 577 | M80: Under Review | N80: =PROPER(M80) -> Under Review | O80: 11-07-2022 | P80: 11-07-2022 | R80: 36 | S80: 0
A81: TXN00080 | B81: CUST0428 | C81: BR003 | D81: Central | E81: Auto Loan | F81: Semi-Secured | G81: 89.2 | H81: 13.92 | I81: 1.746 | J81: 1.104 | K81: Defaulted | L81: 600 | M81: Rejected | N81: =PROPER(M81) -> Rejected | O81: 02-05-2024 | P81: 02-05-2024 | R81: 240 | S81: 78.71
A82: TXN00081 | B82: CUST0049 | C82: BR006 | D82: North | E82: Auto Loan | F82: Semi-Secured | G82: 98.15 | H82: 11.61 | I82: 1.8587 | J82: 4.6024 | K82: Overdue | L82: 800 | M82: Rejected | N82: =PROPER(M82) -> Rejected | O82: 01-03-2022 | P82: 01-03-2022 | R82: 24 | S82: 16.58
A83: TXN00082 | B83: CUST0233 | C83: BR005 | D83: Central | E83: Business Loan | F83: Secured | G83: 33.61 | H83: 14.35 | I83: 0.3965 | J83: 1.1544 | K83: Pending | L83: 659 | M83: Approved | N83: =PROPER(M83) -> Approved | O83: 03-08-2023 | P83: 03-08-2023 | Q83: 09-08-2023 | R83: 36 | S83: 26.16
A84: TXN00083 | B84: CUST0309 | C84: BR007 | D84: North | E84: Education Loan | F84: Unsecured | G84: 18.62 | H84: 17.02 | I84: 0.118 | J84: 0.5375 | K84: Pending | L84: 698 | M84: approved | N84: =PROPER(M84) -> Approved | O84: 04-04-2024 | P84: 04-04-2024 | Q84: 09-04-2024 | R84: 48 | S84: 12.1
A85: TXN00084 | B85: CUST0153 | C85: BR008 | D85: West | E85: Business Loan | F85: Unsecured | G85: 90.47 | H85: 11.45 | I85: 0.5828 | J85: 1.5706 | K85: Defaulted | L85: 865 | M85: Rejected | N85: =PROPER(M85) -> Rejected | O85: 29-09-2024 | P85: 29-09-2024 | R85: 84 | S85: 43.3
A86: TXN00085 | B86: CUST0308 | C86: BR007 | D86: North | E86: Education Loan | F86: Unsecured | G86: 61.77 | H86: 12.19 | I86: 0.3463 | J86: 1.0967 | K86: Partially Paid | L86: 596 | M86: Rejected | N86: =PROPER(M86) -> Rejected | O86: 05-04-2023 | P86: 05-04-2023 | R86: 84 | S86: 40.18
A87: TXN00086 | B87: CUST0270 | C87: BR009 | D87: North | E87: Auto Loan | F87: Unsecured | G87: 44.3 | H87: 12.75 | I87: 0.3202 | J87: 1.4873 | K87: Overdue | L87: 845 | M87: Rejected | N87: =PROPER(M87) -> Rejected | O87: 07-12-2024 | P87: 07-12-2024 | R87: 36 | S87: 20.54
A88: TXN00087 | B88: CUST0470 | C88: BR001 | D88: Central | E88: Home Loan | F88: Semi-Secured | H88: 14.77 | I88: 0.5826 | J88: 1.0194 | K88: Overdue | L88: 724 | M88: Under Review | N88: =PROPER(M88) -> Under Review | O88: 17-06-2022 | P88: 17-06-2022 | R88: 60 | S88: 32.45
A89: TXN00088 | B89: CUST0237 | C89: BR003 | D89: South | E89: Education Loan | F89: Secured | G89: 9.25 | H89: 10.77 | I89: 0.1277 | J89: 0.1038 | K89: Partially Paid | L89: 841 | M89: APPROVED | N89: =PROPER(M89) -> Approved | O89: 27-06-2023 | P89: 27-06-2023 | Q89: 03-07-2023 | R89: 180 | S89: 8.53
A90: TXN00089 | B90: CUST0095 | C90: BR002 | D90: Central | E90: Auto Loan | F90: Semi-Secured | G90: 11.53 | H90: 7.56 | I90: 0.0778 | J90: 0.359 | K90: Partially Paid | L90: 859 | M90: approved | N90: =PROPER(M90) -> Approved | O90: 09-04-2024 | P90: 09-04-2024 | Q90: 23-04-2024 | R90: 36 | S90: 7.6
A91: TXN00090 | B91: CUST0156 | C91: BR010 | D91: Central | E91: Auto Loan | F91: Semi-Secured | G91: 67.71 | H91: 11.84 | I91: 0.6459 | J91: 2.2438 | K91: Pending | L91: 775 | M91: Approved | N91: =PROPER(M91) -> Approved | O91: 26-01-2023 | P91: 26-01-2023 | Q91: 28-01-2023 | R91: 36 | S91: 53.73
A92: TXN00091 | B92: CUST0014 | C92: BR004 | D92: West | E92: Business Loan | F92: Secured | G92: 65.32 | H92: 14.39 | I92: 1.1007 | J92: 1.7978 | K92: Paid | L92: 880 | M92: Under Review | N92: =PROPER(M92) -> Under Review | O92: 07-08-2024 | P92: 07-08-2024 | R92: 48 | S92: 0
A93: TXN00092 | B93: CUST0060 | C93: BR003 | D93: South | E93: Business Loan | F93: Semi-Secured | H93: 7.72 | I93: 0.5294 | J93: 1.0946 | K93: Pending | L93: 672 | M93: Under Review | N93: =PROPER(M93) -> Under Review | O93: 13-03-2024 | P93: 13-03-2024 | R93: 48 | S93: 6.46
A94: TXN00093 | B94: CUST0366 | C94: BR007 | D94: West | E94: Education Loan | F94: Semi-Secured | G94: 58.29 | H94: 18.49 | I94: 0.3238 | J94: 1.0688 | K94: Partially Paid | L94: 875 | M94: APPROVED | N94: =PROPER(M94) -> Approved | O94: 26-09-2024 | P94: 26-09-2024 | Q94: 30-09-2024 | R94: 120 | S94: 41.22
A95: TXN00094 | B95: CUST0162 | C95: BR009 | D95: North | E95: Auto Loan | F95: Semi-Secured | G95: 42.3 | H95: 12.94 | I95: 0.8073 | J95: 0.7681 | K95: Partially Paid | L95: 601 | M95: Rejected | N95: =PROPER(M95) -> Rejected | O95: 12-06-2024 | P95: 12-06-2024 | R95: 84 | S95: 4.98
A96: TXN00095 | B96: CUST0177 | C96: BR008 | D96: South | E96: Gold Loan | F96: Secured | G96: 59.18 | H96: 17.64 | I96: 1.0535 | J96: 0.9378 | K96: Pending | L96: 864 | M96: Under Review | N96: =PROPER(M96) -> Under Review | O96: 10-03-2024 | P96: 10-03-2024 | R96: 180 | S96: 54.2
A97: TXN00096 | B97: CUST0377 | C97: BR006 | D97: West | E97: Personal Loan | F97: Semi-Secured | G97: 21.51 | H97: 8.45 | I97: 0.2634 | J97: 0.6785 | K97: Pending | L97: 690 | M97: Rejected | N97: =PROPER(M97) -> Rejected | O97: 04-10-2024 | P97: 04-10-2024 | R97: 36 | S97: 4
A98: TXN00097 | B98: CUST0156 | C98: BR004 | D98: South | E98: Gold Loan | F98: Secured | G98: 99.93 | H98: 10.37 | I98: 1.5143 | J98: 3.2418 | K98: Defaulted | L98: 775 | M98: Approved | N98: =PROPER(M98) -> Approved | O98: 11-05-2022 | P98: 11-05-2022 | Q98: 17-05-2022 | R98: 36 | S98: 46.57
A99: TXN00098 | B99: CUST0115 | C99: BR008 | D99: East | E99: Auto Loan | F99: Unsecured | G99: 77.17 | H99: 13.63 | I99: 1.4234 | J99: 0.939 | K99: Defaulted | L99: 729 | M99: Rejected | N99: =PROPER(M99) -> Rejected | O99: 02-08-2022 | P99: 02-08-2022 | R99: 240 | S99: 54.05
A100: TXN00099 | B100: CUST0235 | C100: BR002 | D100: North | E100: Gold Loan | F100: Semi-Secured | G100: 78.43 | H100: 16.56 | I100: 0.4415 | J100: 3.8612 | K100: Pending | L100: 563 | M100: Rejected | N100: =PROPER(M100) -> Rejected | O100: 30-08-2022 | P100: 30-08-2022 | R100: 24 | S100: 65.9
...

Sheet Sheet28
A1: NPA_pct | B1: Region | C1: Payment_Status | D1: Transaction_ID
A2: 4.76 | B2: North | C2: Partially Paid | D2: TXN00001
A3: 2.73 | B3: North | C3: Partially Paid | D3: TXN00002
A4: 2.89 | B4: West | C4: Paid | D4: TXN00003
A5: 10.77 | B5: Central | C5: Paid | D5: TXN00004
A6: 10.85 | B6: East | C6: Defaulted | D6: TXN00005
A7: 8.83 | B7: Central | C7: Pending | D7: TXN00006
A8: 10.61 | B8: East | C8: Defaulted | D8: TXN00007
A9: 10.02 | B9: Central | C9: Paid | D9: TXN00008
A10: 6.85 | B10: South | C10: Partially Paid | D10: TXN00009
A11: 2.49 | B11: West | C11: Defaulted | D11: TXN00010
A12: 2.58 | B12: West | C12: Overdue | D12: TXN00011
A13: 11.55 | B13: North | C13: Pending | D13: TXN00012
... A16: 8.32 | B16: West | C16: Partially Paid | D16: TXN00015
A17: 9.32 | B17: North | D17: TXN00016
A18: 8.43 | B18: South | D18: TXN00017
A19: 4.74 | B19: West | C19: Defaulted | D19: TXN00018
A20: 4.8 | B20: North | C20: Paid | D20: TXN00019
A21: 7.15 | B21: Central | C21: Partially Paid | D21: TXN00020
A22: 4.7 | B22: West | C22: Pending | D22: TXN00021
A23: 2.96 | B23: South | C23: Overdue | D23: TXN00022
A24: 6.89 | B24: North | C24: Partially Paid | D24: TXN00023
A25: 6.38 | B25: South | C25: Overdue | D25: TXN00024
A26: 4.88 | B26: South | C26: Pending | D26: TXN00025
A27: 9.99 | B27: South | C27: Overdue | D27: TXN00026
A28: 11.62 | B28: West | C28: Paid | D28: TXN00027
A29: 7.69 | B29: East | D29: TXN00028
A30: 10.92 | B30: North | C30: Partially Paid | D30: TXN00029
A31: 8.03 | B31: West | C31: Overdue | D31: TXN00030
A32: 11.86 | B32: South | C32: Paid | D32: TXN00031
A33: 2.88 | B33: Central | D33: TXN00032
A34: 2.34 | B34: East | C34: Pending | D34: TXN00033
A35: 9.17 | B35: East | C35: Overdue | D35: TXN00034
A36: 10.24 | B36: East | C36: Overdue | D36: TXN00035
A37: 11.81 | B37: Central | C37: Paid | D37: TXN00036
B38: West | C38: Defaulted | D38: TXN00037
B39: West | C39: Pending | D39: TXN00038
B40: South | C40: Partially Paid | D40: TXN00039
B41: North | C41: Overdue | D41: TXN00040
B42: South | C42: Overdue | D42: TXN00041
B43: Central | C43: Paid | D43: TXN00042
B44: East | C44: Partially Paid | D44: TXN00043
B45: North | C45: Overdue | D45: TXN00044
B46: South | C46: Overdue | D46: TXN00045
B47: North | C47: Paid | D47: TXN00046
B48: South | C48: Overdue | D48: TXN00047
B49: West | C49: Partially Paid | D49: TXN00048
... B61: East | C61: Paid | D61: TXN00060
B62: North | D62: TXN00061
B63: East | C63: Partially Paid | D63: TXN00062
B64: Central | C64: Overdue | D64: TXN00063
B65: South | C65: Paid | D65: TXN00064
B66: East | C66: Paid | D66: TXN00065
B67: North | C67: Overdue | D67: TXN00066
B68: West | C68: Overdue | D68: TXN00067
B69: Central | C69: Paid | D69: TXN00068
B70: West | C70: Defaulted | D70: TXN00069
B71: East | C71: Pending | D71: TXN00070
B72: Central | C72: Paid | D72: TXN00071
B73: Central | C73: Paid | D73: TXN00072
B74: East | C74: Pending | D74: TXN00073
... B84: North | C84: Pending | D84: TXN00083
B85: West | C85: Defaulted
B86: North | C86: Partially Paid
B87: North | C87: Overdue
B88: Central | C88: Overdue
B89: South | C89: Partially Paid
B90: Central | C90: Partially Paid
B91: Central | C91: Pending
B92: West | C92: Paid
B93: South | C93: Pending
B94: West | C94: Partially Paid
B95: North | C95: Partially Paid
B96: South | C96: Pending
... B159: South | C159: Overdue
B160: West
B161: West | C161: Overdue
B162: South | C162: Paid
B163: South | C163: Paid
B164: West
B165: South | C165: Pending
B166: South | C166: Paid
B167: Central | C167: Defaulted
B168: South | C168: Paid
B169: South | C169: Overdue
B170: East | C170: Overdue
B171: East
B172: North | C172: Pending
B173: South | C173: Overdue
B174: West | C174: Defaulted
B175: West | C175: Paid
B176: West | C176: Paid
B177: Central | C177: Pending
B178: South | C178: Paid
B179: North | C179: Defaulted
B180: North | C180: Overdue
B181: West | C181: Partially Paid
B182: North | C182: Defaulted
B183: Central | C183: Defaulted
... B252: South | C252: Overdue
...

Sheet Sheet14
A3: Region | B3: NPA%
A4: Central | B4: 0.1874063
A5: Central Total
A6: East | B6: 0.18790605
A7: East Total
A8: North | B8: 0.1954023
B9: 0.20789605
A10: North Total
A11: West | B11: 0.22088956
A12: West Total

Sheet Sheet18
A3: Region | B3: Sum of NPA% | C3: Count of Transaction_ID
A4: Central | B4: 0.1874063 | C4: 376
A5: East | B5: 0.18790605 | C5: 375
A6: North | B6: 0.40329835 | C6: 391
A7: South | C7: 416
A8: West | B8: 0.22088956 | C8: 442

Sheet Sheet10
A1: Transaction_ID | B1: Region | C1: Payment_Status | D1: NPA%
A2: TXN00001 | B2: North | C2: Partially Paid | D2: =COUNTIFS(C:C,"Defaulted")/COUNTA(A:A) -> 0.17941029
A3: TXN00002 | B3: North | C3: Partially Paid
A4: TXN00003 | B4: West | C4: Paid
A5: TXN00004 | B5: Central | C5: Paid
A6: TXN00005 | B6: East | C6: Defaulted
A7: TXN00006 | B7: Central | C7: Pending
A8: TXN00007 | B8: East | C8: Defaulted
A9: TXN00008 | B9: Central | C9: Paid
A10: TXN00009 | B10: South | C10: Partially Paid
A11: TXN00010 | B11: West | C11: Defaulted
A12: TXN00011 | B12: West | C12: Overdue
A13: TXN00012 | B13: North | C13: Pending
A14: TXN00013 | B14: East | C14: Partially Paid
... A16: TXN00015 | B16: West | C16: Partially Paid
A17: TXN00016 | B17: North
A18: TXN00017 | B18: South
A19: TXN00018 | B19: West | C19: Defaulted
A20: TXN00019 | B20: North | C20: Paid
A21: TXN00020 | B21: Central | C21: Partially Paid
A22: TXN00021 | B22: West | C22: Pending
A23: TXN00022 | B23: South | C23: Overdue
A24: TXN00023 | B24: North | C24: Partially Paid
A25: TXN00024 | B25: South | C25: Overdue
A26: TXN00025 | B26: South | C26: Pending
A27: TXN00026 | B27: South | C27: Overdue
A28: TXN00027 | B28: West | C28: Paid
A29: TXN00028 | B29: East
A30: TXN00029 | B30: North | C30: Partially Paid
A31: TXN00030 | B31: West | C31: Overdue
A32: TXN00031 | B32: South | C32: Paid
A33: TXN00032 | B33: Central
A34: TXN00033 | B34: East | C34: Pending
A35: TXN00034 | B35: East | C35: Overdue
A36: TXN00035 | B36: East | C36: Overdue
A37: TXN00036 | B37: Central | C37: Paid
A38: TXN00037 | B38: West | C38: Defaulted
A39: TXN00038 | B39: West | C39: Pending
A40: TXN00039 | B40: South | C40: Partially Paid
A41: TXN00040 | B41: North | C41: Overdue
A42: TXN00041 | B42: South | C42: Overdue
A43: TXN00042 | B43: Central | C43: Paid
A44: TXN00043 | B44: East | C44: Partially Paid
A45: TXN00044 | B45: North | C45: Overdue
... A61: TXN00060 | B61: East | C61: Paid
A62: TXN00061 | B62: North
A63: TXN00062 | B63: East | C63: Partially Paid
A64: TXN00063 | B64: Central | C64: Overdue
A65: TXN00064 | B65: South | C65: Paid
A66: TXN00065 | B66: East | C66: Paid
A67: TXN00066 | B67: North | C67: Overdue
A68: TXN00067 | B68: West | C68: Overdue
A69: TXN00068 | B69: Central | C69: Paid
A70: TXN00069 | B70: West | C70: Defaulted
A71: TXN00070 | B71: East | C71: Pending
A72: TXN00071 | B72: Central | C72: Paid
A73: TXN00072 | B73: Central | C73: Paid
A74: TXN00073 | B74: East | C74: Pending
... A159: TXN00158 | B159: South | C159: Overdue
A160: TXN00159 | B160: West
A161: TXN00160 | B161: West | C161: Overdue
A162: TXN00161 | B162: South | C162: Paid
A163: TXN00162 | B163: South | C163: Paid
A164: TXN00163 | B164: West
A165: TXN00164 | B165: South | C165: Pending
A166: TXN00165 | B166: South | C166: Paid
A167: TXN00166 | B167: Central | C167: Defaulted
A168: TXN00167 | B168: South | C168: Paid
A169: TXN00168 | B169: South | C169: Overdue
A170: TXN00169 | B170: East | C170: Overdue
A171: TXN00170 | B171: East
A172: TXN00171 | B172: North | C172: Pending
A173: TXN00172 | B173: South | C173: Overdue
A174: TXN00173 | B174: West | C174: Defaulted
A175: TXN00174 | B175: West | C175: Paid
A176: TXN00175 | B176: West | C176: Paid
A177: TXN00176 | B177: Central | C177: Pending
A178: TXN00177 | B178: South | C178: Paid
A179: TXN00178 | B179: North | C179: Defaulted
A180: TXN00179 | B180: North | C180: Overdue
A181: TXN00180 | B181: West | C181: Partially Paid
A182: TXN00181 | B182: North | C182: Defaulted
A183: TXN00182 | B183: Central | C183: Defaulted
... A252: TXN00251 | B252: South | C252: Overdue
A253: TXN00252 | B253: Central
A254: TXN00253 | B254: West
A255: TXN00254 | B255: West | C255: Pending
A256: TXN00255 | B256: Central | C256: Paid
A257: TXN00256 | B257: South | C257: Defaulted
A258: TXN00257 | B258: Central | C258: Overdue
A259: TXN00258 | B259: West | C259: Paid
A260: TXN00259 | B260: Central | C260: Overdue
A261: TXN00260 | B261: East | C261: Partially Paid
A262: TXN00261 | B262: West | C262: Overdue
A263: TXN00262 | B263: West | C263: Pending
A264: TXN00263 | B264: Central | C264: Overdue
A265: TXN00264 | B265: West | C265: Paid
A266: TXN00265 | B266: North | C266: Overdue
... A276: TXN00275 | B276: East | C276: Overdue
A277: TXN00276 | B277: North
...

Sheet Sheet8

Sheet Sheet1
A1: Column1 | B1: Column2 | C1: Column3 | D1: Column4

Sheet Sheet19
A3: Approval_Status | B3: Sum of Loan_Amount_Lakhs | C3: Sum of Outstanding_Balance
A4: approved | B4: 50873.35 | C4: 21573.06
A5: Rejected | B5: 15648.11 | C5: 6609.65
A6: Rejected | B6: 15786.06 | C6: 6871.7
A7: Under Review | B7: 18585.93 | C7: 8180.17

Sheet Sheet17

Sheet Sheet15

Sheet Sheet26
A3: Region | B3: Count of Actual_Revenue_Lakhs
A4: Central | B4: 6
A5: East | B5: 7
A6: North | B6: 7
A7: South | B7: 8
A8: West | B8: 8
A9: Grand Total | B9: 36

Sheet KPL_Summary
A1: KPI Summary — Monthly Finance Metrics
A3: Month | B3: Year | C3: Target_Revenue_Lakhs | D3: Actual_Revenue_Lakhs | E3: Loan_Approvals | F3: Loan_Rejections | G3: Recovery_Pct | H3: NPA_Pct | I3: New_Customers | J3: Avg_Loan_Amount | K3: Region | O3: Month | P3: Recovery_Pct
A4: Jan | B4: 2022 | C4: 515.82 | D4: 422.49 | E4: 130 | F4: 26 | G4: 82.9 | H4: 4.76 | I4: 82 | J4: 20.22 | K4: North | O4: Jan | P4: 82.9
A5: Feb | B5: 2022 | C5: 774.56 | D5: 701.67 | E5: 170 | F5: 53 | G5: 79.86 | H5: 2.73 | I5: 87 | J5: 28.94 | K5: North | O5: Feb | P5: 79.86
A6: Mar | B6: 2022 | C6: 751.88 | D6: 631.48 | E6: 144 | F6: 49 | G6: 91.39 | H6: 2.89 | I6: 60 | J6: 13.2 | K6: West | O6: Mar | P6: 91.39
A7: Apr | B7: 2022 | C7: 787.55 | D7: 929.2 | E7: 196 | F7: 59 | G7: 84.94 | H7: 10.77 | I7: 114 | J7: 29.68 | K7: Central | O7: Apr | P7: 84.94
A8: May | B8: 2022 | C8: 723.15 | D8: 718.94 | E8: 183 | F8: 56 | G8: 83.17 | H8: 10.85 | I8: 98 | J8: 15.93 | K8: East | O8: May | P8: 83.17
A9: Jun | B9: 2022 | C9: 500.13 | D9: 479.52 | E9: 148 | F9: 29 | G9: 82.52 | H9: 8.83 | I9: 35 | J9: 22.31 | K9: Central | O9: Jun | P9: 82.52
A10: Jul | B10: 2022 | C10: 640 | D10: 695.99 | E10: 94 | F10: 47 | G10: 77.96 | H10: 10.61 | I10: 107 | J10: 12.66 | K10: East | O10: Jul | P10: 77.96
A11: Aug | B11: 2022 | C11: 588.21 | D11: 627.42 | E11: 101 | F11: 57 | G11: 79.51 | H11: 10.02 | I11: 117 | J11: 28.4 | K11: Central | O11: Aug | P11: 79.51
A12: Sep | B12: 2022 | C12: 513.58 | D12: 484.94 | E12: 190 | F12: 43 | G12: 94.24 | H12: 6.85 | I12: 105 | J12: 16.44 | K12: South | O12: Sep | P12: 94.24
A13: Oct | B13: 2022 | C13: 573.64 | D13: 575.97 | E13: 187 | F13: 58 | G13: 95.39 | H13: 2.49 | I13: 30 | J13: 8.28 | K13: West | O13: Oct | P13: 95.39
A14: Nov | B14: 2022 | C14: 795.22 | D14: 888.69 | E14: 143 | F14: 24 | G14: 88.95 | H14: 2.58 | I14: 109 | J14: 12.82 | K14: West | O14: Nov | P14: 88.95
A15: Dec | B15: 2022 | C15: 688.12 | D15: 725.45 | E15: 96 | F15: 20 | G15: 79.32 | H15: 11.55 | I15: 88 | J15: 8.97 | K15: North | O15: Dec | P15: 79.32
... A39: Dec | B39: 2024 | C39: 567.36 | D39: 449.24 | E39: 98 | F39: 30 | G39: 90.87 | H39: 11.81 | I39: 120 | J39: 5.19 | K39: Central | O39: Dec | P39: 90.87
K40: West
K41: West
K42: South
K43: North
K44: South
K45: Central
K46: East
K47: North
K48: South
K49: North
K50: South
K51: West
... K2003: North

Sheet  (All Answers)
F1: Branches | G1: Processing Fees | H1: (4)Calculate total processing fees collected branch-wise. Which branch collected the highest fee? | I1: Credit_Score | J1: (9)Create a new column 'Risk_Category': If Credit_Score >= 750 → 'Low Risk', 650–749 → 'Medium Risk', < 650 → 'High Risk'. Use IFS or Nested IF. | L1: Target_Revenue_Lakhs | M1: Actual_Revenue_Lakhs | N1: (10)Create a column 'Target_Met': If Actual_Revenue >= Target_Revenue in KPI sheet → 'Yes', else 'No'. Use IF. | P1: Loan_Amount_Lakhs | Q1: (11)Flag transactions where Loan_Amount is blank (missing). Use IF + ISBLANK. | S1: Target_Revenue_Lakhs | T1: Actual_Revenue_Lakhs | U1: (12)In KPI sheet, create a column showing revenue difference (Actual - Target). Use IF to show 'Surplus' or 'Deficit' with the value. | W1: Branch_ID | X1: Manager | Y1: Transaction_ID | Z1: Branch_ID | AA1: (13)Use IFERROR with VLOOKUP to fetch Branch Manager name for each transaction. Handle missing Branch IDs gracefully. | AB1: Loan_Amount_Lakhs | AC1: Occupation | AD1: Annual Income From Customers Sheet | AE1: (5)Using SUMIFS, find total loan disbursed to 'Salaried' customers earning more than 10 Lakhs per year. (Requires VLOOKUP/XLOOKUP across Customers sheet) | AG1: Transaction_ID | AH1: (15)Extract the numeric part of Transaction_ID (e.g., TXN00001 → 00001). Use MID or RIGHT. | AI1: Gender | AJ1: (16)Standardize Gender column (convert M→Male, F→Female, lowercase → proper case). Use IF + UPPER/LOWER. | AK1: Customer Name | AL1: City | AM1: (17)Combine Customer Name and City as a single label: 'Amit Kumar | Bhubaneswar'. Use CONCAT or &. | AO1: Name | AP1: (18)Find all customers whose name starts with 'R'. Use LEFT + IF or FILTER. | AR1: Branch_Name | AS1: (19)Count the number of characters in each Branch Name. Use LEN. | AU1: Approval_Status | AV1: (20)Trim extra spaces from Approval_Status column and standardize to Proper Case. Use TRIM + PROPER. | AY1: Customer_ID | AZ1: City | BA1: Transaction_ID | BB1: Customer_ID in transition sheet | BC1: (27)For each Transaction, fetch the Customer's City using VLOOKUP (from Customers sheet). | BE1: Branch_ID | BF1: Target_Revenue_Lakhs | BG1: Transaction_ID | BH1: Branch_ID | BI1: (28)Fetch Branch Target Revenue for each transaction using XLOOKUP (from Branches sheet). | BK1: Customer_ID | BL1: (30)Build a lookup to check if a given Customer_ID exists in the Customers sheet. Use COUNTIF or XLOOKUP with IFERROR.
F2: BR001 | G2: =SUMIFS(Transitions!I:I,Transitions!C:C,"BR001") -> 122.964 | H2: =VLOOKUP(LARGE(G2:G11,1),CHOOSE({1,2},G2:G11,F2:F11),2,FALSE) -> BR003 | I2: 557 | J2: {=_xlfn.IFS(I2>=750,"Low Risk",AND(I2>=650,I2<=749),"Medium Risk",I2<650,"High Risk")} -> High Risk | L2: 515.82 | M2: 422.49 | N2: =IF(M2>=L2,"Yes","No") -> No | P2: 73.8 | Q2: =IF(ISBLANK(P2),"missing","Available") -> Available | S2: 515.82 | T2: 422.49 | U2: {=_xlfn.IFS(T2>S2,"Surplus",T2<S2,"Deficit")} -> Deficit | W2: BR001 | X2: Rajesh Kumar | Y2: TXN00001 | Z2: BR008 | AA2: =VLOOKUP(Z2,$W$2:$X$11,2,FALSE) -> Kavita Rath | AB2: 73.8 | AC2: retired | AD2: 43.5 | AE2: =SUMIFS(AB:AB,AC:AC,"Salaried",AD:AD,">10") -> 2945.36 | AG2: TXN00001 | AH2: =RIGHT(AG2,5) -> 00001 | AI2: Male | AJ2: =IF(UPPER(AI2)="M","Male","Female") -> Female | AK2: Mira Pradhan | AL2: Dhenkanal | AM2: =_xlfn.CONCAT(AK2,"|",AL2) -> Mira Pradhan|Dhenkanal | AO2: Mira Pradhan | AP2: =IF(LEFT(AO2,1)="R",AO2,"Not True") -> Not True | AR2: Bhubaneswar Main | AS2: =LEN(AR2) -> 16 | AU2: approved | AV2: =PROPER(TRIM(AU2)) -> Approved | AY2: CUST0001 | AZ2: Dhenkanal | BA2: TXN00001 | BB2: CUST0184 | BC2: =VLOOKUP(BB2,$AY$2:$AZ$501,2,FALSE) -> Jharsuguda | BE2: BR001 | BF2: 209.86 | BG2: TXN00001 | BH2: BR008 | BI2: =VLOOKUP(BH2,$BE$2:$BF$11,2,FALSE) -> 103.83 | BK2: CUST0001 | BL2: =IF(COUNTIF(BK:BK,BK2)>0,"Exists","Does Not Exists") -> Exists | BM2: 32 | BN2: Sum of Loan_Amount_Lakhs | BO2: Product | BV2: 34 ---- | BW2: Year | BX2: 2024
A3: SECTION A — AGGREGATE & CONDITIONAL FUNCTIONS | F3: BR002 | G3: =SUMIFS(Transitions!I:I,Transitions!C:C,"BR002") -> 125.9619 | I3: 600 | J3: {=_xlfn.IFS(I3>=750,"Low Risk",AND(I3>=650,I3<=749),"Medium Risk",I3<650,"High Risk")} -> High Risk | L3: 774.56 | M3: 701.67 | N3: =IF(M3>=L3,"Yes","No") -> No | P3: 6.55 | Q3: =IF(ISBLANK(P3),"missing","Available") -> Available | S3: 774.56 | T3: 701.67 | U3: {=_xlfn.IFS(T3>S3,"Surplus",T3<S3,"Deficit")} -> Deficit | W3: BR002 | X3: Priya Mohanty | Y3: TXN00002 | Z3: BR008 | AA3: =VLOOKUP(Z3,$W$2:$X$11,2,FALSE) -> Kavita Rath | AB3: 6.55 | AC3: Government Employee | AD3: 20.15 | AG3: TXN00002 | AH3: =RIGHT(AG3,5) -> 00002 | AI3: Male | AJ3: =IF(UPPER(AI3)="M","Male","Female") -> Female | AK3: Sita Rath | AL3: Balasore | AM3: =_xlfn.CONCAT(AK3,"|",AL3) -> Sita Rath|Balasore | AO3: Sita Rath | AP3: =IF(LEFT(AO3,1)="R",AO3,"Not True") -> Not True | AR3: Cuttack Central | AS3: =LEN(AR3) -> 15 | AU3: Rejected | AV3: =PROPER(TRIM(AU3)) -> Rejected | AY3: CUST0002 | AZ3: Balasore | BA3: TXN00002 | BB3: CUST0428 | BC3: =VLOOKUP(BB3,$AY$2:$AZ$501,2,FALSE) -> Bhubaneswar | BE3: BR002 | BF3: 105.8 | BG3: TXN00002 | BH3: BR008 | BI3: =VLOOKUP(BH3,$BE$2:$BF$11,2,FALSE) -> 103.83 | BK3: CUST0002 | BL3: =IF(COUNTIF(BK:BK,BK3)>0,"Exists","Does Not Exists") -> Exists | BN3: Region | BO3: Auto Loan | BP3: Business Loan | BQ3: Education Loan | BR3: Gold Loan | BS3: Home Loan | BT3: Personal Loan | BU3: Grand Total
A4: Q1 | B4: Calculate the total Loan Amount (in Lakhs) for all APPROVED transactions in the 'East' region. Use SUMIFS. | C4: =SUMIFS(Transitions!G:G,Transitions!N:N,"Approved",Transitions!D:D,"East") -> 10719.63 | D4: (Lakhs) | F4: BR003 | G4: =SUMIFS(Transitions!I:I,Transitions!C:C,"BR003") -> 146.9439 | I4: 690 | J4: {=_xlfn.IFS(I4>=750,"Low Risk",AND(I4>=650,I4<=749),"Medium Risk",I4<650,"High Risk")} -> Medium Risk | L4: 751.88 | M4: 631.48 | N4: =IF(M4>=L4,"Yes","No") -> No | P4: 47.65 | Q4: =IF(ISBLANK(P4),"missing","Available") -> Available | S4: 751.88 | T4: 631.48 | U4: {=_xlfn.IFS(T4>S4,"Surplus",T4<S4,"Deficit")} -> Deficit | W4: BR003 | X4: Suresh Panda | Y4: TXN00003 | Z4: BR003 | AA4: =VLOOKUP(Z4,$W$2:$X$11,2,FALSE) -> Suresh Panda | AB4: 47.65 | AC4: Government Employee | AD4: 49.51 | AG4: TXN00003 | AH4: =RIGHT(AG4,5) -> 00003 | AI4: female | AJ4: =IF(UPPER(AI4)="M","Male","Female") -> Female | AK4: Kavita Rout | AL4: Sambalpur | AM4: =_xlfn.CONCAT(AK4,"|",AL4) -> Kavita Rout|Sambalpur | AO4: Kavita Rout | AP4: =IF(LEFT(AO4,1)="R",AO4,"Not True") -> Not True | AR4: Rourkela Industrial | AS4: =LEN(AR4) -> 19 | AU4: Rejected | AV4: =PROPER(TRIM(AU4)) -> Rejected | AY4: CUST0003 | AZ4: Sambalpur | BA4: TXN00003 | BB4: CUST0377 | BC4: =VLOOKUP(BB4,$AY$2:$AZ$501,2,FALSE) -> Jharsuguda | BE4: BR003 | BF4: 197.62 | BG4: TXN00003 | BH4: BR003 | BI4: =VLOOKUP(BH4,$BE$2:$BF$11,2,FALSE) -> 197.62 | BK4: CUST0003 | BL4: =IF(COUNTIF(BK:BK,BK4)>0,"Exists","Does Not Exists") -> Exists | BN4: Central | BO4: 2751.61 | BP4: 4153.45 | BQ4: 3001.45 | BR4: 3565.22 | BS4: 2929.92 | BT4: 2710 | BU4: 19111.65 | BW4: Month | BX4: Sum of Target_Revenue_Lakhs | BY4: Sum of Actual_Revenue_Lakhs
A5: Q2 | B5: Count how many transactions have Payment_Status = 'Overdue'. Use COUNTIF. | C5: =COUNTIF(Transitions!K:K,"Overdue") -> 393 | F5: BR004 | G5: =SUMIFS(Transitions!I:I,Transitions!C:C,"BR003") -> 146.9439 | I5: 797 | J5: {=_xlfn.IFS(I5>=750,"Low Risk",AND(I5>=650,I5<=749),"Medium Risk",I5<650,"High Risk")} -> Low Risk | L5: 787.55 | M5: 929.2 | N5: =IF(M5>=L5,"Yes","No") -> Yes | P5: 7.33 | Q5: =IF(ISBLANK(P5),"missing","Available") -> Available | S5: 787.55 | T5: 929.2 | U5: {=_xlfn.IFS(T5>S5,"Surplus",T5<S5,"Deficit")} -> Surplus | W5: BR004 | X5: Anita Das | Y5: TXN00004 | Z5: BR008 | AA5: =VLOOKUP(Z5,$W$2:$X$11,2,FALSE) -> Kavita Rath | AB5: 7.33 | AC5: Salaried | AD5: 47.32 | AG5: TXN00004 | AH5: =RIGHT(AG5,5) -> 00004 | AI5: M | AJ5: =IF(UPPER(AI5)="M","Male","Female") -> Male | AK5: Ashok Mohanty | AL5: Balasore | AM5: =_xlfn.CONCAT(AK5,"|",AL5) -> Ashok Mohanty|Balasore | AO5: Ashok Mohanty | AP5: =IF(LEFT(AO5,1)="R",AO5,"Not True") -> Not True | AR5: Puri Tourism | AS5: =LEN(AR5) -> 12 | AU5: Rejected | AV5: =PROPER(TRIM(AU5)) -> Rejected | AY5: CUST0004 | AZ5: Balasore | BA5: TXN00004 | BB5: CUST0050 | BC5: =VLOOKUP(BB5,$AY$2:$AZ$501,2,FALSE) -> Rourkela | BE5: BR004 | BF5: 104.66 | BG5: TXN00004 | BH5: BR008 | BI5: =VLOOKUP(BH5,$BE$2:$BF$11,2,FALSE) -> 103.83 | BK5: CUST0004 | BL5: =IF(COUNTIF(BK:BK,BK5)>0,"Exists","Does Not Exists") -> Exists | BN5: East | BO5: 2948.59 | BP5: 3211.64 | BQ5: 3388.14 | BR5: 3182.5 | BS5: 3324.26 | BT5: 3706.32 | BU5: 19761.45 | BW5: Jan | BX5: 778.81 | BY5: 702.41
A6: Q3 | B6: Find the average EMI for Home Loan customers with Credit Score above 700. Use AVERAGEIFS. | C6: =AVERAGEIFS(Transitions!J:J,Transitions!E:E,"Home Loan",Transitions!L:L,">700") -> 1.5571347 | D6: (Lakhs) | F6: BR005 | G6: =SUMIFS(Transitions!I:I,Transitions!C:C,"BR005") -> 126.066 | I6: 751 | J6: {=_xlfn.IFS(I6>=750,"Low Risk",AND(I6>=650,I6<=749),"Medium Risk",I6<650,"High Risk")} -> Low Risk | L6: 723.15 | M6: 718.94 | N6: =IF(M6>=L6,"Yes","No") -> No | P6: 58.02 | Q6: =IF(ISBLANK(P6),"missing","Available") -> Available | S6: 723.15 | T6: 718.94 | U6: {=_xlfn.IFS(T6>S6,"Surplus",T6<S6,"Deficit")} -> Deficit | W6: BR005 | X6: Bikash Nayak | Y6: TXN00005 | Z6: BR007 | AA6: =VLOOKUP(Z6,$W$2:$X$11,2,FALSE) -> Ramesh Behera | AB6: 58.02 | AC6: retired | AD6: 15.35 | AG6: TXN00005 | AH6: =RIGHT(AG6,5) -> 00005 | AI6: M | AJ6: =IF(UPPER(AI6)="M","Male","Female") -> Male | AK6: Arjun Nayak | AL6: Rourkela | AM6: =_xlfn.CONCAT(AK6,"|",AL6) -> Arjun Nayak|Rourkela | AO6: Arjun Nayak | AP6: =IF(LEFT(AO6,1)="R",AO6,"Not True") -> Not True | AR6: Sambalpur Regional | AS6: =LEN(AR6) -> 18 | AU6: Rejected | AV6: =PROPER(TRIM(AU6)) -> Rejected | AY6: CUST0005 | AZ6: Rourkela | BA6: TXN00005 | BB6: CUST0378 | BC6: =VLOOKUP(BB6,$AY$2:$AZ$501,2,FALSE) -> Bhubaneswar | BE6: BR005 | BF6: 190.31 | BG6: TXN00005 | BH6: BR007 | BI6: =VLOOKUP(BH6,$BE$2:$BF$11,2,FALSE) -> 224.53 | BK6: CUST0005 | BL6: =IF(COUNTIF(BK:BK,BK6)>0,"Exists","Does Not Exists") -> Exists | BN6: North | BO6: 2649.88 | BP6: 2782.17 | BQ6: 3002.91 | BR6: 3571.26 | BS6: 3396.06 | BT6: 4226.59 | BU6: 19628.87 | BW6: Feb | BX6: 555.85 | BY6: 523.94
A7: Q4 | B7: Calculate total processing fees collected branch-wise. Which branch collected the highest fee? | C7: Branches | D7: Processing Fees | F7: BR006 | G7: =SUMIFS(Transitions!I:I,Transitions!C:C,"BR006") -> 127.3054 | I7: 748 | J7: {=_xlfn.IFS(I7>=750,"Low Risk",AND(I7>=650,I7<=749),"Medium Risk",I7<650,"High Risk")} -> Medium Risk | L7: 500.13 | M7: 479.52 | N7: =IF(M7>=L7,"Yes","No") -> No | P7: 25.12 | Q7: =IF(ISBLANK(P7),"missing","Available") -> Available | S7: 500.13 | T7: 479.52 | U7: {=_xlfn.IFS(T7>S7,"Surplus",T7<S7,"Deficit")} -> Deficit | W7: BR006 | X7: Sunita Sahu | Y7: TXN00006 | Z7: BR006 | AA7: =VLOOKUP(Z7,$W$2:$X$11,2,FALSE) -> Sunita Sahu | AB7: 25.12 | AC7: retired | AD7: 34.98 | AG7: TXN00006 | AH7: =RIGHT(AG7,5) -> 00006 | AI7: Male | AJ7: =IF(UPPER(AI7)="M","Male","Female") -> Female | AK7: Nisha Das | AL7: Cuttack | AM7: =_xlfn.CONCAT(AK7,"|",AL7) -> Nisha Das|Cuttack | AO7: Nisha Das | AP7: =IF(LEFT(AO7,1)="R",AO7,"Not True") -> Not True | AR7: Berhampur South | AS7: =LEN(AR7) -> 15 | AU7: approved | AV7: =PROPER(TRIM(AU7)) -> Approved | AY7: CUST0006 | AZ7: Cuttack | BA7: TXN00006 | BB7: CUST0087 | BC7: =VLOOKUP(BB7,$AY$2:$AZ$501,2,FALSE) -> Bhubaneswar | BE7: BR006 | BF7: 162.3 | BG7: TXN00006 | BH7: BR006 | BI7: =VLOOKUP(BH7,$BE$2:$BF$11,2,FALSE) -> 162.3 | BK7: CUST0006 | BL7: =IF(COUNTIF(BK:BK,BK7)>0,"Exists","Does Not Exists") -> Exists | BN7: South | BO7: 3615.17 | BP7: 3141.53 | BQ7: 3667.88 | BR7: 4382.45 | BS7: 3335.53 | BT7: 3511.95 | BU7: 21654.51 | BW7: Mar | BX7: 451.01 | BY7: 392.3
C8: BR007 | D8: =SUMIFS(Transitions!I:I,Transitions!C:C,' (All Answers)'!C8) -> 128.2743 | F8: BR007 | G8: =SUMIFS(Transitions!I:I,Transitions!C:C,"BR007") -> 128.2743 | I8: 866 | J8: {=_xlfn.IFS(I8>=750,"Low Risk",AND(I8>=650,I8<=749),"Medium Risk",I8<650,"High Risk")} -> Low Risk | L8: 640 | M8: 695.99 | N8: =IF(M8>=L8,"Yes","No") -> Yes | W8: BR007 | X8: Ramesh Behera | Y8: TXN00007 | Z8: BR010 | AA8: =VLOOKUP(Z8,$W$2:$X$11,2,FALSE) -> Pooja Tripathi | AB8: 80.93 | AC8: retired | AD8: 38.29 | AG8: TXN00007 | AH8: =RIGHT(AG8,5) -> 00007 | AI8: female | AJ8: =IF(UPPER(AI8)="M","Male","Female") -> Female | AK8: Seema Kumar | AL8: Cuttack | AM8: =_xlfn.CONCAT(AK8,"|",AL8) -> Seema Kumar|Cuttack | AO8: Seema Kumar | AP8: =IF(LEFT(AO8,1)="R",AO8,"Not True") -> Not True | AR8: Balasore North | AS8: =LEN(AR8) -> 14 | AU8: approved | AV8: =PROPER(TRIM(AU8)) -> Approved | AY8: CUST0007 | AZ8: Cuttack | BA8: TXN00007 | BB8: CUST0334 | BC8: =VLOOKUP(BB8,$AY$2:$AZ$501,2,FALSE) -> Puri | BE8: BR007 | BF8: 224.53 | BG8: TXN00007 | BH8: BR010 | BI8: =VLOOKUP(BH8,$BE$2:$BF$11,2,FALSE) -> 251.78 | BK8: CUST0007 | BL8: =IF(COUNTIF(BK:BK,BK8)>0,"Exists","Does Not Exists") -> Exists | BN8: West | BO8: 3698.96 | BP8: 3903.88 | BQ8: 2834.7 | BR8: 3270.67 | BS8: 3858.58 | BT8: 3170.18 | BU8: 20736.97 | BW8: Apr | BX8: 656.67 | BY8: 553.88
A9: Q5 | B9: Using SUMIFS, find total loan disbursed to 'Salaried' customers earning more than 10 Lakhs per year. (Requires VLOOKUP/XLOOKUP across Customers sheet) | C9: Done | F9: BR008 | G9: =SUMIFS(Transitions!I:I,Transitions!C:C,"BR008") -> 131.6551 | I9: 887 | J9: {=_xlfn.IFS(I9>=750,"Low Risk",AND(I9>=650,I9<=749),"Medium Risk",I9<650,"High Risk")} -> Low Risk | L9: 588.21 | M9: 627.42 | N9: =IF(M9>=L9,"Yes","No") -> Yes | P9: 80.93 | Q9: =IF(ISBLANK(P9),"missing","Available") -> Available | S9: 640 | T9: 695.99 | U9: {=_xlfn.IFS(T9>S9,"Surplus",T9<S9,"Deficit")} -> Surplus | W9: BR008 | X9: Kavita Rath | Y9: TXN00008 | Z9: BR008 | AA9: =VLOOKUP(Z9,$W$2:$X$11,2,FALSE) -> Kavita Rath | AB9: 82.82 | AC9: Salaried | AD9: 17.03 | AG9: TXN00008 | AH9: =RIGHT(AG9,5) -> 00008 | AI9: male | AJ9: =IF(UPPER(AI9)="M","Male","Female") -> Female | AK9: Amit Mishra | AL9: Rourkela | AM9: =_xlfn.CONCAT(AK9,"|",AL9) -> Amit Mishra|Rourkela | AO9: Amit Mishra | AP9: =IF(LEFT(AO9,1)="R",AO9,"Not True") -> Not True | AR9: Angul Mining | AS9: =LEN(AR9) -> 12 | AU9: approved | AV9: =PROPER(TRIM(AU9)) -> Approved | AY9: CUST0008 | AZ9: Rourkela | BA9: TXN00008 | BB9: CUST0093 | BC9: =VLOOKUP(BB9,$AY$2:$AZ$501,2,FALSE) -> Angul | BE9: BR008 | BF9: 103.83 | BG9: TXN00008 | BH9: BR008 | BI9: =VLOOKUP(BH9,$BE$2:$BF$11,2,FALSE) -> 103.83 | BK9: CUST0008 | BL9: =IF(COUNTIF(BK:BK,BK9)>0,"Exists","Does Not Exists") -> Exists | BW9: May | BX9: 647.49 | BY9: 701.48
A10: Q6 | B10: Find the count of loans where Amount > 50 Lakhs AND Approval_Status = 'Approved'. Use COUNTIFS. | C10: =COUNTIFS(Transitions!G:G,">50",Transitions!M:M,"approved") -> 524 | F10: BR009 | G10: =SUMIFS(Transitions!I:I,Transitions!C:C,"BR009") -> 127.8823 | I10: 793 | J10: {=_xlfn.IFS(I10>=750,"Low Risk",AND(I10>=650,I10<=749),"Medium Risk",I10<650,"High Risk")} -> Low Risk | L10: 513.58 | M10: 484.94 | N10: =IF(M10>=L10,"Yes","No") -> No | P10: 82.82 | Q10: =IF(ISBLANK(P10),"missing","Available") -> Available | S10: 588.21 | T10: 627.42 | U10: {=_xlfn.IFS(T10>S10,"Surplus",T10<S10,"Deficit")} -> Surplus | W10: BR009 | X10: Deepak Mishra | Y10: TXN00009 | Z10: BR009 | AA10: =VLOOKUP(Z10,$W$2:$X$11,2,FALSE) -> Deepak Mishra | AB10: 66.27 | AC10: Government Employee | AG10: TXN00009 | AH10: =RIGHT(AG10,5) -> 00009 | AI10: Male | AJ10: =IF(UPPER(AI10)="M","Male","Female") -> Female | AK10: Prakash Swain | AL10: Jharsuguda | AM10: =_xlfn.CONCAT(AK10,"|",AL10) -> Prakash Swain|Jharsuguda | AO10: Prakash Swain | AP10: =IF(LEFT(AO10,1)="R",AO10,"Not True") -> Not True | AR10: Jharsuguda Energy | AS10: =LEN(AR10) -> 17 | AU10: Rejected | AV10: =PROPER(TRIM(AU10)) -> Rejected | AY10: CUST0009 | AZ10: Jharsuguda | BA10: TXN00009 | BB10: CUST0277 | BC10: =VLOOKUP(BB10,$AY$2:$AZ$501,2,FALSE) -> Dhenkanal | BE10: BR009 | BF10: 144.98 | BG10: TXN00009 | BH10: BR009 | BI10: =VLOOKUP(BH10,$BE$2:$BF$11,2,FALSE) -> 144.98 | BK10: CUST0009 | BL10: =IF(COUNTIF(BK:BK,BK10)>0,"Exists","Does Not Exists") -> Exists | BM10: 33 | BN10: Month | BO10: Sum of Loan_Approvals | BP10: Sum of Loan_Rejections | BW10: Jun | BX10: 486.09 | BY10: 558.06
A11: Q7 | B11: Find the MAX and MIN loan amount for each loan product type. | C11: Loan product type | D11: Maximum | E11: Minimum | F11: BR010 | G11: =SUMIFS(Transitions!I:I,Transitions!C:C,"BR010") -> 115.1412 | I11: 713 | J11: {=_xlfn.IFS(I11>=750,"Low Risk",AND(I11>=650,I11<=749),"Medium Risk",I11<650,"High Risk")} -> Medium Risk | L11: 573.64 | M11: 575.97 | N11: =IF(M11>=L11,"Yes","No") -> Yes | P11: 66.27 | Q11: =IF(ISBLANK(P11),"missing","Available") -> Available | S11: 513.58 | T11: 484.94 | U11: {=_xlfn.IFS(T11>S11,"Surplus",T11<S11,"Deficit")} -> Deficit | W11: BR010 | X11: Pooja Tripathi | Y11: TXN00010 | Z11: BR004 | AA11: =VLOOKUP(Z11,$W$2:$X$11,2,FALSE) -> Anita Das | AB11: 62.07 | AC11: Self-Employed | AD11: 47.5 | AG11: TXN00010 | AH11: =RIGHT(AG11,5) -> 00010 | AI11: Male | AJ11: =IF(UPPER(AI11)="M","Male","Female") -> Female | AK11: Ravi Dash | AL11: Dhenkanal | AM11: =_xlfn.CONCAT(AK11,"|",AL11) -> Ravi Dash|Dhenkanal | AO11: Ravi Dash | AP11: =IF(LEFT(AO11,1)="R",AO11,"Not True") -> Ravi Dash | AR11: Dhenkanal Rural | AS11: =LEN(AR11) -> 15 | AU11: Rejected | AV11: =PROPER(TRIM(AU11)) -> Rejected | AY11: CUST0010 | AZ11: Dhenkanal | BA11: TXN00010 | BB11: CUST0146 | BC11: =VLOOKUP(BB11,$AY$2:$AZ$501,2,FALSE) -> Angul | BE11: BR010 | BF11: 251.78 | BG11: TXN00010 | BH11: BR004 | BI11: =VLOOKUP(BH11,$BE$2:$BF$11,2,FALSE) -> 104.66 | BK11: CUST0010 | BL11: =IF(COUNTIF(BK:BK,BK11)>0,"Exists","Does Not Exists") -> Exists | BN11: Jan | BO11: 439 | BP11: 124 | BW11: Jul | BX11: 488.42 | BY11: 568.29
C12: Business Loan | D12: =_xlfn.MAXIFS(Transitions!G:G,Transitions!E:E,C12) -> 99.91 | E12: =_xlfn.MINIFS(Transitions!G:G,Transitions!E:E,C12) -> 1.04 | I12: 639 | J12: {=_xlfn.IFS(I12>=750,"Low Risk",AND(I12>=650,I12<=749),"Medium Risk",I12<650,"High Risk")} -> High Risk | L12: 795.22 | M12: 888.69 | N12: =IF(M12>=L12,"Yes","No") -> Yes | P12: 62.07 | Q12: =IF(ISBLANK(P12),"missing","Available") -> Available | S12: 573.64 | T12: 575.97 | U12: {=_xlfn.IFS(T12>S12,"Surplus",T12<S12,"Deficit")} -> Surplus | Y12: TXN00011 | Z12: BR004 | AA12: =VLOOKUP(Z12,$W$2:$X$11,2,FALSE) -> Anita Das | AB12: 33.27 | AC12: retired | AD12: 23.59 | AG12: TXN00011 | AH12: =RIGHT(AG12,5) -> 00011 | AI12: female | AJ12: =IF(UPPER(AI12)="M","Male","Female") -> Female | AK12: Prakash Behera | AL12: Berhampur | AM12: =_xlfn.CONCAT(AK12,"|",AL12) -> Prakash Behera|Berhampur | AO12: Prakash Behera | AP12: =IF(LEFT(AO12,1)="R",AO12,"Not True") -> Not True | AU12: Rejected | AV12: =PROPER(TRIM(AU12)) -> Rejected | AY12: CUST0011 | AZ12: Berhampur | BA12: TXN00011 | BB12: CUST0459 | BC12: =VLOOKUP(BB12,$AY$2:$AZ$501,2,FALSE) -> Sambalpur | BG12: TXN00011 | BH12: BR004 | BI12: =VLOOKUP(BH12,$BE$2:$BF$11,2,FALSE) -> 104.66 | BK12: CUST0011 | BL12: =IF(COUNTIF(BK:BK,BK12)>0,"Exists","Does Not Exists") -> Exists | BN12: Feb | BO12: 394 | BP12: 127 | BW12: Aug | BX12: 626.94 | BY12: 692.38
A13: Q8 | B13: What is the total Outstanding Balance for all 'Defaulted' loans? | C13: =SUMIFS(Transitions!S:S,Transitions!K:K,"Defaulted") -> 9564.88 | I13: 731 | J13: {=_xlfn.IFS(I13>=750,"Low Risk",AND(I13>=650,I13<=749),"Medium Risk",I13<650,"High Risk")} -> Medium Risk | L13: 688.12 | M13: 725.45 | N13: =IF(M13>=L13,"Yes","No") -> Yes | P13: 33.27 | Q13: =IF(ISBLANK(P13),"missing","Available") -> Available | S13: 795.22 | T13: 888.69 | U13: {=_xlfn.IFS(T13>S13,"Surplus",T13<S13,"Deficit")} -> Surplus | Y13: TXN00012 | Z13: BR004 | AA13: =VLOOKUP(Z13,$W$2:$X$11,2,FALSE) -> Anita Das | AB13: 48.96 | AC13: Salaried | AD13: 32.66 | AG13: TXN00012 | AH13: =RIGHT(AG13,5) -> 00012 | AI13: Female | AJ13: =IF(UPPER(AI13)="M","Male","Female") -> Female | AK13: Vijay Rout | AL13: Jharsuguda | AM13: =_xlfn.CONCAT(AK13,"|",AL13) -> Vijay Rout|Jharsuguda | AO13: Vijay Rout | AP13: =IF(LEFT(AO13,1)="R",AO13,"Not True") -> Not True | AU13: approved | AV13: =PROPER(TRIM(AU13)) -> Approved | AY13: CUST0012 | AZ13: Jharsuguda | BA13: TXN00012 | BB13: CUST0457 | BC13: =VLOOKUP(BB13,$AY$2:$AZ$501,2,FALSE) -> Bhubaneswar | BG13: TXN00012 | BH13: BR004 | BI13: =VLOOKUP(BH13,$BE$2:$BF$11,2,FALSE) -> 104.66 | BK13: CUST0012 | BL13: =IF(COUNTIF(BK:BK,BK13)>0,"Exists","Does Not Exists") -> Exists | BN13: Mar | BO13: 406 | BP13: 119 | BW13: Sep | BX13: 433.71 | BY13: 469.59
A14: SECTION B — LOGICAL FUNCTIONS | I14: 738 | J14: {=_xlfn.IFS(I14>=750,"Low Risk",AND(I14>=650,I14<=749),"Medium Risk",I14<650,"High Risk")} -> Medium Risk | L14: 766.04 | M14: 617.34 | N14: =IF(M14>=L14,"Yes","No") -> No | P14: 48.96 | Q14: =IF(ISBLANK(P14),"missing","Available") -> Available | S14: 688.12 | T14: 725.45 | U14: {=_xlfn.IFS(T14>S14,"Surplus",T14<S14,"Deficit")} -> Surplus | Y14: TXN00013 | Z14: BR004 | AA14: =VLOOKUP(Z14,$W$2:$X$11,2,FALSE) -> Anita Das | AB14: 69.53 | AC14: retired | AD14: 29.84 | AG14: TXN00013 | AH14: =RIGHT(AG14,5) -> 00013 | AI14: Female | AJ14: =IF(UPPER(AI14)="M","Male","Female") -> Female | AK14: Bikash Dash | AL14: Dhenkanal | AM14: =_xlfn.CONCAT(AK14,"|",AL14) -> Bikash Dash|Dhenkanal | AO14: Bikash Dash | AP14: =IF(LEFT(AO14,1)="R",AO14,"Not True") -> Not True | AU14: Rejected | AV14: =PROPER(TRIM(AU14)) -> Rejected | AY14: CUST0013 | AZ14: Dhenkanal | BA14: TXN00013 | BB14: CUST0139 | BC14: =VLOOKUP(BB14,$AY$2:$AZ$501,2,FALSE) -> Rourkela | BG14: TXN00013 | BH14: BR004 | BI14: =VLOOKUP(BH14,$BE$2:$BF$11,2,FALSE) -> 104.66 | BK14: CUST0013 | BL14: =IF(COUNTIF(BK:BK,BK14)>0,"Exists","Does Not Exists") -> Exists | BN14: Apr | BO14: 454 | BP14: 122 | BW14: Oct | BX14: 661.38 | BY14: 696.33
A15: Q9 | B15: Create a new column 'Risk_Category': If Credit_Score >= 750 → 'Low Risk', 650–749 → 'Medium Risk', < 650 → 'High Risk'. Use IFS or Nested IF. | C15: Done | I15: 863 | J15: {=_xlfn.IFS(I15>=750,"Low Risk",AND(I15>=650,I15<=749),"Medium Risk",I15<650,"High Risk")} -> Low Risk | L15: 540.74 | M15: 599.37 | N15: =IF(M15>=L15,"Yes","No") -> Yes | P15: 69.53 | Q15: =IF(ISBLANK(P15),"missing","Available") -> Available | S15: 766.04 | T15: 617.34 | U15: {=_xlfn.IFS(T15>S15,"Surplus",T15<S15,"Deficit")} -> Deficit | Y15: TXN00014 | Z15: BR010 | AA15: =VLOOKUP(Z15,$W$2:$X$11,2,FALSE) -> Pooja Tripathi | AB15: 85.65 | AC15: Government Employee | AD15: 5.55 | AG15: TXN00014 | AH15: =RIGHT(AG15,5) -> 00014 | AI15: M | AJ15: =IF(UPPER(AI15)="M","Male","Female") -> Male | AK15: Rekha Patnaik | AL15: Balasore | AM15: =_xlfn.CONCAT(AK15,"|",AL15) -> Rekha Patnaik|Balasore | AO15: Rekha Patnaik | AP15: =IF(LEFT(AO15,1)="R",AO15,"Not True") -> Rekha Patnaik | AU15: approved | AV15: =PROPER(TRIM(AU15)) -> Approved | AY15: CUST0014 | AZ15: Balasore | BA15: TXN00014 | BB15: CUST0407 | BC15: =VLOOKUP(BB15,$AY$2:$AZ$501,2,FALSE) -> Dhenkanal | BG15: TXN00014 | BH15: BR010 | BI15: =VLOOKUP(BH15,$BE$2:$BF$11,2,FALSE) -> 251.78 | BK15: CUST0014 | BL15: =IF(COUNTIF(BK:BK,BK15)>0,"Exists","Does Not Exists") -> Exists | BN15: May | BO15: 456 | BP15: 117 | BW15: Nov | BX15: 500.47 | BY15: 423.91
A16: Q10 | B16: Create a column 'Target_Met': If Actual_Revenue >= Target_Revenue in KPI sheet → 'Yes', else 'No'. Use IF. | C16: Done | I16: 560 | J16: {=_xlfn.IFS(I16>=750,"Low Risk",AND(I16>=650,I16<=749),"Medium Risk",I16<650,"High Risk")} -> High Risk | L16: 460.2 | M16: 364.59 | N16: =IF(M16>=L16,"Yes","No") -> No | P16: 85.65 | Q16: =IF(ISBLANK(P16),"missing","Available") -> Available | S16: 540.74 | T16: 599.37 | U16: {=_xlfn.IFS(T16>S16,"Surplus",T16<S16,"Deficit")} -> Surplus | Y16: TXN00015 | Z16: BR006 | AA16: =VLOOKUP(Z16,$W$2:$X$11,2,FALSE) -> Sunita Sahu | AB16: 89.29 | AC16: Self-Employed | AD16: 16.09 | AG16: TXN00015 | AH16: =RIGHT(AG16,5) -> 00015 | AI16: Female | AJ16: =IF(UPPER(AI16)="M","Male","Female") -> Female | AK16: Anita Behera | AL16: Dhenkanal | AM16: =_xlfn.CONCAT(AK16,"|",AL16) -> Anita Behera|Dhenkanal | AO16: Anita Behera | AP16: =IF(LEFT(AO16,1)="R",AO16,"Not True") -> Not True | AU16: approved | AV16: =PROPER(TRIM(AU16)) -> Approved | AY16: CUST0015 | AZ16: Dhenkanal | BA16: TXN00015 | BB16: CUST0127 | BC16: =VLOOKUP(BB16,$AY$2:$AZ$501,2,FALSE) -> Puri | BG16: TXN00015 | BH16: BR006 | BI16: =VLOOKUP(BH16,$BE$2:$BF$11,2,FALSE) -> 162.3 | BK16: CUST0015 | BL16: =IF(COUNTIF(BK:BK,BK16)>0,"Exists","Does Not Exists") -> Exists | BN16: Jun | BO16: 487 | BP16: 91 | BW16: Dec | BX16: 567.36 | BY16: 449.24
A17: Q11 | B17: Flag transactions where Loan_Amount is blank (missing). Use IF + ISBLANK. | C17: Done | I17: 582 | J17: {=_xlfn.IFS(I17>=750,"Low Risk",AND(I17>=650,I17<=749),"Medium Risk",I17<650,"High Risk")} -> High Risk | L17: 794.16 | M17: 721.7 | N17: =IF(M17>=L17,"Yes","No") -> No | P17: 89.29 | Q17: =IF(ISBLANK(P17),"missing","Available") -> Available | S17: 460.2 | T17: 364.59 | U17: {=_xlfn.IFS(T17>S17,"Surplus",T17<S17,"Deficit")} -> Deficit | Y17: TXN00016 | Z17: BR008 | AA17: =VLOOKUP(Z17,$W$2:$X$11,2,FALSE) -> Kavita Rath | AB17: 24.81 | AC17: Self-Employed | AD17: 25.62 | AG17: TXN00016 | AH17: =RIGHT(AG17,5) -> 00016 | AI17: Male | AJ17: =IF(UPPER(AI17)="M","Male","Female") -> Female | AK17: Manoj Rout | AL17: Cuttack | AM17: =_xlfn.CONCAT(AK17,"|",AL17) -> Manoj Rout|Cuttack | AO17: Manoj Rout | AP17: =IF(LEFT(AO17,1)="R",AO17,"Not True") -> Not True | AU17: Under Review | AV17: =PROPER(TRIM(AU17)) -> Under Review | AY17: CUST0016 | AZ17: Cuttack | BA17: TXN00016 | BB17: CUST0202 | BC17: =VLOOKUP(BB17,$AY$2:$AZ$501,2,FALSE) -> Bhubaneswar | BG17: TXN00016 | BH17: BR008 | BI17: =VLOOKUP(BH17,$BE$2:$BF$11,2,FALSE) -> 103.83 | BK17: CUST0016 | BL17: =IF(COUNTIF(BK:BK,BK17)>0,"Exists","Does Not Exists") -> Exists | BN17: Jul | BO17: 366 | BP17: 147
A18: Q12 | B18: In KPI sheet, create a column showing revenue difference (Actual - Target). Use IF to show 'Surplus' or 'Deficit' with the value. | C18: Done | I18: 649 | J18: {=_xlfn.IFS(I18>=750,"Low Risk",AND(I18>=650,I18<=749),"Medium Risk",I18<650,"High Risk")} -> High Risk | L18: 496.23 | M18: 492.41 | N18: =IF(M18>=L18,"Yes","No") -> No | P18: 24.81 | Q18: =IF(ISBLANK(P18),"missing","Available") -> Available | S18: 794.16 | T18: 721.7 | U18: {=_xlfn.IFS(T18>S18,"Surplus",T18<S18,"Deficit")} -> Deficit | Y18: TXN00017 | Z18: BR005 | AA18: =VLOOKUP(Z18,$W$2:$X$11,2,FALSE) -> Bikash Nayak | AB18: 85.93 | AC18: retired | AD18: 10.28 | AG18: TXN00017 | AH18: =RIGHT(AG18,5) -> 00017 | AI18: M | AJ18: =IF(UPPER(AI18)="M","Male","Female") -> Male | AK18: Mira Sethi | AL18: Balasore | AM18: =_xlfn.CONCAT(AK18,"|",AL18) -> Mira Sethi|Balasore | AO18: Mira Sethi | AP18: =IF(LEFT(AO18,1)="R",AO18,"Not True") -> Not True | AU18: Rejected | AV18: =PROPER(TRIM(AU18)) -> Rejected | AY18: CUST0017 | AZ18: Balasore | BA18: TXN00017 | BB18: CUST0343 | BC18: =VLOOKUP(BB18,$AY$2:$AZ$501,2,FALSE) -> Balasore | BG18: TXN00017 | BH18: BR005 | BI18: =VLOOKUP(BH18,$BE$2:$BF$11,2,FALSE) -> 190.31 | BK18: CUST0017 | BL18: =IF(COUNTIF(BK:BK,BK18)>0,"Exists","Does Not Exists") -> Exists | BN18: Aug | BO18: 411 | BP18: 141 | BU18: 36 | BV18: Month | BW18: Average of Recovery_Pct
A19: Q13 | B19: Use IFERROR with VLOOKUP to fetch Branch Manager name for each transaction. Handle missing Branch IDs gracefully. | C19: Done | I19: 849 | J19: {=_xlfn.IFS(I19>=750,"Low Risk",AND(I19>=650,I19<=749),"Medium Risk",I19<650,"High Risk")} -> Low Risk | L19: 742.05 | M19: 809.22 | N19: =IF(M19>=L19,"Yes","No") -> Yes | P19: 85.93 | Q19: =IF(ISBLANK(P19),"missing","Available") -> Available | S19: 496.23 | T19: 492.41 | U19: {=_xlfn.IFS(T19>S19,"Surplus",T19<S19,"Deficit")} -> Deficit | Y19: TXN00018 | Z19: BR002 | AA19: =VLOOKUP(Z19,$W$2:$X$11,2,FALSE) -> Priya Mohanty | AB19: 53.56 | AC19: Freelancer | AD19: 27.96 | AG19: TXN00018 | AH19: =RIGHT(AG19,5) -> 00018 | AI19: Male | AJ19: =IF(UPPER(AI19)="M","Male","Female") -> Female | AK19: Deepak Mohanty | AL19: Jharsuguda | AM19: =_xlfn.CONCAT(AK19,"|",AL19) -> Deepak Mohanty|Jharsuguda | AO19: Deepak Mohanty | AP19: =IF(LEFT(AO19,1)="R",AO19,"Not True") -> Not True | AU19: Rejected | AV19: =PROPER(TRIM(AU19)) -> Rejected | AY19: CUST0018 | AZ19: Jharsuguda | BA19: TXN00018 | BB19: CUST0322 | BC19: =VLOOKUP(BB19,$AY$2:$AZ$501,2,FALSE) -> Angul | BG19: TXN00018 | BH19: BR002 | BI19: =VLOOKUP(BH19,$BE$2:$BF$11,2,FALSE) -> 105.8 | BK19: CUST0018 | BL19: =IF(COUNTIF(BK:BK,BK19)>0,"Exists","Does Not Exists") -> Exists | BN19: Sep | BO19: 462 | BP19: 95 | BV19: Jan | BW19: 89.623333
I20: 580 | J20: {=_xlfn.IFS(I20>=750,"Low Risk",AND(I20>=650,I20<=749),"Medium Risk",I20<650,"High Risk")} -> High Risk | L20: 753.66 | M20: 744.73 | N20: =IF(M20>=L20,"Yes","No") -> No | P20: 53.56 | Q20: =IF(ISBLANK(P20),"missing","Available") -> Available | S20: 742.05 | T20: 809.22 | U20: {=_xlfn.IFS(T20>S20,"Surplus",T20<S20,"Deficit")} -> Surplus | Y20: TXN00019 | Z20: BR006 | AA20: =VLOOKUP(Z20,$W$2:$X$11,2,FALSE) -> Sunita Sahu | AB20: 37.19 | AC20: Self-Employed | AD20: 4.87 | AG20: TXN00019 | AH20: =RIGHT(AG20,5) -> 00019 | AI20: F | AJ20: =IF(UPPER(AI20)="M","Male","Female") -> Female | AK20: Ravi Rath | AL20: Cuttack | AM20: =_xlfn.CONCAT(AK20,"|",AL20) -> Ravi Rath|Cuttack | AO20: Ravi Rath | AP20: =IF(LEFT(AO20,1)="R",AO20,"Not True") -> Ravi Rath | AU20: approved | AV20: =PROPER(TRIM(AU20)) -> Approved | AY20: CUST0019 | AZ20: Cuttack | BA20: TXN00019 | BB20: CUST0264 | BC20: =VLOOKUP(BB20,$AY$2:$AZ$501,2,FALSE) -> Rourkela | BG20: TXN00019 | BH20: BR006 | BI20: =VLOOKUP(BH20,$BE$2:$BF$11,2,FALSE) -> 162.3 | BK20: CUST0019 | BL20: =IF(COUNTIF(BK:BK,BK20)>0,"Exists","Does Not Exists") -> Exists | BN20: Oct | BO20: 502 | BP20: 103 | BV20: Feb | BW20: 87.32
A21: SECTION C — TEXT FUNCTIONS | I21: 702 | J21: {=_xlfn.IFS(I21>=750,"Low Risk",AND(I21>=650,I21<=749),"Medium Risk",I21<650,"High Risk")} -> Medium Risk | L21: 698.25 | M21: 590.41 | N21: =IF(M21>=L21,"Yes","No") -> No | P21: 37.19 | Q21: =IF(ISBLANK(P21),"missing","Available") -> Available | S21: 753.66 | T21: 744.73 | U21: {=_xlfn.IFS(T21>S21,"Surplus",T21<S21,"Deficit")} -> Deficit | Y21: TXN00020 | Z21: BR008 | AA21: =VLOOKUP(Z21,$W$2:$X$11,2,FALSE) -> Kavita Rath | AB21: 75.56 | AC21: Self-Employed | AD21: 17.1 | AG21: TXN00020 | AH21: =RIGHT(AG21,5) -> 00020 | AI21: Female | AJ21: =IF(UPPER(AI21)="M","Male","Female") -> Female | AK21: Suresh Sahoo | AL21: Berhampur | AM21: =_xlfn.CONCAT(AK21,"|",AL21) -> Suresh Sahoo|Berhampur | AO21: Suresh Sahoo | AP21: =IF(LEFT(AO21,1)="R",AO21,"Not True") -> Not True | AU21: Under Review | AV21: =PROPER(TRIM(AU21)) -> Under Review | AY21: CUST0020 | AZ21: Berhampur | BA21: TXN00020 | BB21: CUST0059 | BC21: =VLOOKUP(BB21,$AY$2:$AZ$501,2,FALSE) -> Jharsuguda | BG21: TXN00020 | BH21: BR008 | BI21: =VLOOKUP(BH21,$BE$2:$BF$11,2,FALSE) -> 103.83 | BK21: CUST0020 | BL21: =IF(COUNTIF(BK:BK,BK21)>0,"Exists","Does Not Exists") -> Exists | BN21: Nov | BO21: 367 | BP21: 90 | BV21: Mar | BW21: 89.97
A22: Q14 | B22: Extract the first 4 characters of Customer_ID to verify prefix consistency. Use LEFT. | C22: =LEFT(Customers!A2,4) -> CUST | I22: 845 | J22: {=_xlfn.IFS(I22>=750,"Low Risk",AND(I22>=650,I22<=749),"Medium Risk",I22<650,"High Risk")} -> Low Risk | L22: 752.79 | M22: 770.59 | N22: =IF(M22>=L22,"Yes","No") -> Yes | P22: 75.56 | Q22: =IF(ISBLANK(P22),"missing","Available") -> Available | S22: 698.25 | T22: 590.41 | U22: {=_xlfn.IFS(T22>S22,"Surplus",T22<S22,"Deficit")} -> Deficit | Y22: TXN00021 | Z22: BR002 | AA22: =VLOOKUP(Z22,$W$2:$X$11,2,FALSE) -> Priya Mohanty | AB22: 68.15 | AC22: Self-Employed | AD22: 44.4 | AG22: TXN00021 | AH22: =RIGHT(AG22,5) -> 00021 | AI22: Female | AJ22: =IF(UPPER(AI22)="M","Male","Female") -> Female | AK22: Ravi Rout | AL22: Dhenkanal | AM22: =_xlfn.CONCAT(AK22,"|",AL22) -> Ravi Rout|Dhenkanal | AO22: Ravi Rout | AP22: =IF(LEFT(AO22,1)="R",AO22,"Not True") -> Ravi Rout | AU22: approved | AV22: =PROPER(TRIM(AU22)) -> Approved | AY22: CUST0021 | AZ22: Dhenkanal | BA22: TXN00021 | BB22: CUST0270 | BC22: =VLOOKUP(BB22,$AY$2:$AZ$501,2,FALSE) -> Balasore | BG22: TXN00021 | BH22: BR002 | BI22: =VLOOKUP(BH22,$BE$2:$BF$11,2,FALSE) -> 105.8 | BK22: CUST0021 | BL22: =IF(COUNTIF(BK:BK,BK22)>0,"Exists","Does Not Exists") -> Exists | BN22: Dec | BO22: 306 | BP22: 98 | BV22: Apr | BW22: 85.4
A23: Q15 | B23: Extract the numeric part of Transaction_ID (e.g., TXN00001 → 00001). Use MID or RIGHT. | C23: Done | I23: 788 | J23: {=_xlfn.IFS(I23>=750,"Low Risk",AND(I23>=650,I23<=749),"Medium Risk",I23<650,"High Risk")} -> Low Risk | L23: 480.88 | M23: 365.86 | N23: =IF(M23>=L23,"Yes","No") -> No | P23: 68.15 | Q23: =IF(ISBLANK(P23),"missing","Available") -> Available | S23: 752.79 | T23: 770.59 | U23: {=_xlfn.IFS(T23>S23,"Surplus",T23<S23,"Deficit")} -> Surplus | Y23: TXN00022 | Z23: BR002 | AA23: =VLOOKUP(Z23,$W$2:$X$11,2,FALSE) -> Priya Mohanty | AB23: 70.01 | AC23: retired | AD23: 17.07 | AG23: TXN00022 | AH23: =RIGHT(AG23,5) -> 00022 | AI23: female | AJ23: =IF(UPPER(AI23)="M","Male","Female") -> Female | AK23: Pooja Barik | AL23: Dhenkanal | AM23: =_xlfn.CONCAT(AK23,"|",AL23) -> Pooja Barik|Dhenkanal | AO23: Pooja Barik | AP23: =IF(LEFT(AO23,1)="R",AO23,"Not True") -> Not True | AU23: approved | AV23: =PROPER(TRIM(AU23)) -> Approved | AY23: CUST0022 | AZ23: Dhenkanal | BA23: TXN00022 | BB23: CUST0040 | BC23: =VLOOKUP(BB23,$AY$2:$AZ$501,2,FALSE) -> Cuttack | BG23: TXN00022 | BH23: BR002 | BI23: =VLOOKUP(BH23,$BE$2:$BF$11,2,FALSE) -> 105.8 | BK23: CUST0022 | BL23: =IF(COUNTIF(BK:BK,BK23)>0,"Exists","Does Not Exists") -> Exists | BV23: May | BW23: 83.393333
A24: Q16 | B24: Standardize Gender column (convert M→Male, F→Female, lowercase → proper case). Use IF + UPPER/LOWER. | C24: Done | I24: 853 | J24: {=_xlfn.IFS(I24>=750,"Low Risk",AND(I24>=650,I24<=749),"Medium Risk",I24<650,"High Risk")} -> Low Risk | L24: 671.07 | M24: 715.48 | N24: =IF(M24>=L24,"Yes","No") -> Yes | P24: 70.01 | Q24: =IF(ISBLANK(P24),"missing","Available") -> Available | S24: 480.88 | T24: 365.86 | U24: {=_xlfn.IFS(T24>S24,"Surplus",T24<S24,"Deficit")} -> Deficit | Y24: TXN00023 | Z24: BR004 | AA24: =VLOOKUP(Z24,$W$2:$X$11,2,FALSE) -> Anita Das | AB24: 83.66 | AC24: Self-Employed | AD24: 43.09 | AG24: TXN00023 | AH24: =RIGHT(AG24,5) -> 00023 | AI24: male | AJ24: =IF(UPPER(AI24)="M","Male","Female") -> Female | AK24: Bikash Tripathi | AL24: Sambalpur | AM24: =_xlfn.CONCAT(AK24,"|",AL24) -> Bikash Tripathi|Sambalpur | AO24: Bikash Tripathi | AP24: =IF(LEFT(AO24,1)="R",AO24,"Not True") -> Not True | AU24: Rejected | AV24: =PROPER(TRIM(AU24)) -> Rejected | AY24: CUST0023 | AZ24: Sambalpur | BA24: TXN00023 | BB24: CUST0150 | BC24: =VLOOKUP(BB24,$AY$2:$AZ$501,2,FALSE) -> Rourkela | BG24: TXN00023 | BH24: BR004 | BI24: =VLOOKUP(BH24,$BE$2:$BF$11,2,FALSE) -> 104.66 | BK24: CUST0023 | BL24: =IF(COUNTIF(BK:BK,BK24)>0,"Exists","Does Not Exists") -> Exists | BM24: 37 | BN24: Sum of Loan_Amount_Lakhs | BO24: Loan_Type | BV24: Jun | BW24: 84.383333
A25: Q17 | B25: Combine Customer Name and City as a single label: 'Amit Kumar | Bhubaneswar'. Use CONCAT or &. | C25: Done | I25: 617 | J25: {=_xlfn.IFS(I25>=750,"Low Risk",AND(I25>=650,I25<=749),"Medium Risk",I25<650,"High Risk")} -> High Risk | L25: 595.81 | M25: 541.93 | N25: =IF(M25>=L25,"Yes","No") -> No | P25: 83.66 | Q25: =IF(ISBLANK(P25),"missing","Available") -> Available | S25: 671.07 | T25: 715.48 | U25: {=_xlfn.IFS(T25>S25,"Surplus",T25<S25,"Deficit")} -> Surplus | Y25: TXN00024 | Z25: BR005 | AA25: =VLOOKUP(Z25,$W$2:$X$11,2,FALSE) -> Bikash Nayak | AB25: 48.94 | AC25: Self-Employed | AD25: 15.31 | AG25: TXN00024 | AH25: =RIGHT(AG25,5) -> 00024 | AJ25: =IF(UPPER(AI25)="M","Male","Female") -> Female | AK25: Lata Mishra | AL25: Bhubaneswar | AM25: =_xlfn.CONCAT(AK25,"|",AL25) -> Lata Mishra|Bhubaneswar | AO25: Lata Mishra | AP25: =IF(LEFT(AO25,1)="R",AO25,"Not True") -> Not True | AU25: approved | AV25: =PROPER(TRIM(AU25)) -> Approved | AY25: CUST0024 | AZ25: Bhubaneswar | BA25: TXN00024 | BB25: CUST0068 | BC25: =VLOOKUP(BB25,$AY$2:$AZ$501,2,FALSE) -> Jharsuguda | BG25: TXN00024 | BH25: BR005 | BI25: =VLOOKUP(BH25,$BE$2:$BF$11,2,FALSE) -> 190.31 | BK25: CUST0024 | BL25: =IF(COUNTIF(BK:BK,BK25)>0,"Exists","Does Not Exists") -> Exists | BN25: Approval_Status | BO25: Secured | BP25: Semi-Secured | BQ25: Unsecured | BR25: Grand Total | BV25: Jul | BW25: 77.203333
A26: Q18 | B26: Find all customers whose name starts with 'R'. Use LEFT + IF or FILTER. | C26: Done | I26: 881 | J26: {=_xlfn.IFS(I26>=750,"Low Risk",AND(I26>=650,I26<=749),"Medium Risk",I26<650,"High Risk")} -> Low Risk | L26: 778.81 | M26: 702.41 | N26: =IF(M26>=L26,"Yes","No") -> No | P26: 48.94 | Q26: =IF(ISBLANK(P26),"missing","Available") -> Available | S26: 595.81 | T26: 541.93 | U26: {=_xlfn.IFS(T26>S26,"Surplus",T26<S26,"Deficit")} -> Deficit | Y26: TXN00025 | Z26: BR003 | AA26: =VLOOKUP(Z26,$W$2:$X$11,2,FALSE) -> Suresh Panda | AB26: 12.57 | AC26: Freelancer | AD26: 23.2 | AG26: TXN00025 | AH26: =RIGHT(AG26,5) -> 00025 | AI26: male | AJ26: =IF(UPPER(AI26)="M","Male","Female") -> Female | AK26: Ravi Nayak | AL26: Bhubaneswar | AM26: =_xlfn.CONCAT(AK26,"|",AL26) -> Ravi Nayak|Bhubaneswar | AO26: Ravi Nayak | AP26: =IF(LEFT(AO26,1)="R",AO26,"Not True") -> Ravi Nayak | AU26: Rejected | AV26: =PROPER(TRIM(AU26)) -> Rejected | AY26: CUST0025 | AZ26: Bhubaneswar | BA26: TXN00025 | BB26: CUST0499 | BC26: =VLOOKUP(BB26,$AY$2:$AZ$501,2,FALSE) -> Jharsuguda | BG26: TXN00025 | BH26: BR003 | BI26: =VLOOKUP(BH26,$BE$2:$BF$11,2,FALSE) -> 197.62 | BK26: CUST0025 | BL26: =IF(COUNTIF(BK:BK,BK26)>0,"Exists","Does Not Exists") -> Exists | BN26: approved | BO26: 16898.56 | BP26: 17391.62 | BQ26: 16583.17 | BR26: 50873.35 | BV26: Aug | BW26: 88.843333
A27: Q19 | B27: Count the number of characters in each Branch Name. Use LEN. | C27: Done | I27: 706 | J27: {=_xlfn.IFS(I27>=750,"Low Risk",AND(I27>=650,I27<=749),"Medium Risk",I27<650,"High Risk")} -> Medium Risk | L27: 555.85 | M27: 523.94 | N27: =IF(M27>=L27,"Yes","No") -> No | P27: 12.57 | Q27: =IF(ISBLANK(P27),"missing","Available") -> Available | S27: 778.81 | T27: 702.41 | U27: {=_xlfn.IFS(T27>S27,"Surplus",T27<S27,"Deficit")} -> Deficit | Y27: TXN00026 | Z27: BR009 | AA27: =VLOOKUP(Z27,$W$2:$X$11,2,FALSE) -> Deepak Mishra | AB27: 13.03 | AC27: Freelancer | AD27: 22.1 | AG27: TXN00026 | AH27: =RIGHT(AG27,5) -> 00026 | AI27: female | AJ27: =IF(UPPER(AI27)="M","Male","Female") -> Female | AK27: Rekha Rath | AL27: Cuttack | AM27: =_xlfn.CONCAT(AK27,"|",AL27) -> Rekha Rath|Cuttack | AO27: Rekha Rath | AP27: =IF(LEFT(AO27,1)="R",AO27,"Not True") -> Rekha Rath | AU27: Rejected | AV27: =PROPER(TRIM(AU27)) -> Rejected | AY27: CUST0026 | AZ27: Cuttack | BA27: TXN00026 | BB27: CUST0230 | BC27: =VLOOKUP(BB27,$AY$2:$AZ$501,2,FALSE) -> Cuttack | BG27: TXN00026 | BH27: BR009 | BI27: =VLOOKUP(BH27,$BE$2:$BF$11,2,FALSE) -> 144.98 | BK27: CUST0026 | BL27: =IF(COUNTIF(BK:BK,BK27)>0,"Exists","Does Not Exists") -> Exists | BN27: Rejected | BO27: 4882.78 | BP27: 5518.21 | BQ27: 5247.12 | BR27: 15648.11 | BV27: Sep | BW27: 90.02
A28: Q20 | B28: Trim extra spaces from Approval_Status column and standardize to Proper Case. Use TRIM + PROPER. | C28: Done | I28: 855 | J28: {=_xlfn.IFS(I28>=750,"Low Risk",AND(I28>=650,I28<=749),"Medium Risk",I28<650,"High Risk")} -> Low Risk | L28: 451.01 | M28: 392.3 | N28: =IF(M28>=L28,"Yes","No") -> No | P28: 13.03 | Q28: =IF(ISBLANK(P28),"missing","Available") -> Available | S28: 555.85 | T28: 523.94 | U28: {=_xlfn.IFS(T28>S28,"Surplus",T28<S28,"Deficit")} -> Deficit | Y28: TXN00027 | Z28: BR005 | AA28: =VLOOKUP(Z28,$W$2:$X$11,2,FALSE) -> Bikash Nayak | AB28: 67.02 | AC28: Government Employee | AD28: 43.61 | AG28: TXN00027 | AH28: =RIGHT(AG28,5) -> 00027 | AI28: Male | AJ28: =IF(UPPER(AI28)="M","Male","Female") -> Female | AK28: Dilip Patnaik | AL28: Rourkela | AM28: =_xlfn.CONCAT(AK28,"|",AL28) -> Dilip Patnaik|Rourkela | AO28: Dilip Patnaik | AP28: =IF(LEFT(AO28,1)="R",AO28,"Not True") -> Not True | AU28: Rejected | AV28: =PROPER(TRIM(AU28)) -> Rejected | AY28: CUST0027 | AZ28: Rourkela | BA28: TXN00027 | BB28: CUST0332 | BC28: =VLOOKUP(BB28,$AY$2:$AZ$501,2,FALSE) -> Puri | BG28: TXN00027 | BH28: BR005 | BI28: =VLOOKUP(BH28,$BE$2:$BF$11,2,FALSE) -> 190.31 | BK28: CUST0027 | BL28: =IF(COUNTIF(BK:BK,BK28)>0,"Exists","Does Not Exists") -> Exists | BN28: Rejected | BO28: 5642.46 | BP28: 4777.99 | BQ28: 5365.61 | BR28: 15786.06 | BV28: Oct | BW28: 85.736667
I29: 740 | J29: {=_xlfn.IFS(I29>=750,"Low Risk",AND(I29>=650,I29<=749),"Medium Risk",I29<650,"High Risk")} -> Medium Risk | L29: 656.67 | M29: 553.88 | N29: =IF(M29>=L29,"Yes","No") -> No | P29: 67.02 | Q29: =IF(ISBLANK(P29),"missing","Available") -> Available | S29: 451.01 | T29: 392.3 | U29: {=_xlfn.IFS(T29>S29,"Surplus",T29<S29,"Deficit")} -> Deficit | Y29: TXN00028 | Z29: BR002 | AA29: =VLOOKUP(Z29,$W$2:$X$11,2,FALSE) -> Priya Mohanty | AB29: 62.13 | AC29: Business Owner | AD29: 40.38 | AG29: TXN00028 | AH29: =RIGHT(AG29,5) -> 00028 | AI29: Female | AJ29: =IF(UPPER(AI29)="M","Male","Female") -> Female | AK29: Sita Dash | AL29: Sambalpur | AM29: =_xlfn.CONCAT(AK29,"|",AL29) -> Sita Dash|Sambalpur | AO29: Sita Dash | AP29: =IF(LEFT(AO29,1)="R",AO29,"Not True") -> Not True | AU29: approved | AV29: =PROPER(TRIM(AU29)) -> Approved | AY29: CUST0028 | AZ29: Sambalpur | BA29: TXN00028 | BB29: CUST0283 | BC29: =VLOOKUP(BB29,$AY$2:$AZ$501,2,FALSE) -> Balasore | BG29: TXN00028 | BH29: BR002 | BI29: =VLOOKUP(BH29,$BE$2:$BF$11,2,FALSE) -> 105.8 | BK29: CUST0028 | BL29: =IF(COUNTIF(BK:BK,BK29)>0,"Exists","Does Not Exists") -> Exists | BN29: Under Review | BO29: 7041.7 | BP29: 5788.78 | BQ29: 5755.45 | BR29: 18585.93 | BV29: Nov | BW29: 87.373333
A30: SECTION D — DATE FUNCTIONS | I30: 891 | J30: {=_xlfn.IFS(I30>=750,"Low Risk",AND(I30>=650,I30<=749),"Medium Risk",I30<650,"High Risk")} -> Low Risk | L30: 647.49 | M30: 701.48 | N30: =IF(M30>=L30,"Yes","No") -> Yes | P30: 62.13 | Q30: =IF(ISBLANK(P30),"missing","Available") -> Available | S30: 656.67 | T30: 553.88 | U30: {=_xlfn.IFS(T30>S30,"Surplus",T30<S30,"Deficit")} -> Deficit | Y30: TXN00029 | Z30: BR008 | AA30: =VLOOKUP(Z30,$W$2:$X$11,2,FALSE) -> Kavita Rath | AB30: 20.25 | AC30: Government Employee | AD30: 42.65 | AG30: TXN00029 | AH30: =RIGHT(AG30,5) -> 00029 | AI30: M | AJ30: =IF(UPPER(AI30)="M","Male","Female") -> Male | AK30: Sita Das | AL30: Puri | AM30: =_xlfn.CONCAT(AK30,"|",AL30) -> Sita Das|Puri | AO30: Sita Das | AP30: =IF(LEFT(AO30,1)="R",AO30,"Not True") -> Not True | AU30: Rejected | AV30: =PROPER(TRIM(AU30)) -> Rejected | AY30: CUST0029 | AZ30: Puri | BA30: TXN00029 | BB30: CUST0276 | BC30: =VLOOKUP(BB30,$AY$2:$AZ$501,2,FALSE) -> Angul | BG30: TXN00029 | BH30: BR008 | BI30: =VLOOKUP(BH30,$BE$2:$BF$11,2,FALSE) -> 103.83 | BK30: CUST0029 | BL30: =IF(COUNTIF(BK:BK,BK30)>0,"Exists","Does Not Exists") -> Exists | BV30: Dec | BW30: 84.78
A31: Q21 | B31: Calculate how many days have elapsed since each transaction date. Use TODAY() - Transaction_Date. | C31: Done | I31: 639 | J31: {=_xlfn.IFS(I31>=750,"Low Risk",AND(I31>=650,I31<=749),"Medium Risk",I31<650,"High Risk")} -> High Risk | L31: 486.09 | M31: 558.06 | N31: =IF(M31>=L31,"Yes","No") -> Yes | P31: 20.25 | Q31: =IF(ISBLANK(P31),"missing","Available") -> Available | S31: 647.49 | T31: 701.48 | U31: {=_xlfn.IFS(T31>S31,"Surplus",T31<S31,"Deficit")} -> Surplus | Y31: TXN00030 | Z31: BR005 | AA31: =VLOOKUP(Z31,$W$2:$X$11,2,FALSE) -> Bikash Nayak | AB31: 22.35 | AC31: Business Owner | AD31: 17.74 | AG31: TXN00030 | AH31: =RIGHT(AG31,5) -> 00030 | AI31: Male | AJ31: =IF(UPPER(AI31)="M","Male","Female") -> Female | AK31: Bikash Mohanty | AL31: Jharsuguda | AM31: =_xlfn.CONCAT(AK31,"|",AL31) -> Bikash Mohanty|Jharsuguda | AO31: Bikash Mohanty | AP31: =IF(LEFT(AO31,1)="R",AO31,"Not True") -> Not True | AU31: Rejected | AV31: =PROPER(TRIM(AU31)) -> Rejected | AY31: CUST0030 | AZ31: Jharsuguda | BA31: TXN00030 | BB31: CUST0180 | BC31: =VLOOKUP(BB31,$AY$2:$AZ$501,2,FALSE) -> Dhenkanal | BG31: TXN00030 | BH31: BR005 | BI31: =VLOOKUP(BH31,$BE$2:$BF$11,2,FALSE) -> 190.31 | BK31: CUST0030 | BL31: =IF(COUNTIF(BK:BK,BK31)>0,"Exists","Does Not Exists") -> Exists
A32: Q22 | B32: Extract the Month and Year from Transaction_Date. Use MONTH() and YEAR(). | C32: Done | I32: 830 | J32: {=_xlfn.IFS(I32>=750,"Low Risk",AND(I32>=650,I32<=749),"Medium Risk",I32<650,"High Risk")} -> Low Risk | L32: 488.42 | M32: 568.29 | N32: =IF(M32>=L32,"Yes","No") -> Yes | P32: 22.35 | Q32: =IF(ISBLANK(P32),"missing","Available") -> Available | S32: 486.09 | T32: 558.06 | U32: {=_xlfn.IFS(T32>S32,"Surplus",T32<S32,"Deficit")} -> Surplus | Y32: TXN00031 | Z32: BR002 | AA32: =VLOOKUP(Z32,$W$2:$X$11,2,FALSE) -> Priya Mohanty | AB32: 47.99 | AC32: retired | AD32: 37.87 | AG32: TXN00031 | AH32: =RIGHT(AG32,5) -> 00031 | AI32: Male | AJ32: =IF(UPPER(AI32)="M","Male","Female") -> Female | AK32: Priya Patnaik | AL32: Dhenkanal | AM32: =_xlfn.CONCAT(AK32,"|",AL32) -> Priya Patnaik|Dhenkanal | AO32: Priya Patnaik | AP32: =IF(LEFT(AO32,1)="R",AO32,"Not True") -> Not True | AU32: approved | AV32: =PROPER(TRIM(AU32)) -> Approved | AY32: CUST0031 | AZ32: Dhenkanal | BA32: TXN00031 | BB32: CUST0307 | BC32: =VLOOKUP(BB32,$AY$2:$AZ$501,2,FALSE) -> Berhampur | BG32: TXN00031 | BH32: BR002 | BI32: =VLOOKUP(BH32,$BE$2:$BF$11,2,FALSE) -> 105.8 | BK32: CUST0031 | BL32: =IF(COUNTIF(BK:BK,BK32)>0,"Exists","Does Not Exists") -> Exists | BM32: 35 | BN32: Count of Transaction_ID | BO32: Payment_Status | BV32: Branch_Name | BX32: (35)Create a Pivot Table: Payment Status distribution by Branch. Which branch has most Defaulted loans? | BY32: 37 | BZ32: Sum of Loan_Amount_Lakhs | CA32: Loan_Type
A33: Q23 | B33: Calculate Loan Tenure completion % based on Transaction_Date and today. Use DATEDIF. | I33: 578 | J33: {=_xlfn.IFS(I33>=750,"Low Risk",AND(I33>=650,I33<=749),"Medium Risk",I33<650,"High Risk")} -> High Risk | L33: 626.94 | M33: 692.38 | N33: =IF(M33>=L33,"Yes","No") -> Yes | P33: 47.99 | Q33: =IF(ISBLANK(P33),"missing","Available") -> Available | S33: 488.42 | T33: 568.29 | U33: {=_xlfn.IFS(T33>S33,"Surplus",T33<S33,"Deficit")} -> Surplus | Y33: TXN00032 | Z33: BR008 | AA33: =VLOOKUP(Z33,$W$2:$X$11,2,FALSE) -> Kavita Rath | AB33: 19.41 | AC33: Business Owner | AD33: 18.33 | AG33: TXN00032 | AH33: =RIGHT(AG33,5) -> 00032 | AI33: female | AJ33: =IF(UPPER(AI33)="M","Male","Female") -> Female | AK33: Rekha Panda | AL33: Berhampur | AM33: =_xlfn.CONCAT(AK33,"|",AL33) -> Rekha Panda|Berhampur | AO33: Rekha Panda | AP33: =IF(LEFT(AO33,1)="R",AO33,"Not True") -> Rekha Panda | AU33: Under Review | AV33: =PROPER(TRIM(AU33)) -> Under Review | AY33: CUST0032 | AZ33: Berhampur | BA33: TXN00032 | BB33: CUST0285 | BC33: =VLOOKUP(BB33,$AY$2:$AZ$501,2,FALSE) -> Sambalpur | BG33: TXN00032 | BH33: BR008 | BI33: =VLOOKUP(BH33,$BE$2:$BF$11,2,FALSE) -> 103.83 | BK33: CUST0032 | BL33: =IF(COUNTIF(BK:BK,BK33)>0,"Exists","Does Not Exists") -> Exists | BN33: Branch_ID | BO33: Defaulted | BP33: Overdue | BQ33: Paid | BR33: Partially Paid | BS33: Pending | BT33: Grand Total | BV33: Bhubaneswar Main | BX33: =INDEX(BV33:BV42,MATCH(MAX(BO34:BO43),BO34:BO43,0)) -> Dhenkanal Rural | BZ33: Approval_Status | CA33: Secured | CB33: Semi-Secured | CC33: Unsecured | CD33: Grand Total
A34: Q24 | B34: Find all transactions that occurred in Q4 (Oct–Dec) of any year. Use MONTH(). | C34: Done | I34: 657 | J34: {=_xlfn.IFS(I34>=750,"Low Risk",AND(I34>=650,I34<=749),"Medium Risk",I34<650,"High Risk")} -> Medium Risk | L34: 433.71 | M34: 469.59 | N34: =IF(M34>=L34,"Yes","No") -> Yes | P34: 19.41 | Q34: =IF(ISBLANK(P34),"missing","Available") -> Available | S34: 626.94 | T34: 692.38 | U34: {=_xlfn.IFS(T34>S34,"Surplus",T34<S34,"Deficit")} -> Surplus | Y34: TXN00033 | Z34: BR003 | AA34: =VLOOKUP(Z34,$W$2:$X$11,2,FALSE) -> Suresh Panda | AB34: 83.59 | AC34: Government Employee | AD34: 3.02 | AG34: TXN00033 | AH34: =RIGHT(AG34,5) -> 00033 | AI34: male | AJ34: =IF(UPPER(AI34)="M","Male","Female") -> Female | AK34: Rekha Sahu | AL34: Jharsuguda | AM34: =_xlfn.CONCAT(AK34,"|",AL34) -> Rekha Sahu|Jharsuguda | AO34: Rekha Sahu | AP34: =IF(LEFT(AO34,1)="R",AO34,"Not True") -> Rekha Sahu | AU34: approved | AV34: =PROPER(TRIM(AU34)) -> Approved | AY34: CUST0033 | AZ34: Jharsuguda | BA34: TXN00033 | BB34: CUST0002 | BC34: =VLOOKUP(BB34,$AY$2:$AZ$501,2,FALSE) -> Balasore | BG34: TXN00033 | BH34: BR003 | BI34: =VLOOKUP(BH34,$BE$2:$BF$11,2,FALSE) -> 197.62 | BK34: CUST0033 | BL34: =IF(COUNTIF(BK:BK,BK34)>0,"Exists","Does Not Exists") -> Exists | BN34: BR001 | BO34: 42 | BP34: 36 | BQ34: 47 | BR34: 37 | BS34: 34 | BT34: 196 | BV34: Cuttack Central | BZ34: approved | CA34: 16898.56 | CB34: 17391.62 | CC34: 16583.17 | CD34: 50873.35
A35: Q25 | B35: Calculate the number of working days between Transaction_Date and Disbursal_Date. Use NETWORKDAYS. | C35: Done | I35: 573 | J35: {=_xlfn.IFS(I35>=750,"Low Risk",AND(I35>=650,I35<=749),"Medium Risk",I35<650,"High Risk")} -> High Risk | L35: 661.38 | M35: 696.33 | N35: =IF(M35>=L35,"Yes","No") -> Yes | P35: 83.59 | Q35: =IF(ISBLANK(P35),"missing","Available") -> Available | S35: 433.71 | T35: 469.59 | U35: {=_xlfn.IFS(T35>S35,"Surplus",T35<S35,"Deficit")} -> Surplus | Y35: TXN00034 | Z35: BR010 | AA35: =VLOOKUP(Z35,$W$2:$X$11,2,FALSE) -> Pooja Tripathi | AB35: 56.99 | AC35: Freelancer | AD35: 45.36 | AG35: TXN00034 | AH35: =RIGHT(AG35,5) -> 00034 | AI35: F | AJ35: =IF(UPPER(AI35)="M","Male","Female") -> Female | AK35: Arjun Sethi | AL35: Bhubaneswar | AM35: =_xlfn.CONCAT(AK35,"|",AL35) -> Arjun Sethi|Bhubaneswar | AO35: Arjun Sethi | AP35: =IF(LEFT(AO35,1)="R",AO35,"Not True") -> Not True | AU35: approved | AV35: =PROPER(TRIM(AU35)) -> Approved | AY35: CUST0034 | AZ35: Bhubaneswar | BA35: TXN00034 | BB35: CUST0035 | BC35: =VLOOKUP(BB35,$AY$2:$AZ$501,2,FALSE) -> Cuttack | BG35: TXN00034 | BH35: BR010 | BI35: =VLOOKUP(BH35,$BE$2:$BF$11,2,FALSE) -> 251.78 | BK35: CUST0034 | BL35: =IF(COUNTIF(BK:BK,BK35)>0,"Exists","Does Not Exists") -> Exists | BN35: BR002 | BO35: 35 | BP35: 32 | BQ35: 43 | BR35: 46 | BS35: 36 | BT35: 192 | BV35: Rourkela Industrial | BZ35: Rejected | CA35: 4882.78 | CB35: 5518.21 | CC35: 5247.12 | CD35: 15648.11
A36: Q26 | B36: Find customer Joining_Date in Customers sheet and calculate how many years they have been a customer. Use DATEDIF. | I36: 841 | J36: {=_xlfn.IFS(I36>=750,"Low Risk",AND(I36>=650,I36<=749),"Medium Risk",I36<650,"High Risk")} -> Low Risk | L36: 500.47 | M36: 423.91 | N36: =IF(M36>=L36,"Yes","No") -> No | P36: 56.99 | Q36: =IF(ISBLANK(P36),"missing","Available") -> Available | S36: 661.38 | T36: 696.33 | U36: {=_xlfn.IFS(T36>S36,"Surplus",T36<S36,"Deficit")} -> Surplus | Y36: TXN00035 | Z36: BR003 | AA36: =VLOOKUP(Z36,$W$2:$X$11,2,FALSE) -> Suresh Panda | AB36: 27.99 | AC36: retired | AD36: 40.91 | AG36: TXN00035 | AH36: =RIGHT(AG36,5) -> 00035 | AI36: M | AJ36: =IF(UPPER(AI36)="M","Male","Female") -> Male | AK36: Manoj Barik | AL36: Cuttack | AM36: =_xlfn.CONCAT(AK36,"|",AL36) -> Manoj Barik|Cuttack | AO36: Manoj Barik | AP36: =IF(LEFT(AO36,1)="R",AO36,"Not True") -> Not True | AU36: approved | AV36: =PROPER(TRIM(AU36)) -> Approved | AY36: CUST0035 | AZ36: Cuttack | BA36: TXN00035 | BB36: CUST0237 | BC36: =VLOOKUP(BB36,$AY$2:$AZ$501,2,FALSE) -> Dhenkanal | BG36: TXN00035 | BH36: BR003 | BI36: =VLOOKUP(BH36,$BE$2:$BF$11,2,FALSE) -> 197.62 | BK36: CUST0035 | BL36: =IF(COUNTIF(BK:BK,BK36)>0,"Exists","Does Not Exists") -> Exists | BN36: BR003 | BO36: 34 | BP36: 52 | BQ36: 49 | BR36: 44 | BS36: 44 | BT36: 223 | BV36: Puri Tourism | BZ36: Rejected | CA36: 5642.46 | CB36: 4777.99 | CC36: 5365.61 | CD36: 15786.06
I37: 830 | J37: {=_xlfn.IFS(I37>=750,"Low Risk",AND(I37>=650,I37<=749),"Medium Risk",I37<650,"High Risk")} -> Low Risk | L37: 567.36 | M37: 449.24 | N37: =IF(M37>=L37,"Yes","No") -> No | P37: 27.99 | Q37: =IF(ISBLANK(P37),"missing","Available") -> Available | S37: 500.47 | T37: 423.91 | U37: {=_xlfn.IFS(T37>S37,"Surplus",T37<S37,"Deficit")} -> Deficit | Y37: TXN00036 | Z37: BR003 | AA37: =VLOOKUP(Z37,$W$2:$X$11,2,FALSE) -> Suresh Panda | AB37: 82.86 | AC37: retired | AD37: 26.24 | AG37: TXN00036 | AH37: =RIGHT(AG37,5) -> 00036 | AI37: female | AJ37: =IF(UPPER(AI37)="M","Male","Female") -> Female | AK37: Arjun Patnaik | AL37: Jharsuguda | AM37: =_xlfn.CONCAT(AK37,"|",AL37) -> Arjun Patnaik|Jharsuguda | AO37: Arjun Patnaik | AP37: =IF(LEFT(AO37,1)="R",AO37,"Not True") -> Not True | AU37: approved | AV37: =PROPER(TRIM(AU37)) -> Approved | AY37: CUST0036 | AZ37: Jharsuguda | BA37: TXN00036 | BB37: CUST0307 | BC37: =VLOOKUP(BB37,$AY$2:$AZ$501,2,FALSE) -> Berhampur | BG37: TXN00036 | BH37: BR003 | BI37: =VLOOKUP(BH37,$BE$2:$BF$11,2,FALSE) -> 197.62 | BK37: CUST0036 | BL37: =IF(COUNTIF(BK:BK,BK37)>0,"Exists","Does Not Exists") -> Exists | BN37: BR004 | BO37: 39 | BP37: 40 | BQ37: 32 | BR37: 40 | BS37: 32 | BT37: 183 | BV37: Sambalpur Regional | BZ37: Under Review | CA37: 7041.7 | CB37: 5788.78 | CC37: 5755.45 | CD37: 18585.93
A38: SECTION E — LOOKUP FUNCTIONS | I38: 704 | J38: {=_xlfn.IFS(I38>=750,"Low Risk",AND(I38>=650,I38<=749),"Medium Risk",I38<650,"High Risk")} -> Medium Risk | P38: 82.86 | Q38: =IF(ISBLANK(P38),"missing","Available") -> Available | S38: 567.36 | T38: 449.24 | U38: {=_xlfn.IFS(T38>S38,"Surplus",T38<S38,"Deficit")} -> Deficit | Y38: TXN00037 | Z38: BR006 | AA38: =VLOOKUP(Z38,$W$2:$X$11,2,FALSE) -> Sunita Sahu | AB38: 92.17 | AC38: Self-Employed | AD38: 8.7 | AG38: TXN00037 | AH38: =RIGHT(AG38,5) -> 00037 | AI38: F | AJ38: =IF(UPPER(AI38)="M","Male","Female") -> Female | AK38: Kavita Swain | AL38: Bhubaneswar | AM38: =_xlfn.CONCAT(AK38,"|",AL38) -> Kavita Swain|Bhubaneswar | AO38: Kavita Swain | AP38: =IF(LEFT(AO38,1)="R",AO38,"Not True") -> Not True | AU38: approved | AV38: =PROPER(TRIM(AU38)) -> Approved | AY38: CUST0037 | AZ38: Bhubaneswar | BA38: TXN00037 | BB38: CUST0145 | BC38: =VLOOKUP(BB38,$AY$2:$AZ$501,2,FALSE) -> Jharsuguda | BG38: TXN00037 | BH38: BR006 | BI38: =VLOOKUP(BH38,$BE$2:$BF$11,2,FALSE) -> 162.3 | BK38: CUST0037 | BL38: =IF(COUNTIF(BK:BK,BK38)>0,"Exists","Does Not Exists") -> Exists | BN38: BR005 | BO38: 31 | BP38: 39 | BQ38: 43 | BR38: 35 | BS38: 39 | BT38: 187 | BV38: Berhampur South | BZ38: Grand Total | CA38: 34465.5 | CB38: 33476.6 | CC38: 32951.35 | CD38: 100893.45
A39: Q27 | B39: For each Transaction, fetch the Customer's City using VLOOKUP (from Customers sheet). | C39: Done | I39: 702 | J39: {=_xlfn.IFS(I39>=750,"Low Risk",AND(I39>=650,I39<=749),"Medium Risk",I39<650,"High Risk")} -> Medium Risk | P39: 92.17 | Q39: =IF(ISBLANK(P39),"missing","Available") -> Available | Y39: TXN00038 | Z39: BR007 | AA39: =VLOOKUP(Z39,$W$2:$X$11,2,FALSE) -> Ramesh Behera | AB39: 82.07 | AC39: Government Employee | AD39: 28.75 | AG39: TXN00038 | AH39: =RIGHT(AG39,5) -> 00038 | AI39: male | AJ39: =IF(UPPER(AI39)="M","Male","Female") -> Female | AK39: Prakash Sethi | AL39: Cuttack | AM39: =_xlfn.CONCAT(AK39,"|",AL39) -> Prakash Sethi|Cuttack | AO39: Prakash Sethi | AP39: =IF(LEFT(AO39,1)="R",AO39,"Not True") -> Not True | AU39: approved | AV39: =PROPER(TRIM(AU39)) -> Approved | AY39: CUST0038 | AZ39: Cuttack | BA39: TXN00038 | BB39: CUST0059 | BC39: =VLOOKUP(BB39,$AY$2:$AZ$501,2,FALSE) -> Jharsuguda | BG39: TXN00038 | BH39: BR007 | BI39: =VLOOKUP(BH39,$BE$2:$BF$11,2,FALSE) -> 224.53 | BK39: CUST0038 | BL39: =IF(COUNTIF(BK:BK,BK39)>0,"Exists","Does Not Exists") -> Exists | BN39: BR006 | BO39: 29 | BP39: 44 | BQ39: 35 | BR39: 38 | BS39: 40 | BT39: 186 | BV39: Balasore North
A40: Q28 | B40: Fetch Branch Target Revenue for each transaction using XLOOKUP (from Branches sheet). | C40: Done | I40: 837 | J40: {=_xlfn.IFS(I40>=750,"Low Risk",AND(I40>=650,I40<=749),"Medium Risk",I40<650,"High Risk")} -> Low Risk | P40: 82.07 | Q40: =IF(ISBLANK(P40),"missing","Available") -> Available | Y40: TXN00039 | Z40: BR002 | AA40: =VLOOKUP(Z40,$W$2:$X$11,2,FALSE) -> Priya Mohanty | AB40: 15.09 | AC40: Business Owner | AD40: 36.54 | AG40: TXN00039 | AH40: =RIGHT(AG40,5) -> 00039 | AI40: F | AJ40: =IF(UPPER(AI40)="M","Male","Female") -> Female | AK40: Prakash Swain | AL40: Bhubaneswar | AM40: =_xlfn.CONCAT(AK40,"|",AL40) -> Prakash Swain|Bhubaneswar | AO40: Prakash Swain | AP40: =IF(LEFT(AO40,1)="R",AO40,"Not True") -> Not True | AU40: Rejected | AV40: =PROPER(TRIM(AU40)) -> Rejected | AY40: CUST0039 | AZ40: Bhubaneswar | BA40: TXN00039 | BB40: CUST0382 | BC40: =VLOOKUP(BB40,$AY$2:$AZ$501,2,FALSE) -> Rourkela | BG40: TXN00039 | BH40: BR002 | BI40: =VLOOKUP(BH40,$BE$2:$BF$11,2,FALSE) -> 105.8 | BK40: CUST0039 | BL40: =IF(COUNTIF(BK:BK,BK40)>0,"Exists","Does Not Exists") -> Exists | BN40: BR007 | BO40: 34 | BP40: 33 | BQ40: 53 | BR40: 34 | BS40: 43 | BT40: 197 | BV40: Angul Mining
A41: Q29 | B41: Use INDEX-MATCH to find the manager of the branch with the highest Target Revenue. | C41: =INDEX(Branches!C:C,MATCH(MAX(Branches!F:F),Branches!F:F,0)) -> Pooja Tripathi | I41: 618 | J41: {=_xlfn.IFS(I41>=750,"Low Risk",AND(I41>=650,I41<=749),"Medium Risk",I41<650,"High Risk")} -> High Risk | P41: 15.09 | Q41: =IF(ISBLANK(P41),"missing","Available") -> Available | Y41: TXN00040 | Z41: BR004 | AA41: =VLOOKUP(Z41,$W$2:$X$11,2,FALSE) -> Anita Das | AB41: 51.83 | AC41: retired | AD41: 22.5 | AG41: TXN00040 | AH41: =RIGHT(AG41,5) -> 00040 | AI41: F | AJ41: =IF(UPPER(AI41)="M","Male","Female") -> Female | AK41: Rajesh Rath | AL41: Cuttack | AM41: =_xlfn.CONCAT(AK41,"|",AL41) -> Rajesh Rath|Cuttack | AO41: Rajesh Rath | AP41: =IF(LEFT(AO41,1)="R",AO41,"Not True") -> Rajesh Rath | AU41: Rejected | AV41: =PROPER(TRIM(AU41)) -> Rejected | AY41: CUST0040 | AZ41: Cuttack | BA41: TXN00040 | BB41: CUST0022 | BC41: =VLOOKUP(BB41,$AY$2:$AZ$501,2,FALSE) -> Dhenkanal | BG41: TXN00040 | BH41: BR004 | BI41: =VLOOKUP(BH41,$BE$2:$BF$11,2,FALSE) -> 104.66 | BK41: CUST0040 | BL41: =IF(COUNTIF(BK:BK,BK41)>0,"Exists","Does Not Exists") -> Exists | BN41: BR008 | BO41: 33 | BP41: 40 | BQ41: 33 | BR41: 50 | BS41: 42 | BT41: 198 | BV41: Jharsuguda Energy
A42: Q30 | B42: Build a lookup to check if a given Customer_ID exists in the Customers sheet. Use COUNTIF or XLOOKUP with IFERROR. | C42: Done | I42: 877 | J42: {=_xlfn.IFS(I42>=750,"Low Risk",AND(I42>=650,I42<=749),"Medium Risk",I42<650,"High Risk")} -> Low Risk | P42: 51.83 | Q42: =IF(ISBLANK(P42),"missing","Available") -> Available | Y42: TXN00041 | Z42: BR010 | AA42: =VLOOKUP(Z42,$W$2:$X$11,2,FALSE) -> Pooja Tripathi | AB42: 35.8 | AC42: Government Employee | AD42: 47.31 | AG42: TXN00041 | AH42: =RIGHT(AG42,5) -> 00041 | AI42: female | AJ42: =IF(UPPER(AI42)="M","Male","Female") -> Female | AK42: Dilip Mallick | AL42: Bhubaneswar | AM42: =_xlfn.CONCAT(AK42,"|",AL42) -> Dilip Mallick|Bhubaneswar | AO42: Dilip Mallick | AP42: =IF(LEFT(AO42,1)="R",AO42,"Not True") -> Not True | AU42: Rejected | AV42: =PROPER(TRIM(AU42)) -> Rejected | AY42: CUST0041 | AZ42: Bhubaneswar | BA42: TXN00041 | BB42: CUST0106 | BC42: =VLOOKUP(BB42,$AY$2:$AZ$501,2,FALSE) -> Bhubaneswar | BG42: TXN00041 | BH42: BR010 | BI42: =VLOOKUP(BH42,$BE$2:$BF$11,2,FALSE) -> 251.78 | BK42: CUST0041 | BL42: =IF(COUNTIF(BK:BK,BK42)>0,"Exists","Does Not Exists") -> Exists | BN42: BR009 | BO42: 39 | BP42: 42 | BQ42: 46 | BR42: 35 | BS42: 28 | BT42: 190 | BV42: Dhenkanal Rural
A43: Q31 | B43: Use HLOOKUP on the KPI Summary to fetch July 2023 Actual Revenue. | C43: =HLOOKUP("Jul2023",'31'!B1:AK5,5,FALSE) -> 744.73 | I43: 573 | J43: {=_xlfn.IFS(I43>=750,"Low Risk",AND(I43>=650,I43<=749),"Medium Risk",I43<650,"High Risk")} -> High Risk | P43: 35.8 | Q43: =IF(ISBLANK(P43),"missing","Available") -> Available | Y43: TXN00042 | Z43: BR002 | AA43: =VLOOKUP(Z43,$W$2:$X$11,2,FALSE) -> Priya Mohanty | AB43: 22.48 | AC43: Self-Employed | AD43: 25.83 | AG43: TXN00042 | AH43: =RIGHT(AG43,5) -> 00042 | AI43: male | AJ43: =IF(UPPER(AI43)="M","Male","Female") -> Female | AK43: Mamata Rout | AL43: Sambalpur | AM43: =_xlfn.CONCAT(AK43,"|",AL43) -> Mamata Rout|Sambalpur | AO43: Mamata Rout | AP43: =IF(LEFT(AO43,1)="R",AO43,"Not True") -> Not True | AU43: Rejected | AV43: =PROPER(TRIM(AU43)) -> Rejected | AY43: CUST0042 | AZ43: Sambalpur | BA43: TXN00042 | BB43: CUST0035 | BC43: =VLOOKUP(BB43,$AY$2:$AZ$501,2,FALSE) -> Cuttack | BG43: TXN00042 | BH43: BR002 | BI43: =VLOOKUP(BH43,$BE$2:$BF$11,2,FALSE) -> 105.8 | BK43: CUST0042 | BL43: =IF(COUNTIF(BK:BK,BK43)>0,"Exists","Does Not Exists") -> Exists | BN43: BR010 | BO43: 43 | BP43: 35 | BQ43: 30 | BR43: 33 | BS43: 43 | BT43: 184
I44: 859 | J44: {=_xlfn.IFS(I44>=750,"Low Risk",AND(I44>=650,I44<=749),"Medium Risk",I44<650,"High Risk")} -> Low Risk | P44: 22.48 | Q44: =IF(ISBLANK(P44),"missing","Available") -> Available | Y44: TXN00043 | Z44: BR008 | AA44: =VLOOKUP(Z44,$W$2:$X$11,2,FALSE) -> Kavita Rath | AB44: 19.33 | AC44: Government Employee | AD44: 34.16 | AG44: TXN00043 | AH44: =RIGHT(AG44,5) -> 00043 | AI44: male | AJ44: =IF(UPPER(AI44)="M","Male","Female") -> Female | AK44: Mira Nayak | AL44: Dhenkanal | AM44: =_xlfn.CONCAT(AK44,"|",AL44) -> Mira Nayak|Dhenkanal | AO44: Mira Nayak | AP44: =IF(LEFT(AO44,1)="R",AO44,"Not True") -> Not True | AU44: Rejected | AV44: =PROPER(TRIM(AU44)) -> Rejected | AY44: CUST0043 | AZ44: Dhenkanal | BA44: TXN00043 | BB44: CUST0436 | BC44: =VLOOKUP(BB44,$AY$2:$AZ$501,2,FALSE) -> Sambalpur | BG44: TXN00043 | BH44: BR008 | BI44: =VLOOKUP(BH44,$BE$2:$BF$11,2,FALSE) -> 103.83 | BK44: CUST0043 | BL44: =IF(COUNTIF(BK:BK,BK44)>0,"Exists","Does Not Exists") -> Exists
A45: SECTION F — PIVOT TABLES & CHARTS | I45: 895 | J45: {=_xlfn.IFS(I45>=750,"Low Risk",AND(I45>=650,I45<=749),"Medium Risk",I45<650,"High Risk")} -> Low Risk | P45: 19.33 | Q45: =IF(ISBLANK(P45),"missing","Available") -> Available | Y45: TXN00044 | Z45: BR008 | AA45: =VLOOKUP(Z45,$W$2:$X$11,2,FALSE) -> Kavita Rath | AB45: 50.09 | AC45: Business Owner | AD45: 44.34 | AG45: TXN00044 | AH45: =RIGHT(AG45,5) -> 00044 | AI45: M | AJ45: =IF(UPPER(AI45)="M","Male","Female") -> Male | AK45: Bikash Pradhan | AL45: Sambalpur | AM45: =_xlfn.CONCAT(AK45,"|",AL45) -> Bikash Pradhan|Sambalpur | AO45: Bikash Pradhan | AP45: =IF(LEFT(AO45,1)="R",AO45,"Not True") -> Not True | AU45: approved | AV45: =PROPER(TRIM(AU45)) -> Approved | AY45: CUST0044 | AZ45: Sambalpur | BA45: TXN00044 | BB45: CUST0064 | BC45: =VLOOKUP(BB45,$AY$2:$AZ$501,2,FALSE) -> Puri | BG45: TXN00044 | BH45: BR008 | BI45: =VLOOKUP(BH45,$BE$2:$BF$11,2,FALSE) -> 103.83 | BK45: CUST0044 | BL45: =IF(COUNTIF(BK:BK,BK45)>0,"Exists","Does Not Exists") -> Exists
A46: Q32 | B46: Create a Pivot Table showing: Rows = Region, Columns = Loan Product, Values = Sum of Loan Amount. | C46: Done | I46: 703 | J46: {=_xlfn.IFS(I46>=750,"Low Risk",AND(I46>=650,I46<=749),"Medium Risk",I46<650,"High Risk")} -> Medium Risk | P46: 50.09 | Q46: =IF(ISBLANK(P46),"missing","Available") -> Available | Y46: TXN00045 | Z46: BR008 | AA46: =VLOOKUP(Z46,$W$2:$X$11,2,FALSE) -> Kavita Rath | AB46: 29.77 | AC46: retired | AD46: 47.99 | AG46: TXN00045 | AH46: =RIGHT(AG46,5) -> 00045 | AI46: Male | AJ46: =IF(UPPER(AI46)="M","Male","Female") -> Female | AK46: Mamata Rout | AL46: Puri | AM46: =_xlfn.CONCAT(AK46,"|",AL46) -> Mamata Rout|Puri | AO46: Mamata Rout | AP46: =IF(LEFT(AO46,1)="R",AO46,"Not True") -> Not True | AU46: Rejected | AV46: =PROPER(TRIM(AU46)) -> Rejected | AY46: CUST0045 | AZ46: Puri | BA46: TXN00045 | BB46: CUST0500 | BC46: =VLOOKUP(BB46,$AY$2:$AZ$501,2,FALSE) -> Bhubaneswar | BG46: TXN00045 | BH46: BR008 | BI46: =VLOOKUP(BH46,$BE$2:$BF$11,2,FALSE) -> 103.83 | BK46: CUST0045 | BL46: =IF(COUNTIF(BK:BK,BK46)>0,"Exists","Does Not Exists") -> Exists
A47: Q33 | B47: Build a Pivot Table: Monthly Loan Approvals vs Rejections trend (from KPI sheet). | C47: Done | I47: 677 | J47: {=_xlfn.IFS(I47>=750,"Low Risk",AND(I47>=650,I47<=749),"Medium Risk",I47<650,"High Risk")} -> Medium Risk | P47: 29.77 | Q47: =IF(ISBLANK(P47),"missing","Available") -> Available | Y47: TXN00046 | Z47: BR009 | AA47: =VLOOKUP(Z47,$W$2:$X$11,2,FALSE) -> Deepak Mishra | AB47: 40.09 | AC47: retired | AD47: 47.54 | AG47: TXN00046 | AH47: =RIGHT(AG47,5) -> 00046 | AI47: Female | AJ47: =IF(UPPER(AI47)="M","Male","Female") -> Female | AK47: Puja Nayak | AL47: Rourkela | AM47: =_xlfn.CONCAT(AK47,"|",AL47) -> Puja Nayak|Rourkela | AO47: Puja Nayak | AP47: =IF(LEFT(AO47,1)="R",AO47,"Not True") -> Not True | AU47: Under Review | AV47: =PROPER(TRIM(AU47)) -> Under Review | AY47: CUST0046 | AZ47: Rourkela | BA47: TXN00046 | BB47: CUST0225 | BC47: =VLOOKUP(BB47,$AY$2:$AZ$501,2,FALSE) -> Balasore | BG47: TXN00046 | BH47: BR009 | BI47: =VLOOKUP(BH47,$BE$2:$BF$11,2,FALSE) -> 144.98 | BK47: CUST0046 | BL47: =IF(COUNTIF(BK:BK,BK47)>0,"Exists","Does Not Exists") -> Exists
A48: Q34 | B48: Create a Pivot Chart (Bar/Column) showing Actual vs Target Revenue for each month in 2024. | C48: Done | I48: 887 | J48: {=_xlfn.IFS(I48>=750,"Low Risk",AND(I48>=650,I48<=749),"Medium Risk",I48<650,"High Risk")} -> Low Risk | P48: 40.09 | Q48: =IF(ISBLANK(P48),"missing","Available") -> Available | Y48: TXN00047 | Z48: BR002 | AA48: =VLOOKUP(Z48,$W$2:$X$11,2,FALSE) -> Priya Mohanty | AB48: 50.41 | AC48: Freelancer | AG48: TXN00047 | AH48: =RIGHT(AG48,5) -> 00047 | AI48: Female | AJ48: =IF(UPPER(AI48)="M","Male","Female") -> Female | AK48: Mamata Panda | AL48: Berhampur | AM48: =_xlfn.CONCAT(AK48,"|",AL48) -> Mamata Panda|Berhampur | AO48: Mamata Panda | AP48: =IF(LEFT(AO48,1)="R",AO48,"Not True") -> Not True | AU48: approved | AV48: =PROPER(TRIM(AU48)) -> Approved | AY48: CUST0047 | AZ48: Berhampur | BA48: TXN00047 | BB48: CUST0207 | BC48: =VLOOKUP(BB48,$AY$2:$AZ$501,2,FALSE) -> Cuttack | BG48: TXN00047 | BH48: BR002 | BI48: =VLOOKUP(BH48,$BE$2:$BF$11,2,FALSE) -> 105.8 | BK48: CUST0047 | BL48: =IF(COUNTIF(BK:BK,BK48)>0,"Exists","Does Not Exists") -> Exists
A49: Q35 | B49: Create a Pivot Table: Payment Status distribution by Branch. Which branch has most Defaulted loans? | C49: Done | I49: 806 | J49: {=_xlfn.IFS(I49>=750,"Low Risk",AND(I49>=650,I49<=749),"Medium Risk",I49<650,"High Risk")} -> Low Risk | P49: 50.41 | Q49: =IF(ISBLANK(P49),"missing","Available") -> Available | Y49: TXN00048 | Z49: BR005 | AA49: =VLOOKUP(Z49,$W$2:$X$11,2,FALSE) -> Bikash Nayak | AB49: 63.21 | AC49: Salaried | AD49: 17.17 | AG49: TXN00048 | AH49: =RIGHT(AG49,5) -> 00048 | AI49: male | AJ49: =IF(UPPER(AI49)="M","Male","Female") -> Female | AK49: Suresh Das | AL49: Cuttack | AM49: =_xlfn.CONCAT(AK49,"|",AL49) -> Suresh Das|Cuttack | AO49: Suresh Das | AP49: =IF(LEFT(AO49,1)="R",AO49,"Not True") -> Not True | AU49: Rejected | AV49: =PROPER(TRIM(AU49)) -> Rejected | AY49: CUST0048 | AZ49: Cuttack | BA49: TXN00048 | BB49: CUST0063 | BC49: =VLOOKUP(BB49,$AY$2:$AZ$501,2,FALSE) -> Angul | BG49: TXN00048 | BH49: BR005 | BI49: =VLOOKUP(BH49,$BE$2:$BF$11,2,FALSE) -> 190.31 | BK49: CUST0048 | BL49: =IF(COUNTIF(BK:BK,BK49)>0,"Exists","Does Not Exists") -> Exists
A50: Q36 | B50: Build a Pivot Chart showing Recovery % trend across months (Line Chart). | C50: Done | I50: 726 | J50: {=_xlfn.IFS(I50>=750,"Low Risk",AND(I50>=650,I50<=749),"Medium Risk",I50<650,"High Risk")} -> Medium Risk | P50: 63.21 | Q50: =IF(ISBLANK(P50),"missing","Available") -> Available | Y50: TXN00049 | Z50: BR005 | AA50: =VLOOKUP(Z50,$W$2:$X$11,2,FALSE) -> Bikash Nayak | AB50: 76.26 | AC50: Freelancer | AD50: 3.59 | AG50: TXN00049 | AH50: =RIGHT(AG50,5) -> 00049 | AI50: female | AJ50: =IF(UPPER(AI50)="M","Male","Female") -> Female | AK50: Seema Patnaik | AL50: Puri | AM50: =_xlfn.CONCAT(AK50,"|",AL50) -> Seema Patnaik|Puri | AO50: Seema Patnaik | AP50: =IF(LEFT(AO50,1)="R",AO50,"Not True") -> Not True | AU50: Under Review | AV50: =PROPER(TRIM(AU50)) -> Under Review | AY50: CUST0049 | AZ50: Puri | BA50: TXN00049 | BB50: CUST0079 | BC50: =VLOOKUP(BB50,$AY$2:$AZ$501,2,FALSE) -> Bhubaneswar | BG50: TXN00049 | BH50: BR005 | BI50: =VLOOKUP(BH50,$BE$2:$BF$11,2,FALSE) -> 190.31 | BK50: CUST0049 | BL50: =IF(COUNTIF(BK:BK,BK50)>0,"Exists","Does Not Exists") -> Exists
A51: Q37 | B51: Summarize total loan amount by Loan Type and Approval Status using Pivot Table. | C51: Done | I51: 814 | J51: {=_xlfn.IFS(I51>=750,"Low Risk",AND(I51>=650,I51<=749),"Medium Risk",I51<650,"High Risk")} -> Low Risk | P51: 76.26 | Q51: =IF(ISBLANK(P51),"missing","Available") -> Available | Y51: TXN00050 | Z51: BR009 | AA51: =VLOOKUP(Z51,$W$2:$X$11,2,FALSE) -> Deepak Mishra | AB51: 99.08 | AC51: retired | AD51: 40.99 | AG51: TXN00050 | AH51: =RIGHT(AG51,5) -> 00050 | AI51: F | AJ51: =IF(UPPER(AI51)="M","Male","Female") -> Female | AK51: Ganesh Nayak | AL51: Rourkela | AM51: =_xlfn.CONCAT(AK51,"|",AL51) -> Ganesh Nayak|Rourkela | AO51: Ganesh Nayak | AP51: =IF(LEFT(AO51,1)="R",AO51,"Not True") -> Not True | AU51: approved | AV51: =PROPER(TRIM(AU51)) -> Approved | AY51: CUST0050 | AZ51: Rourkela | BA51: TXN00050 | BB51: CUST0441 | BC51: =VLOOKUP(BB51,$AY$2:$AZ$501,2,FALSE) -> Berhampur | BG51: TXN00050 | BH51: BR009 | BI51: =VLOOKUP(BH51,$BE$2:$BF$11,2,FALSE) -> 144.98 | BK51: CUST0050 | BL51: =IF(COUNTIF(BK:BK,BK51)>0,"Exists","Does Not Exists") -> Exists
I52: 900 | J52: {=_xlfn.IFS(I52>=750,"Low Risk",AND(I52>=650,I52<=749),"Medium Risk",I52<650,"High Risk")} -> Low Risk | P52: 99.08 | Q52: =IF(ISBLANK(P52),"missing","Available") -> Available | Y52: TXN00051 | Z52: BR003 | AA52: =VLOOKUP(Z52,$W$2:$X$11,2,FALSE) -> Suresh Panda | AB52: 31.93 | AC52: Self-Employed | AD52: 29.78 | AG52: TXN00051 | AH52: =RIGHT(AG52,5) -> 00051 | AI52: Male | AJ52: =IF(UPPER(AI52)="M","Male","Female") -> Female | AK52: Sita Rath | AL52: Berhampur | AM52: =_xlfn.CONCAT(AK52,"|",AL52) -> Sita Rath|Berhampur | AO52: Sita Rath | AP52: =IF(LEFT(AO52,1)="R",AO52,"Not True") -> Not True | AU52: approved | AV52: =PROPER(TRIM(AU52)) -> Approved | AY52: CUST0051 | AZ52: Berhampur | BA52: TXN00051 | BB52: CUST0453 | BC52: =VLOOKUP(BB52,$AY$2:$AZ$501,2,FALSE) -> Cuttack | BG52: TXN00051 | BH52: BR003 | BI52: =VLOOKUP(BH52,$BE$2:$BF$11,2,FALSE) -> 197.62 | BK52: CUST0051 | BL52: =IF(COUNTIF(BK:BK,BK52)>0,"Exists","Does Not Exists") -> Exists
A53: SECTION G — DASHBOARD PREPARATION | I53: 897 | J53: {=_xlfn.IFS(I53>=750,"Low Risk",AND(I53>=650,I53<=749),"Medium Risk",I53<650,"High Risk")} -> Low Risk | P53: 31.93 | Q53: =IF(ISBLANK(P53),"missing","Available") -> Available | Y53: TXN00052 | Z53: BR008 | AA53: =VLOOKUP(Z53,$W$2:$X$11,2,FALSE) -> Kavita Rath | AB53: 67.97 | AC53: Freelancer | AD53: 15.98 | AG53: TXN00052 | AH53: =RIGHT(AG53,5) -> 00052 | AI53: M | AJ53: =IF(UPPER(AI53)="M","Male","Female") -> Male | AK53: Suresh Biswal | AL53: Puri | AM53: =_xlfn.CONCAT(AK53,"|",AL53) -> Suresh Biswal|Puri | AO53: Suresh Biswal | AP53: =IF(LEFT(AO53,1)="R",AO53,"Not True") -> Not True | AU53: Under Review | AV53: =PROPER(TRIM(AU53)) -> Under Review | AY53: CUST0052 | AZ53: Puri | BA53: TXN00052 | BB53: CUST0135 | BC53: =VLOOKUP(BB53,$AY$2:$AZ$501,2,FALSE) -> Sambalpur | BG53: TXN00052 | BH53: BR008 | BI53: =VLOOKUP(BH53,$BE$2:$BF$11,2,FALSE) -> 103.83 | BK53: CUST0052 | BL53: =IF(COUNTIF(BK:BK,BK53)>0,"Exists","Does Not Exists") -> Exists
A54: Q38 | B54: Prepare a summary card: Total Loans Disbursed | Total Approved | Total Rejected | Recovery % (use COUNTIF, SUMIF). | C54: Done | I54: 894 | J54: {=_xlfn.IFS(I54>=750,"Low Risk",AND(I54>=650,I54<=749),"Medium Risk",I54<650,"High Risk")} -> Low Risk | P54: 67.97 | Q54: =IF(ISBLANK(P54),"missing","Available") -> Available | Y54: TXN00053 | Z54: BR006 | AA54: =VLOOKUP(Z54,$W$2:$X$11,2,FALSE) -> Sunita Sahu | AB54: 35.17 | AC54: retired | AD54: 24.06 | AG54: TXN00053 | AH54: =RIGHT(AG54,5) -> 00053 | AI54: male | AJ54: =IF(UPPER(AI54)="M","Male","Female") -> Female | AK54: Lata Dash | AL54: Sambalpur | AM54: =_xlfn.CONCAT(AK54,"|",AL54) -> Lata Dash|Sambalpur | AO54: Lata Dash | AP54: =IF(LEFT(AO54,1)="R",AO54,"Not True") -> Not True | AU54: Rejected | AV54: =PROPER(TRIM(AU54)) -> Rejected | AY54: CUST0053 | AZ54: Sambalpur | BA54: TXN00053 | BB54: CUST0321 | BC54: =VLOOKUP(BB54,$AY$2:$AZ$501,2,FALSE) -> Cuttack | BG54: TXN00053 | BH54: BR006 | BI54: =VLOOKUP(BH54,$BE$2:$BF$11,2,FALSE) -> 162.3 | BK54: CUST0053 | BL54: =IF(COUNTIF(BK:BK,BK54)>0,"Exists","Does Not Exists") -> Exists
A55: Q39 | B55: Create a region-wise NPA % comparison chart using Pivot Table data. | C55: Done | I55: 837 | J55: {=_xlfn.IFS(I55>=750,"Low Risk",AND(I55>=650,I55<=749),"Medium Risk",I55<650,"High Risk")} -> Low Risk | P55: 35.17 | Q55: =IF(ISBLANK(P55),"missing","Available") -> Available | Y55: TXN00054 | Z55: BR002 | AA55: =VLOOKUP(Z55,$W$2:$X$11,2,FALSE) -> Priya Mohanty | AB55: 54.3 | AC55: Freelancer | AD55: 49.84 | AG55: TXN00054 | AH55: =RIGHT(AG55,5) -> 00054 | AI55: M | AJ55: =IF(UPPER(AI55)="M","Male","Female") -> Male | AK55: Rekha Mallick | AL55: Angul | AM55: =_xlfn.CONCAT(AK55,"|",AL55) -> Rekha Mallick|Angul | AO55: Rekha Mallick | AP55: =IF(LEFT(AO55,1)="R",AO55,"Not True") -> Rekha Mallick | AU55: Under Review | AV55: =PROPER(TRIM(AU55)) -> Under Review | AY55: CUST0054 | AZ55: Angul | BA55: TXN00054 | BB55: CUST0157 | BC55: =VLOOKUP(BB55,$AY$2:$AZ$501,2,FALSE) -> Jharsuguda | BG55: TXN00054 | BH55: BR002 | BI55: =VLOOKUP(BH55,$BE$2:$BF$11,2,FALSE) -> 105.8 | BK55: CUST0054 | BL55: =IF(COUNTIF(BK:BK,BK55)>0,"Exists","Does Not Exists") -> Exists
A56: Q40 | B56: Design a monthly revenue trend visual (use KPI sheet data). Highlight months where target was not met using conditional formatting. | C56: Done | I56: 719 | J56: {=_xlfn.IFS(I56>=750,"Low Risk",AND(I56>=650,I56<=749),"Medium Risk",I56<650,"High Risk")} -> Medium Risk | P56: 54.3 | Q56: =IF(ISBLANK(P56),"missing","Available") -> Available | Y56: TXN00055 | Z56: BR010 | AA56: =VLOOKUP(Z56,$W$2:$X$11,2,FALSE) -> Pooja Tripathi | AB56: 10.67 | AC56: Salaried | AD56: 47.69 | AG56: TXN00055 | AH56: =RIGHT(AG56,5) -> 00055 | AI56: female | AJ56: =IF(UPPER(AI56)="M","Male","Female") -> Female | AK56: Anita Panda | AL56: Sambalpur | AM56: =_xlfn.CONCAT(AK56,"|",AL56) -> Anita Panda|Sambalpur | AO56: Anita Panda | AP56: =IF(LEFT(AO56,1)="R",AO56,"Not True") -> Not True | AU56: Rejected | AV56: =PROPER(TRIM(AU56)) -> Rejected | AY56: CUST0055 | AZ56: Sambalpur | BA56: TXN00055 | BB56: CUST0194 | BC56: =VLOOKUP(BB56,$AY$2:$AZ$501,2,FALSE) -> Bhubaneswar | BG56: TXN00055 | BH56: BR010 | BI56: =VLOOKUP(BH56,$BE$2:$BF$11,2,FALSE) -> 251.78 | BK56: CUST0055 | BL56: =IF(COUNTIF(BK:BK,BK56)>0,"Exists","Does Not Exists") -> Exists
I57: 654 | J57: {=_xlfn.IFS(I57>=750,"Low Risk",AND(I57>=650,I57<=749),"Medium Risk",I57<650,"High Risk")} -> Medium Risk | P57: 10.67 | Q57: =IF(ISBLANK(P57),"missing","Available") -> Available | Y57: TXN00056 | Z57: BR008 | AA57: =VLOOKUP(Z57,$W$2:$X$11,2,FALSE) -> Kavita Rath | AB57: 29.45 | AC57: Self-Employed | AD57: 19.96 | AG57: TXN00056 | AH57: =RIGHT(AG57,5) -> 00056 | AI57: male | AJ57: =IF(UPPER(AI57)="M","Male","Female") -> Female | AK57: Vijay Swain | AL57: Berhampur | AM57: =_xlfn.CONCAT(AK57,"|",AL57) -> Vijay Swain|Berhampur | AO57: Vijay Swain | AP57: =IF(LEFT(AO57,1)="R",AO57,"Not True") -> Not True | AU57: Rejected | AV57: =PROPER(TRIM(AU57)) -> Rejected | AY57: CUST0056 | AZ57: Berhampur | BA57: TXN00056 | BB57: CUST0104 | BC57: =VLOOKUP(BB57,$AY$2:$AZ$501,2,FALSE) -> Dhenkanal | BG57: TXN00056 | BH57: BR008 | BI57: =VLOOKUP(BH57,$BE$2:$BF$11,2,FALSE) -> 103.83 | BK57: CUST0056 | BL57: =IF(COUNTIF(BK:BK,BK57)>0,"Exists","Does Not Exists") -> Exists
I58: 844 | J58: {=_xlfn.IFS(I58>=750,"Low Risk",AND(I58>=650,I58<=749),"Medium Risk",I58<650,"High Risk")} -> Low Risk | P58: 29.45 | Q58: =IF(ISBLANK(P58),"missing","Available") -> Available | Y58: TXN00057 | Z58: BR002 | AA58: =VLOOKUP(Z58,$W$2:$X$11,2,FALSE) -> Priya Mohanty | AB58: 43.28 | AC58: Salaried | AD58: 25.06 | AG58: TXN00057 | AH58: =RIGHT(AG58,5) -> 00057 | AI58: female | AJ58: =IF(UPPER(AI58)="M","Male","Female") -> Female | AK58: Pooja Nayak | AL58: Angul | AM58: =_xlfn.CONCAT(AK58,"|",AL58) -> Pooja Nayak|Angul | AO58: Pooja Nayak | AP58: =IF(LEFT(AO58,1)="R",AO58,"Not True") -> Not True | AU58: approved | AV58: =PROPER(TRIM(AU58)) -> Approved | AY58: CUST0057 | AZ58: Angul | BA58: TXN00057 | BB58: CUST0140 | BC58: =VLOOKUP(BB58,$AY$2:$AZ$501,2,FALSE) -> Berhampur | BG58: TXN00057 | BH58: BR002 | BI58: =VLOOKUP(BH58,$BE$2:$BF$11,2,FALSE) -> 105.8 | BK58: CUST0057 | BL58: =IF(COUNTIF(BK:BK,BK58)>0,"Exists","Does Not Exists") -> Exists
I59: 719 | J59: {=_xlfn.IFS(I59>=750,"Low Risk",AND(I59>=650,I59<=749),"Medium Risk",I59<650,"High Risk")} -> Medium Risk | P59: 43.28 | Q59: =IF(ISBLANK(P59),"missing","Available") -> Available | Y59: TXN00058 | Z59: BR009 | AA59: =VLOOKUP(Z59,$W$2:$X$11,2,FALSE) -> Deepak Mishra | AB59: 70.63 | AC59: Freelancer | AD59: 5.52 | AG59: TXN00058 | AH59: =RIGHT(AG59,5) -> 00058 | AI59: F | AJ59: =IF(UPPER(AI59)="M","Male","Female") -> Female | AK59: Ashok Das | AL59: Angul | AM59: =_xlfn.CONCAT(AK59,"|",AL59) -> Ashok Das|Angul | AO59: Ashok Das | AP59: =IF(LEFT(AO59,1)="R",AO59,"Not True") -> Not True | AU59: Rejected | AV59: =PROPER(TRIM(AU59)) -> Rejected | AY59: CUST0058 | AZ59: Angul | BA59: TXN00058 | BB59: CUST0344 | BC59: =VLOOKUP(BB59,$AY$2:$AZ$501,2,FALSE) -> Berhampur | BG59: TXN00058 | BH59: BR009 | BI59: =VLOOKUP(BH59,$BE$2:$BF$11,2,FALSE) -> 144.98 | BK59: CUST0058 | BL59: =IF(COUNTIF(BK:BK,BK59)>0,"Exists","Does Not Exists") -> Exists
I60: 767 | J60: {=_xlfn.IFS(I60>=750,"Low Risk",AND(I60>=650,I60<=749),"Medium Risk",I60<650,"High Risk")} -> Low Risk | P60: 70.63 | Q60: =IF(ISBLANK(P60),"missing","Available") -> Available | Y60: TXN00059 | Z60: BR010 | AA60: =VLOOKUP(Z60,$W$2:$X$11,2,FALSE) -> Pooja Tripathi | AB60: 37.06 | AC60: Self-Employed | AD60: 20.88 | AG60: TXN00059 | AH60: =RIGHT(AG60,5) -> 00059 | AI60: male | AJ60: =IF(UPPER(AI60)="M","Male","Female") -> Female | AK60: Seema Patnaik | AL60: Jharsuguda | AM60: =_xlfn.CONCAT(AK60,"|",AL60) -> Seema Patnaik|Jharsuguda | AO60: Seema Patnaik | AP60: =IF(LEFT(AO60,1)="R",AO60,"Not True") -> Not True | AU60: approved | AV60: =PROPER(TRIM(AU60)) -> Approved | AY60: CUST0059 | AZ60: Jharsuguda | BA60: TXN00059 | BB60: CUST0479 | BC60: =VLOOKUP(BB60,$AY$2:$AZ$501,2,FALSE) -> Dhenkanal | BG60: TXN00059 | BH60: BR010 | BI60: =VLOOKUP(BH60,$BE$2:$BF$11,2,FALSE) -> 251.78 | BK60: CUST0059 | BL60: =IF(COUNTIF(BK:BK,BK60)>0,"Exists","Does Not Exists") -> Exists
I61: 713 | J61: {=_xlfn.IFS(I61>=750,"Low Risk",AND(I61>=650,I61<=749),"Medium Risk",I61<650,"High Risk")} -> Medium Risk | P61: 37.06 | Q61: =IF(ISBLANK(P61),"missing","Available") -> Available | Y61: TXN00060 | Z61: BR005 | AA61: =VLOOKUP(Z61,$W$2:$X$11,2,FALSE) -> Bikash Nayak | AB61: 26.39 | AC61: Self-Employed | AD61: 15.44 | AG61: TXN00060 | AH61: =RIGHT(AG61,5) -> 00060 | AI61: male | AJ61: =IF(UPPER(AI61)="M","Male","Female") -> Female | AK61: Puja Mohanty | AL61: Cuttack | AM61: =_xlfn.CONCAT(AK61,"|",AL61) -> Puja Mohanty|Cuttack | AO61: Puja Mohanty | AP61: =IF(LEFT(AO61,1)="R",AO61,"Not True") -> Not True | AU61: Rejected | AV61: =PROPER(TRIM(AU61)) -> Rejected | AY61: CUST0060 | AZ61: Cuttack | BA61: TXN00060 | BB61: CUST0212 | BC61: =VLOOKUP(BB61,$AY$2:$AZ$501,2,FALSE) -> Dhenkanal | BG61: TXN00060 | BH61: BR005 | BI61: =VLOOKUP(BH61,$BE$2:$BF$11,2,FALSE) -> 190.31 | BK61: CUST0060 | BL61: =IF(COUNTIF(BK:BK,BK61)>0,"Exists","Does Not Exists") -> Exists
I62: 699 | J62: {=_xlfn.IFS(I62>=750,"Low Risk",AND(I62>=650,I62<=749),"Medium Risk",I62<650,"High Risk")} -> Medium Risk | P62: 26.39 | Q62: =IF(ISBLANK(P62),"missing","Available") -> Available | Y62: TXN00061 | Z62: BR007 | AA62: =VLOOKUP(Z62,$W$2:$X$11,2,FALSE) -> Ramesh Behera | AB62: 28 | AC62: Business Owner | AD62: 16.54 | AG62: TXN00061 | AH62: =RIGHT(AG62,5) -> 00061 | AI62: female | AJ62: =IF(UPPER(AI62)="M","Male","Female") -> Female | AK62: Lata Sethi | AL62: Jharsuguda | AM62: =_xlfn.CONCAT(AK62,"|",AL62) -> Lata Sethi|Jharsuguda | AO62: Lata Sethi | AP62: =IF(LEFT(AO62,1)="R",AO62,"Not True") -> Not True | AU62: Rejected | AV62: =PROPER(TRIM(AU62)) -> Rejected | AY62: CUST0061 | AZ62: Jharsuguda | BA62: TXN00061 | BB62: CUST0224 | BC62: =VLOOKUP(BB62,$AY$2:$AZ$501,2,FALSE) -> Bhubaneswar | BG62: TXN00061 | BH62: BR007 | BI62: =VLOOKUP(BH62,$BE$2:$BF$11,2,FALSE) -> 224.53 | BK62: CUST0061 | BL62: =IF(COUNTIF(BK:BK,BK62)>0,"Exists","Does Not Exists") -> Exists
I63: 814 | J63: {=_xlfn.IFS(I63>=750,"Low Risk",AND(I63>=650,I63<=749),"Medium Risk",I63<650,"High Risk")} -> Low Risk | P63: 28 | Q63: =IF(ISBLANK(P63),"missing","Available") -> Available | Y63: TXN00062 | Z63: BR002 | AA63: =VLOOKUP(Z63,$W$2:$X$11,2,FALSE) -> Priya Mohanty | AB63: 86.85 | AC63: Self-Employed | AD63: 45.7 | AG63: TXN00062 | AH63: =RIGHT(AG63,5) -> 00062 | AI63: F | AJ63: =IF(UPPER(AI63)="M","Male","Female") -> Female | AK63: Vijay Behera | AL63: Cuttack | AM63: =_xlfn.CONCAT(AK63,"|",AL63) -> Vijay Behera|Cuttack | AO63: Vijay Behera | AP63: =IF(LEFT(AO63,1)="R",AO63,"Not True") -> Not True | AU63: Rejected | AV63: =PROPER(TRIM(AU63)) -> Rejected | AY63: CUST0062 | AZ63: Cuttack | BA63: TXN00062 | BB63: CUST0441 | BC63: =VLOOKUP(BB63,$AY$2:$AZ$501,2,FALSE) -> Berhampur | BG63: TXN00062 | BH63: BR002 | BI63: =VLOOKUP(BH63,$BE$2:$BF$11,2,FALSE) -> 105.8 | BK63: CUST0062 | BL63: =IF(COUNTIF(BK:BK,BK63)>0,"Exists","Does Not Exists") -> Exists
I64: 586 | J64: {=_xlfn.IFS(I64>=750,"Low Risk",AND(I64>=650,I64<=749),"Medium Risk",I64<650,"High Risk")} -> High Risk | P64: 86.85 | Q64: =IF(ISBLANK(P64),"missing","Available") -> Available | Y64: TXN00063 | Z64: BR009 | AA64: =VLOOKUP(Z64,$W$2:$X$11,2,FALSE) -> Deepak Mishra | AB64: 50.15 | AC64: Government Employee | AD64: 35.89 | AG64: TXN00063 | AH64: =RIGHT(AG64,5) -> 00063 | AI64: M | AJ64: =IF(UPPER(AI64)="M","Male","Female") -> Male | AK64: Ashok Mallick | AL64: Angul | AM64: =_xlfn.CONCAT(AK64,"|",AL64) -> Ashok Mallick|Angul | AO64: Ashok Mallick | AP64: =IF(LEFT(AO64,1)="R",AO64,"Not True") -> Not True | AU64: approved | AV64: =PROPER(TRIM(AU64)) -> Approved | AY64: CUST0063 | AZ64: Angul | BA64: TXN00063 | BB64: CUST0062 | BC64: =VLOOKUP(BB64,$AY$2:$AZ$501,2,FALSE) -> Cuttack | BG64: TXN00063 | BH64: BR009 | BI64: =VLOOKUP(BH64,$BE$2:$BF$11,2,FALSE) -> 144.98 | BK64: CUST0063 | BL64: =IF(COUNTIF(BK:BK,BK64)>0,"Exists","Does Not Exists") -> Exists
I65: 759 | J65: {=_xlfn.IFS(I65>=750,"Low Risk",AND(I65>=650,I65<=749),"Medium Risk",I65<650,"High Risk")} -> Low Risk | P65: 50.15 | Q65: =IF(ISBLANK(P65),"missing","Available") -> Available | Y65: TXN00064 | Z65: BR002 | AA65: =VLOOKUP(Z65,$W$2:$X$11,2,FALSE) -> Priya Mohanty | AB65: 44.51 | AC65: Business Owner | AG65: TXN00064 | AH65: =RIGHT(AG65,5) -> 00064 | AI65: female | AJ65: =IF(UPPER(AI65)="M","Male","Female") -> Female | AK65: Priya Patnaik | AL65: Puri | AM65: =_xlfn.CONCAT(AK65,"|",AL65) -> Priya Patnaik|Puri | AO65: Priya Patnaik | AP65: =IF(LEFT(AO65,1)="R",AO65,"Not True") -> Not True | AU65: Under Review | AV65: =PROPER(TRIM(AU65)) -> Under Review | AY65: CUST0064 | AZ65: Puri | BA65: TXN00064 | BB65: CUST0074 | BC65: =VLOOKUP(BB65,$AY$2:$AZ$501,2,FALSE) -> Cuttack | BG65: TXN00064 | BH65: BR002 | BI65: =VLOOKUP(BH65,$BE$2:$BF$11,2,FALSE) -> 105.8 | BK65: CUST0064 | BL65: =IF(COUNTIF(BK:BK,BK65)>0,"Exists","Does Not Exists") -> Exists
I66: 878 | J66: {=_xlfn.IFS(I66>=750,"Low Risk",AND(I66>=650,I66<=749),"Medium Risk",I66<650,"High Risk")} -> Low Risk | P66: 44.51 | Q66: =IF(ISBLANK(P66),"missing","Available") -> Available | Y66: TXN00065 | Z66: BR003 | AA66: =VLOOKUP(Z66,$W$2:$X$11,2,FALSE) -> Suresh Panda | AB66: 37.41 | AC66: Government Employee | AD66: 23.78 | AG66: TXN00065 | AH66: =RIGHT(AG66,5) -> 00065 | AI66: male | AJ66: =IF(UPPER(AI66)="M","Male","Female") -> Female | AK66: Prakash Mishra | AL66: Bhubaneswar | AM66: =_xlfn.CONCAT(AK66,"|",AL66) -> Prakash Mishra|Bhubaneswar | AO66: Prakash Mishra | AP66: =IF(LEFT(AO66,1)="R",AO66,"Not True") -> Not True | AU66: Rejected | AV66: =PROPER(TRIM(AU66)) -> Rejected | AY66: CUST0065 | AZ66: Bhubaneswar | BA66: TXN00065 | BB66: CUST0143 | BC66: =VLOOKUP(BB66,$AY$2:$AZ$501,2,FALSE) -> Dhenkanal | BG66: TXN00065 | BH66: BR003 | BI66: =VLOOKUP(BH66,$BE$2:$BF$11,2,FALSE) -> 197.62 | BK66: CUST0065 | BL66: =IF(COUNTIF(BK:BK,BK66)>0,"Exists","Does Not Exists") -> Exists
I67: 837 | J67: {=_xlfn.IFS(I67>=750,"Low Risk",AND(I67>=650,I67<=749),"Medium Risk",I67<650,"High Risk")} -> Low Risk | P67: 37.41 | Q67: =IF(ISBLANK(P67),"missing","Available") -> Available | Y67: TXN00066 | Z67: BR006 | AA67: =VLOOKUP(Z67,$W$2:$X$11,2,FALSE) -> Sunita Sahu | AB67: 85.91 | AC67: Self-Employed | AD67: 35.6 | AG67: TXN00066 | AH67: =RIGHT(AG67,5) -> 00066 | AI67: M | AJ67: =IF(UPPER(AI67)="M","Male","Female") -> Male | AK67: Meena Patnaik | AL67: Puri | AM67: =_xlfn.CONCAT(AK67,"|",AL67) -> Meena Patnaik|Puri | AO67: Meena Patnaik | AP67: =IF(LEFT(AO67,1)="R",AO67,"Not True") -> Not True | AU67: approved | AV67: =PROPER(TRIM(AU67)) -> Approved | AY67: CUST0066 | AZ67: Puri | BA67: TXN00066 | BB67: CUST0328 | BC67: =VLOOKUP(BB67,$AY$2:$AZ$501,2,FALSE) -> Dhenkanal | BG67: TXN00066 | BH67: BR006 | BI67: =VLOOKUP(BH67,$BE$2:$BF$11,2,FALSE) -> 162.3 | BK67: CUST0066 | BL67: =IF(COUNTIF(BK:BK,BK67)>0,"Exists","Does Not Exists") -> Exists
I68: 703 | J68: {=_xlfn.IFS(I68>=750,"Low Risk",AND(I68>=650,I68<=749),"Medium Risk",I68<650,"High Risk")} -> Medium Risk | P68: 85.91 | Q68: =IF(ISBLANK(P68),"missing","Available") -> Available | Y68: TXN00067 | Z68: BR006 | AA68: =VLOOKUP(Z68,$W$2:$X$11,2,FALSE) -> Sunita Sahu | AB68: 86.78 | AC68: Government Employee | AD68: 41.77 | AG68: TXN00067 | AH68: =RIGHT(AG68,5) -> 00067 | AI68: M | AJ68: =IF(UPPER(AI68)="M","Male","Female") -> Male | AK68: Ravi Sahoo | AL68: Puri | AM68: =_xlfn.CONCAT(AK68,"|",AL68) -> Ravi Sahoo|Puri | AO68: Ravi Sahoo | AP68: =IF(LEFT(AO68,1)="R",AO68,"Not True") -> Ravi Sahoo | AU68: Rejected | AV68: =PROPER(TRIM(AU68)) -> Rejected | AY68: CUST0067 | AZ68: Puri | BA68: TXN00067 | BB68: CUST0324 | BC68: =VLOOKUP(BB68,$AY$2:$AZ$501,2,FALSE) -> Angul | BG68: TXN00067 | BH68: BR006 | BI68: =VLOOKUP(BH68,$BE$2:$BF$11,2,FALSE) -> 162.3 | BK68: CUST0067 | BL68: =IF(COUNTIF(BK:BK,BK68)>0,"Exists","Does Not Exists") -> Exists
I69: 855 | J69: {=_xlfn.IFS(I69>=750,"Low Risk",AND(I69>=650,I69<=749),"Medium Risk",I69<650,"High Risk")} -> Low Risk | P69: 86.78 | Q69: =IF(ISBLANK(P69),"missing","Available") -> Available | Y69: TXN00068 | Z69: BR005 | AA69: =VLOOKUP(Z69,$W$2:$X$11,2,FALSE) -> Bikash Nayak | AB69: 42.67 | AC69: retired | AD69: 5.43 | AG69: TXN00068 | AH69: =RIGHT(AG69,5) -> 00068 | AI69: M | AJ69: =IF(UPPER(AI69)="M","Male","Female") -> Male | AK69: Suresh Swain | AL69: Jharsuguda | AM69: =_xlfn.CONCAT(AK69,"|",AL69) -> Suresh Swain|Jharsuguda | AO69: Suresh Swain | AP69: =IF(LEFT(AO69,1)="R",AO69,"Not True") -> Not True | AU69: Rejected | AV69: =PROPER(TRIM(AU69)) -> Rejected | AY69: CUST0068 | AZ69: Jharsuguda | BA69: TXN00068 | BB69: CUST0358 | BC69: =VLOOKUP(BB69,$AY$2:$AZ$501,2,FALSE) -> Jharsuguda | BG69: TXN00068 | BH69: BR005 | BI69: =VLOOKUP(BH69,$BE$2:$BF$11,2,FALSE) -> 190.31 | BK69: CUST0068 | BL69: =IF(COUNTIF(BK:BK,BK69)>0,"Exists","Does Not Exists") -> Exists
I70: 832 | J70: {=_xlfn.IFS(I70>=750,"Low Risk",AND(I70>=650,I70<=749),"Medium Risk",I70<650,"High Risk")} -> Low Risk | P70: 42.67 | Q70: =IF(ISBLANK(P70),"missing","Available") -> Available | Y70: TXN00069 | Z70: BR001 | AA70: =VLOOKUP(Z70,$W$2:$X$11,2,FALSE) -> Rajesh Kumar | AB70: 31.25 | AC70: Business Owner | AD70: 28.96 | AG70: TXN00069 | AH70: =RIGHT(AG70,5) -> 00069 | AI70: Female | AJ70: =IF(UPPER(AI70)="M","Male","Female") -> Female | AK70: Amit Barik | AL70: Cuttack | AM70: =_xlfn.CONCAT(AK70,"|",AL70) -> Amit Barik|Cuttack | AO70: Amit Barik | AP70: =IF(LEFT(AO70,1)="R",AO70,"Not True") -> Not True | AU70: Rejected | AV70: =PROPER(TRIM(AU70)) -> Rejected | AY70: CUST0069 | AZ70: Cuttack | BA70: TXN00069 | BB70: CUST0070 | BC70: =VLOOKUP(BB70,$AY$2:$AZ$501,2,FALSE) -> Cuttack | BG70: TXN00069 | BH70: BR001 | BI70: =VLOOKUP(BH70,$BE$2:$BF$11,2,FALSE) -> 209.86 | BK70: CUST0069 | BL70: =IF(COUNTIF(BK:BK,BK70)>0,"Exists","Does Not Exists") -> Exists
I71: 690 | J71: {=_xlfn.IFS(I71>=750,"Low Risk",AND(I71>=650,I71<=749),"Medium Risk",I71<650,"High Risk")} -> Medium Risk | P71: 31.25 | Q71: =IF(ISBLANK(P71),"missing","Available") -> Available | Y71: TXN00070 | Z71: BR003 | AA71: =VLOOKUP(Z71,$W$2:$X$11,2,FALSE) -> Suresh Panda | AB71: 59.71 | AC71: Government Employee | AD71: 49.07 | AG71: TXN00070 | AH71: =RIGHT(AG71,5) -> 00070 | AI71: male | AJ71: =IF(UPPER(AI71)="M","Male","Female") -> Female | AK71: Nisha Tripathi | AL71: Cuttack | AM71: =_xlfn.CONCAT(AK71,"|",AL71) -> Nisha Tripathi|Cuttack | AO71: Nisha Tripathi | AP71: =IF(LEFT(AO71,1)="R",AO71,"Not True") -> Not True | AU71: approved | AV71: =PROPER(TRIM(AU71)) -> Approved | AY71: CUST0070 | AZ71: Cuttack | BA71: TXN00070 | BB71: CUST0377 | BC71: =VLOOKUP(BB71,$AY$2:$AZ$501,2,FALSE) -> Jharsuguda | BG71: TXN00070 | BH71: BR003 | BI71: =VLOOKUP(BH71,$BE$2:$BF$11,2,FALSE) -> 197.62 | BK71: CUST0070 | BL71: =IF(COUNTIF(BK:BK,BK71)>0,"Exists","Does Not Exists") -> Exists
I72: 755 | J72: {=_xlfn.IFS(I72>=750,"Low Risk",AND(I72>=650,I72<=749),"Medium Risk",I72<650,"High Risk")} -> Low Risk | P72: 59.71 | Q72: =IF(ISBLANK(P72),"missing","Available") -> Available | Y72: TXN00071 | Z72: BR009 | AA72: =VLOOKUP(Z72,$W$2:$X$11,2,FALSE) -> Deepak Mishra | AB72: 90.78 | AC72: Business Owner | AD72: 26.86 | AG72: TXN00071 | AH72: =RIGHT(AG72,5) -> 00071 | AI72: Male | AJ72: =IF(UPPER(AI72)="M","Male","Female") -> Female | AK72: Mamata Nayak | AL72: Berhampur | AM72: =_xlfn.CONCAT(AK72,"|",AL72) -> Mamata Nayak|Berhampur | AO72: Mamata Nayak | AP72: =IF(LEFT(AO72,1)="R",AO72,"Not True") -> Not True | AU72: approved | AV72: =PROPER(TRIM(AU72)) -> Approved | AY72: CUST0071 | AZ72: Berhampur | BA72: TXN00071 | BB72: CUST0473 | BC72: =VLOOKUP(BB72,$AY$2:$AZ$501,2,FALSE) -> Sambalpur | BG72: TXN00071 | BH72: BR009 | BI72: =VLOOKUP(BH72,$BE$2:$BF$11,2,FALSE) -> 144.98 | BK72: CUST0071 | BL72: =IF(COUNTIF(BK:BK,BK72)>0,"Exists","Does Not Exists") -> Exists
I73: 580 | J73: {=_xlfn.IFS(I73>=750,"Low Risk",AND(I73>=650,I73<=749),"Medium Risk",I73<650,"High Risk")} -> High Risk | P73: 90.78 | Q73: =IF(ISBLANK(P73),"missing","Available") -> Available | Y73: TXN00072 | Z73: BR003 | AA73: =VLOOKUP(Z73,$W$2:$X$11,2,FALSE) -> Suresh Panda | AB73: 72.14 | AC73: Business Owner | AD73: 38.86 | AG73: TXN00072 | AH73: =RIGHT(AG73,5) -> 00072 | AI73: F | AJ73: =IF(UPPER(AI73)="M","Male","Female") -> Female | AK73: Nisha Nayak | AL73: Dhenkanal | AM73: =_xlfn.CONCAT(AK73,"|",AL73) -> Nisha Nayak|Dhenkanal | AO73: Nisha Nayak | AP73: =IF(LEFT(AO73,1)="R",AO73,"Not True") -> Not True | AU73: Rejected | AV73: =PROPER(TRIM(AU73)) -> Rejected | AY73: CUST0072 | AZ73: Dhenkanal | BA73: TXN00072 | BB73: CUST0189 | BC73: =VLOOKUP(BB73,$AY$2:$AZ$501,2,FALSE) -> Rourkela | BG73: TXN00072 | BH73: BR003 | BI73: =VLOOKUP(BH73,$BE$2:$BF$11,2,FALSE) -> 197.62 | BK73: CUST0072 | BL73: =IF(COUNTIF(BK:BK,BK73)>0,"Exists","Does Not Exists") -> Exists
I74: 764 | J74: {=_xlfn.IFS(I74>=750,"Low Risk",AND(I74>=650,I74<=749),"Medium Risk",I74<650,"High Risk")} -> Low Risk | P74: 72.14 | Q74: =IF(ISBLANK(P74),"missing","Available") -> Available | Y74: TXN00073 | Z74: BR005 | AA74: =VLOOKUP(Z74,$W$2:$X$11,2,FALSE) -> Bikash Nayak | AB74: 38.83 | AC74: retired | AD74: 20.92 | AG74: TXN00073 | AH74: =RIGHT(AG74,5) -> 00073 | AI74: Male | AJ74: =IF(UPPER(AI74)="M","Male","Female") -> Female | AK74: Anita Patnaik | AL74: Puri | AM74: =_xlfn.CONCAT(AK74,"|",AL74) -> Anita Patnaik|Puri | AO74: Anita Patnaik | AP74: =IF(LEFT(AO74,1)="R",AO74,"Not True") -> Not True | AU74: Rejected | AV74: =PROPER(TRIM(AU74)) -> Rejected | AY74: CUST0073 | AZ74: Puri | BA74: TXN00073 | BB74: CUST0401 | BC74: =VLOOKUP(BB74,$AY$2:$AZ$501,2,FALSE) -> Cuttack | BG74: TXN00073 | BH74: BR005 | BI74: =VLOOKUP(BH74,$BE$2:$BF$11,2,FALSE) -> 190.31 | BK74: CUST0073 | BL74: =IF(COUNTIF(BK:BK,BK74)>0,"Exists","Does Not Exists") -> Exists
I75: 602 | J75: {=_xlfn.IFS(I75>=750,"Low Risk",AND(I75>=650,I75<=749),"Medium Risk",I75<650,"High Risk")} -> High Risk | P75: 38.83 | Q75: =IF(ISBLANK(P75),"missing","Available") -> Available | Y75: TXN00074 | Z75: BR010 | AA75: =VLOOKUP(Z75,$W$2:$X$11,2,FALSE) -> Pooja Tripathi | AB75: 58.71 | AC75: Salaried | AD75: 24.48 | AG75: TXN00074 | AH75: =RIGHT(AG75,5) -> 00074 | AI75: M | AJ75: =IF(UPPER(AI75)="M","Male","Female") -> Male | AK75: Rohit Mallick | AL75: Cuttack | AM75: =_xlfn.CONCAT(AK75,"|",AL75) -> Rohit Mallick|Cuttack | AO75: Rohit Mallick | AP75: =IF(LEFT(AO75,1)="R",AO75,"Not True") -> Rohit Mallick | AU75: Rejected | AV75: =PROPER(TRIM(AU75)) -> Rejected | AY75: CUST0074 | AZ75: Cuttack | BA75: TXN00074 | BB75: CUST0121 | BC75: =VLOOKUP(BB75,$AY$2:$AZ$501,2,FALSE) -> Rourkela | BG75: TXN00074 | BH75: BR010 | BI75: =VLOOKUP(BH75,$BE$2:$BF$11,2,FALSE) -> 251.78 | BK75: CUST0074 | BL75: =IF(COUNTIF(BK:BK,BK75)>0,"Exists","Does Not Exists") -> Exists
I76: 642 | J76: {=_xlfn.IFS(I76>=750,"Low Risk",AND(I76>=650,I76<=749),"Medium Risk",I76<650,"High Risk")} -> High Risk | P76: 58.71 | Q76: =IF(ISBLANK(P76),"missing","Available") -> Available | Y76: TXN00075 | Z76: BR002 | AA76: =VLOOKUP(Z76,$W$2:$X$11,2,FALSE) -> Priya Mohanty | AB76: 6.16 | AC76: retired | AD76: 18.44 | AG76: TXN00075 | AH76: =RIGHT(AG76,5) -> 00075 | AI76: M | AJ76: =IF(UPPER(AI76)="M","Male","Female") -> Male | AK76: Suman Mishra | AL76: Jharsuguda | AM76: =_xlfn.CONCAT(AK76,"|",AL76) -> Suman Mishra|Jharsuguda | AO76: Suman Mishra | AP76: =IF(LEFT(AO76,1)="R",AO76,"Not True") -> Not True | AU76: Under Review | AV76: =PROPER(TRIM(AU76)) -> Under Review | AY76: CUST0075 | AZ76: Jharsuguda | BA76: TXN00075 | BB76: CUST0132 | BC76: =VLOOKUP(BB76,$AY$2:$AZ$501,2,FALSE) -> Dhenkanal | BG76: TXN00075 | BH76: BR002 | BI76: =VLOOKUP(BH76,$BE$2:$BF$11,2,FALSE) -> 105.8 | BK76: CUST0075 | BL76: =IF(COUNTIF(BK:BK,BK76)>0,"Exists","Does Not Exists") -> Exists
I77: 604 | J77: {=_xlfn.IFS(I77>=750,"Low Risk",AND(I77>=650,I77<=749),"Medium Risk",I77<650,"High Risk")} -> High Risk | P77: 6.16 | Q77: =IF(ISBLANK(P77),"missing","Available") -> Available | Y77: TXN00076 | Z77: BR006 | AA77: =VLOOKUP(Z77,$W$2:$X$11,2,FALSE) -> Sunita Sahu | AB77: 58.47 | AC77: Salaried | AD77: 35.17 | AG77: TXN00076 | AH77: =RIGHT(AG77,5) -> 00076 | AI77: male | AJ77: =IF(UPPER(AI77)="M","Male","Female") -> Female | AK77: Dilip Dash | AL77: Bhubaneswar | AM77: =_xlfn.CONCAT(AK77,"|",AL77) -> Dilip Dash|Bhubaneswar | AO77: Dilip Dash | AP77: =IF(LEFT(AO77,1)="R",AO77,"Not True") -> Not True | AU77: approved | AV77: =PROPER(TRIM(AU77)) -> Approved | AY77: CUST0076 | AZ77: Bhubaneswar | BA77: TXN00076 | BB77: CUST0203 | BC77: =VLOOKUP(BB77,$AY$2:$AZ$501,2,FALSE) -> Berhampur | BG77: TXN00076 | BH77: BR006 | BI77: =VLOOKUP(BH77,$BE$2:$BF$11,2,FALSE) -> 162.3 | BK77: CUST0076 | BL77: =IF(COUNTIF(BK:BK,BK77)>0,"Exists","Does Not Exists") -> Exists
... I87: 845 | J87: {=_xlfn.IFS(I87>=750,"Low Risk",AND(I87>=650,I87<=749),"Medium Risk",I87<650,"High Risk")} -> Low Risk | P87: 61.77 | Q87: =IF(ISBLANK(P87),"missing","Available") -> Available | Y87: TXN00086 | Z87: BR009 | AA87: =VLOOKUP(Z87,$W$2:$X$11,2,FALSE) -> Deepak Mishra | AB87: 44.3 | AC87: Business Owner | AD87: 13.4 | AG87: TXN00086 | AH87: =RIGHT(AG87,5) -> 00086 | AI87: Male | AJ87: =IF(UPPER(AI87)="M","Male","Female") -> Female | AK87: Anita Dash | AL87: Jharsuguda | AM87: =_xlfn.CONCAT(AK87,"|",AL87) -> Anita Dash|Jharsuguda | AO87: Anita Dash | AP87: =IF(LEFT(AO87,1)="R",AO87,"Not True") -> Not True | AU87: Rejected | AV87: =PROPER(TRIM(AU87)) -> Rejected | AY87: CUST0086 | AZ87: Jharsuguda | BA87: TXN00086 | BB87: CUST0270 | BC87: =VLOOKUP(BB87,$AY$2:$AZ$501,2,FALSE) -> Balasore | BG87: TXN00086 | BH87: BR009 | BI87: =VLOOKUP(BH87,$BE$2:$BF$11,2,FALSE) -> 144.98 | BK87: CUST0086 | BL87: =IF(COUNTIF(BK:BK,BK87)>0,"Exists","Does Not Exists") -> Exists
I88: 724 | J88: {=_xlfn.IFS(I88>=750,"Low Risk",AND(I88>=650,I88<=749),"Medium Risk",I88<650,"High Risk")} -> Medium Risk | P88: 44.3 | Q88: =IF(ISBLANK(P88),"missing","Available") -> Available | Y88: TXN00087 | Z88: BR001 | AA88: =VLOOKUP(Z88,$W$2:$X$11,2,FALSE) -> Rajesh Kumar | AC88: Government Employee | AD88: 14.04 | AG88: TXN00087 | AH88: =RIGHT(AG88,5) -> 00087 | AI88: Male | AJ88: =IF(UPPER(AI88)="M","Male","Female") -> Female | AK88: Sunita Nayak | AL88: Bhubaneswar | AM88: =_xlfn.CONCAT(AK88,"|",AL88) -> Sunita Nayak|Bhubaneswar | AO88: Sunita Nayak | AP88: =IF(LEFT(AO88,1)="R",AO88,"Not True") -> Not True | AU88: Under Review | AV88: =PROPER(TRIM(AU88)) -> Under Review | AY88: CUST0087 | AZ88: Bhubaneswar | BA88: TXN00087 | BB88: CUST0470 | BC88: =VLOOKUP(BB88,$AY$2:$AZ$501,2,FALSE) -> Sambalpur | BG88: TXN00087 | BH88: BR001 | BI88: =VLOOKUP(BH88,$BE$2:$BF$11,2,FALSE) -> 209.86 | BK88: CUST0087 | BL88: =IF(COUNTIF(BK:BK,BK88)>0,"Exists","Does Not Exists") -> Exists
I89: 841 | J89: {=_xlfn.IFS(I89>=750,"Low Risk",AND(I89>=650,I89<=749),"Medium Risk",I89<650,"High Risk")} -> Low Risk | Q89: =IF(ISBLANK(P89),"missing","Available") -> missing | Y89: TXN00088 | Z89: BR003 | AA89: =VLOOKUP(Z89,$W$2:$X$11,2,FALSE) -> Suresh Panda | AB89: 9.25 | AC89: Government Employee | AD89: 47.14 | AG89: TXN00088 | AH89: =RIGHT(AG89,5) -> 00088 | AI89: F | AJ89: =IF(UPPER(AI89)="M","Male","Female") -> Female | AK89: Mamata Nayak | AL89: Bhubaneswar | AM89: =_xlfn.CONCAT(AK89,"|",AL89) -> Mamata Nayak|Bhubaneswar | AO89: Mamata Nayak | AP89: =IF(LEFT(AO89,1)="R",AO89,"Not True") -> Not True | AU89: approved | AV89: =PROPER(TRIM(AU89)) -> Approved | AY89: CUST0088 | AZ89: Bhubaneswar | BA89: TXN00088 | BB89: CUST0237 | BC89: =VLOOKUP(BB89,$AY$2:$AZ$501,2,FALSE) -> Dhenkanal | BG89: TXN00088 | BH89: BR003 | BI89: =VLOOKUP(BH89,$BE$2:$BF$11,2,FALSE) -> 197.62 | BK89: CUST0088 | BL89: =IF(COUNTIF(BK:BK,BK89)>0,"Exists","Does Not Exists") -> Exists
I90: 859 | J90: {=_xlfn.IFS(I90>=750,"Low Risk",AND(I90>=650,I90<=749),"Medium Risk",I90<650,"High Risk")} -> Low Risk | P90: 9.25 | Q90: =IF(ISBLANK(P90),"missing","Available") -> Available | Y90: TXN00089 | Z90: BR002 | AA90: =VLOOKUP(Z90,$W$2:$X$11,2,FALSE) -> Priya Mohanty | AB90: 11.53 | AC90: Salaried | AD90: 11.92 | AG90: TXN00089 | AH90: =RIGHT(AG90,5) -> 00089 | AI90: male | AJ90: =IF(UPPER(AI90)="M","Male","Female") -> Female | AK90: Sunita Biswal | AL90: Bhubaneswar | AM90: =_xlfn.CONCAT(AK90,"|",AL90) -> Sunita Biswal|Bhubaneswar | AO90: Sunita Biswal | AP90: =IF(LEFT(AO90,1)="R",AO90,"Not True") -> Not True | AU90: approved | AV90: =PROPER(TRIM(AU90)) -> Approved | AY90: CUST0089 | AZ90: Bhubaneswar | BA90: TXN00089 | BB90: CUST0095 | BC90: =VLOOKUP(BB90,$AY$2:$AZ$501,2,FALSE) -> Cuttack | BG90: TXN00089 | BH90: BR002 | BI90: =VLOOKUP(BH90,$BE$2:$BF$11,2,FALSE) -> 105.8 | BK90: CUST0089 | BL90: =IF(COUNTIF(BK:BK,BK90)>0,"Exists","Does Not Exists") -> Exists
I91: 775 | J91: {=_xlfn.IFS(I91>=750,"Low Risk",AND(I91>=650,I91<=749),"Medium Risk",I91<650,"High Risk")} -> Low Risk | P91: 11.53 | Q91: =IF(ISBLANK(P91),"missing","Available") -> Available | Y91: TXN00090 | Z91: BR010 | AA91: =VLOOKUP(Z91,$W$2:$X$11,2,FALSE) -> Pooja Tripathi | AB91: 67.71 | AC91: Self-Employed | AD91: 12.64 | AG91: TXN00090 | AH91: =RIGHT(AG91,5) -> 00090 | AI91: Male | AJ91: =IF(UPPER(AI91)="M","Male","Female") -> Female | AK91: Puja Kumar | AL91: Puri | AM91: =_xlfn.CONCAT(AK91,"|",AL91) -> Puja Kumar|Puri | AO91: Puja Kumar | AP91: =IF(LEFT(AO91,1)="R",AO91,"Not True") -> Not True | AU91: approved | AV91: =PROPER(TRIM(AU91)) -> Approved | AY91: CUST0090 | AZ91: Puri | BA91: TXN00090 | BB91: CUST0156 | BC91: =VLOOKUP(BB91,$AY$2:$AZ$501,2,FALSE) -> Rourkela | BG91: TXN00090 | BH91: BR010 | BI91: =VLOOKUP(BH91,$BE$2:$BF$11,2,FALSE) -> 251.78 | BK91: CUST0090 | BL91: =IF(COUNTIF(BK:BK,BK91)>0,"Exists","Does Not Exists") -> Exists
I92: 880 | J92: {=_xlfn.IFS(I92>=750,"Low Risk",AND(I92>=650,I92<=749),"Medium Risk",I92<650,"High Risk")} -> Low Risk | P92: 67.71 | Q92: =IF(ISBLANK(P92),"missing","Available") -> Available | Y92: TXN00091 | Z92: BR004 | AA92: =VLOOKUP(Z92,$W$2:$X$11,2,FALSE) -> Anita Das | AB92: 65.32 | AC92: Self-Employed | AD92: 28.39 | AG92: TXN00091 | AH92: =RIGHT(AG92,5) -> 00091 | AI92: male | AJ92: =IF(UPPER(AI92)="M","Male","Female") -> Female | AK92: Prakash Nayak | AL92: Bhubaneswar | AM92: =_xlfn.CONCAT(AK92,"|",AL92) -> Prakash Nayak|Bhubaneswar | AO92: Prakash Nayak | AP92: =IF(LEFT(AO92,1)="R",AO92,"Not True") -> Not True | AU92: Under Review | AV92: =PROPER(TRIM(AU92)) -> Under Review | AY92: CUST0091 | AZ92: Bhubaneswar | BA92: TXN00091 | BB92: CUST0014 | BC92: =VLOOKUP(BB92,$AY$2:$AZ$501,2,FALSE) -> Balasore | BG92: TXN00091 | BH92: BR004 | BI92: =VLOOKUP(BH92,$BE$2:$BF$11,2,FALSE) -> 104.66 | BK92: CUST0091 | BL92: =IF(COUNTIF(BK:BK,BK92)>0,"Exists","Does Not Exists") -> Exists
I93: 672 | J93: {=_xlfn.IFS(I93>=750,"Low Risk",AND(I93>=650,I93<=749),"Medium Risk",I93<650,"High Risk")} -> Medium Risk | P93: 65.32 | Q93: =IF(ISBLANK(P93),"missing","Available") -> Available | Y93: TXN00092 | Z93: BR003 | AA93: =VLOOKUP(Z93,$W$2:$X$11,2,FALSE) -> Suresh Panda | AC93: Self-Employed | AD93: 8.96 | AG93: TXN00092 | AH93: =RIGHT(AG93,5) -> 00092 | AI93: male | AJ93: =IF(UPPER(AI93)="M","Male","Female") -> Female | AK93: Meena Rath | AL93: Puri | AM93: =_xlfn.CONCAT(AK93,"|",AL93) -> Meena Rath|Puri | AO93: Meena Rath | AP93: =IF(LEFT(AO93,1)="R",AO93,"Not True") -> Not True | AU93: Under Review | AV93: =PROPER(TRIM(AU93)) -> Under Review | AY93: CUST0092 | AZ93: Puri | BA93: TXN00092 | BB93: CUST0060 | BC93: =VLOOKUP(BB93,$AY$2:$AZ$501,2,FALSE) -> Cuttack | BG93: TXN00092 | BH93: BR003 | BI93: =VLOOKUP(BH93,$BE$2:$BF$11,2,FALSE) -> 197.62 | BK93: CUST0092 | BL93: =IF(COUNTIF(BK:BK,BK93)>0,"Exists","Does Not Exists") -> Exists
I94: 875 | J94: {=_xlfn.IFS(I94>=750,"Low Risk",AND(I94>=650,I94<=749),"Medium Risk",I94<650,"High Risk")} -> Low Risk | Q94: =IF(ISBLANK(P94),"missing","Available") -> missing | Y94: TXN00093 | Z94: BR007 | AA94: =VLOOKUP(Z94,$W$2:$X$11,2,FALSE) -> Ramesh Behera | AB94: 58.29 | AC94: Self-Employed | AD94: 5.04 | AG94: TXN00093 | AH94: =RIGHT(AG94,5) -> 00093 | AI94: Male | AJ94: =IF(UPPER(AI94)="M","Male","Female") -> Female | AK94: Rohit Mallick | AL94: Angul | AM94: =_xlfn.CONCAT(AK94,"|",AL94) -> Rohit Mallick|Angul | AO94: Rohit Mallick | AP94: =IF(LEFT(AO94,1)="R",AO94,"Not True") -> Rohit Mallick | AU94: approved | AV94: =PROPER(TRIM(AU94)) -> Approved | AY94: CUST0093 | AZ94: Angul | BA94: TXN00093 | BB94: CUST0366 | BC94: =VLOOKUP(BB94,$AY$2:$AZ$501,2,FALSE) -> Puri | BG94: TXN00093 | BH94: BR007 | BI94: =VLOOKUP(BH94,$BE$2:$BF$11,2,FALSE) -> 224.53 | BK94: CUST0093 | BL94: =IF(COUNTIF(BK:BK,BK94)>0,"Exists","Does Not Exists") -> Exists
I95: 601 | J95: {=_xlfn.IFS(I95>=750,"Low Risk",AND(I95>=650,I95<=749),"Medium Risk",I95<650,"High Risk")} -> High Risk | P95: 58.29 | Q95: =IF(ISBLANK(P95),"missing","Available") -> Available | Y95: TXN00094 | Z95: BR009 | AA95: =VLOOKUP(Z95,$W$2:$X$11,2,FALSE) -> Deepak Mishra | AB95: 42.3 | AC95: Government Employee | AD95: 23.85 | AG95: TXN00094 | AH95: =RIGHT(AG95,5) -> 00094 | AI95: F | AJ95: =IF(UPPER(AI95)="M","Male","Female") -> Female | AK95: Priya Dash | AL95: Balasore | AM95: =_xlfn.CONCAT(AK95,"|",AL95) -> Priya Dash|Balasore | AO95: Priya Dash | AP95: =IF(LEFT(AO95,1)="R",AO95,"Not True") -> Not True | AU95: Rejected | AV95: =PROPER(TRIM(AU95)) -> Rejected | AY95: CUST0094 | AZ95: Balasore | BA95: TXN00094 | BB95: CUST0162 | BC95: =VLOOKUP(BB95,$AY$2:$AZ$501,2,FALSE) -> Sambalpur | BG95: TXN00094 | BH95: BR009 | BI95: =VLOOKUP(BH95,$BE$2:$BF$11,2,FALSE) -> 144.98 | BK95: CUST0094 | BL95: =IF(COUNTIF(BK:BK,BK95)>0,"Exists","Does Not Exists") -> Exists
I96: 864 | J96: {=_xlfn.IFS(I96>=750,"Low Risk",AND(I96>=650,I96<=749),"Medium Risk",I96<650,"High Risk")} -> Low Risk | P96: 42.3 | Q96: =IF(ISBLANK(P96),"missing","Available") -> Available | Y96: TXN00095 | Z96: BR008 | AA96: =VLOOKUP(Z96,$W$2:$X$11,2,FALSE) -> Kavita Rath | AB96: 59.18 | AC96: Government Employee | AD96: 27.94 | AG96: TXN00095 | AH96: =RIGHT(AG96,5) -> 00095 | AI96: male | AJ96: =IF(UPPER(AI96)="M","Male","Female") -> Female | AK96: Puja Mallick | AL96: Cuttack | AM96: =_xlfn.CONCAT(AK96,"|",AL96) -> Puja Mallick|Cuttack | AO96: Puja Mallick | AP96: =IF(LEFT(AO96,1)="R",AO96,"Not True") -> Not True | AU96: Under Review | AV96: =PROPER(TRIM(AU96)) -> Under Review | AY96: CUST0095 | AZ96: Cuttack | BA96: TXN00095 | BB96: CUST0177 | BC96: =VLOOKUP(BB96,$AY$2:$AZ$501,2,FALSE) -> Berhampur | BG96: TXN00095 | BH96: BR008 | BI96: =VLOOKUP(BH96,$BE$2:$BF$11,2,FALSE) -> 103.83 | BK96: CUST0095 | BL96: =IF(COUNTIF(BK:BK,BK96)>0,"Exists","Does Not Exists") -> Exists
I97: 690 | J97: {=_xlfn.IFS(I97>=750,"Low Risk",AND(I97>=650,I97<=749),"Medium Risk",I97<650,"High Risk")} -> Medium Risk | P97: 59.18 | Q97: =IF(ISBLANK(P97),"missing","Available") -> Available | Y97: TXN00096 | Z97: BR006 | AA97: =VLOOKUP(Z97,$W$2:$X$11,2,FALSE) -> Sunita Sahu | AB97: 21.51 | AC97: Government Employee | AD97: 22.45 | AG97: TXN00096 | AH97: =RIGHT(AG97,5) -> 00096 | AI97: female | AJ97: =IF(UPPER(AI97)="M","Male","Female") -> Female | AK97: Dilip Rout | AL97: Sambalpur | AM97: =_xlfn.CONCAT(AK97,"|",AL97) -> Dilip Rout|Sambalpur | AO97: Dilip Rout | AP97: =IF(LEFT(AO97,1)="R",AO97,"Not True") -> Not True | AU97: Rejected | AV97: =PROPER(TRIM(AU97)) -> Rejected | AY97: CUST0096 | AZ97: Sambalpur | BA97: TXN00096 | BB97: CUST0377 | BC97: =VLOOKUP(BB97,$AY$2:$AZ$501,2,FALSE) -> Jharsuguda | BG97: TXN00096 | BH97: BR006 | BI97: =VLOOKUP(BH97,$BE$2:$BF$11,2,FALSE) -> 162.3 | BK97: CUST0096 | BL97: =IF(COUNTIF(BK:BK,BK97)>0,"Exists","Does Not Exists") -> Exists
I98: 775 | J98: {=_xlfn.IFS(I98>=750,"Low Risk",AND(I98>=650,I98<=749),"Medium Risk",I98<650,"High Risk")} -> Low Risk | P98: 21.51 | Q98: =IF(ISBLANK(P98),"missing","Available") -> Available | Y98: TXN00097 | Z98: BR004 | AA98: =VLOOKUP(Z98,$W$2:$X$11,2,FALSE) -> Anita Das | AB98: 99.93 | AC98: Salaried | AD98: 7.01 | AG98: TXN00097 | AH98: =RIGHT(AG98,5) -> 00097 | AI98: M | AJ98: =IF(UPPER(AI98)="M","Male","Female") -> Male | AK98: Deepak Mishra | AL98: Rourkela | AM98: =_xlfn.CONCAT(AK98,"|",AL98) -> Deepak Mishra|Rourkela | AO98: Deepak Mishra | AP98: =IF(LEFT(AO98,1)="R",AO98,"Not True") -> Not True | AU98: approved | AV98: =PROPER(TRIM(AU98)) -> Approved | AY98: CUST0097 | AZ98: Rourkela | BA98: TXN00097 | BB98: CUST0156 | BC98: =VLOOKUP(BB98,$AY$2:$AZ$501,2,FALSE) -> Rourkela | BG98: TXN00097 | BH98: BR004 | BI98: =VLOOKUP(BH98,$BE$2:$BF$11,2,FALSE) -> 104.66 | BK98: CUST0097 | BL98: =IF(COUNTIF(BK:BK,BK98)>0,"Exists","Does Not Exists") -> Exists
I99: 729 | J99: {=_xlfn.IFS(I99>=750,"Low Risk",AND(I99>=650,I99<=749),"Medium Risk",I99<650,"High Risk")} -> Medium Risk | P99: 99.93 | Q99: =IF(ISBLANK(P99),"missing","Available") -> Available | Y99: TXN00098 | Z99: BR008 | AA99: =VLOOKUP(Z99,$W$2:$X$11,2,FALSE) -> Kavita Rath | AB99: 77.17 | AC99: Government Employee | AD99: 34.27 | AG99: TXN00098 | AH99: =RIGHT(AG99,5) -> 00098 | AI99: M | AJ99: =IF(UPPER(AI99)="M","Male","Female") -> Male | AK99: Seema Rout | AL99: Bhubaneswar | AM99: =_xlfn.CONCAT(AK99,"|",AL99) -> Seema Rout|Bhubaneswar | AO99: Seema Rout | AP99: =IF(LEFT(AO99,1)="R",AO99,"Not True") -> Not True | AU99: Rejected | AV99: =PROPER(TRIM(AU99)) -> Rejected | AY99: CUST0098 | AZ99: Bhubaneswar | BA99: TXN00098 | BB99: CUST0115 | BC99: =VLOOKUP(BB99,$AY$2:$AZ$501,2,FALSE) -> Berhampur | BG99: TXN00098 | BH99: BR008 | BI99: =VLOOKUP(BH99,$BE$2:$BF$11,2,FALSE) -> 103.83 | BK99: CUST0098 | BL99: =IF(COUNTIF(BK:BK,BK99)>0,"Exists","Does Not Exists") -> Exists
I100: 563 | J100: {=_xlfn.IFS(I100>=750,"Low Risk",AND(I100>=650,I100<=749),"Medium Risk",I100<650,"High Risk")} -> High Risk | P100: 77.17 | Q100: =IF(ISBLANK(P100),"missing","Available") -> Available | Y100: TXN00099 | Z100: BR002 | AA100: =VLOOKUP(Z100,$W$2:$X$11,2,FALSE) -> Priya Mohanty | AB100: 78.43 | AC100: retired | AD100: 42.82 | AG100: TXN00099 | AH100: =RIGHT(AG100,5) -> 00099 | AI100: male | AJ100: =IF(UPPER(AI100)="M","Male","Female") -> Female | AK100: Sunita Mallick | AL100: Sambalpur | AM100: =_xlfn.CONCAT(AK100,"|",AL100) -> Sunita Mallick|Sambalpur | AO100: Sunita Mallick | AP100: =IF(LEFT(AO100,1)="R",AO100,"Not True") -> Not True | AU100: Rejected | AV100: =PROPER(TRIM(AU100)) -> Rejected | AY100: CUST0099 | AZ100: Sambalpur | BA100: TXN00099 | BB100: CUST0235 | BC100: =VLOOKUP(BB100,$AY$2:$AZ$501,2,FALSE) -> Dhenkanal | BG100: TXN00099 | BH100: BR002 | BI100: =VLOOKUP(BH100,$BE$2:$BF$11,2,FALSE) -> 105.8 | BK100: CUST0099 | BL100: =IF(COUNTIF(BK:BK,BK100)>0,"Exists","Does Not Exists") -> Exists
I101: 774 | J101: {=_xlfn.IFS(I101>=750,"Low Risk",AND(I101>=650,I101<=749),"Medium Risk",I101<650,"High Risk")} -> Low Risk | P101: 78.43 | Q101: =IF(ISBLANK(P101),"missing","Available") -> Available | Y101: TXN00100 | Z101: BR008 | AA101: =VLOOKUP(Z101,$W$2:$X$11,2,FALSE) -> Kavita Rath | AB101: 87.18 | AC101: retired | AD101: 4.23 | AG101: TXN00100 | AH101: =RIGHT(AG101,5) -> 00100 | AI101: male | AJ101: =IF(UPPER(AI101)="M","Male","Female") -> Female | AK101: Suman Patnaik | AL101: Jharsuguda | AM101: =_xlfn.CONCAT(AK101,"|",AL101) -> Suman Patnaik|Jharsuguda | AO101: Suman Patnaik | AP101: =IF(LEFT(AO101,1)="R",AO101,"Not True") -> Not True | AU101: approved | AV101: =PROPER(TRIM(AU101)) -> Approved | AY101: CUST0100 | AZ101: Jharsuguda | BA101: TXN00100 | BB101: CUST0150 | BC101: =VLOOKUP(BB101,$AY$2:$AZ$501,2,FALSE) -> Rourkela | BG101: TXN00100 | BH101: BR008 | BI101: =VLOOKUP(BH101,$BE$2:$BF$11,2,FALSE) -> 103.83 | BK101: CUST0100 | BL101: =IF(COUNTIF(BK:BK,BK101)>0,"Exists","Does Not Exists") -> Exists
I102: 739 | J102: {=_xlfn.IFS(I102>=750,"Low Risk",AND(I102>=650,I102<=749),"Medium Risk",I102<650,"High Risk")} -> Medium Risk | P102: 87.18 | Q102: =IF(ISBLANK(P102),"missing","Available") -> Available | Y102: TXN00101 | Z102: BR002 | AA102: =VLOOKUP(Z102,$W$2:$X$11,2,FALSE) -> Priya Mohanty | AB102: 75.73 | AC102: retired | AD102: 9.67 | AG102: TXN00101 | AH102: =RIGHT(AG102,5) -> 00101 | AI102: Female | AJ102: =IF(UPPER(AI102)="M","Male","Female") -> Female | AK102: Meena Kumar | AL102: Rourkela | AM102: =_xlfn.CONCAT(AK102,"|",AL102) -> Meena Kumar|Rourkela | AO102: Meena Kumar | AP102: =IF(LEFT(AO102,1)="R",AO102,"Not True") -> Not True | AU102: Rejected | AV102: =PROPER(TRIM(AU102)) -> Rejected | AY102: CUST0101 | AZ102: Rourkela | BA102: TXN00101 | BB102: CUST0088 | BC102: =VLOOKUP(BB102,$AY$2:$AZ$501,2,FALSE) -> Bhubaneswar | BG102: TXN00101 | BH102: BR002 | BI102: =VLOOKUP(BH102,$BE$2:$BF$11,2,FALSE) -> 105.8 | BK102: CUST0101 | BL102: =IF(COUNTIF(BK:BK,BK102)>0,"Exists","Does Not Exists") -> Exists
I103: 563 | J103: {=_xlfn.IFS(I103>=750,"Low Risk",AND(I103>=650,I103<=749),"Medium Risk",I103<650,"High Risk")} -> High Risk | P103: 75.73 | Q103: =IF(ISBLANK(P103),"missing","Available") -> Available | Y103: TXN00102 | Z103: BR009 | AA103: =VLOOKUP(Z103,$W$2:$X$11,2,FALSE) -> Deepak Mishra | AB103: 15.41 | AC103: Business Owner | AD103: 39.51 | AG103: TXN00102 | AH103: =RIGHT(AG103,5) -> 00102 | AI103: M | AJ103: =IF(UPPER(AI103)="M","Male","Female") -> Male | AK103: Lata Sethi | AL103: Rourkela | AM103: =_xlfn.CONCAT(AK103,"|",AL103) -> Lata Sethi|Rourkela | AO103: Lata Sethi | AP103: =IF(LEFT(AO103,1)="R",AO103,"Not True") -> Not True | AU103: Under Review | AV103: =PROPER(TRIM(AU103)) -> Under Review | AY103: CUST0102 | AZ103: Rourkela | BA103: TXN00102 | BB103: CUST0235 | BC103: =VLOOKUP(BB103,$AY$2:$AZ$501,2,FALSE) -> Dhenkanal | BG103: TXN00102 | BH103: BR009 | BI103: =VLOOKUP(BH103,$BE$2:$BF$11,2,FALSE) -> 144.98 | BK103: CUST0102 | BL103: =IF(COUNTIF(BK:BK,BK103)>0,"Exists","Does Not Exists") -> Exists
I104: 862 | J104: {=_xlfn.IFS(I104>=750,"Low Risk",AND(I104>=650,I104<=749),"Medium Risk",I104<650,"High Risk")} -> Low Risk | P104: 15.41 | Q104: =IF(ISBLANK(P104),"missing","Available") -> Available | Y104: TXN00103 | Z104: BR001 | AA104: =VLOOKUP(Z104,$W$2:$X$11,2,FALSE) -> Rajesh Kumar | AB104: 92.33 | AC104: Government Employee | AD104: 22.47 | AG104: TXN00103 | AH104: =RIGHT(AG104,5) -> 00103 | AI104: M | AJ104: =IF(UPPER(AI104)="M","Male","Female") -> Male | AK104: Priya Das | AL104: Angul | AM104: =_xlfn.CONCAT(AK104,"|",AL104) -> Priya Das|Angul | AO104: Priya Das | AP104: =IF(LEFT(AO104,1)="R",AO104,"Not True") -> Not True | AU104: approved | AV104: =PROPER(TRIM(AU104)) -> Approved | AY104: CUST0103 | AZ104: Angul | BA104: TXN00103 | BB104: CUST0223 | BC104: =VLOOKUP(BB104,$AY$2:$AZ$501,2,FALSE) -> Angul | BG104: TXN00103 | BH104: BR001 | BI104: =VLOOKUP(BH104,$BE$2:$BF$11,2,FALSE) -> 209.86 | BK104: CUST0103 | BL104: =IF(COUNTIF(BK:BK,BK104)>0,"Exists","Does Not Exists") -> Exists
I105: 745 | J105: {=_xlfn.IFS(I105>=750,"Low Risk",AND(I105>=650,I105<=749),"Medium Risk",I105<650,"High Risk")} -> Medium Risk | P105: 92.33 | Q105: =IF(ISBLANK(P105),"missing","Available") -> Available | Y105: TXN00104 | Z105: BR006 | AA105: =VLOOKUP(Z105,$W$2:$X$11,2,FALSE) -> Sunita Sahu | AB105: 90.12 | AC105: Salaried | AD105: 49.27 | AG105: TXN00104 | AH105: =RIGHT(AG105,5) -> 00104 | AI105: F | AJ105: =IF(UPPER(AI105)="M","Male","Female") -> Female | AK105: Rekha Mallick | AL105: Dhenkanal | AM105: =_xlfn.CONCAT(AK105,"|",AL105) -> Rekha Mallick|Dhenkanal | AO105: Rekha Mallick | AP105: =IF(LEFT(AO105,1)="R",AO105,"Not True") -> Rekha Mallick | AU105: approved | AV105: =PROPER(TRIM(AU105)) -> Approved | AY105: CUST0104 | AZ105: Dhenkanal | BA105: TXN00104 | BB105: CUST0381 | BC105: =VLOOKUP(BB105,$AY$2:$AZ$501,2,FALSE) -> Jharsuguda | BG105: TXN00104 | BH105: BR006 | BI105: =VLOOKUP(BH105,$BE$2:$BF$11,2,FALSE) -> 162.3 | BK105: CUST0104 | BL105: =IF(COUNTIF(BK:BK,BK105)>0,"Exists","Does Not Exists") -> Exists
I106: 776 | J106: {=_xlfn.IFS(I106>=750,"Low Risk",AND(I106>=650,I106<=749),"Medium Risk",I106<650,"High Risk")} -> Low Risk | P106: 90.12 | Q106: =IF(ISBLANK(P106),"missing","Available") -> Available | Y106: TXN00105 | Z106: BR004 | AA106: =VLOOKUP(Z106,$W$2:$X$11,2,FALSE) -> Anita Das | AB106: 54.21 | AC106: retired | AD106: 9.07 | AG106: TXN00105 | AH106: =RIGHT(AG106,5) -> 00105 | AI106: Male | AJ106: =IF(UPPER(AI106)="M","Male","Female") -> Female | AK106: Pooja Sahoo | AL106: Bhubaneswar | AM106: =_xlfn.CONCAT(AK106,"|",AL106) -> Pooja Sahoo|Bhubaneswar | AO106: Pooja Sahoo | AP106: =IF(LEFT(AO106,1)="R",AO106,"Not True") -> Not True | AU106: Under Review | AV106: =PROPER(TRIM(AU106)) -> Under Review | AY106: CUST0105 | AZ106: Bhubaneswar | BA106: TXN00105 | BB106: CUST0398 | BC106: =VLOOKUP(BB106,$AY$2:$AZ$501,2,FALSE) -> Balasore | BG106: TXN00105 | BH106: BR004 | BI106: =VLOOKUP(BH106,$BE$2:$BF$11,2,FALSE) -> 104.66 | BK106: CUST0105 | BL106: =IF(COUNTIF(BK:BK,BK106)>0,"Exists","Does Not Exists") -> Exists
... I138: 823 | J138: {=_xlfn.IFS(I138>=750,"Low Risk",AND(I138>=650,I138<=749),"Medium Risk",I138<650,"High Risk")} -> Low Risk | P138: 31.81 | Q138: =IF(ISBLANK(P138),"missing","Available") -> Available | Y138: TXN00137 | Z138: BR001 | AA138: =VLOOKUP(Z138,$W$2:$X$11,2,FALSE) -> Rajesh Kumar | AB138: 86.01 | AC138: retired | AD138: 49.83 | AG138: TXN00137 | AH138: =RIGHT(AG138,5) -> 00137 | AI138: Male | AJ138: =IF(UPPER(AI138)="M","Male","Female") -> Female | AK138: Sanjay Rout | AL138: Berhampur | AM138: =_xlfn.CONCAT(AK138,"|",AL138) -> Sanjay Rout|Berhampur | AO138: Sanjay Rout | AP138: =IF(LEFT(AO138,1)="R",AO138,"Not True") -> Not True | AU138: Under Review | AV138: =PROPER(TRIM(AU138)) -> Under Review | AY138: CUST0137 | AZ138: Berhampur | BA138: TXN00137 | BB138: CUST0075 | BC138: =VLOOKUP(BB138,$AY$2:$AZ$501,2,FALSE) -> Jharsuguda | BG138: TXN00137 | BH138: BR001 | BI138: =VLOOKUP(BH138,$BE$2:$BF$11,2,FALSE) -> 209.86 | BK138: CUST0137 | BL138: =IF(COUNTIF(BK:BK,BK138)>0,"Exists","Does Not Exists") -> Exists
I139: 579 | J139: {=_xlfn.IFS(I139>=750,"Low Risk",AND(I139>=650,I139<=749),"Medium Risk",I139<650,"High Risk")} -> High Risk | P139: 86.01 | Q139: =IF(ISBLANK(P139),"missing","Available") -> Available | Y139: TXN00138 | Z139: BR010 | AA139: =VLOOKUP(Z139,$W$2:$X$11,2,FALSE) -> Pooja Tripathi | AC139: retired | AD139: 6.05 | AG139: TXN00138 | AH139: =RIGHT(AG139,5) -> 00138 | AI139: Male | AJ139: =IF(UPPER(AI139)="M","Male","Female") -> Female | AK139: Kavita Sethi | AL139: Bhubaneswar | AM139: =_xlfn.CONCAT(AK139,"|",AL139) -> Kavita Sethi|Bhubaneswar | AO139: Kavita Sethi | AP139: =IF(LEFT(AO139,1)="R",AO139,"Not True") -> Not True | AU139: approved | AV139: =PROPER(TRIM(AU139)) -> Approved | AY139: CUST0138 | AZ139: Bhubaneswar | BA139: TXN00138 | BB139: CUST0240 | BC139: =VLOOKUP(BB139,$AY$2:$AZ$501,2,FALSE) -> Jharsuguda | BG139: TXN00138 | BH139: BR010 | BI139: =VLOOKUP(BH139,$BE$2:$BF$11,2,FALSE) -> 251.78 | BK139: CUST0138 | BL139: =IF(COUNTIF(BK:BK,BK139)>0,"Exists","Does Not Exists") -> Exists
I140: 855 | J140: {=_xlfn.IFS(I140>=750,"Low Risk",AND(I140>=650,I140<=749),"Medium Risk",I140<650,"High Risk")} -> Low Risk | Q140: =IF(ISBLANK(P140),"missing","Available") -> missing | Y140: TXN00139 | Z140: BR008 | AA140: =VLOOKUP(Z140,$W$2:$X$11,2,FALSE) -> Kavita Rath | AB140: 48.59 | AC140: Government Employee | AG140: TXN00139 | AH140: =RIGHT(AG140,5) -> 00139 | AI140: Female | AJ140: =IF(UPPER(AI140)="M","Male","Female") -> Female | AK140: Anita Panda | AL140: Rourkela | AM140: =_xlfn.CONCAT(AK140,"|",AL140) -> Anita Panda|Rourkela | AO140: Anita Panda | AP140: =IF(LEFT(AO140,1)="R",AO140,"Not True") -> Not True | AU140: approved | AV140: =PROPER(TRIM(AU140)) -> Approved | AY140: CUST0139 | AZ140: Rourkela | BA140: TXN00139 | BB140: CUST0118 | BC140: =VLOOKUP(BB140,$AY$2:$AZ$501,2,FALSE) -> Dhenkanal | BG140: TXN00139 | BH140: BR008 | BI140: =VLOOKUP(BH140,$BE$2:$BF$11,2,FALSE) -> 103.83 | BK140: CUST0139 | BL140: =IF(COUNTIF(BK:BK,BK140)>0,"Exists","Does Not Exists") -> Exists
...

Sheet 21-26
A1: Transaction_ID | B1: Customer_ID | C1: Branch_ID | D1: Region | E1: NPA% | F1: Product | G1: Loan_Type | H1: Loan_Amount_Lakhs | I1: Interest_Rate_Pct | J1: Processing_Fee_Lakhs | K1: EMI_Monthly | L1: Payment_Status | M1: Credit_Score | N1: Approval_Status | O1: Transaction_Date | P1: Actual date | Q1: Transaction_Date | R1: Disbursal_Date | T1: Tenure_Months | U1: Outstanding_Balance | W1: Count of Defaulted loan | X1: Total Transition | Z1: (21)Calculate how many days have elapsed since each transaction date. Use TODAY() - Transaction_Date. | AA1: (22)Extract the Month and Year from Transaction_Date. Use MONTH() and YEAR(). | AB1: (23)Calculate Loan Tenure completion % based on Transaction_Date and today. Use DATEDIF. | AC1: (24)Find all transactions that occurred in Q4 (Oct–Dec) of any year. Use MONTH(). | AD1: (25)Calculate the number of working days between Transaction_Date and Disbursal_Date. Use NETWORKDAYS. | AE1: (26)Find customer Joining_Date in Customers sheet and calculate how many years they have been a customer. Use DATEDIF.
A2: TXN00001 | B2: CUST0184 | C2: BR008 | D2: North | E2: =W2/X2*100 -> 17.95 | F2: Business Loan | G2: Unsecured | H2: 73.8 | I2: 9.62 | J2: 1.1658 | K2: 1.8583 | L2: Partially Paid | M2: 557 | N2: approved | O2: 10-05-2022 | P2: =DATE(RIGHT(O2,4),MID(O2,4,2),LEFT(O2,2)) -> 44691 | Q2: 10-05-2022 | R2: 23-05-2022 | S2: =DATE(RIGHT(R2,4),MID(R2,4,2),LEFT(R2,2)) -> 44704 | T2: 48 | U2: 41.29 | W2: =COUNTIF(L:L,"Defaulted") -> 359 | X2: =COUNTA(A2:A2001) -> 2000 | Z2: =TODAY()-P2 -> 1557 | AA2: =MONTH(P2)&"-"&YEAR(P2) -> 5-2022 | AC2: =IF(MONTH(P2)>=10,"Q4","Empty") -> Empty | AD2: =NETWORKDAYS(P2,S2) -> 10
A3: TXN00002 | B3: CUST0428 | C3: BR008 | D3: North | F3: Home Loan | G3: Unsecured | H3: 6.55 | I3: 7.97 | J3: 0.0444 | K3: 0.0547 | L3: Partially Paid | M3: 600 | N3: Rejected | O3: 02-11-2022 | P3: =DATE(RIGHT(O3,4),MID(O3,4,2),LEFT(O3,2)) -> 44867 | Q3: 02-11-2022 | S3: =DATE(RIGHT(R3,4),MID(R3,4,2),LEFT(R3,2)) -> #VALUE! | T3: 240 | U3: 4.78 | Z3: =TODAY()-P3 -> 1381 | AA3: =MONTH(P3)&"-"&YEAR(P3) -> 11-2022 | AC3: =IF(MONTH(P3)>=10,"Q4","Empty") -> Q4 | AD3: =NETWORKDAYS(P3,S3) -> #VALUE!
A4: TXN00003 | B4: CUST0377 | C4: BR003 | D4: West | F4: Business Loan | G4: Secured | H4: 47.65 | I4: 8 | J4: 0.7395 | K4: 1.4932 | L4: Paid | M4: 690 | N4: Rejected | O4: 13-04-2022 | P4: =DATE(RIGHT(O4,4),MID(O4,4,2),LEFT(O4,2)) -> 44664 | Q4: 13-04-2022 | S4: =DATE(RIGHT(R4,4),MID(R4,4,2),LEFT(R4,2)) -> #VALUE! | T4: 36 | U4: 0 | Z4: =TODAY()-P4 -> 1584 | AA4: =MONTH(P4)&"-"&YEAR(P4) -> 4-2022 | AC4: =IF(MONTH(P4)>=10,"Q4","Empty") -> Empty | AD4: =NETWORKDAYS(P4,S4) -> #VALUE!
A5: TXN00004 | B5: CUST0050 | C5: BR008 | D5: Central | F5: Personal Loan | G5: Semi-Secured | H5: 7.33 | I5: 8.76 | J5: 0.1021 | K5: 0.1816 | L5: Paid | M5: 797 | N5: Rejected | O5: 22-05-2024 | P5: =DATE(RIGHT(O5,4),MID(O5,4,2),LEFT(O5,2)) -> 45434 | Q5: 22-05-2024 | S5: =DATE(RIGHT(R5,4),MID(R5,4,2),LEFT(R5,2)) -> #VALUE! | T5: 48 | U5: 0 | Z5: =TODAY()-P5 -> 814 | AA5: =MONTH(P5)&"-"&YEAR(P5) -> 5-2024 | AC5: =IF(MONTH(P5)>=10,"Q4","Empty") -> Empty | AD5: =NETWORKDAYS(P5,S5) -> #VALUE!
A6: TXN00005 | B6: CUST0378 | C6: BR007 | D6: East | F6: Home Loan | G6: Semi-Secured | H6: 58.02 | I6: 16.7 | J6: 0.9803 | K6: 5.2834 | L6: Defaulted | M6: 751 | N6: Rejected | O6: 19-11-2023 | P6: =DATE(RIGHT(O6,4),MID(O6,4,2),LEFT(O6,2)) -> 45249 | Q6: 19-11-2023 | S6: =DATE(RIGHT(R6,4),MID(R6,4,2),LEFT(R6,2)) -> #VALUE! | T6: 12 | U6: 8.92 | Z6: =TODAY()-P6 -> 999 | AA6: =MONTH(P6)&"-"&YEAR(P6) -> 11-2023 | AC6: =IF(MONTH(P6)>=10,"Q4","Empty") -> Q4 | AD6: =NETWORKDAYS(P6,S6) -> #VALUE!
A7: TXN00006 | B7: CUST0087 | C7: BR006 | D7: Central | F7: Personal Loan | G7: Unsecured | H7: 25.12 | I7: 8.97 | J7: 0.4237 | K7: 0.3178 | L7: Pending | M7: 748 | N7: Approved | O7: 24-09-2024 | P7: =DATE(RIGHT(O7,4),MID(O7,4,2),LEFT(O7,2)) -> 45559 | Q7: 24-09-2024 | R7: 26-09-2024 | S7: =DATE(RIGHT(R7,4),MID(R7,4,2),LEFT(R7,2)) -> 45561 | T7: 120 | U7: 2.65 | Z7: =TODAY()-P7 -> 689 | AA7: =MONTH(P7)&"-"&YEAR(P7) -> 9-2024 | AC7: =IF(MONTH(P7)>=10,"Q4","Empty") -> Empty | AD7: =NETWORKDAYS(P7,S7) -> 3
A8: TXN00007 | B8: CUST0334 | C8: BR010 | D8: East | F8: Education Loan | G8: Semi-Secured | H8: 80.93 | I8: 15.12 | J8: 0.6549 | K8: 1.9304 | L8: Defaulted | M8: 866 | N8: approved | O8: 23-04-2024 | P8: =DATE(RIGHT(O8,4),MID(O8,4,2),LEFT(O8,2)) -> 45405 | Q8: 23-04-2024 | R8: 27-04-2024 | S8: =DATE(RIGHT(R8,4),MID(R8,4,2),LEFT(R8,2)) -> 45409 | T8: 60 | U8: 72.62 | Z8: =TODAY()-P8 -> 843 | AA8: =MONTH(P8)&"-"&YEAR(P8) -> 4-2024 | AC8: =IF(MONTH(P8)>=10,"Q4","Empty") -> Empty | AD8: =NETWORKDAYS(P8,S8) -> 4
A9: TXN00008 | B9: CUST0093 | C9: BR008 | D9: Central | F9: Home Loan | G9: Semi-Secured | H9: 82.82 | I9: 12.11 | J9: 1.1069 | K9: 2.1854 | L9: Paid | M9: 887 | N9: APPROVED | O9: 15-07-2022 | P9: =DATE(RIGHT(O9,4),MID(O9,4,2),LEFT(O9,2)) -> 44757 | Q9: 15-07-2022 | R9: 25-07-2022 | S9: =DATE(RIGHT(R9,4),MID(R9,4,2),LEFT(R9,2)) -> 44767 | T9: 48 | U9: 0 | Z9: =TODAY()-P9 -> 1491 | AA9: =MONTH(P9)&"-"&YEAR(P9) -> 7-2022 | AC9: =IF(MONTH(P9)>=10,"Q4","Empty") -> Empty | AD9: =NETWORKDAYS(P9,S9) -> 7
A10: TXN00009 | B10: CUST0277 | C10: BR009 | D10: South | F10: Education Loan | G10: Semi-Secured | H10: 66.27 | I10: 9.63 | J10: 1.1232 | K10: 0.6972 | L10: Partially Paid | M10: 793 | N10: Rejected | O10: 24-11-2022 | P10: =DATE(RIGHT(O10,4),MID(O10,4,2),LEFT(O10,2)) -> 44889 | Q10: 24-11-2022 | S10: =DATE(RIGHT(R10,4),MID(R10,4,2),LEFT(R10,2)) -> #VALUE! | T10: 180 | U10: 44.38 | Z10: =TODAY()-P10 -> 1359 | AA10: =MONTH(P10)&"-"&YEAR(P10) -> 11-2022 | AC10: =IF(MONTH(P10)>=10,"Q4","Empty") -> Q4 | AD10: =NETWORKDAYS(P10,S10) -> #VALUE!
A11: TXN00010 | B11: CUST0146 | C11: BR004 | D11: West | F11: Auto Loan | G11: Unsecured | H11: 62.07 | I11: 12.48 | J11: 0.4076 | K11: 5.5288 | L11: Defaulted | M11: 713 | N11: Rejected | O11: 20-11-2022 | P11: =DATE(RIGHT(O11,4),MID(O11,4,2),LEFT(O11,2)) -> 44885 | Q11: 20-11-2022 | S11: =DATE(RIGHT(R11,4),MID(R11,4,2),LEFT(R11,2)) -> #VALUE! | T11: 12 | U11: 47.65 | Z11: =TODAY()-P11 -> 1363 | AA11: =MONTH(P11)&"-"&YEAR(P11) -> 11-2022 | AC11: =IF(MONTH(P11)>=10,"Q4","Empty") -> Q4 | AD11: =NETWORKDAYS(P11,S11) -> #VALUE!
A12: TXN00011 | B12: CUST0459 | C12: BR004 | D12: West | F12: Gold Loan | G12: Semi-Secured | H12: 33.27 | I12: 14.95 | J12: 0.3289 | K12: 1.6124 | L12: Overdue | M12: 639 | N12: Rejected | O12: 20-07-2022 | P12: =DATE(RIGHT(O12,4),MID(O12,4,2),LEFT(O12,2)) -> 44762 | Q12: 20-07-2022 | S12: =DATE(RIGHT(R12,4),MID(R12,4,2),LEFT(R12,2)) -> #VALUE! | T12: 24 | U12: 10.03 | Z12: =TODAY()-P12 -> 1486 | AA12: =MONTH(P12)&"-"&YEAR(P12) -> 7-2022 | AC12: =IF(MONTH(P12)>=10,"Q4","Empty") -> Empty | AD12: =NETWORKDAYS(P12,S12) -> #VALUE!
A13: TXN00012 | B13: CUST0457 | C13: BR004 | D13: North | F13: Education Loan | G13: Semi-Secured | H13: 48.96 | I13: 9.09 | J13: 0.9262 | K13: 0.4992 | L13: Pending | M13: 731 | N13: approved | O13: 04-02-2024 | P13: =DATE(RIGHT(O13,4),MID(O13,4,2),LEFT(O13,2)) -> 45326 | Q13: 04-02-2024 | R13: 07-02-2024 | S13: =DATE(RIGHT(R13,4),MID(R13,4,2),LEFT(R13,2)) -> 45329 | T13: 180 | U13: 23.95 | Z13: =TODAY()-P13 -> 922 | AA13: =MONTH(P13)&"-"&YEAR(P13) -> 2-2024 | AC13: =IF(MONTH(P13)>=10,"Q4","Empty") -> Empty | AD13: =NETWORKDAYS(P13,S13) -> 3
A14: TXN00013 | B14: CUST0139 | C14: BR004 | D14: East | F14: Personal Loan | G14: Secured | H14: 69.53 | I14: 9 | J14: 1.2359 | K14: 0.7052 | L14: Partially Paid | M14: 738 | N14: Rejected | O14: 05-12-2023 | P14: =DATE(RIGHT(O14,4),MID(O14,4,2),LEFT(O14,2)) -> 45265 | Q14: 05-12-2023 | S14: =DATE(RIGHT(R14,4),MID(R14,4,2),LEFT(R14,2)) -> #VALUE! | T14: 180 | U14: 19.95 | Z14: =TODAY()-P14 -> 983 | AA14: =MONTH(P14)&"-"&YEAR(P14) -> 12-2023 | AC14: =IF(MONTH(P14)>=10,"Q4","Empty") -> Q4 | AD14: =NETWORKDAYS(P14,S14) -> #VALUE!
A15: TXN00014 | B15: CUST0407 | C15: BR010 | D15: South | F15: Gold Loan | G15: Semi-Secured | H15: 85.65 | I15: 16.93 | J15: 1.0568 | K15: 2.4683 | L15: Defaulted | M15: 863 | N15: approved | O15: 05-08-2024 | P15: =DATE(RIGHT(O15,4),MID(O15,4,2),LEFT(O15,2)) -> 45509 | Q15: 05-08-2024 | R15: 10-08-2024 | S15: =DATE(RIGHT(R15,4),MID(R15,4,2),LEFT(R15,2)) -> 45514 | T15: 48 | U15: 9.62 | Z15: =TODAY()-P15 -> 739 | AA15: =MONTH(P15)&"-"&YEAR(P15) -> 8-2024 | AC15: =IF(MONTH(P15)>=10,"Q4","Empty") -> Empty | AD15: =NETWORKDAYS(P15,S15) -> 5
A16: TXN00015 | B16: CUST0127 | C16: BR006 | D16: West | F16: Gold Loan | G16: Secured | H16: 89.29 | I16: 9.14 | J16: 1.2148 | K16: 7.8143 | L16: Partially Paid | M16: 560 | N16: Approved | O16: 24-03-2022 | P16: =DATE(RIGHT(O16,4),MID(O16,4,2),LEFT(O16,2)) -> 44644 | Q16: 24-03-2022 | R16: 01-04-2022 | S16: =DATE(RIGHT(R16,4),MID(R16,4,2),LEFT(R16,2)) -> 44652 | T16: 12 | U16: 64.6 | Z16: =TODAY()-P16 -> 1604 | AA16: =MONTH(P16)&"-"&YEAR(P16) -> 3-2022 | AC16: =IF(MONTH(P16)>=10,"Q4","Empty") -> Empty | AD16: =NETWORKDAYS(P16,S16) -> 7
A17: TXN00016 | B17: CUST0202 | C17: BR008 | D17: North | F17: Education Loan | G17: Unsecured | H17: 24.81 | I17: 7.64 | J17: 0.3964 | K17: 0.6015 | M17: 582 | N17: Under Review | O17: 29-08-2023 | P17: =DATE(RIGHT(O17,4),MID(O17,4,2),LEFT(O17,2)) -> 45167 | Q17: 29-08-2023 | S17: =DATE(RIGHT(R17,4),MID(R17,4,2),LEFT(R17,2)) -> #VALUE! | T17: 48 | U17: 7.52 | Z17: =TODAY()-P17 -> 1081 | AA17: =MONTH(P17)&"-"&YEAR(P17) -> 8-2023 | AC17: =IF(MONTH(P17)>=10,"Q4","Empty") -> Empty | AD17: =NETWORKDAYS(P17,S17) -> #VALUE!
A18: TXN00017 | B18: CUST0343 | C18: BR005 | D18: South | F18: Business Loan | G18: Unsecured | H18: 85.93 | I18: 7.77 | J18: 1.0159 | K18: 2.6836 | M18: 649 | N18: Rejected | O18: 29-01-2024 | P18: =DATE(RIGHT(O18,4),MID(O18,4,2),LEFT(O18,2)) -> 45320 | Q18: 29-01-2024 | S18: =DATE(RIGHT(R18,4),MID(R18,4,2),LEFT(R18,2)) -> #VALUE! | T18: 36 | U18: 54.38 | Z18: =TODAY()-P18 -> 928 | AA18: =MONTH(P18)&"-"&YEAR(P18) -> 1-2024 | AC18: =IF(MONTH(P18)>=10,"Q4","Empty") -> Empty | AD18: =NETWORKDAYS(P18,S18) -> #VALUE!
A19: TXN00018 | B19: CUST0322 | C19: BR002 | D19: West | F19: Business Loan | G19: Unsecured | H19: 53.56 | I19: 15.78 | J19: 0.8286 | K19: 0.7363 | L19: Defaulted | M19: 849 | N19: Rejected | O19: 15-06-2022 | P19: =DATE(RIGHT(O19,4),MID(O19,4,2),LEFT(O19,2)) -> 44727 | Q19: 15-06-2022 | S19: =DATE(RIGHT(R19,4),MID(R19,4,2),LEFT(R19,2)) -> #VALUE! | T19: 240 | U19: 33.6 | Z19: =TODAY()-P19 -> 1521 | AA19: =MONTH(P19)&"-"&YEAR(P19) -> 6-2022 | AC19: =IF(MONTH(P19)>=10,"Q4","Empty") -> Empty | AD19: =NETWORKDAYS(P19,S19) -> #VALUE!
